Workbook

Sheet COVER
B2: Raise Ready
B3: Complete Financial Model — Everything
B6: HOW TO USE THIS MODEL
B8: Step 01: ASSUMPTIONS | C8: Enter all your business inputs here. Every cell with a yellow background is yours to fill in. Pre-loaded with example values — replace with your actuals.
B9: Step 02: REVENUE | C9: Driver-based revenue model. Marketplace GMV, take rate, seller subscriptions, and SaaS subscription revenue — all calculated from your assumptions.
B10: Step 03: HEADCOUNT | C10: Monthly staff costs by department, driven by start month and salary from the Assumptions tab. Add or remove roles in Assumptions section 6.
B11: Step 04: P&L | C11: Full Profit and Loss statement — revenue, COGS, headcount, and operating expenses. Generates EBITDA and net income automatically.
B12: Step 05: CASH FLOW | C12: Operating, investing and financing cash flows. Opening balance, equity rounds, and closing cash. Runway calculated automatically.
B13: Step 06: BALANCE SHEET | C13: Assets, liabilities and equity. Includes a balance check row — it should always show zero. If not, check your inputs.
B14: Step 07: KPI DASHBOARD | C14: Annual summary of every investor-relevant metric. Use this as your model output page for board packs and investor updates.
B17: COLOR CODING
B18: Yellow background + blue text | C18: Your input — enter your numbers here
B19: White background + black text | C19: Formula — calculated automatically, do not edit
B20: Green background + green text | C20: Total or cross-sheet link — auto-populated
B21: Blue shaded column | C21: Year total — sum or closing balance of the year

Sheet ASSUMPTIONS
A1: ASSUMPTIONS — All Model Inputs
A2: Yellow cells = your inputs (blue text). Replace example values with your own data. Do not edit white/green cells — these are formulas.
A4: SECTION 1 — COMPANY INFORMATION
A5: Company Name | B5: My Marketplace Ltd | C5: Your legal trading name
A6: Reporting Currency | B6: £ | C6: Currency symbol used throughout the model
A7: Model Start Month & Year | B7: Jan 2025 | C7: Text label for display — e.g. Jan 2025
A9: SECTION 2 — MARKETPLACE REVENUE DRIVERS
A10: Parameter | B10: Year 1 | C10: Year 2 | D10: Year 3 | E10: Year 4 | F10: Year 5 | G10: Source / Research Note
A11: Initial Active Buyers (Month 0 — your starting base) | B11: 500 | G11: Existing buyers before model starts. If pre-launch, enter 0.
A12: New Buyers Added — Month 1 | B12: 50 | G12: Gross new buyers in the first month. Model grows this at the rate below.
A13: Monthly New Buyer Growth Rate % | B13: 0.1 | C13: 0.1 | D13: 0.1 | E13: 0.1 | F13: 0.1 | G13: Month-on-month growth of new buyers added. 10% = compounding adds each month.
A14: Monthly Buyer Churn Rate % | B14: 0.05 | C14: 0.05 | D14: 0.05 | E14: 0.05 | F14: 0.05 | G14: % of active buyers who stop transacting each month. Marketplace avg: 3–8%.
A15: Average Order Value (£) | B15: 150 | C15: 150 | D15: 150 | E15: 150 | F15: 150 | G15: Average basket size per transaction. Source: Shopify 2024 SMB avg £140–£180.
A16: Average Orders per Active Buyer/Month | B16: 1.2 | C16: 1.2 | D16: 1.2 | E16: 1.2 | F16: 1.2 | G16: How often buyers transact. Increases with engagement and product depth.
A17: Marketplace Take Rate (% of GMV) | B17: 0.15 | C17: 0.15 | D17: 0.15 | E17: 0.15 | F17: 0.15 | G17: Platform commission. UK marketplaces avg 12–20%. Indeed Flex: ~18%.
A18: Initial Active Sellers (Month 0) | B18: 50 | G18: Sellers listed on platform at model start.
A19: New Sellers Added — Month 1 | B19: 8 | G19: Gross new sellers in month 1.
A20: Monthly Seller Growth Rate % | B20: 0.08 | C20: 0.08 | D20: 0.08 | E20: 0.08 | F20: 0.08 | G20: Month-on-month growth of new sellers added.
A21: Monthly Seller Churn Rate % | B21: 0.03 | C21: 0.03 | D21: 0.03 | E21: 0.03 | F21: 0.03 | G21: % of active sellers who leave each month.
A22: Seller Monthly Subscription Fee (£) | B22: 50 | C22: 50 | D22: 50 | E22: 50 | F22: 50 | G22: If you charge sellers a SaaS fee to list. Enter 0 if marketplace-only model.
A23: SECTION 3 — SAAS SUBSCRIPTION REVENUE
A25: Initial SaaS Subscribers (Month 0) | B25: 20 | G25: Existing paying SaaS subscribers at model start.
A26: New Subscribers Added — Month 1 | B26: 5 | G26: New paying SaaS subscribers in month 1.
A27: Monthly New Subscriber Growth Rate % | B27: 0.15 | C27: 0.15 | D27: 0.15 | E27: 0.15 | F27: 0.15 | G27: Month-on-month growth of new SaaS subscribers. 15% = aggressive early-stage growth.
A28: Monthly SaaS Subscriber Churn Rate % | B28: 0.02 | C28: 0.02 | D28: 0.02 | E28: 0.02 | F28: 0.02 | G28: % of SaaS subscribers who cancel each month. World-class = <1%. Good = <2%.
A29: Monthly ARPU — SaaS (£) | B29: 299 | C29: 299 | D29: 299 | E29: 299 | F29: 299 | G29: Average monthly revenue per SaaS subscriber. Check vs your pricing tiers.
A31: SECTION 4 — UNIT ECONOMICS
A33: CAC — Paid Channel (£ per customer) | B33: 80 | C33: 80 | D33: 80 | E33: 80 | F33: 80 | G33: Fully loaded cost to acquire 1 customer via paid ads/sales. Include agency fees.
A34: CAC — Organic / Content (£ per customer) | B34: 20 | C34: 20 | D34: 20 | E34: 20 | F34: 20 | G34: Cost per customer via SEO/content/referral. Include team time.
A35: % of New Customers from Paid Channel | B35: 0.6 | C35: 0.6 | D35: 0.6 | E35: 0.6 | F35: 0.6 | G35: Split between paid and organic acquisition.
A36: Blended CAC (£) — calculated | B36: =ASSUMPTIONS!$B$33*ASSUMPTIONS!$B$35+ASSUMPTIONS!$B$34*(1-ASSUMPTIONS!$B$35) -> 56 | C36: =C33*C35+C34*(1-C35) -> 56 | D36: =D33*D35+D34*(1-D35) -> 56 | E36: =E33*E35+E34*(1-E35) -> 56 | F36: =F33*F35+F34*(1-F35) -> 56
A38: SECTION 5 — COST OF GOODS SOLD (COGS)
A39: Payment Processing Fee (% of GMV) | B39: 0.02 | C39: 0.02 | D39: 0.02 | E39: 0.02 | F39: 0.02 | G39: Stripe/Adyen/Checkout typically 1.4–2.5% + fixed. Model as % of GMV.
A40: Cloud / Infrastructure — Fixed (£/mo) | B40: 2000 | C40: 2000 | D40: 2000 | E40: 2000 | F40: 2000 | G40: Fixed monthly server/cloud cost at current scale. AWS/GCP/Azure baseline.
A41: Infrastructure Variable (£ per 1k transactions) | B41: 50 | C41: 50 | D41: 50 | E41: 50 | F41: 50 | G41: Variable cloud cost per 1,000 transactions processed.
A42: Customer Support Cost (£ per 100 active users/mo) | B42: 500 | C42: 500 | D42: 500 | E42: 500 | F42: 500 | G42: Combined marketplace buyers + sellers support cost per 100 active.
A43: Fraud & Risk Cost (% of GMV) | B43: 0.002 | C43: 0.002 | D43: 0.002 | E43: 0.002 | F43: 0.002 | G43: Chargebacks, fraud losses, risk ops. Typical range: 0.1–0.5% of GMV.
A45: SECTION 6 — HEADCOUNT PLAN
A46: Role / Position | B46: Department | C46: Start Month # | D46: Monthly Salary (£) | E46: Notes
A47: CTO / Head of Engineering | B47: Engineering | C47: 1 | D47: 9000 | E47: Replace with your hire plan
A48: Senior Engineer | B48: Engineering | C48: 1 | D48: 7000 | E48: Replace with your hire plan
A49: Engineer | B49: Engineering | C49: 3 | D49: 5500 | E49: Replace with your hire plan
A50: Engineer | B50: Engineering | C50: 6 | D50: 5500 | E50: Replace with your hire plan
A51: QA / Test Engineer | B51: Engineering | C51: 6 | D51: 4500 | E51: Replace with your hire plan
A52: VP Product / CPO | B52: Product | C52: 1 | D52: 8000 | E52: Replace with your hire plan
A53: Product Manager | B53: Product | C53: 3 | D53: 6000 | E53: Replace with your hire plan
A54: UX / Designer | B54: Product | C54: 6 | D54: 5000 | E54: Replace with your hire plan
A55: VP Sales / Head of Growth | B55: Sales | C55: 6 | D55: 9000 | E55: Replace with your hire plan
A56: Account Executive | B56: Sales | C56: 9 | D56: 5000 | E56: Replace with your hire plan
A57: Account Executive | B57: Sales | C57: 12 | D57: 5000 | E57: Replace with your hire plan
A58: SDR / BDR | B58: Sales | C58: 9 | D58: 3500 | E58: Replace with your hire plan
... A65: CEO / Founder | B65: G&A | C65: 1 | D65: 8000 | E65: Replace with your hire plan
A66: Employer NI Rate % | B66: 0.138 | G66: UK: 13.8% on salaries above £9,100/yr. Update for your jurisdiction.
A68: SECTION 7 — OPERATING EXPENSES (NON-HEADCOUNT)
A70: Sales & Marketing Non-HC — Monthly Spend (£) | B70: 3000 | C70: 3000 | D70: 3000 | E70: 3000 | F70: 3000 | G70: Paid ads, events, PR, tools. Excludes marketing headcount.
A71: S&M: enter each year's monthly amount in row 70 above | B71: 0.08 | C71: Month-on-month compound growth of S&M non-HC spend.
A72: Research & Development Non-HC — Monthly Spend (£) | B72: 1000 | C72: 1000 | D72: 1000 | E72: 1000 | F72: 1000 | G72: Software licences, dev tools, hosting for dev. Excludes eng headcount.
A73: R&D: enter each year's monthly amount in row 72 above | B73: 0.05 | C73: Month-on-month compound growth of R&D non-HC spend.
A74: General & Administrative Non-HC — Monthly Spend (£) | B74: 2500 | C74: 2500 | D74: 2500 | E74: 2500 | F74: 2500 | G74: Legal, insurance, accountancy, office. Excludes G&A headcount.
A75: G&A: enter each year's monthly amount in row 74 above | B75: 0.03 | C75: Month-on-month compound growth of G&A non-HC spend.
A77: SECTION 8 — CAPITAL, FUNDING & WORKING CAPITAL
A79: Opening Cash Balance (£) | B79: 500000 | G79: Cash in bank at start of model (Month 1 opening).
A80: Funding Round 1 — Amount (£) | B80: 1500000 | G80: Equity raised in Round 1. Enter 0 if no round planned.
A81: Funding Round 1 — Month Number | B81: 6 | G81: Month in which Round 1 cash is received (1–60).
A82: Funding Round 2 — Amount (£) | B82: 3000000 | G82: Equity raised in Round 2. Enter 0 if no round planned.
A83: Funding Round 2 — Month Number | B83: 18 | G83: Month in which Round 2 cash is received (1–60).
A84: Debtor Days (avg days to collect cash) | B84: 5 | G84: Marketplace: typically 1–7 days (card payment). SaaS: 30 days invoiced.
A85: Creditor Days (avg days to pay suppliers) | B85: 30 | G85: Average payment terms to suppliers.
A86: Corporation Tax Rate % | B86: 0.25 | G86: UK: 25% above £250k profit. Enter your jurisdiction rate.

Sheet REVENUE
A1: REVENUE MODEL — Marketplace + SaaS
A2: Driver-based model. All inputs flow from ASSUMPTIONS tab. White cells = formulas (do not edit).
B4: YEAR 1 | N4: Y1 | O4: YEAR 2 | AA4: Y2 | AB4: YEAR 3 | AN4: Y3 | AO4: YEAR 4 | BA4: Y4 | BB4: YEAR 5 | BN4: Y5
B5: Jan | C5: Feb | D5: Mar | E5: Apr | F5: May | G5: Jun | H5: Jul | I5: Aug | J5: Sep | K5: Oct | L5: Nov | M5: Dec | N5: Y1 Total | O5: Jan | P5: Feb | Q5: Mar | R5: Apr | S5: May | T5: Jun | U5: Jul | V5: Aug | W5: Sep | X5: Oct | Y5: Nov | Z5: Dec | AA5: Y2 Total | AB5: Jan | AC5: Feb | AD5: Mar | AE5: Apr | AF5: May | AG5: Jun | AH5: Jul | AI5: Aug | AJ5: Sep | AK5: Oct | AL5: Nov | AM5: Dec | AN5: Y3 Total | AO5: Jan | AP5: Feb | AQ5: Mar | AR5: Apr | AS5: May | AT5: Jun | AU5: Jul | AV5: Aug | AW5: Sep | AX5: Oct | AY5: Nov | AZ5: Dec | BA5: Y4 Total | BB5: Jan | BC5: Feb | BD5: Mar | BE5: Apr | BF5: May | BG5: Jun | BH5: Jul | BI5: Aug | BJ5: Sep | BK5: Oct | BL5: Nov | BM5: Dec | BN5: Y5 Total
A6: MARKETPLACE — BUYERS & SELLERS
A7: New Buyers Added | B7: =IFERROR(ASSUMPTIONS!$B$12,0) -> 50 | C7: =IFERROR(ROUND(B7*(1+ASSUMPTIONS!$B$13),0),0) -> 55 | D7: =IFERROR(ROUND(C7*(1+ASSUMPTIONS!$B$13),0),0) -> 61 | E7: =IFERROR(ROUND(D7*(1+ASSUMPTIONS!$B$13),0),0) -> 67 | F7: =IFERROR(ROUND(E7*(1+ASSUMPTIONS!$B$13),0),0) -> 74 | G7: =IFERROR(ROUND(F7*(1+ASSUMPTIONS!$B$13),0),0) -> 81 | H7: =IFERROR(ROUND(G7*(1+ASSUMPTIONS!$B$13),0),0) -> 89 | I7: =IFERROR(ROUND(H7*(1+ASSUMPTIONS!$B$13),0),0) -> 98 | J7: =IFERROR(ROUND(I7*(1+ASSUMPTIONS!$B$13),0),0) -> 108 | ... M7: =IFERROR(ROUND(L7*(1+ASSUMPTIONS!$B$13),0),0) -> 144 | N7: =SUM(B7:M7) -> 1077 | O7: =IFERROR(ROUND(M7*(1+ASSUMPTIONS!$C$13),0),0) -> 158 | P7: =IFERROR(ROUND(O7*(1+ASSUMPTIONS!$C$13),0),0) -> 174 | Q7: =IFERROR(ROUND(P7*(1+ASSUMPTIONS!$C$13),0),0) -> 191 | R7: =IFERROR(ROUND(Q7*(1+ASSUMPTIONS!$C$13),0),0) -> 210 | S7: =IFERROR(ROUND(R7*(1+ASSUMPTIONS!$C$13),0),0) -> 231 | T7: =IFERROR(ROUND(S7*(1+ASSUMPTIONS!$C$13),0),0) -> 254 | U7: =IFERROR(ROUND(T7*(1+ASSUMPTIONS!$C$13),0),0) -> 279 | V7: =IFERROR(ROUND(U7*(1+ASSUMPTIONS!$C$13),0),0) -> 307 | W7: =IFERROR(ROUND(V7*(1+ASSUMPTIONS!$C$13),0),0) -> 338 | ... Z7: =IFERROR(ROUND(Y7*(1+ASSUMPTIONS!$C$13),0),0) -> 450 | AA7: =SUM(O7:Z7) -> 3373 | AB7: =IFERROR(ROUND(Z7*(1+ASSUMPTIONS!$D$13),0),0) -> 495 | AC7: =IFERROR(ROUND(AB7*(1+ASSUMPTIONS!$D$13),0),0) -> 545 | AD7: =IFERROR(ROUND(AC7*(1+ASSUMPTIONS!$D$13),0),0) -> 600 | AE7: =IFERROR(ROUND(AD7*(1+ASSUMPTIONS!$D$13),0),0) -> 660 | AF7: =IFERROR(ROUND(AE7*(1+ASSUMPTIONS!$D$13),0),0) -> 726 | AG7: =IFERROR(ROUND(AF7*(1+ASSUMPTIONS!$D$13),0),0) -> 799 | AH7: =IFERROR(ROUND(AG7*(1+ASSUMPTIONS!$D$13),0),0) -> 879 | AI7: =IFERROR(ROUND(AH7*(1+ASSUMPTIONS!$D$13),0),0) -> 967 | AJ7: =IFERROR(ROUND(AI7*(1+ASSUMPTIONS!$D$13),0),0) -> 1064 | ... AM7: =IFERROR(ROUND(AL7*(1+ASSUMPTIONS!$D$13),0),0) -> 1416 | AN7: =SUM(AB7:AM7) -> 10608 | AO7: =IFERROR(ROUND(AM7*(1+ASSUMPTIONS!$E$13),0),0) -> 1558 | AP7: =IFERROR(ROUND(AO7*(1+ASSUMPTIONS!$E$13),0),0) -> 1714 | AQ7: =IFERROR(ROUND(AP7*(1+ASSUMPTIONS!$E$13),0),0) -> 1885 | AR7: =IFERROR(ROUND(AQ7*(1+ASSUMPTIONS!$E$13),0),0) -> 2074 | AS7: =IFERROR(ROUND(AR7*(1+ASSUMPTIONS!$E$13),0),0) -> 2281 | AT7: =IFERROR(ROUND(AS7*(1+ASSUMPTIONS!$E$13),0),0) -> 2509 | AU7: =IFERROR(ROUND(AT7*(1+ASSUMPTIONS!$E$13),0),0) -> 2760 | AV7: =IFERROR(ROUND(AU7*(1+ASSUMPTIONS!$E$13),0),0) -> 3036 | AW7: =IFERROR(ROUND(AV7*(1+ASSUMPTIONS!$E$13),0),0) -> 3340 | ... AZ7: =IFERROR(ROUND(AY7*(1+ASSUMPTIONS!$E$13),0),0) -> 4445 | BA7: =SUM(AO7:AZ7) -> 33317 | BB7: =IFERROR(ROUND(AZ7*(1+ASSUMPTIONS!$F$13),0),0) -> 4890 | BC7: =IFERROR(ROUND(BB7*(1+ASSUMPTIONS!$F$13),0),0) -> 5379 | BD7: =IFERROR(ROUND(BC7*(1+ASSUMPTIONS!$F$13),0),0) -> 5917 | BE7: =IFERROR(ROUND(BD7*(1+ASSUMPTIONS!$F$13),0),0) -> 6509 | BF7: =IFERROR(ROUND(BE7*(1+ASSUMPTIONS!$F$13),0),0) -> 7160 | BG7: =IFERROR(ROUND(BF7*(1+ASSUMPTIONS!$F$13),0),0) -> 7876 | BH7: =IFERROR(ROUND(BG7*(1+ASSUMPTIONS!$F$13),0),0) -> 8664 | BI7: =IFERROR(ROUND(BH7*(1+ASSUMPTIONS!$F$13),0),0) -> 9530 | BJ7: =IFERROR(ROUND(BI7*(1+ASSUMPTIONS!$F$13),0),0) -> 10483 | ... BM7: =IFERROR(ROUND(BL7*(1+ASSUMPTIONS!$F$13),0),0) -> 13952 | BN7: =SUM(BB7:BM7) -> 104575
A8: Buyers Churned | B8: =IFERROR(ROUND(ASSUMPTIONS!$B$11*ASSUMPTIONS!$B$14,0),0) -> 25 | C8: =IFERROR(ROUND(B9*ASSUMPTIONS!$B$14,0),0) -> 26 | D8: =IFERROR(ROUND(C9*ASSUMPTIONS!$B$14,0),0) -> 28 | E8: =IFERROR(ROUND(D9*ASSUMPTIONS!$B$14,0),0) -> 29 | F8: =IFERROR(ROUND(E9*ASSUMPTIONS!$B$14,0),0) -> 31 | G8: =IFERROR(ROUND(F9*ASSUMPTIONS!$B$14,0),0) -> 33 | H8: =IFERROR(ROUND(G9*ASSUMPTIONS!$B$14,0),0) -> 36 | I8: =IFERROR(ROUND(H9*ASSUMPTIONS!$B$14,0),0) -> 38 | J8: =IFERROR(ROUND(I9*ASSUMPTIONS!$B$14,0),0) -> 41 | ... M8: =IFERROR(ROUND(L9*ASSUMPTIONS!$B$14,0),0) -> 53 | N8: =SUM(B8:M8) -> 434 | O8: =IFERROR(ROUND(M9*ASSUMPTIONS!$C$14,0),0) -> 57 | P8: =IFERROR(ROUND(O9*ASSUMPTIONS!$C$14,0),0) -> 62 | Q8: =IFERROR(ROUND(P9*ASSUMPTIONS!$C$14,0),0) -> 68 | R8: =IFERROR(ROUND(Q9*ASSUMPTIONS!$C$14,0),0) -> 74 | S8: =IFERROR(ROUND(R9*ASSUMPTIONS!$C$14,0),0) -> 81 | T8: =IFERROR(ROUND(S9*ASSUMPTIONS!$C$14,0),0) -> 88 | U8: =IFERROR(ROUND(T9*ASSUMPTIONS!$C$14,0),0) -> 97 | V8: =IFERROR(ROUND(U9*ASSUMPTIONS!$C$14,0),0) -> 106 | W8: =IFERROR(ROUND(V9*ASSUMPTIONS!$C$14,0),0) -> 116 | ... Z8: =IFERROR(ROUND(Y9*ASSUMPTIONS!$C$14,0),0) -> 153 | AA8: =SUM(O8:Z8) -> 1168 | AB8: =IFERROR(ROUND(Z9*ASSUMPTIONS!$D$14,0),0) -> 167 | AC8: =IFERROR(ROUND(AB9*ASSUMPTIONS!$D$14,0),0) -> 184 | AD8: =IFERROR(ROUND(AC9*ASSUMPTIONS!$D$14,0),0) -> 202 | AE8: =IFERROR(ROUND(AD9*ASSUMPTIONS!$D$14,0),0) -> 222 | AF8: =IFERROR(ROUND(AE9*ASSUMPTIONS!$D$14,0),0) -> 244 | AG8: =IFERROR(ROUND(AF9*ASSUMPTIONS!$D$14,0),0) -> 268 | AH8: =IFERROR(ROUND(AG9*ASSUMPTIONS!$D$14,0),0) -> 294 | AI8: =IFERROR(ROUND(AH9*ASSUMPTIONS!$D$14,0),0) -> 324 | AJ8: =IFERROR(ROUND(AI9*ASSUMPTIONS!$D$14,0),0) -> 356 | ... AM8: =IFERROR(ROUND(AL9*ASSUMPTIONS!$D$14,0),0) -> 473 | AN8: =SUM(AB8:AM8) -> 3555 | AO8: =IFERROR(ROUND(AM9*ASSUMPTIONS!$E$14,0),0) -> 520 | AP8: =IFERROR(ROUND(AO9*ASSUMPTIONS!$E$14,0),0) -> 572 | AQ8: =IFERROR(ROUND(AP9*ASSUMPTIONS!$E$14,0),0) -> 629 | AR8: =IFERROR(ROUND(AQ9*ASSUMPTIONS!$E$14,0),0) -> 692 | AS8: =IFERROR(ROUND(AR9*ASSUMPTIONS!$E$14,0),0) -> 761 | AT8: =IFERROR(ROUND(AS9*ASSUMPTIONS!$E$14,0),0) -> 837 | AU8: =IFERROR(ROUND(AT9*ASSUMPTIONS!$E$14,0),0) -> 921 | AV8: =IFERROR(ROUND(AU9*ASSUMPTIONS!$E$14,0),0) -> 1013 | AW8: =IFERROR(ROUND(AV9*ASSUMPTIONS!$E$14,0),0) -> 1114 | ... AZ8: =IFERROR(ROUND(AY9*ASSUMPTIONS!$E$14,0),0) -> 1482 | BA8: =SUM(AO8:AZ8) -> 11113 | BB8: =IFERROR(ROUND(AZ9*ASSUMPTIONS!$F$14,0),0) -> 1630 | BC8: =IFERROR(ROUND(BB9*ASSUMPTIONS!$F$14,0),0) -> 1793 | BD8: =IFERROR(ROUND(BC9*ASSUMPTIONS!$F$14,0),0) -> 1973 | BE8: =IFERROR(ROUND(BD9*ASSUMPTIONS!$F$14,0),0) -> 2170 | BF8: =IFERROR(ROUND(BE9*ASSUMPTIONS!$F$14,0),0) -> 2387 | BG8: =IFERROR(ROUND(BF9*ASSUMPTIONS!$F$14,0),0) -> 2625 | BH8: =IFERROR(ROUND(BG9*ASSUMPTIONS!$F$14,0),0) -> 2888 | BI8: =IFERROR(ROUND(BH9*ASSUMPTIONS!$F$14,0),0) -> 3177 | BJ8: =IFERROR(ROUND(BI9*ASSUMPTIONS!$F$14,0),0) -> 3494 | ... BM8: =IFERROR(ROUND(BL9*ASSUMPTIONS!$F$14,0),0) -> 4651 | BN8: =SUM(BB8:BM8) -> 34860
A9: Active Buyers — End of Month | B9: =IFERROR(MAX(0,ASSUMPTIONS!$B$11+B7-B8),0) -> 525 | C9: =IFERROR(MAX(0,B9+C7-C8),0) -> 554 | D9: =IFERROR(MAX(0,C9+D7-D8),0) -> 587 | E9: =IFERROR(MAX(0,D9+E7-E8),0) -> 625 | F9: =IFERROR(MAX(0,E9+F7-F8),0) -> 668 | G9: =IFERROR(MAX(0,F9+G7-G8),0) -> 716 | H9: =IFERROR(MAX(0,G9+H7-H8),0) -> 769 | I9: =IFERROR(MAX(0,H9+I7-I8),0) -> 829 | J9: =IFERROR(MAX(0,I9+J7-J8),0) -> 896 | ... M9: =IFERROR(MAX(0,L9+M7-M8),0) -> 1143 | N9: =M9 -> 1143 | O9: =IFERROR(MAX(0,M9+O7-O8),0) -> 1244 | P9: =IFERROR(MAX(0,O9+P7-P8),0) -> 1356 | Q9: =IFERROR(MAX(0,P9+Q7-Q8),0) -> 1479 | R9: =IFERROR(MAX(0,Q9+R7-R8),0) -> 1615 | S9: =IFERROR(MAX(0,R9+S7-S8),0) -> 1765 | T9: =IFERROR(MAX(0,S9+T7-T8),0) -> 1931 | U9: =IFERROR(MAX(0,T9+U7-U8),0) -> 2113 | V9: =IFERROR(MAX(0,U9+V7-V8),0) -> 2314 | W9: =IFERROR(MAX(0,V9+W7-W8),0) -> 2536 | ... Z9: =IFERROR(MAX(0,Y9+Z7-Z8),0) -> 3348 | AA9: =Z9 -> 3348 | AB9: =IFERROR(MAX(0,Z9+AB7-AB8),0) -> 3676 | AC9: =IFERROR(MAX(0,AB9+AC7-AC8),0) -> 4037 | AD9: =IFERROR(MAX(0,AC9+AD7-AD8),0) -> 4435 | AE9: =IFERROR(MAX(0,AD9+AE7-AE8),0) -> 4873 | AF9: =IFERROR(MAX(0,AE9+AF7-AF8),0) -> 5355 | AG9: =IFERROR(MAX(0,AF9+AG7-AG8),0) -> 5886 | AH9: =IFERROR(MAX(0,AG9+AH7-AH8),0) -> 6471 | AI9: =IFERROR(MAX(0,AH9+AI7-AI8),0) -> 7114 | AJ9: =IFERROR(MAX(0,AI9+AJ7-AJ8),0) -> 7822 | ... AM9: =IFERROR(MAX(0,AL9+AM7-AM8),0) -> 10401 | AN9: =AM9 -> 10401 | AO9: =IFERROR(MAX(0,AM9+AO7-AO8),0) -> 11439 | AP9: =IFERROR(MAX(0,AO9+AP7-AP8),0) -> 12581 | AQ9: =IFERROR(MAX(0,AP9+AQ7-AQ8),0) -> 13837 | AR9: =IFERROR(MAX(0,AQ9+AR7-AR8),0) -> 15219 | AS9: =IFERROR(MAX(0,AR9+AS7-AS8),0) -> 16739 | AT9: =IFERROR(MAX(0,AS9+AT7-AT8),0) -> 18411 | AU9: =IFERROR(MAX(0,AT9+AU7-AU8),0) -> 20250 | AV9: =IFERROR(MAX(0,AU9+AV7-AV8),0) -> 22273 | AW9: =IFERROR(MAX(0,AV9+AW7-AW8),0) -> 24499 | ... AZ9: =IFERROR(MAX(0,AY9+AZ7-AZ8),0) -> 32605 | BA9: =AZ9 -> 32605 | BB9: =IFERROR(MAX(0,AZ9+BB7-BB8),0) -> 35865 | BC9: =IFERROR(MAX(0,BB9+BC7-BC8),0) -> 39451 | BD9: =IFERROR(MAX(0,BC9+BD7-BD8),0) -> 43395 | BE9: =IFERROR(MAX(0,BD9+BE7-BE8),0) -> 47734 | BF9: =IFERROR(MAX(0,BE9+BF7-BF8),0) -> 52507 | BG9: =IFERROR(MAX(0,BF9+BG7-BG8),0) -> 57758 | BH9: =IFERROR(MAX(0,BG9+BH7-BH8),0) -> 63534 | BI9: =IFERROR(MAX(0,BH9+BI7-BI8),0) -> 69887 | BJ9: =IFERROR(MAX(0,BI9+BJ7-BJ8),0) -> 76876 | ... BM9: =IFERROR(MAX(0,BL9+BM7-BM8),0) -> 102320 | BN9: =BM9 -> 102320
A11: New Sellers Added | B11: =IFERROR(ASSUMPTIONS!$B$19,0) -> 8 | C11: =IFERROR(ROUND(B10*(1+ASSUMPTIONS!$B$20),0),0) -> 0 | D11: =IFERROR(ROUND(C10*(1+ASSUMPTIONS!$B$20),0),0) -> 0 | E11: =IFERROR(ROUND(D10*(1+ASSUMPTIONS!$B$20),0),0) -> 0 | F11: =IFERROR(ROUND(E10*(1+ASSUMPTIONS!$B$20),0),0) -> 0 | G11: =IFERROR(ROUND(F10*(1+ASSUMPTIONS!$B$20),0),0) -> 0 | H11: =IFERROR(ROUND(G10*(1+ASSUMPTIONS!$B$20),0),0) -> 0 | I11: =IFERROR(ROUND(H10*(1+ASSUMPTIONS!$B$20),0),0) -> 0 | J11: =IFERROR(ROUND(I10*(1+ASSUMPTIONS!$B$20),0),0) -> 0 | ... M11: =IFERROR(ROUND(L10*(1+ASSUMPTIONS!$B$20),0),0) -> 0 | N11: =SUM(B11:M11) -> 8 | O11: =IFERROR(ROUND(M10*(1+ASSUMPTIONS!$C$20),0),0) -> 0 | P11: =IFERROR(ROUND(O10*(1+ASSUMPTIONS!$C$20),0),0) -> 0 | Q11: =IFERROR(ROUND(P10*(1+ASSUMPTIONS!$C$20),0),0) -> 0 | R11: =IFERROR(ROUND(Q10*(1+ASSUMPTIONS!$C$20),0),0) -> 0 | S11: =IFERROR(ROUND(R10*(1+ASSUMPTIONS!$C$20),0),0) -> 0 | T11: =IFERROR(ROUND(S10*(1+ASSUMPTIONS!$C$20),0),0) -> 0 | U11: =IFERROR(ROUND(T10*(1+ASSUMPTIONS!$C$20),0),0) -> 0 | V11: =IFERROR(ROUND(U10*(1+ASSUMPTIONS!$C$20),0),0) -> 0 | W11: =IFERROR(ROUND(V10*(1+ASSUMPTIONS!$C$20),0),0) -> 0 | ... Z11: =IFERROR(ROUND(Y10*(1+ASSUMPTIONS!$C$20),0),0) -> 0 | AA11: =SUM(O11:Z11) -> 0 | AB11: =IFERROR(ROUND(Z10*(1+ASSUMPTIONS!$D$20),0),0) -> 0 | AC11: =IFERROR(ROUND(AB10*(1+ASSUMPTIONS!$D$20),0),0) -> 0 | AD11: =IFERROR(ROUND(AC10*(1+ASSUMPTIONS!$D$20),0),0) -> 0 | AE11: =IFERROR(ROUND(AD10*(1+ASSUMPTIONS!$D$20),0),0) -> 0 | AF11: =IFERROR(ROUND(AE10*(1+ASSUMPTIONS!$D$20),0),0) -> 0 | AG11: =IFERROR(ROUND(AF10*(1+ASSUMPTIONS!$D$20),0),0) -> 0 | AH11: =IFERROR(ROUND(AG10*(1+ASSUMPTIONS!$D$20),0),0) -> 0 | AI11: =IFERROR(ROUND(AH10*(1+ASSUMPTIONS!$D$20),0),0) -> 0 | AJ11: =IFERROR(ROUND(AI10*(1+ASSUMPTIONS!$D$20),0),0) -> 0 | ... AM11: =IFERROR(ROUND(AL10*(1+ASSUMPTIONS!$D$20),0),0) -> 0 | AN11: =SUM(AB11:AM11) -> 0 | AO11: =IFERROR(ROUND(AM10*(1+ASSUMPTIONS!$E$20),0),0) -> 0 | AP11: =IFERROR(ROUND(AO10*(1+ASSUMPTIONS!$E$20),0),0) -> 0 | AQ11: =IFERROR(ROUND(AP10*(1+ASSUMPTIONS!$E$20),0),0) -> 0 | AR11: =IFERROR(ROUND(AQ10*(1+ASSUMPTIONS!$E$20),0),0) -> 0 | AS11: =IFERROR(ROUND(AR10*(1+ASSUMPTIONS!$E$20),0),0) -> 0 | AT11: =IFERROR(ROUND(AS10*(1+ASSUMPTIONS!$E$20),0),0) -> 0 | AU11: =IFERROR(ROUND(AT10*(1+ASSUMPTIONS!$E$20),0),0) -> 0 | AV11: =IFERROR(ROUND(AU10*(1+ASSUMPTIONS!$E$20),0),0) -> 0 | AW11: =IFERROR(ROUND(AV10*(1+ASSUMPTIONS!$E$20),0),0) -> 0 | ... AZ11: =IFERROR(ROUND(AY10*(1+ASSUMPTIONS!$E$20),0),0) -> 0 | BA11: =SUM(AO11:AZ11) -> 0 | BB11: =IFERROR(ROUND(AZ10*(1+ASSUMPTIONS!$F$20),0),0) -> 0 | BC11: =IFERROR(ROUND(BB10*(1+ASSUMPTIONS!$F$20),0),0) -> 0 | BD11: =IFERROR(ROUND(BC10*(1+ASSUMPTIONS!$F$20),0),0) -> 0 | BE11: =IFERROR(ROUND(BD10*(1+ASSUMPTIONS!$F$20),0),0) -> 0 | BF11: =IFERROR(ROUND(BE10*(1+ASSUMPTIONS!$F$20),0),0) -> 0 | BG11: =IFERROR(ROUND(BF10*(1+ASSUMPTIONS!$F$20),0),0) -> 0 | BH11: =IFERROR(ROUND(BG10*(1+ASSUMPTIONS!$F$20),0),0) -> 0 | BI11: =IFERROR(ROUND(BH10*(1+ASSUMPTIONS!$F$20),0),0) -> 0 | BJ11: =IFERROR(ROUND(BI10*(1+ASSUMPTIONS!$F$20),0),0) -> 0 | ... BM11: =IFERROR(ROUND(BL10*(1+ASSUMPTIONS!$F$20),0),0) -> 0 | BN11: =SUM(BB11:BM11) -> 0
A12: Sellers Churned | B12: =IFERROR(ROUND(ASSUMPTIONS!$B$18*ASSUMPTIONS!$B$21,0),0) -> 2 | C12: =IFERROR(ROUND(B12*ASSUMPTIONS!$B$21,0),0) -> 0 | D12: =IFERROR(ROUND(C12*ASSUMPTIONS!$B$21,0),0) -> 0 | E12: =IFERROR(ROUND(D12*ASSUMPTIONS!$B$21,0),0) -> 0 | F12: =IFERROR(ROUND(E12*ASSUMPTIONS!$B$21,0),0) -> 0 | G12: =IFERROR(ROUND(F12*ASSUMPTIONS!$B$21,0),0) -> 0 | H12: =IFERROR(ROUND(G12*ASSUMPTIONS!$B$21,0),0) -> 0 | I12: =IFERROR(ROUND(H12*ASSUMPTIONS!$B$21,0),0) -> 0 | J12: =IFERROR(ROUND(I12*ASSUMPTIONS!$B$21,0),0) -> 0 | ... M12: =IFERROR(ROUND(L12*ASSUMPTIONS!$B$21,0),0) -> 0 | N12: =SUM(B12:M12) -> 2 | O12: =IFERROR(ROUND(M12*ASSUMPTIONS!$C$21,0),0) -> 0 | P12: =IFERROR(ROUND(O12*ASSUMPTIONS!$C$21,0),0) -> 0 | Q12: =IFERROR(ROUND(P12*ASSUMPTIONS!$C$21,0),0) -> 0 | R12: =IFERROR(ROUND(Q12*ASSUMPTIONS!$C$21,0),0) -> 0 | S12: =IFERROR(ROUND(R12*ASSUMPTIONS!$C$21,0),0) -> 0 | T12: =IFERROR(ROUND(S12*ASSUMPTIONS!$C$21,0),0) -> 0 | U12: =IFERROR(ROUND(T12*ASSUMPTIONS!$C$21,0),0) -> 0 | V12: =IFERROR(ROUND(U12*ASSUMPTIONS!$C$21,0),0) -> 0 | W12: =IFERROR(ROUND(V12*ASSUMPTIONS!$C$21,0),0) -> 0 | ... Z12: =IFERROR(ROUND(Y12*ASSUMPTIONS!$C$21,0),0) -> 0 | AA12: =SUM(O12:Z12) -> 0 | AB12: =IFERROR(ROUND(Z12*ASSUMPTIONS!$D$21,0),0) -> 0 | AC12: =IFERROR(ROUND(AB12*ASSUMPTIONS!$D$21,0),0) -> 0 | AD12: =IFERROR(ROUND(AC12*ASSUMPTIONS!$D$21,0),0) -> 0 | AE12: =IFERROR(ROUND(AD12*ASSUMPTIONS!$D$21,0),0) -> 0 | AF12: =IFERROR(ROUND(AE12*ASSUMPTIONS!$D$21,0),0) -> 0 | AG12: =IFERROR(ROUND(AF12*ASSUMPTIONS!$D$21,0),0) -> 0 | AH12: =IFERROR(ROUND(AG12*ASSUMPTIONS!$D$21,0),0) -> 0 | AI12: =IFERROR(ROUND(AH12*ASSUMPTIONS!$D$21,0),0) -> 0 | AJ12: =IFERROR(ROUND(AI12*ASSUMPTIONS!$D$21,0),0) -> 0 | ... AM12: =IFERROR(ROUND(AL12*ASSUMPTIONS!$D$21,0),0) -> 0 | AN12: =SUM(AB12:AM12) -> 0 | AO12: =IFERROR(ROUND(AM12*ASSUMPTIONS!$E$21,0),0) -> 0 | AP12: =IFERROR(ROUND(AO12*ASSUMPTIONS!$E$21,0),0) -> 0 | AQ12: =IFERROR(ROUND(AP12*ASSUMPTIONS!$E$21,0),0) -> 0 | AR12: =IFERROR(ROUND(AQ12*ASSUMPTIONS!$E$21,0),0) -> 0 | AS12: =IFERROR(ROUND(AR12*ASSUMPTIONS!$E$21,0),0) -> 0 | AT12: =IFERROR(ROUND(AS12*ASSUMPTIONS!$E$21,0),0) -> 0 | AU12: =IFERROR(ROUND(AT12*ASSUMPTIONS!$E$21,0),0) -> 0 | AV12: =IFERROR(ROUND(AU12*ASSUMPTIONS!$E$21,0),0) -> 0 | AW12: =IFERROR(ROUND(AV12*ASSUMPTIONS!$E$21,0),0) -> 0 | ... AZ12: =IFERROR(ROUND(AY12*ASSUMPTIONS!$E$21,0),0) -> 0 | BA12: =SUM(AO12:AZ12) -> 0 | BB12: =IFERROR(ROUND(AZ12*ASSUMPTIONS!$F$21,0),0) -> 0 | BC12: =IFERROR(ROUND(BB12*ASSUMPTIONS!$F$21,0),0) -> 0 | BD12: =IFERROR(ROUND(BC12*ASSUMPTIONS!$F$21,0),0) -> 0 | BE12: =IFERROR(ROUND(BD12*ASSUMPTIONS!$F$21,0),0) -> 0 | BF12: =IFERROR(ROUND(BE12*ASSUMPTIONS!$F$21,0),0) -> 0 | BG12: =IFERROR(ROUND(BF12*ASSUMPTIONS!$F$21,0),0) -> 0 | BH12: =IFERROR(ROUND(BG12*ASSUMPTIONS!$F$21,0),0) -> 0 | BI12: =IFERROR(ROUND(BH12*ASSUMPTIONS!$F$21,0),0) -> 0 | BJ12: =IFERROR(ROUND(BI12*ASSUMPTIONS!$F$21,0),0) -> 0 | ... BM12: =IFERROR(ROUND(BL12*ASSUMPTIONS!$F$21,0),0) -> 0 | BN12: =SUM(BB12:BM12) -> 0
A13: Active Sellers — End of Month | B13: =IFERROR(MAX(0,ASSUMPTIONS!$B$18+B10-B11),0) -> 42 | C13: =IFERROR(MAX(0,B12+C10-C11),0) -> 2 | D13: =IFERROR(MAX(0,C12+D10-D11),0) -> 0 | E13: =IFERROR(MAX(0,D12+E10-E11),0) -> 0 | F13: =IFERROR(MAX(0,E12+F10-F11),0) -> 0 | G13: =IFERROR(MAX(0,F12+G10-G11),0) -> 0 | H13: =IFERROR(MAX(0,G12+H10-H11),0) -> 0 | I13: =IFERROR(MAX(0,H12+I10-I11),0) -> 0 | J13: =IFERROR(MAX(0,I12+J10-J11),0) -> 0 | ... M13: =IFERROR(MAX(0,L12+M10-M11),0) -> 0 | N13: =M13 -> 0 | O13: =IFERROR(MAX(0,M12+O10-O11),0) -> 0 | P13: =IFERROR(MAX(0,O12+P10-P11),0) -> 0 | Q13: =IFERROR(MAX(0,P12+Q10-Q11),0) -> 0 | R13: =IFERROR(MAX(0,Q12+R10-R11),0) -> 0 | S13: =IFERROR(MAX(0,R12+S10-S11),0) -> 0 | T13: =IFERROR(MAX(0,S12+T10-T11),0) -> 0 | U13: =IFERROR(MAX(0,T12+U10-U11),0) -> 0 | V13: =IFERROR(MAX(0,U12+V10-V11),0) -> 0 | W13: =IFERROR(MAX(0,V12+W10-W11),0) -> 0 | ... Z13: =IFERROR(MAX(0,Y12+Z10-Z11),0) -> 0 | AA13: =Z13 -> 0 | AB13: =IFERROR(MAX(0,Z12+AB10-AB11),0) -> 0 | AC13: =IFERROR(MAX(0,AB12+AC10-AC11),0) -> 0 | AD13: =IFERROR(MAX(0,AC12+AD10-AD11),0) -> 0 | AE13: =IFERROR(MAX(0,AD12+AE10-AE11),0) -> 0 | AF13: =IFERROR(MAX(0,AE12+AF10-AF11),0) -> 0 | AG13: =IFERROR(MAX(0,AF12+AG10-AG11),0) -> 0 | AH13: =IFERROR(MAX(0,AG12+AH10-AH11),0) -> 0 | AI13: =IFERROR(MAX(0,AH12+AI10-AI11),0) -> 0 | AJ13: =IFERROR(MAX(0,AI12+AJ10-AJ11),0) -> 0 | ... AM13: =IFERROR(MAX(0,AL12+AM10-AM11),0) -> 0 | AN13: =AM13 -> 0 | AO13: =IFERROR(MAX(0,AM12+AO10-AO11),0) -> 0 | AP13: =IFERROR(MAX(0,AO12+AP10-AP11),0) -> 0 | AQ13: =IFERROR(MAX(0,AP12+AQ10-AQ11),0) -> 0 | AR13: =IFERROR(MAX(0,AQ12+AR10-AR11),0) -> 0 | AS13: =IFERROR(MAX(0,AR12+AS10-AS11),0) -> 0 | AT13: =IFERROR(MAX(0,AS12+AT10-AT11),0) -> 0 | AU13: =IFERROR(MAX(0,AT12+AU10-AU11),0) -> 0 | AV13: =IFERROR(MAX(0,AU12+AV10-AV11),0) -> 0 | AW13: =IFERROR(MAX(0,AV12+AW10-AW11),0) -> 0 | ... AZ13: =IFERROR(MAX(0,AY12+AZ10-AZ11),0) -> 0 | BA13: =AZ13 -> 0 | BB13: =IFERROR(MAX(0,AZ12+BB10-BB11),0) -> 0 | BC13: =IFERROR(MAX(0,BB12+BC10-BC11),0) -> 0 | BD13: =IFERROR(MAX(0,BC12+BD10-BD11),0) -> 0 | BE13: =IFERROR(MAX(0,BD12+BE10-BE11),0) -> 0 | BF13: =IFERROR(MAX(0,BE12+BF10-BF11),0) -> 0 | BG13: =IFERROR(MAX(0,BF12+BG10-BG11),0) -> 0 | BH13: =IFERROR(MAX(0,BG12+BH10-BH11),0) -> 0 | BI13: =IFERROR(MAX(0,BH12+BI10-BI11),0) -> 0 | BJ13: =IFERROR(MAX(0,BI12+BJ10-BJ11),0) -> 0 | ... BM13: =IFERROR(MAX(0,BL12+BM10-BM11),0) -> 0 | BN13: =BM13 -> 0
A15: MARKETPLACE REVENUE
A16: Gross Merchandise Value — GMV (£) | B16: =IFERROR(B9*ASSUMPTIONS!$B$16*ASSUMPTIONS!$B$15,0) -> 94500 | C16: =IFERROR(C9*ASSUMPTIONS!$B$16*ASSUMPTIONS!$B$15,0) -> 99720 | D16: =IFERROR(D9*ASSUMPTIONS!$B$16*ASSUMPTIONS!$B$15,0) -> 105660 | E16: =IFERROR(E9*ASSUMPTIONS!$B$16*ASSUMPTIONS!$B$15,0) -> 112500 | F16: =IFERROR(F9*ASSUMPTIONS!$B$16*ASSUMPTIONS!$B$15,0) -> 120240 | G16: =IFERROR(G9*ASSUMPTIONS!$B$16*ASSUMPTIONS!$B$15,0) -> 128880 | H16: =IFERROR(H9*ASSUMPTIONS!$B$16*ASSUMPTIONS!$B$15,0) -> 138420 | I16: =IFERROR(I9*ASSUMPTIONS!$B$16*ASSUMPTIONS!$B$15,0) -> 149220 | ... M16: =IFERROR(M9*ASSUMPTIONS!$B$16*ASSUMPTIONS!$B$15,0) -> 205740 | N16: =SUM(B16:M16) -> 1680120 | O16: =IFERROR(O9*ASSUMPTIONS!$C$16*ASSUMPTIONS!$C$15,0) -> 223920 | P16: =IFERROR(P9*ASSUMPTIONS!$C$16*ASSUMPTIONS!$C$15,0) -> 244080 | Q16: =IFERROR(Q9*ASSUMPTIONS!$C$16*ASSUMPTIONS!$C$15,0) -> 266220 | R16: =IFERROR(R9*ASSUMPTIONS!$C$16*ASSUMPTIONS!$C$15,0) -> 290700 | S16: =IFERROR(S9*ASSUMPTIONS!$C$16*ASSUMPTIONS!$C$15,0) -> 317700 | T16: =IFERROR(T9*ASSUMPTIONS!$C$16*ASSUMPTIONS!$C$15,0) -> 347580 | U16: =IFERROR(U9*ASSUMPTIONS!$C$16*ASSUMPTIONS!$C$15,0) -> 380340 | V16: =IFERROR(V9*ASSUMPTIONS!$C$16*ASSUMPTIONS!$C$15,0) -> 416520 | ... Z16: =IFERROR(Z9*ASSUMPTIONS!$C$16*ASSUMPTIONS!$C$15,0) -> 602640 | AA16: =SUM(O16:Z16) -> 4595940 | AB16: =IFERROR(AB9*ASSUMPTIONS!$D$16*ASSUMPTIONS!$D$15,0) -> 661680 | AC16: =IFERROR(AC9*ASSUMPTIONS!$D$16*ASSUMPTIONS!$D$15,0) -> 726660 | AD16: =IFERROR(AD9*ASSUMPTIONS!$D$16*ASSUMPTIONS!$D$15,0) -> 798300 | AE16: =IFERROR(AE9*ASSUMPTIONS!$D$16*ASSUMPTIONS!$D$15,0) -> 877140 | AF16: =IFERROR(AF9*ASSUMPTIONS!$D$16*ASSUMPTIONS!$D$15,0) -> 963900 | AG16: =IFERROR(AG9*ASSUMPTIONS!$D$16*ASSUMPTIONS!$D$15,0) -> 1059480 | AH16: =IFERROR(AH9*ASSUMPTIONS!$D$16*ASSUMPTIONS!$D$15,0) -> 1164780 | AI16: =IFERROR(AI9*ASSUMPTIONS!$D$16*ASSUMPTIONS!$D$15,0) -> 1280520 | ... AM16: =IFERROR(AM9*ASSUMPTIONS!$D$16*ASSUMPTIONS!$D$15,0) -> 1872180 | AN16: =SUM(AB16:AM16) -> 14063220 | AO16: =IFERROR(AO9*ASSUMPTIONS!$E$16*ASSUMPTIONS!$E$15,0) -> 2059020 | AP16: =IFERROR(AP9*ASSUMPTIONS!$E$16*ASSUMPTIONS!$E$15,0) -> 2264580 | AQ16: =IFERROR(AQ9*ASSUMPTIONS!$E$16*ASSUMPTIONS!$E$15,0) -> 2490660 | AR16: =IFERROR(AR9*ASSUMPTIONS!$E$16*ASSUMPTIONS!$E$15,0) -> 2739420 | AS16: =IFERROR(AS9*ASSUMPTIONS!$E$16*ASSUMPTIONS!$E$15,0) -> 3013020 | AT16: =IFERROR(AT9*ASSUMPTIONS!$E$16*ASSUMPTIONS!$E$15,0) -> 3313980 | AU16: =IFERROR(AU9*ASSUMPTIONS!$E$16*ASSUMPTIONS!$E$15,0) -> 3645000 | AV16: =IFERROR(AV9*ASSUMPTIONS!$E$16*ASSUMPTIONS!$E$15,0) -> 4009140 | ... AZ16: =IFERROR(AZ9*ASSUMPTIONS!$E$16*ASSUMPTIONS!$E$15,0) -> 5868900 | BA16: =SUM(AO16:AZ16) -> 43999740 | BB16: =IFERROR(BB9*ASSUMPTIONS!$F$16*ASSUMPTIONS!$F$15,0) -> 6455700 | BC16: =IFERROR(BC9*ASSUMPTIONS!$F$16*ASSUMPTIONS!$F$15,0) -> 7101180 | BD16: =IFERROR(BD9*ASSUMPTIONS!$F$16*ASSUMPTIONS!$F$15,0) -> 7811100 | BE16: =IFERROR(BE9*ASSUMPTIONS!$F$16*ASSUMPTIONS!$F$15,0) -> 8592120 | BF16: =IFERROR(BF9*ASSUMPTIONS!$F$16*ASSUMPTIONS!$F$15,0) -> 9451260 | BG16: =IFERROR(BG9*ASSUMPTIONS!$F$16*ASSUMPTIONS!$F$15,0) -> 10396440 | BH16: =IFERROR(BH9*ASSUMPTIONS!$F$16*ASSUMPTIONS!$F$15,0) -> 11436120 | BI16: =IFERROR(BI9*ASSUMPTIONS!$F$16*ASSUMPTIONS!$F$15,0) -> 12579660 | ... BM16: =IFERROR(BM9*ASSUMPTIONS!$F$16*ASSUMPTIONS!$F$15,0) -> 18417600 | BN16: =SUM(BB16:BM16) -> 138043620
A17: Transaction Revenue (GMV × Take Rate) | B17: =IFERROR(B16*ASSUMPTIONS!$B$17,0) -> 14175 | C17: =IFERROR(C16*ASSUMPTIONS!$B$17,0) -> 14958 | D17: =IFERROR(D16*ASSUMPTIONS!$B$17,0) -> 15849 | E17: =IFERROR(E16*ASSUMPTIONS!$B$17,0) -> 16875 | F17: =IFERROR(F16*ASSUMPTIONS!$B$17,0) -> 18036 | G17: =IFERROR(G16*ASSUMPTIONS!$B$17,0) -> 19332 | H17: =IFERROR(H16*ASSUMPTIONS!$B$17,0) -> 20763 | I17: =IFERROR(I16*ASSUMPTIONS!$B$17,0) -> 22383 | ... M17: =IFERROR(M16*ASSUMPTIONS!$B$17,0) -> 30861 | N17: =SUM(B17:M17) -> 252018 | O17: =IFERROR(O16*ASSUMPTIONS!$C$17,0) -> 33588 | P17: =IFERROR(P16*ASSUMPTIONS!$C$17,0) -> 36612 | Q17: =IFERROR(Q16*ASSUMPTIONS!$C$17,0) -> 39933 | R17: =IFERROR(R16*ASSUMPTIONS!$C$17,0) -> 43605 | S17: =IFERROR(S16*ASSUMPTIONS!$C$17,0) -> 47655 | T17: =IFERROR(T16*ASSUMPTIONS!$C$17,0) -> 52137 | U17: =IFERROR(U16*ASSUMPTIONS!$C$17,0) -> 57051 | V17: =IFERROR(V16*ASSUMPTIONS!$C$17,0) -> 62478 | ... Z17: =IFERROR(Z16*ASSUMPTIONS!$C$17,0) -> 90396 | AA17: =SUM(O17:Z17) -> 689391 | AB17: =IFERROR(AB16*ASSUMPTIONS!$D$17,0) -> 99252 | AC17: =IFERROR(AC16*ASSUMPTIONS!$D$17,0) -> 108999 | AD17: =IFERROR(AD16*ASSUMPTIONS!$D$17,0) -> 119745 | AE17: =IFERROR(AE16*ASSUMPTIONS!$D$17,0) -> 131571 | AF17: =IFERROR(AF16*ASSUMPTIONS!$D$17,0) -> 144585 | AG17: =IFERROR(AG16*ASSUMPTIONS!$D$17,0) -> 158922 | AH17: =IFERROR(AH16*ASSUMPTIONS!$D$17,0) -> 174717 | AI17: =IFERROR(AI16*ASSUMPTIONS!$D$17,0) -> 192078 | ... AM17: =IFERROR(AM16*ASSUMPTIONS!$D$17,0) -> 280827 | AN17: =SUM(AB17:AM17) -> 2109483 | AO17: =IFERROR(AO16*ASSUMPTIONS!$E$17,0) -> 308853 | AP17: =IFERROR(AP16*ASSUMPTIONS!$E$17,0) -> 339687 | AQ17: =IFERROR(AQ16*ASSUMPTIONS!$E$17,0) -> 373599 | AR17: =IFERROR(AR16*ASSUMPTIONS!$E$17,0) -> 410913 | AS17: =IFERROR(AS16*ASSUMPTIONS!$E$17,0) -> 451953 | AT17: =IFERROR(AT16*ASSUMPTIONS!$E$17,0) -> 497097 | AU17: =IFERROR(AU16*ASSUMPTIONS!$E$17,0) -> 546750 | AV17: =IFERROR(AV16*ASSUMPTIONS!$E$17,0) -> 601371 | ... AZ17: =IFERROR(AZ16*ASSUMPTIONS!$E$17,0) -> 880335 | BA17: =SUM(AO17:AZ17) -> 6599961 | BB17: =IFERROR(BB16*ASSUMPTIONS!$F$17,0) -> 968355 | BC17: =IFERROR(BC16*ASSUMPTIONS!$F$17,0) -> 1065177 | BD17: =IFERROR(BD16*ASSUMPTIONS!$F$17,0) -> 1171665 | BE17: =IFERROR(BE16*ASSUMPTIONS!$F$17,0) -> 1288818 | BF17: =IFERROR(BF16*ASSUMPTIONS!$F$17,0) -> 1417689 | BG17: =IFERROR(BG16*ASSUMPTIONS!$F$17,0) -> 1559466 | BH17: =IFERROR(BH16*ASSUMPTIONS!$F$17,0) -> 1715418 | BI17: =IFERROR(BI16*ASSUMPTIONS!$F$17,0) -> 1886949 | ... BM17: =IFERROR(BM16*ASSUMPTIONS!$F$17,0) -> 2762640 | BN17: =SUM(BB17:BM17) -> 20706543
A18: Seller Subscription Revenue (£) | B18: =IFERROR(B13*ASSUMPTIONS!$B$22,0) -> 2100 | C18: =IFERROR(C13*ASSUMPTIONS!$B$22,0) -> 100 | D18: =IFERROR(D13*ASSUMPTIONS!$B$22,0) -> 0 | E18: =IFERROR(E13*ASSUMPTIONS!$B$22,0) -> 0 | F18: =IFERROR(F13*ASSUMPTIONS!$B$22,0) -> 0 | G18: =IFERROR(G13*ASSUMPTIONS!$B$22,0) -> 0 | H18: =IFERROR(H13*ASSUMPTIONS!$B$22,0) -> 0 | I18: =IFERROR(I13*ASSUMPTIONS!$B$22,0) -> 0 | ... M18: =IFERROR(M13*ASSUMPTIONS!$B$22,0) -> 0 | N18: =SUM(B18:M18) -> 2200 | O18: =IFERROR(O13*ASSUMPTIONS!$C$22,0) -> 0 | P18: =IFERROR(P13*ASSUMPTIONS!$C$22,0) -> 0 | Q18: =IFERROR(Q13*ASSUMPTIONS!$C$22,0) -> 0 | R18: =IFERROR(R13*ASSUMPTIONS!$C$22,0) -> 0 | S18: =IFERROR(S13*ASSUMPTIONS!$C$22,0) -> 0 | T18: =IFERROR(T13*ASSUMPTIONS!$C$22,0) -> 0 | U18: =IFERROR(U13*ASSUMPTIONS!$C$22,0) -> 0 | V18: =IFERROR(V13*ASSUMPTIONS!$C$22,0) -> 0 | ... Z18: =IFERROR(Z13*ASSUMPTIONS!$C$22,0) -> 0 | AA18: =SUM(O18:Z18) -> 0 | AB18: =IFERROR(AB13*ASSUMPTIONS!$D$22,0) -> 0 | AC18: =IFERROR(AC13*ASSUMPTIONS!$D$22,0) -> 0 | AD18: =IFERROR(AD13*ASSUMPTIONS!$D$22,0) -> 0 | AE18: =IFERROR(AE13*ASSUMPTIONS!$D$22,0) -> 0 | AF18: =IFERROR(AF13*ASSUMPTIONS!$D$22,0) -> 0 | AG18: =IFERROR(AG13*ASSUMPTIONS!$D$22,0) -> 0 | AH18: =IFERROR(AH13*ASSUMPTIONS!$D$22,0) -> 0 | AI18: =IFERROR(AI13*ASSUMPTIONS!$D$22,0) -> 0 | ... AM18: =IFERROR(AM13*ASSUMPTIONS!$D$22,0) -> 0 | AN18: =SUM(AB18:AM18) -> 0 | AO18: =IFERROR(AO13*ASSUMPTIONS!$E$22,0) -> 0 | AP18: =IFERROR(AP13*ASSUMPTIONS!$E$22,0) -> 0 | AQ18: =IFERROR(AQ13*ASSUMPTIONS!$E$22,0) -> 0 | AR18: =IFERROR(AR13*ASSUMPTIONS!$E$22,0) -> 0 | AS18: =IFERROR(AS13*ASSUMPTIONS!$E$22,0) -> 0 | AT18: =IFERROR(AT13*ASSUMPTIONS!$E$22,0) -> 0 | AU18: =IFERROR(AU13*ASSUMPTIONS!$E$22,0) -> 0 | AV18: =IFERROR(AV13*ASSUMPTIONS!$E$22,0) -> 0 | ... AZ18: =IFERROR(AZ13*ASSUMPTIONS!$E$22,0) -> 0 | BA18: =SUM(AO18:AZ18) -> 0 | BB18: =IFERROR(BB13*ASSUMPTIONS!$F$22,0) -> 0 | BC18: =IFERROR(BC13*ASSUMPTIONS!$F$22,0) -> 0 | BD18: =IFERROR(BD13*ASSUMPTIONS!$F$22,0) -> 0 | BE18: =IFERROR(BE13*ASSUMPTIONS!$F$22,0) -> 0 | BF18: =IFERROR(BF13*ASSUMPTIONS!$F$22,0) -> 0 | BG18: =IFERROR(BG13*ASSUMPTIONS!$F$22,0) -> 0 | BH18: =IFERROR(BH13*ASSUMPTIONS!$F$22,0) -> 0 | BI18: =IFERROR(BI13*ASSUMPTIONS!$F$22,0) -> 0 | ... BM18: =IFERROR(BM13*ASSUMPTIONS!$F$22,0) -> 0 | BN18: =SUM(BB18:BM18) -> 0
A19: TOTAL MARKETPLACE REVENUE (£) | B19: =IFERROR(B17+B18,0) -> 16275 | C19: =IFERROR(C17+C18,0) -> 15058 | D19: =IFERROR(D17+D18,0) -> 15849 | E19: =IFERROR(E17+E18,0) -> 16875 | F19: =IFERROR(F17+F18,0) -> 18036 | G19: =IFERROR(G17+G18,0) -> 19332 | H19: =IFERROR(H17+H18,0) -> 20763 | I19: =IFERROR(I17+I18,0) -> 22383 | ... M19: =IFERROR(M17+M18,0) -> 30861 | N19: =SUM(B19:M19) -> 254218 | O19: =IFERROR(O17+O18,0) -> 33588 | P19: =IFERROR(P17+P18,0) -> 36612 | Q19: =IFERROR(Q17+Q18,0) -> 39933 | R19: =IFERROR(R17+R18,0) -> 43605 | S19: =IFERROR(S17+S18,0) -> 47655 | T19: =IFERROR(T17+T18,0) -> 52137 | U19: =IFERROR(U17+U18,0) -> 57051 | V19: =IFERROR(V17+V18,0) -> 62478 | ... Z19: =IFERROR(Z17+Z18,0) -> 90396 | AA19: =SUM(O19:Z19) -> 689391 | AB19: =IFERROR(AB17+AB18,0) -> 99252 | AC19: =IFERROR(AC17+AC18,0) -> 108999 | AD19: =IFERROR(AD17+AD18,0) -> 119745 | AE19: =IFERROR(AE17+AE18,0) -> 131571 | AF19: =IFERROR(AF17+AF18,0) -> 144585 | AG19: =IFERROR(AG17+AG18,0) -> 158922 | AH19: =IFERROR(AH17+AH18,0) -> 174717 | AI19: =IFERROR(AI17+AI18,0) -> 192078 | ... AM19: =IFERROR(AM17+AM18,0) -> 280827 | AN19: =SUM(AB19:AM19) -> 2109483 | AO19: =IFERROR(AO17+AO18,0) -> 308853 | AP19: =IFERROR(AP17+AP18,0) -> 339687 | AQ19: =IFERROR(AQ17+AQ18,0) -> 373599 | AR19: =IFERROR(AR17+AR18,0) -> 410913 | AS19: =IFERROR(AS17+AS18,0) -> 451953 | AT19: =IFERROR(AT17+AT18,0) -> 497097 | AU19: =IFERROR(AU17+AU18,0) -> 546750 | AV19: =IFERROR(AV17+AV18,0) -> 601371 | ... AZ19: =IFERROR(AZ17+AZ18,0) -> 880335 | BA19: =SUM(AO19:AZ19) -> 6599961 | BB19: =IFERROR(BB17+BB18,0) -> 968355 | BC19: =IFERROR(BC17+BC18,0) -> 1065177 | BD19: =IFERROR(BD17+BD18,0) -> 1171665 | BE19: =IFERROR(BE17+BE18,0) -> 1288818 | BF19: =IFERROR(BF17+BF18,0) -> 1417689 | BG19: =IFERROR(BG17+BG18,0) -> 1559466 | BH19: =IFERROR(BH17+BH18,0) -> 1715418 | BI19: =IFERROR(BI17+BI18,0) -> 1886949 | ... BM19: =IFERROR(BM17+BM18,0) -> 2762640 | BN19: =SUM(BB19:BM19) -> 20706543
A21: SAAS SUBSCRIPTION REVENUE
A22: New SaaS Subscribers Added | B22: =IFERROR(ASSUMPTIONS!$B$26,0) -> 5 | C22: =IFERROR(ROUND(B22*(1+ASSUMPTIONS!$B$27),0),0) -> 6 | D22: =IFERROR(ROUND(C22*(1+ASSUMPTIONS!$B$27),0),0) -> 7 | E22: =IFERROR(ROUND(D22*(1+ASSUMPTIONS!$B$27),0),0) -> 8 | F22: =IFERROR(ROUND(E22*(1+ASSUMPTIONS!$B$27),0),0) -> 9 | G22: =IFERROR(ROUND(F22*(1+ASSUMPTIONS!$B$27),0),0) -> 10 | H22: =IFERROR(ROUND(G22*(1+ASSUMPTIONS!$B$27),0),0) -> 12 | I22: =IFERROR(ROUND(H22*(1+ASSUMPTIONS!$B$27),0),0) -> 14 | J22: =IFERROR(ROUND(I22*(1+ASSUMPTIONS!$B$27),0),0) -> 16 | ... M22: =IFERROR(ROUND(L22*(1+ASSUMPTIONS!$B$27),0),0) -> 24 | N22: =SUM(B22:M22) -> 150 | O22: =IFERROR(ROUND(M22*(1+ASSUMPTIONS!$C$27),0),0) -> 28 | P22: =IFERROR(ROUND(O22*(1+ASSUMPTIONS!$C$27),0),0) -> 32 | Q22: =IFERROR(ROUND(P22*(1+ASSUMPTIONS!$C$27),0),0) -> 37 | R22: =IFERROR(ROUND(Q22*(1+ASSUMPTIONS!$C$27),0),0) -> 43 | S22: =IFERROR(ROUND(R22*(1+ASSUMPTIONS!$C$27),0),0) -> 49 | T22: =IFERROR(ROUND(S22*(1+ASSUMPTIONS!$C$27),0),0) -> 56 | U22: =IFERROR(ROUND(T22*(1+ASSUMPTIONS!$C$27),0),0) -> 64 | V22: =IFERROR(ROUND(U22*(1+ASSUMPTIONS!$C$27),0),0) -> 74 | W22: =IFERROR(ROUND(V22*(1+ASSUMPTIONS!$C$27),0),0) -> 85 | ... Z22: =IFERROR(ROUND(Y22*(1+ASSUMPTIONS!$C$27),0),0) -> 130 | AA22: =SUM(O22:Z22) -> 809 | AB22: =IFERROR(ROUND(Z22*(1+ASSUMPTIONS!$D$27),0),0) -> 150 | AC22: =IFERROR(ROUND(AB22*(1+ASSUMPTIONS!$D$27),0),0) -> 173 | AD22: =IFERROR(ROUND(AC22*(1+ASSUMPTIONS!$D$27),0),0) -> 199 | AE22: =IFERROR(ROUND(AD22*(1+ASSUMPTIONS!$D$27),0),0) -> 229 | AF22: =IFERROR(ROUND(AE22*(1+ASSUMPTIONS!$D$27),0),0) -> 263 | AG22: =IFERROR(ROUND(AF22*(1+ASSUMPTIONS!$D$27),0),0) -> 302 | AH22: =IFERROR(ROUND(AG22*(1+ASSUMPTIONS!$D$27),0),0) -> 347 | AI22: =IFERROR(ROUND(AH22*(1+ASSUMPTIONS!$D$27),0),0) -> 399 | AJ22: =IFERROR(ROUND(AI22*(1+ASSUMPTIONS!$D$27),0),0) -> 459 | ... AM22: =IFERROR(ROUND(AL22*(1+ASSUMPTIONS!$D$27),0),0) -> 698 | AN22: =SUM(AB22:AM22) -> 4354 | AO22: =IFERROR(ROUND(AM22*(1+ASSUMPTIONS!$E$27),0),0) -> 803 | AP22: =IFERROR(ROUND(AO22*(1+ASSUMPTIONS!$E$27),0),0) -> 923 | AQ22: =IFERROR(ROUND(AP22*(1+ASSUMPTIONS!$E$27),0),0) -> 1061 | AR22: =IFERROR(ROUND(AQ22*(1+ASSUMPTIONS!$E$27),0),0) -> 1220 | AS22: =IFERROR(ROUND(AR22*(1+ASSUMPTIONS!$E$27),0),0) -> 1403 | AT22: =IFERROR(ROUND(AS22*(1+ASSUMPTIONS!$E$27),0),0) -> 1613 | AU22: =IFERROR(ROUND(AT22*(1+ASSUMPTIONS!$E$27),0),0) -> 1855 | AV22: =IFERROR(ROUND(AU22*(1+ASSUMPTIONS!$E$27),0),0) -> 2133 | AW22: =IFERROR(ROUND(AV22*(1+ASSUMPTIONS!$E$27),0),0) -> 2453 | ... AZ22: =IFERROR(ROUND(AY22*(1+ASSUMPTIONS!$E$27),0),0) -> 3731 | BA22: =SUM(AO22:AZ22) -> 23260 | BB22: =IFERROR(ROUND(AZ22*(1+ASSUMPTIONS!$F$27),0),0) -> 4291 | BC22: =IFERROR(ROUND(BB22*(1+ASSUMPTIONS!$F$27),0),0) -> 4935 | BD22: =IFERROR(ROUND(BC22*(1+ASSUMPTIONS!$F$27),0),0) -> 5675 | BE22: =IFERROR(ROUND(BD22*(1+ASSUMPTIONS!$F$27),0),0) -> 6526 | BF22: =IFERROR(ROUND(BE22*(1+ASSUMPTIONS!$F$27),0),0) -> 7505 | BG22: =IFERROR(ROUND(BF22*(1+ASSUMPTIONS!$F$27),0),0) -> 8631 | BH22: =IFERROR(ROUND(BG22*(1+ASSUMPTIONS!$F$27),0),0) -> 9926 | BI22: =IFERROR(ROUND(BH22*(1+ASSUMPTIONS!$F$27),0),0) -> 11415 | BJ22: =IFERROR(ROUND(BI22*(1+ASSUMPTIONS!$F$27),0),0) -> 13127 | ... BM22: =IFERROR(ROUND(BL22*(1+ASSUMPTIONS!$F$27),0),0) -> 19964 | BN22: =SUM(BB22:BM22) -> 124451
A23: SaaS Subscribers Churned | B23: =IFERROR(ROUND(ASSUMPTIONS!$B$25*ASSUMPTIONS!$B$28,0),0) -> 0 | C23: =IFERROR(ROUND(B24*ASSUMPTIONS!$B$28,0),0) -> 1 | D23: =IFERROR(ROUND(C24*ASSUMPTIONS!$B$28,0),0) -> 1 | E23: =IFERROR(ROUND(D24*ASSUMPTIONS!$B$28,0),0) -> 1 | F23: =IFERROR(ROUND(E24*ASSUMPTIONS!$B$28,0),0) -> 1 | G23: =IFERROR(ROUND(F24*ASSUMPTIONS!$B$28,0),0) -> 1 | H23: =IFERROR(ROUND(G24*ASSUMPTIONS!$B$28,0),0) -> 1 | I23: =IFERROR(ROUND(H24*ASSUMPTIONS!$B$28,0),0) -> 1 | J23: =IFERROR(ROUND(I24*ASSUMPTIONS!$B$28,0),0) -> 2 | ... M23: =IFERROR(ROUND(L24*ASSUMPTIONS!$B$28,0),0) -> 3 | N23: =SUM(B23:M23) -> 16 | O23: =IFERROR(ROUND(M24*ASSUMPTIONS!$C$28,0),0) -> 3 | P23: =IFERROR(ROUND(O24*ASSUMPTIONS!$C$28,0),0) -> 4 | Q23: =IFERROR(ROUND(P24*ASSUMPTIONS!$C$28,0),0) -> 4 | R23: =IFERROR(ROUND(Q24*ASSUMPTIONS!$C$28,0),0) -> 5 | S23: =IFERROR(ROUND(R24*ASSUMPTIONS!$C$28,0),0) -> 6 | T23: =IFERROR(ROUND(S24*ASSUMPTIONS!$C$28,0),0) -> 6 | U23: =IFERROR(ROUND(T24*ASSUMPTIONS!$C$28,0),0) -> 7 | V23: =IFERROR(ROUND(U24*ASSUMPTIONS!$C$28,0),0) -> 9 | W23: =IFERROR(ROUND(V24*ASSUMPTIONS!$C$28,0),0) -> 10 | ... Z23: =IFERROR(ROUND(Y24*ASSUMPTIONS!$C$28,0),0) -> 15 | AA23: =SUM(O23:Z23) -> 93 | AB23: =IFERROR(ROUND(Z24*ASSUMPTIONS!$D$28,0),0) -> 17 | AC23: =IFERROR(ROUND(AB24*ASSUMPTIONS!$D$28,0),0) -> 20 | AD23: =IFERROR(ROUND(AC24*ASSUMPTIONS!$D$28,0),0) -> 23 | AE23: =IFERROR(ROUND(AD24*ASSUMPTIONS!$D$28,0),0) -> 27 | AF23: =IFERROR(ROUND(AE24*ASSUMPTIONS!$D$28,0),0) -> 31 | AG23: =IFERROR(ROUND(AF24*ASSUMPTIONS!$D$28,0),0) -> 35 | AH23: =IFERROR(ROUND(AG24*ASSUMPTIONS!$D$28,0),0) -> 41 | AI23: =IFERROR(ROUND(AH24*ASSUMPTIONS!$D$28,0),0) -> 47 | AJ23: =IFERROR(ROUND(AI24*ASSUMPTIONS!$D$28,0),0) -> 54 | ... AM23: =IFERROR(ROUND(AL24*ASSUMPTIONS!$D$28,0),0) -> 82 | AN23: =SUM(AB23:AM23) -> 510 | AO23: =IFERROR(ROUND(AM24*ASSUMPTIONS!$E$28,0),0) -> 94 | AP23: =IFERROR(ROUND(AO24*ASSUMPTIONS!$E$28,0),0) -> 108 | AQ23: =IFERROR(ROUND(AP24*ASSUMPTIONS!$E$28,0),0) -> 125 | AR23: =IFERROR(ROUND(AQ24*ASSUMPTIONS!$E$28,0),0) -> 143 | AS23: =IFERROR(ROUND(AR24*ASSUMPTIONS!$E$28,0),0) -> 165 | AT23: =IFERROR(ROUND(AS24*ASSUMPTIONS!$E$28,0),0) -> 190 | AU23: =IFERROR(ROUND(AT24*ASSUMPTIONS!$E$28,0),0) -> 218 | AV23: =IFERROR(ROUND(AU24*ASSUMPTIONS!$E$28,0),0) -> 251 | AW23: =IFERROR(ROUND(AV24*ASSUMPTIONS!$E$28,0),0) -> 289 | ... AZ23: =IFERROR(ROUND(AY24*ASSUMPTIONS!$E$28,0),0) -> 439 | BA23: =SUM(AO23:AZ23) -> 2736 | BB23: =IFERROR(ROUND(AZ24*ASSUMPTIONS!$F$28,0),0) -> 505 | BC23: =IFERROR(ROUND(BB24*ASSUMPTIONS!$F$28,0),0) -> 580 | BD23: =IFERROR(ROUND(BC24*ASSUMPTIONS!$F$28,0),0) -> 668 | BE23: =IFERROR(ROUND(BD24*ASSUMPTIONS!$F$28,0),0) -> 768 | BF23: =IFERROR(ROUND(BE24*ASSUMPTIONS!$F$28,0),0) -> 883 | BG23: =IFERROR(ROUND(BF24*ASSUMPTIONS!$F$28,0),0) -> 1015 | BH23: =IFERROR(ROUND(BG24*ASSUMPTIONS!$F$28,0),0) -> 1168 | BI23: =IFERROR(ROUND(BH24*ASSUMPTIONS!$F$28,0),0) -> 1343 | BJ23: =IFERROR(ROUND(BI24*ASSUMPTIONS!$F$28,0),0) -> 1544 | ... BM23: =IFERROR(ROUND(BL24*ASSUMPTIONS!$F$28,0),0) -> 2349 | BN23: =SUM(BB23:BM23) -> 14641
A24: Active SaaS Subscribers — End of Month | B24: =IFERROR(MAX(0,ASSUMPTIONS!$B$25+B22-B23),0) -> 25 | C24: =IFERROR(MAX(0,B24+C22-C23),0) -> 30 | D24: =IFERROR(MAX(0,C24+D22-D23),0) -> 36 | E24: =IFERROR(MAX(0,D24+E22-E23),0) -> 43 | F24: =IFERROR(MAX(0,E24+F22-F23),0) -> 51 | G24: =IFERROR(MAX(0,F24+G22-G23),0) -> 60 | H24: =IFERROR(MAX(0,G24+H22-H23),0) -> 71 | I24: =IFERROR(MAX(0,H24+I22-I23),0) -> 84 | J24: =IFERROR(MAX(0,I24+J22-J23),0) -> 98 | ... M24: =IFERROR(MAX(0,L24+M22-M23),0) -> 154 | N24: =M24 -> 154 | O24: =IFERROR(MAX(0,M24+O22-O23),0) -> 179 | P24: =IFERROR(MAX(0,O24+P22-P23),0) -> 207 | Q24: =IFERROR(MAX(0,P24+Q22-Q23),0) -> 240 | R24: =IFERROR(MAX(0,Q24+R22-R23),0) -> 278 | S24: =IFERROR(MAX(0,R24+S22-S23),0) -> 321 | T24: =IFERROR(MAX(0,S24+T22-T23),0) -> 371 | U24: =IFERROR(MAX(0,T24+U22-U23),0) -> 428 | V24: =IFERROR(MAX(0,U24+V22-V23),0) -> 493 | W24: =IFERROR(MAX(0,V24+W22-W23),0) -> 568 | ... Z24: =IFERROR(MAX(0,Y24+Z22-Z23),0) -> 870 | AA24: =Z24 -> 870 | AB24: =IFERROR(MAX(0,Z24+AB22-AB23),0) -> 1003 | AC24: =IFERROR(MAX(0,AB24+AC22-AC23),0) -> 1156 | AD24: =IFERROR(MAX(0,AC24+AD22-AD23),0) -> 1332 | AE24: =IFERROR(MAX(0,AD24+AE22-AE23),0) -> 1534 | AF24: =IFERROR(MAX(0,AE24+AF22-AF23),0) -> 1766 | AG24: =IFERROR(MAX(0,AF24+AG22-AG23),0) -> 2033 | AH24: =IFERROR(MAX(0,AG24+AH22-AH23),0) -> 2339 | AI24: =IFERROR(MAX(0,AH24+AI22-AI23),0) -> 2691 | AJ24: =IFERROR(MAX(0,AI24+AJ22-AJ23),0) -> 3096 | ... AM24: =IFERROR(MAX(0,AL24+AM22-AM23),0) -> 4714 | AN24: =AM24 -> 4714 | AO24: =IFERROR(MAX(0,AM24+AO22-AO23),0) -> 5423 | AP24: =IFERROR(MAX(0,AO24+AP22-AP23),0) -> 6238 | AQ24: =IFERROR(MAX(0,AP24+AQ22-AQ23),0) -> 7174 | AR24: =IFERROR(MAX(0,AQ24+AR22-AR23),0) -> 8251 | AS24: =IFERROR(MAX(0,AR24+AS22-AS23),0) -> 9489 | AT24: =IFERROR(MAX(0,AS24+AT22-AT23),0) -> 10912 | AU24: =IFERROR(MAX(0,AT24+AU22-AU23),0) -> 12549 | AV24: =IFERROR(MAX(0,AU24+AV22-AV23),0) -> 14431 | AW24: =IFERROR(MAX(0,AV24+AW22-AW23),0) -> 16595 | ... AZ24: =IFERROR(MAX(0,AY24+AZ22-AZ23),0) -> 25238 | BA24: =AZ24 -> 25238 | BB24: =IFERROR(MAX(0,AZ24+BB22-BB23),0) -> 29024 | BC24: =IFERROR(MAX(0,BB24+BC22-BC23),0) -> 33379 | BD24: =IFERROR(MAX(0,BC24+BD22-BD23),0) -> 38386 | BE24: =IFERROR(MAX(0,BD24+BE22-BE23),0) -> 44144 | BF24: =IFERROR(MAX(0,BE24+BF22-BF23),0) -> 50766 | BG24: =IFERROR(MAX(0,BF24+BG22-BG23),0) -> 58382 | BH24: =IFERROR(MAX(0,BG24+BH22-BH23),0) -> 67140 | BI24: =IFERROR(MAX(0,BH24+BI22-BI23),0) -> 77212 | BJ24: =IFERROR(MAX(0,BI24+BJ22-BJ23),0) -> 88795 | ... BM24: =IFERROR(MAX(0,BL24+BM22-BM23),0) -> 135048 | BN24: =BM24 -> 135048
A25: Monthly ARPU (£) | B25: =ASSUMPTIONS!$B$29 -> 299 | C25: =ASSUMPTIONS!$B$29 -> 299 | D25: =ASSUMPTIONS!$B$29 -> 299 | E25: =ASSUMPTIONS!$B$29 -> 299 | F25: =ASSUMPTIONS!$B$29 -> 299 | G25: =ASSUMPTIONS!$B$29 -> 299 | H25: =ASSUMPTIONS!$B$29 -> 299 | I25: =ASSUMPTIONS!$B$29 -> 299 | ... M25: =ASSUMPTIONS!$B$29 -> 299 | N25: =M25 -> 299 | O25: =ASSUMPTIONS!$C$29 -> 299 | P25: =ASSUMPTIONS!$C$29 -> 299 | Q25: =ASSUMPTIONS!$C$29 -> 299 | R25: =ASSUMPTIONS!$C$29 -> 299 | S25: =ASSUMPTIONS!$C$29 -> 299 | T25: =ASSUMPTIONS!$C$29 -> 299 | U25: =ASSUMPTIONS!$C$29 -> 299 | V25: =ASSUMPTIONS!$C$29 -> 299 | ... Z25: =ASSUMPTIONS!$C$29 -> 299 | AA25: =Z25 -> 299 | AB25: =ASSUMPTIONS!$D$29 -> 299 | AC25: =ASSUMPTIONS!$D$29 -> 299 | AD25: =ASSUMPTIONS!$D$29 -> 299 | AE25: =ASSUMPTIONS!$D$29 -> 299 | AF25: =ASSUMPTIONS!$D$29 -> 299 | AG25: =ASSUMPTIONS!$D$29 -> 299 | AH25: =ASSUMPTIONS!$D$29 -> 299 | AI25: =ASSUMPTIONS!$D$29 -> 299 | ... AM25: =ASSUMPTIONS!$D$29 -> 299 | AN25: =AM25 -> 299 | AO25: =ASSUMPTIONS!$E$29 -> 299 | AP25: =ASSUMPTIONS!$E$29 -> 299 | AQ25: =ASSUMPTIONS!$E$29 -> 299 | AR25: =ASSUMPTIONS!$E$29 -> 299 | AS25: =ASSUMPTIONS!$E$29 -> 299 | AT25: =ASSUMPTIONS!$E$29 -> 299 | AU25: =ASSUMPTIONS!$E$29 -> 299 | AV25: =ASSUMPTIONS!$E$29 -> 299 | ... AZ25: =ASSUMPTIONS!$E$29 -> 299 | BA25: =AZ25 -> 299 | BB25: =ASSUMPTIONS!$F$29 -> 299 | BC25: =ASSUMPTIONS!$F$29 -> 299 | BD25: =ASSUMPTIONS!$F$29 -> 299 | BE25: =ASSUMPTIONS!$F$29 -> 299 | BF25: =ASSUMPTIONS!$F$29 -> 299 | BG25: =ASSUMPTIONS!$F$29 -> 299 | BH25: =ASSUMPTIONS!$F$29 -> 299 | BI25: =ASSUMPTIONS!$F$29 -> 299 | ... BM25: =ASSUMPTIONS!$F$29 -> 299 | BN25: =BM25 -> 299
A26: TOTAL SAAS REVENUE (£) | B26: =IFERROR(B24*ASSUMPTIONS!$B$29,0) -> 7475 | C26: =IFERROR(C24*ASSUMPTIONS!$B$29,0) -> 8970 | D26: =IFERROR(D24*ASSUMPTIONS!$B$29,0) -> 10764 | E26: =IFERROR(E24*ASSUMPTIONS!$B$29,0) -> 12857 | F26: =IFERROR(F24*ASSUMPTIONS!$B$29,0) -> 15249 | G26: =IFERROR(G24*ASSUMPTIONS!$B$29,0) -> 17940 | H26: =IFERROR(H24*ASSUMPTIONS!$B$29,0) -> 21229 | I26: =IFERROR(I24*ASSUMPTIONS!$B$29,0) -> 25116 | ... M26: =IFERROR(M24*ASSUMPTIONS!$B$29,0) -> 46046 | N26: =SUM(B26:M26) -> 268801 | O26: =IFERROR(O24*ASSUMPTIONS!$C$29,0) -> 53521 | P26: =IFERROR(P24*ASSUMPTIONS!$C$29,0) -> 61893 | Q26: =IFERROR(Q24*ASSUMPTIONS!$C$29,0) -> 71760 | R26: =IFERROR(R24*ASSUMPTIONS!$C$29,0) -> 83122 | S26: =IFERROR(S24*ASSUMPTIONS!$C$29,0) -> 95979 | T26: =IFERROR(T24*ASSUMPTIONS!$C$29,0) -> 110929 | U26: =IFERROR(U24*ASSUMPTIONS!$C$29,0) -> 127972 | V26: =IFERROR(V24*ASSUMPTIONS!$C$29,0) -> 147407 | ... Z26: =IFERROR(Z24*ASSUMPTIONS!$C$29,0) -> 260130 | AA26: =SUM(O26:Z26) -> 1604135 | AB26: =IFERROR(AB24*ASSUMPTIONS!$D$29,0) -> 299897 | AC26: =IFERROR(AC24*ASSUMPTIONS!$D$29,0) -> 345644 | AD26: =IFERROR(AD24*ASSUMPTIONS!$D$29,0) -> 398268 | AE26: =IFERROR(AE24*ASSUMPTIONS!$D$29,0) -> 458666 | AF26: =IFERROR(AF24*ASSUMPTIONS!$D$29,0) -> 528034 | AG26: =IFERROR(AG24*ASSUMPTIONS!$D$29,0) -> 607867 | AH26: =IFERROR(AH24*ASSUMPTIONS!$D$29,0) -> 699361 | AI26: =IFERROR(AI24*ASSUMPTIONS!$D$29,0) -> 804609 | ... AM26: =IFERROR(AM24*ASSUMPTIONS!$D$29,0) -> 1409486 | AN26: =SUM(AB26:AM26) -> 8767876 | AO26: =IFERROR(AO24*ASSUMPTIONS!$E$29,0) -> 1621477 | AP26: =IFERROR(AP24*ASSUMPTIONS!$E$29,0) -> 1865162 | AQ26: =IFERROR(AQ24*ASSUMPTIONS!$E$29,0) -> 2145026 | AR26: =IFERROR(AR24*ASSUMPTIONS!$E$29,0) -> 2467049 | AS26: =IFERROR(AS24*ASSUMPTIONS!$E$29,0) -> 2837211 | AT26: =IFERROR(AT24*ASSUMPTIONS!$E$29,0) -> 3262688 | AU26: =IFERROR(AU24*ASSUMPTIONS!$E$29,0) -> 3752151 | AV26: =IFERROR(AV24*ASSUMPTIONS!$E$29,0) -> 4314869 | ... AZ26: =IFERROR(AZ24*ASSUMPTIONS!$E$29,0) -> 7546162 | BA26: =SUM(AO26:AZ26) -> 47041670 | BB26: =IFERROR(BB24*ASSUMPTIONS!$F$29,0) -> 8678176 | BC26: =IFERROR(BC24*ASSUMPTIONS!$F$29,0) -> 9980321 | BD26: =IFERROR(BD24*ASSUMPTIONS!$F$29,0) -> 11477414 | BE26: =IFERROR(BE24*ASSUMPTIONS!$F$29,0) -> 13199056 | BF26: =IFERROR(BF24*ASSUMPTIONS!$F$29,0) -> 15179034 | BG26: =IFERROR(BG24*ASSUMPTIONS!$F$29,0) -> 17456218 | BH26: =IFERROR(BH24*ASSUMPTIONS!$F$29,0) -> 20074860 | BI26: =IFERROR(BI24*ASSUMPTIONS!$F$29,0) -> 23086388 | ... BM26: =IFERROR(BM24*ASSUMPTIONS!$F$29,0) -> 40379352 | BN26: =SUM(BB26:BM26) -> 251705376
A28: TOTAL REVENUE SUMMARY
A29: Marketplace Revenue (£) | B29: =B19 -> 16275 | C29: =C19 -> 15058 | D29: =D19 -> 15849 | E29: =E19 -> 16875 | F29: =F19 -> 18036 | G29: =G19 -> 19332 | H29: =H19 -> 20763 | I29: =I19 -> 22383 | ... M29: =M19 -> 30861 | N29: =SUM(B29:M29) -> 254218 | O29: =O19 -> 33588 | P29: =P19 -> 36612 | Q29: =Q19 -> 39933 | R29: =R19 -> 43605 | S29: =S19 -> 47655 | T29: =T19 -> 52137 | U29: =U19 -> 57051 | V29: =V19 -> 62478 | ... Z29: =Z19 -> 90396 | AA29: =SUM(O29:Z29) -> 689391 | AB29: =AB19 -> 99252 | AC29: =AC19 -> 108999 | AD29: =AD19 -> 119745 | AE29: =AE19 -> 131571 | AF29: =AF19 -> 144585 | AG29: =AG19 -> 158922 | AH29: =AH19 -> 174717 | AI29: =AI19 -> 192078 | ... AM29: =AM19 -> 280827 | AN29: =SUM(AB29:AM29) -> 2109483 | AO29: =AO19 -> 308853 | AP29: =AP19 -> 339687 | AQ29: =AQ19 -> 373599 | AR29: =AR19 -> 410913 | AS29: =AS19 -> 451953 | AT29: =AT19 -> 497097 | AU29: =AU19 -> 546750 | AV29: =AV19 -> 601371 | ... AZ29: =AZ19 -> 880335 | BA29: =SUM(AO29:AZ29) -> 6599961 | BB29: =BB19 -> 968355 | BC29: =BC19 -> 1065177 | BD29: =BD19 -> 1171665 | BE29: =BE19 -> 1288818 | BF29: =BF19 -> 1417689 | BG29: =BG19 -> 1559466 | BH29: =BH19 -> 1715418 | BI29: =BI19 -> 1886949 | ... BM29: =BM19 -> 2762640 | BN29: =SUM(BB29:BM29) -> 20706543
A30: SaaS Revenue (£) | B30: =B26 -> 7475 | C30: =C26 -> 8970 | D30: =D26 -> 10764 | E30: =E26 -> 12857 | F30: =F26 -> 15249 | G30: =G26 -> 17940 | H30: =H26 -> 21229 | I30: =I26 -> 25116 | ... M30: =M26 -> 46046 | N30: =SUM(B30:M30) -> 268801 | O30: =O26 -> 53521 | P30: =P26 -> 61893 | Q30: =Q26 -> 71760 | R30: =R26 -> 83122 | S30: =S26 -> 95979 | T30: =T26 -> 110929 | U30: =U26 -> 127972 | V30: =V26 -> 147407 | ... Z30: =Z26 -> 260130 | AA30: =SUM(O30:Z30) -> 1604135 | AB30: =AB26 -> 299897 | AC30: =AC26 -> 345644 | AD30: =AD26 -> 398268 | AE30: =AE26 -> 458666 | AF30: =AF26 -> 528034 | AG30: =AG26 -> 607867 | AH30: =AH26 -> 699361 | AI30: =AI26 -> 804609 | ... AM30: =AM26 -> 1409486 | AN30: =SUM(AB30:AM30) -> 8767876 | AO30: =AO26 -> 1621477 | AP30: =AP26 -> 1865162 | AQ30: =AQ26 -> 2145026 | AR30: =AR26 -> 2467049 | AS30: =AS26 -> 2837211 | AT30: =AT26 -> 3262688 | AU30: =AU26 -> 3752151 | AV30: =AV26 -> 4314869 | ... AZ30: =AZ26 -> 7546162 | BA30: =SUM(AO30:AZ30) -> 47041670 | BB30: =BB26 -> 8678176 | BC30: =BC26 -> 9980321 | BD30: =BD26 -> 11477414 | BE30: =BE26 -> 13199056 | BF30: =BF26 -> 15179034 | BG30: =BG26 -> 17456218 | BH30: =BH26 -> 20074860 | BI30: =BI26 -> 23086388 | ... BM30: =BM26 -> 40379352 | BN30: =SUM(BB30:BM30) -> 251705376
A31: TOTAL REVENUE (£) | B31: =IFERROR(B19+B26,0) -> 23750 | C31: =IFERROR(C19+C26,0) -> 24028 | D31: =IFERROR(D19+D26,0) -> 26613 | E31: =IFERROR(E19+E26,0) -> 29732 | F31: =IFERROR(F19+F26,0) -> 33285 | G31: =IFERROR(G19+G26,0) -> 37272 | H31: =IFERROR(H19+H26,0) -> 41992 | I31: =IFERROR(I19+I26,0) -> 47499 | ... M31: =IFERROR(M19+M26,0) -> 76907 | N31: =SUM(B31:M31) -> 523019 | O31: =IFERROR(O19+O26,0) -> 87109 | P31: =IFERROR(P19+P26,0) -> 98505 | Q31: =IFERROR(Q19+Q26,0) -> 111693 | R31: =IFERROR(R19+R26,0) -> 126727 | S31: =IFERROR(S19+S26,0) -> 143634 | T31: =IFERROR(T19+T26,0) -> 163066 | U31: =IFERROR(U19+U26,0) -> 185023 | V31: =IFERROR(V19+V26,0) -> 209885 | ... Z31: =IFERROR(Z19+Z26,0) -> 350526 | AA31: =SUM(O31:Z31) -> 2293526 | AB31: =IFERROR(AB19+AB26,0) -> 399149 | AC31: =IFERROR(AC19+AC26,0) -> 454643 | AD31: =IFERROR(AD19+AD26,0) -> 518013 | AE31: =IFERROR(AE19+AE26,0) -> 590237 | AF31: =IFERROR(AF19+AF26,0) -> 672619 | AG31: =IFERROR(AG19+AG26,0) -> 766789 | AH31: =IFERROR(AH19+AH26,0) -> 874078 | AI31: =IFERROR(AI19+AI26,0) -> 996687 | ... AM31: =IFERROR(AM19+AM26,0) -> 1690313 | AN31: =SUM(AB31:AM31) -> 10877359 | AO31: =IFERROR(AO19+AO26,0) -> 1930330 | AP31: =IFERROR(AP19+AP26,0) -> 2204849 | AQ31: =IFERROR(AQ19+AQ26,0) -> 2518625 | AR31: =IFERROR(AR19+AR26,0) -> 2877962 | AS31: =IFERROR(AS19+AS26,0) -> 3289164 | AT31: =IFERROR(AT19+AT26,0) -> 3759785 | AU31: =IFERROR(AU19+AU26,0) -> 4298901 | AV31: =IFERROR(AV19+AV26,0) -> 4916240 | ... AZ31: =IFERROR(AZ19+AZ26,0) -> 8426497 | BA31: =SUM(AO31:AZ31) -> 53641631 | BB31: =IFERROR(BB19+BB26,0) -> 9646531 | BC31: =IFERROR(BC19+BC26,0) -> 11045498 | BD31: =IFERROR(BD19+BD26,0) -> 12649079 | BE31: =IFERROR(BE19+BE26,0) -> 14487874 | BF31: =IFERROR(BF19+BF26,0) -> 16596723 | BG31: =IFERROR(BG19+BG26,0) -> 19015684 | BH31: =IFERROR(BH19+BH26,0) -> 21790278 | BI31: =IFERROR(BI19+BI26,0) -> 24973337 | ... BM31: =IFERROR(BM19+BM26,0) -> 43141992 | BN31: =SUM(BB31:BM31) -> 272411919
A32: Month-on-Month Revenue Growth % | C32: =IFERROR((C29-B29)/B29,0) -> -0.074777266 | D32: =IFERROR((D29-C29)/C29,0) -> 0.052530216 | E32: =IFERROR((E29-D29)/D29,0) -> 0.064735945 | F32: =IFERROR((F29-E29)/E29,0) -> 0.0688 | G32: =IFERROR((G29-F29)/F29,0) -> 0.071856287 | H32: =IFERROR((H29-G29)/G29,0) -> 0.074022346 | I32: =IFERROR((I29-H29)/H29,0) -> 0.078023407 | J32: =IFERROR((J29-I29)/I29,0) -> 0.080820265 | ... M32: =IFERROR((M29-L29)/L29,0) -> 0.086501901 | N32: =M32 -> 0.086501901 | O32: =IFERROR((O29-M29)/M29,0) -> 0.088363955 | P32: =IFERROR((P29-O29)/O29,0) -> 0.090032154 | Q32: =IFERROR((Q29-P29)/P29,0) -> 0.090707965 | R32: =IFERROR((R29-Q29)/Q29,0) -> 0.091954023 | S32: =IFERROR((S29-R29)/R29,0) -> 0.092879257 | T32: =IFERROR((T29-S29)/S29,0) -> 0.094050992 | U32: =IFERROR((U29-T29)/T29,0) -> 0.094251683 | V32: =IFERROR((V29-U29)/U29,0) -> 0.095125414 | W32: =IFERROR((W29-V29)/V29,0) -> 0.09593777 | ... Z32: =IFERROR((Z29-Y29)/Y29,0) -> 0.097345133 | AA32: =Z32 -> 0.097345133 | AB32: =IFERROR((AB29-Z29)/Z29,0) -> 0.097968937 | AC32: =IFERROR((AC29-AB29)/AB29,0) -> 0.09820457 | AD32: =IFERROR((AD29-AC29)/AC29,0) -> 0.09858806 | AE32: =IFERROR((AE29-AD29)/AD29,0) -> 0.098759865 | AF32: =IFERROR((AF29-AE29)/AE29,0) -> 0.098912374 | AG32: =IFERROR((AG29-AF29)/AF29,0) -> 0.099159664 | AH32: =IFERROR((AH29-AG29)/AG29,0) -> 0.099388379 | AI32: =IFERROR((AI29-AH29)/AH29,0) -> 0.099366404 | AJ32: =IFERROR((AJ29-AI29)/AI29,0) -> 0.099522069 | ... AM32: =IFERROR((AM29-AL29)/AL29,0) -> 0.099703954 | AN32: =AM32 -> 0.099703954 | AO32: =IFERROR((AO29-AM29)/AM29,0) -> 0.099798096 | AP32: =IFERROR((AP29-AO29)/AO29,0) -> 0.099833902 | AQ32: =IFERROR((AQ29-AP29)/AP29,0) -> 0.099833082 | AR32: =IFERROR((AR29-AQ29)/AQ29,0) -> 0.099877141 | AS32: =IFERROR((AS29-AR29)/AR29,0) -> 0.099875156 | AT32: =IFERROR((AT29-AS29)/AS29,0) -> 0.099886493 | AU32: =IFERROR((AU29-AT29)/AT29,0) -> 0.099885938 | AV32: =IFERROR((AV29-AU29)/AU29,0) -> 0.099901235 | AW32: =IFERROR((AW29-AV29)/AV29,0) -> 0.099941633 | ... AZ32: =IFERROR((AZ29-AY29)/AY29,0) -> 0.099959517 | BA32: =AZ32 -> 0.099959517 | BB32: =IFERROR((BB29-AZ29)/AZ29,0) -> 0.099984665 | BC32: =IFERROR((BC29-BB29)/BB29,0) -> 0.099986059 | BD32: =IFERROR((BD29-BC29)/BC29,0) -> 0.099972117 | BE32: =IFERROR((BE29-BD29)/BD29,0) -> 0.099988478 | BF32: =IFERROR((BF29-BE29)/BE29,0) -> 0.09999162 | BG32: =IFERROR((BG29-BF29)/BF29,0) -> 0.10000571 | BH32: =IFERROR((BH29-BG29)/BG29,0) -> 0.10000346 | BI32: =IFERROR((BI29-BH29)/BH29,0) -> 0.099993704 | BJ32: =IFERROR((BJ29-BI29)/BI29,0) -> 0.10000429 | ... BM32: =IFERROR((BM29-BL29)/BL29,0) -> 0.099990325 | BN32: =BM32 -> 0.099990325
A34: COST OF GOODS SOLD (COGS)
A35: Payment Processing (% of GMV) | B35: =IFERROR(B16*ASSUMPTIONS!$B$39,0) -> 1890 | C35: =IFERROR(C16*ASSUMPTIONS!$B$39,0) -> 1994.4 | D35: =IFERROR(D16*ASSUMPTIONS!$B$39,0) -> 2113.2 | E35: =IFERROR(E16*ASSUMPTIONS!$B$39,0) -> 2250 | F35: =IFERROR(F16*ASSUMPTIONS!$B$39,0) -> 2404.8 | G35: =IFERROR(G16*ASSUMPTIONS!$B$39,0) -> 2577.6 | H35: =IFERROR(H16*ASSUMPTIONS!$B$39,0) -> 2768.4 | I35: =IFERROR(I16*ASSUMPTIONS!$B$39,0) -> 2984.4 | ... M35: =IFERROR(M16*ASSUMPTIONS!$B$39,0) -> 4114.8 | N35: =SUM(B35:M35) -> 33602.4 | O35: =IFERROR(O16*ASSUMPTIONS!$C$39,0) -> 4478.4 | P35: =IFERROR(P16*ASSUMPTIONS!$C$39,0) -> 4881.6 | Q35: =IFERROR(Q16*ASSUMPTIONS!$C$39,0) -> 5324.4 | R35: =IFERROR(R16*ASSUMPTIONS!$C$39,0) -> 5814 | S35: =IFERROR(S16*ASSUMPTIONS!$C$39,0) -> 6354 | T35: =IFERROR(T16*ASSUMPTIONS!$C$39,0) -> 6951.6 | U35: =IFERROR(U16*ASSUMPTIONS!$C$39,0) -> 7606.8 | V35: =IFERROR(V16*ASSUMPTIONS!$C$39,0) -> 8330.4 | ... Z35: =IFERROR(Z16*ASSUMPTIONS!$C$39,0) -> 12052.8 | AA35: =SUM(O35:Z35) -> 91918.8 | AB35: =IFERROR(AB16*ASSUMPTIONS!$D$39,0) -> 13233.6 | AC35: =IFERROR(AC16*ASSUMPTIONS!$D$39,0) -> 14533.2 | AD35: =IFERROR(AD16*ASSUMPTIONS!$D$39,0) -> 15966 | AE35: =IFERROR(AE16*ASSUMPTIONS!$D$39,0) -> 17542.8 | AF35: =IFERROR(AF16*ASSUMPTIONS!$D$39,0) -> 19278 | AG35: =IFERROR(AG16*ASSUMPTIONS!$D$39,0) -> 21189.6 | AH35: =IFERROR(AH16*ASSUMPTIONS!$D$39,0) -> 23295.6 | AI35: =IFERROR(AI16*ASSUMPTIONS!$D$39,0) -> 25610.4 | ... AM35: =IFERROR(AM16*ASSUMPTIONS!$D$39,0) -> 37443.6 | AN35: =SUM(AB35:AM35) -> 281264.4 | AO35: =IFERROR(AO16*ASSUMPTIONS!$E$39,0) -> 41180.4 | AP35: =IFERROR(AP16*ASSUMPTIONS!$E$39,0) -> 45291.6 | AQ35: =IFERROR(AQ16*ASSUMPTIONS!$E$39,0) -> 49813.2 | AR35: =IFERROR(AR16*ASSUMPTIONS!$E$39,0) -> 54788.4 | AS35: =IFERROR(AS16*ASSUMPTIONS!$E$39,0) -> 60260.4 | AT35: =IFERROR(AT16*ASSUMPTIONS!$E$39,0) -> 66279.6 | AU35: =IFERROR(AU16*ASSUMPTIONS!$E$39,0) -> 72900 | AV35: =IFERROR(AV16*ASSUMPTIONS!$E$39,0) -> 80182.8 | ... AZ35: =IFERROR(AZ16*ASSUMPTIONS!$E$39,0) -> 117378 | BA35: =SUM(AO35:AZ35) -> 879994.8 | BB35: =IFERROR(BB16*ASSUMPTIONS!$F$39,0) -> 129114 | BC35: =IFERROR(BC16*ASSUMPTIONS!$F$39,0) -> 142023.6 | BD35: =IFERROR(BD16*ASSUMPTIONS!$F$39,0) -> 156222 | BE35: =IFERROR(BE16*ASSUMPTIONS!$F$39,0) -> 171842.4 | BF35: =IFERROR(BF16*ASSUMPTIONS!$F$39,0) -> 189025.2 | BG35: =IFERROR(BG16*ASSUMPTIONS!$F$39,0) -> 207928.8 | BH35: =IFERROR(BH16*ASSUMPTIONS!$F$39,0) -> 228722.4 | BI35: =IFERROR(BI16*ASSUMPTIONS!$F$39,0) -> 251593.2 | ... BM35: =IFERROR(BM16*ASSUMPTIONS!$F$39,0) -> 368352 | BN35: =SUM(BB35:BM35) -> 2760872.4
A36: Cloud Infrastructure — Fixed | B36: =IFERROR(ASSUMPTIONS!$B$40,0) -> 2000 | C36: =IFERROR(ASSUMPTIONS!$B$40,0) -> 2000 | D36: =IFERROR(ASSUMPTIONS!$B$40,0) -> 2000 | E36: =IFERROR(ASSUMPTIONS!$B$40,0) -> 2000 | F36: =IFERROR(ASSUMPTIONS!$B$40,0) -> 2000 | G36: =IFERROR(ASSUMPTIONS!$B$40,0) -> 2000 | H36: =IFERROR(ASSUMPTIONS!$B$40,0) -> 2000 | I36: =IFERROR(ASSUMPTIONS!$B$40,0) -> 2000 | ... M36: =IFERROR(ASSUMPTIONS!$B$40,0) -> 2000 | N36: =SUM(B36:M36) -> 24000 | O36: =IFERROR(ASSUMPTIONS!$C$40,0) -> 2000 | P36: =IFERROR(ASSUMPTIONS!$C$40,0) -> 2000 | Q36: =IFERROR(ASSUMPTIONS!$C$40,0) -> 2000 | R36: =IFERROR(ASSUMPTIONS!$C$40,0) -> 2000 | S36: =IFERROR(ASSUMPTIONS!$C$40,0) -> 2000 | T36: =IFERROR(ASSUMPTIONS!$C$40,0) -> 2000 | U36: =IFERROR(ASSUMPTIONS!$C$40,0) -> 2000 | V36: =IFERROR(ASSUMPTIONS!$C$40,0) -> 2000 | ... Z36: =IFERROR(ASSUMPTIONS!$C$40,0) -> 2000 | AA36: =SUM(O36:Z36) -> 24000 | AB36: =IFERROR(ASSUMPTIONS!$D$40,0) -> 2000 | AC36: =IFERROR(ASSUMPTIONS!$D$40,0) -> 2000 | AD36: =IFERROR(ASSUMPTIONS!$D$40,0) -> 2000 | AE36: =IFERROR(ASSUMPTIONS!$D$40,0) -> 2000 | AF36: =IFERROR(ASSUMPTIONS!$D$40,0) -> 2000 | AG36: =IFERROR(ASSUMPTIONS!$D$40,0) -> 2000 | AH36: =IFERROR(ASSUMPTIONS!$D$40,0) -> 2000 | AI36: =IFERROR(ASSUMPTIONS!$D$40,0) -> 2000 | ... AM36: =IFERROR(ASSUMPTIONS!$D$40,0) -> 2000 | AN36: =SUM(AB36:AM36) -> 24000 | AO36: =IFERROR(ASSUMPTIONS!$E$40,0) -> 2000 | AP36: =IFERROR(ASSUMPTIONS!$E$40,0) -> 2000 | AQ36: =IFERROR(ASSUMPTIONS!$E$40,0) -> 2000 | AR36: =IFERROR(ASSUMPTIONS!$E$40,0) -> 2000 | AS36: =IFERROR(ASSUMPTIONS!$E$40,0) -> 2000 | AT36: =IFERROR(ASSUMPTIONS!$E$40,0) -> 2000 | AU36: =IFERROR(ASSUMPTIONS!$E$40,0) -> 2000 | AV36: =IFERROR(ASSUMPTIONS!$E$40,0) -> 2000 | ... AZ36: =IFERROR(ASSUMPTIONS!$E$40,0) -> 2000 | BA36: =SUM(AO36:AZ36) -> 24000 | BB36: =IFERROR(ASSUMPTIONS!$F$40,0) -> 2000 | BC36: =IFERROR(ASSUMPTIONS!$F$40,0) -> 2000 | BD36: =IFERROR(ASSUMPTIONS!$F$40,0) -> 2000 | BE36: =IFERROR(ASSUMPTIONS!$F$40,0) -> 2000 | BF36: =IFERROR(ASSUMPTIONS!$F$40,0) -> 2000 | BG36: =IFERROR(ASSUMPTIONS!$F$40,0) -> 2000 | BH36: =IFERROR(ASSUMPTIONS!$F$40,0) -> 2000 | BI36: =IFERROR(ASSUMPTIONS!$F$40,0) -> 2000 | ... BM36: =IFERROR(ASSUMPTIONS!$F$40,0) -> 2000 | BN36: =SUM(BB36:BM36) -> 24000
A37: Cloud Infrastructure — Variable | B37: =IFERROR(IFERROR(B16/ASSUMPTIONS!$B$15,0)*ASSUMPTIONS!$B$41/1000,0) -> 31.5 | C37: =IFERROR(IFERROR(C16/ASSUMPTIONS!$B$15,0)*ASSUMPTIONS!$B$41/1000,0) -> 33.24 | D37: =IFERROR(IFERROR(D16/ASSUMPTIONS!$B$15,0)*ASSUMPTIONS!$B$41/1000,0) -> 35.22 | E37: =IFERROR(IFERROR(E16/ASSUMPTIONS!$B$15,0)*ASSUMPTIONS!$B$41/1000,0) -> 37.5 | F37: =IFERROR(IFERROR(F16/ASSUMPTIONS!$B$15,0)*ASSUMPTIONS!$B$41/1000,0) -> 40.08 | G37: =IFERROR(IFERROR(G16/ASSUMPTIONS!$B$15,0)*ASSUMPTIONS!$B$41/1000,0) -> 42.96 | H37: =IFERROR(IFERROR(H16/ASSUMPTIONS!$B$15,0)*ASSUMPTIONS!$B$41/1000,0) -> 46.14 | I37: =IFERROR(IFERROR(I16/ASSUMPTIONS!$B$15,0)*ASSUMPTIONS!$B$41/1000,0) -> 49.74 | ... M37: =IFERROR(IFERROR(M16/ASSUMPTIONS!$B$15,0)*ASSUMPTIONS!$B$41/1000,0) -> 68.58 | N37: =SUM(B37:M37) -> 560.04 | O37: =IFERROR(IFERROR(O16/ASSUMPTIONS!$C$15,0)*ASSUMPTIONS!$C$41/1000,0) -> 74.64 | P37: =IFERROR(IFERROR(P16/ASSUMPTIONS!$C$15,0)*ASSUMPTIONS!$C$41/1000,0) -> 81.36 | Q37: =IFERROR(IFERROR(Q16/ASSUMPTIONS!$C$15,0)*ASSUMPTIONS!$C$41/1000,0) -> 88.74 | R37: =IFERROR(IFERROR(R16/ASSUMPTIONS!$C$15,0)*ASSUMPTIONS!$C$41/1000,0) -> 96.9 | S37: =IFERROR(IFERROR(S16/ASSUMPTIONS!$C$15,0)*ASSUMPTIONS!$C$41/1000,0) -> 105.9 | T37: =IFERROR(IFERROR(T16/ASSUMPTIONS!$C$15,0)*ASSUMPTIONS!$C$41/1000,0) -> 115.86 | U37: =IFERROR(IFERROR(U16/ASSUMPTIONS!$C$15,0)*ASSUMPTIONS!$C$41/1000,0) -> 126.78 | V37: =IFERROR(IFERROR(V16/ASSUMPTIONS!$C$15,0)*ASSUMPTIONS!$C$41/1000,0) -> 138.84 | ... Z37: =IFERROR(IFERROR(Z16/ASSUMPTIONS!$C$15,0)*ASSUMPTIONS!$C$41/1000,0) -> 200.88 | AA37: =SUM(O37:Z37) -> 1531.98 | AB37: =IFERROR(IFERROR(AB16/ASSUMPTIONS!$D$15,0)*ASSUMPTIONS!$D$41/1000,0) -> 220.56 | AC37: =IFERROR(IFERROR(AC16/ASSUMPTIONS!$D$15,0)*ASSUMPTIONS!$D$41/1000,0) -> 242.22 | AD37: =IFERROR(IFERROR(AD16/ASSUMPTIONS!$D$15,0)*ASSUMPTIONS!$D$41/1000,0) -> 266.1 | AE37: =IFERROR(IFERROR(AE16/ASSUMPTIONS!$D$15,0)*ASSUMPTIONS!$D$41/1000,0) -> 292.38 | AF37: =IFERROR(IFERROR(AF16/ASSUMPTIONS!$D$15,0)*ASSUMPTIONS!$D$41/1000,0) -> 321.3 | AG37: =IFERROR(IFERROR(AG16/ASSUMPTIONS!$D$15,0)*ASSUMPTIONS!$D$41/1000,0) -> 353.16 | AH37: =IFERROR(IFERROR(AH16/ASSUMPTIONS!$D$15,0)*ASSUMPTIONS!$D$41/1000,0) -> 388.26 | AI37: =IFERROR(IFERROR(AI16/ASSUMPTIONS!$D$15,0)*ASSUMPTIONS!$D$41/1000,0) -> 426.84 | ... AM37: =IFERROR(IFERROR(AM16/ASSUMPTIONS!$D$15,0)*ASSUMPTIONS!$D$41/1000,0) -> 624.06 | AN37: =SUM(AB37:AM37) -> 4687.74 | AO37: =IFERROR(IFERROR(AO16/ASSUMPTIONS!$E$15,0)*ASSUMPTIONS!$E$41/1000,0) -> 686.34 | AP37: =IFERROR(IFERROR(AP16/ASSUMPTIONS!$E$15,0)*ASSUMPTIONS!$E$41/1000,0) -> 754.86 | AQ37: =IFERROR(IFERROR(AQ16/ASSUMPTIONS!$E$15,0)*ASSUMPTIONS!$E$41/1000,0) -> 830.22 | AR37: =IFERROR(IFERROR(AR16/ASSUMPTIONS!$E$15,0)*ASSUMPTIONS!$E$41/1000,0) -> 913.14 | AS37: =IFERROR(IFERROR(AS16/ASSUMPTIONS!$E$15,0)*ASSUMPTIONS!$E$41/1000,0) -> 1004.34 | AT37: =IFERROR(IFERROR(AT16/ASSUMPTIONS!$E$15,0)*ASSUMPTIONS!$E$41/1000,0) -> 1104.66 | AU37: =IFERROR(IFERROR(AU16/ASSUMPTIONS!$E$15,0)*ASSUMPTIONS!$E$41/1000,0) -> 1215 | AV37: =IFERROR(IFERROR(AV16/ASSUMPTIONS!$E$15,0)*ASSUMPTIONS!$E$41/1000,0) -> 1336.38 | ... AZ37: =IFERROR(IFERROR(AZ16/ASSUMPTIONS!$E$15,0)*ASSUMPTIONS!$E$41/1000,0) -> 1956.3 | BA37: =SUM(AO37:AZ37) -> 14666.58 | BB37: =IFERROR(IFERROR(BB16/ASSUMPTIONS!$F$15,0)*ASSUMPTIONS!$F$41/1000,0) -> 2151.9 | BC37: =IFERROR(IFERROR(BC16/ASSUMPTIONS!$F$15,0)*ASSUMPTIONS!$F$41/1000,0) -> 2367.06 | BD37: =IFERROR(IFERROR(BD16/ASSUMPTIONS!$F$15,0)*ASSUMPTIONS!$F$41/1000,0) -> 2603.7 | BE37: =IFERROR(IFERROR(BE16/ASSUMPTIONS!$F$15,0)*ASSUMPTIONS!$F$41/1000,0) -> 2864.04 | BF37: =IFERROR(IFERROR(BF16/ASSUMPTIONS!$F$15,0)*ASSUMPTIONS!$F$41/1000,0) -> 3150.42 | BG37: =IFERROR(IFERROR(BG16/ASSUMPTIONS!$F$15,0)*ASSUMPTIONS!$F$41/1000,0) -> 3465.48 | BH37: =IFERROR(IFERROR(BH16/ASSUMPTIONS!$F$15,0)*ASSUMPTIONS!$F$41/1000,0) -> 3812.04 | BI37: =IFERROR(IFERROR(BI16/ASSUMPTIONS!$F$15,0)*ASSUMPTIONS!$F$41/1000,0) -> 4193.22 | ... BM37: =IFERROR(IFERROR(BM16/ASSUMPTIONS!$F$15,0)*ASSUMPTIONS!$F$41/1000,0) -> 6139.2 | BN37: =SUM(BB37:BM37) -> 46014.54
A38: Customer Support & Operations | B38: =IFERROR((B9+B13)/100*ASSUMPTIONS!$B$42,0) -> 2835 | C38: =IFERROR((C9+C13)/100*ASSUMPTIONS!$B$42,0) -> 2780 | D38: =IFERROR((D9+D13)/100*ASSUMPTIONS!$B$42,0) -> 2935 | E38: =IFERROR((E9+E13)/100*ASSUMPTIONS!$B$42,0) -> 3125 | F38: =IFERROR((F9+F13)/100*ASSUMPTIONS!$B$42,0) -> 3340 | G38: =IFERROR((G9+G13)/100*ASSUMPTIONS!$B$42,0) -> 3580 | H38: =IFERROR((H9+H13)/100*ASSUMPTIONS!$B$42,0) -> 3845 | I38: =IFERROR((I9+I13)/100*ASSUMPTIONS!$B$42,0) -> 4145 | ... M38: =IFERROR((M9+M13)/100*ASSUMPTIONS!$B$42,0) -> 5715 | N38: =SUM(B38:M38) -> 46890 | O38: =IFERROR((O9+O13)/100*ASSUMPTIONS!$C$42,0) -> 6220 | P38: =IFERROR((P9+P13)/100*ASSUMPTIONS!$C$42,0) -> 6780 | Q38: =IFERROR((Q9+Q13)/100*ASSUMPTIONS!$C$42,0) -> 7395 | R38: =IFERROR((R9+R13)/100*ASSUMPTIONS!$C$42,0) -> 8075 | S38: =IFERROR((S9+S13)/100*ASSUMPTIONS!$C$42,0) -> 8825 | T38: =IFERROR((T9+T13)/100*ASSUMPTIONS!$C$42,0) -> 9655 | U38: =IFERROR((U9+U13)/100*ASSUMPTIONS!$C$42,0) -> 10565 | V38: =IFERROR((V9+V13)/100*ASSUMPTIONS!$C$42,0) -> 11570 | ... Z38: =IFERROR((Z9+Z13)/100*ASSUMPTIONS!$C$42,0) -> 16740 | AA38: =SUM(O38:Z38) -> 127665 | AB38: =IFERROR((AB9+AB13)/100*ASSUMPTIONS!$D$42,0) -> 18380 | AC38: =IFERROR((AC9+AC13)/100*ASSUMPTIONS!$D$42,0) -> 20185 | AD38: =IFERROR((AD9+AD13)/100*ASSUMPTIONS!$D$42,0) -> 22175 | AE38: =IFERROR((AE9+AE13)/100*ASSUMPTIONS!$D$42,0) -> 24365 | AF38: =IFERROR((AF9+AF13)/100*ASSUMPTIONS!$D$42,0) -> 26775 | AG38: =IFERROR((AG9+AG13)/100*ASSUMPTIONS!$D$42,0) -> 29430 | AH38: =IFERROR((AH9+AH13)/100*ASSUMPTIONS!$D$42,0) -> 32355 | AI38: =IFERROR((AI9+AI13)/100*ASSUMPTIONS!$D$42,0) -> 35570 | ... AM38: =IFERROR((AM9+AM13)/100*ASSUMPTIONS!$D$42,0) -> 52005 | AN38: =SUM(AB38:AM38) -> 390645 | AO38: =IFERROR((AO9+AO13)/100*ASSUMPTIONS!$E$42,0) -> 57195 | AP38: =IFERROR((AP9+AP13)/100*ASSUMPTIONS!$E$42,0) -> 62905 | AQ38: =IFERROR((AQ9+AQ13)/100*ASSUMPTIONS!$E$42,0) -> 69185 | AR38: =IFERROR((AR9+AR13)/100*ASSUMPTIONS!$E$42,0) -> 76095 | AS38: =IFERROR((AS9+AS13)/100*ASSUMPTIONS!$E$42,0) -> 83695 | AT38: =IFERROR((AT9+AT13)/100*ASSUMPTIONS!$E$42,0) -> 92055 | AU38: =IFERROR((AU9+AU13)/100*ASSUMPTIONS!$E$42,0) -> 101250 | AV38: =IFERROR((AV9+AV13)/100*ASSUMPTIONS!$E$42,0) -> 111365 | ... AZ38: =IFERROR((AZ9+AZ13)/100*ASSUMPTIONS!$E$42,0) -> 163025 | BA38: =SUM(AO38:AZ38) -> 1222215 | BB38: =IFERROR((BB9+BB13)/100*ASSUMPTIONS!$F$42,0) -> 179325 | BC38: =IFERROR((BC9+BC13)/100*ASSUMPTIONS!$F$42,0) -> 197255 | BD38: =IFERROR((BD9+BD13)/100*ASSUMPTIONS!$F$42,0) -> 216975 | BE38: =IFERROR((BE9+BE13)/100*ASSUMPTIONS!$F$42,0) -> 238670 | BF38: =IFERROR((BF9+BF13)/100*ASSUMPTIONS!$F$42,0) -> 262535 | BG38: =IFERROR((BG9+BG13)/100*ASSUMPTIONS!$F$42,0) -> 288790 | BH38: =IFERROR((BH9+BH13)/100*ASSUMPTIONS!$F$42,0) -> 317670 | BI38: =IFERROR((BI9+BI13)/100*ASSUMPTIONS!$F$42,0) -> 349435 | ... BM38: =IFERROR((BM9+BM13)/100*ASSUMPTIONS!$F$42,0) -> 511600 | BN38: =SUM(BB38:BM38) -> 3834545
A39: Fraud & Risk (% of GMV) | B39: =IFERROR(B16*ASSUMPTIONS!$B$43,0) -> 189 | C39: =IFERROR(C16*ASSUMPTIONS!$B$43,0) -> 199.44 | D39: =IFERROR(D16*ASSUMPTIONS!$B$43,0) -> 211.32 | E39: =IFERROR(E16*ASSUMPTIONS!$B$43,0) -> 225 | F39: =IFERROR(F16*ASSUMPTIONS!$B$43,0) -> 240.48 | G39: =IFERROR(G16*ASSUMPTIONS!$B$43,0) -> 257.76 | H39: =IFERROR(H16*ASSUMPTIONS!$B$43,0) -> 276.84 | I39: =IFERROR(I16*ASSUMPTIONS!$B$43,0) -> 298.44 | ... M39: =IFERROR(M16*ASSUMPTIONS!$B$43,0) -> 411.48 | N39: =SUM(B39:M39) -> 3360.24 | O39: =IFERROR(O16*ASSUMPTIONS!$C$43,0) -> 447.84 | P39: =IFERROR(P16*ASSUMPTIONS!$C$43,0) -> 488.16 | Q39: =IFERROR(Q16*ASSUMPTIONS!$C$43,0) -> 532.44 | R39: =IFERROR(R16*ASSUMPTIONS!$C$43,0) -> 581.4 | S39: =IFERROR(S16*ASSUMPTIONS!$C$43,0) -> 635.4 | T39: =IFERROR(T16*ASSUMPTIONS!$C$43,0) -> 695.16 | U39: =IFERROR(U16*ASSUMPTIONS!$C$43,0) -> 760.68 | V39: =IFERROR(V16*ASSUMPTIONS!$C$43,0) -> 833.04 | ... Z39: =IFERROR(Z16*ASSUMPTIONS!$C$43,0) -> 1205.28 | AA39: =SUM(O39:Z39) -> 9191.88 | AB39: =IFERROR(AB16*ASSUMPTIONS!$D$43,0) -> 1323.36 | AC39: =IFERROR(AC16*ASSUMPTIONS!$D$43,0) -> 1453.32 | AD39: =IFERROR(AD16*ASSUMPTIONS!$D$43,0) -> 1596.6 | AE39: =IFERROR(AE16*ASSUMPTIONS!$D$43,0) -> 1754.28 | AF39: =IFERROR(AF16*ASSUMPTIONS!$D$43,0) -> 1927.8 | AG39: =IFERROR(AG16*ASSUMPTIONS!$D$43,0) -> 2118.96 | AH39: =IFERROR(AH16*ASSUMPTIONS!$D$43,0) -> 2329.56 | AI39: =IFERROR(AI16*ASSUMPTIONS!$D$43,0) -> 2561.04 | ... AM39: =IFERROR(AM16*ASSUMPTIONS!$D$43,0) -> 3744.36 | AN39: =SUM(AB39:AM39) -> 28126.44 | AO39: =IFERROR(AO16*ASSUMPTIONS!$E$43,0) -> 4118.04 | AP39: =IFERROR(AP16*ASSUMPTIONS!$E$43,0) -> 4529.16 | AQ39: =IFERROR(AQ16*ASSUMPTIONS!$E$43,0) -> 4981.32 | AR39: =IFERROR(AR16*ASSUMPTIONS!$E$43,0) -> 5478.84 | AS39: =IFERROR(AS16*ASSUMPTIONS!$E$43,0) -> 6026.04 | AT39: =IFERROR(AT16*ASSUMPTIONS!$E$43,0) -> 6627.96 | AU39: =IFERROR(AU16*ASSUMPTIONS!$E$43,0) -> 7290 | AV39: =IFERROR(AV16*ASSUMPTIONS!$E$43,0) -> 8018.28 | ... AZ39: =IFERROR(AZ16*ASSUMPTIONS!$E$43,0) -> 11737.8 | BA39: =SUM(AO39:AZ39) -> 87999.48 | BB39: =IFERROR(BB16*ASSUMPTIONS!$F$43,0) -> 12911.4 | BC39: =IFERROR(BC16*ASSUMPTIONS!$F$43,0) -> 14202.36 | BD39: =IFERROR(BD16*ASSUMPTIONS!$F$43,0) -> 15622.2 | BE39: =IFERROR(BE16*ASSUMPTIONS!$F$43,0) -> 17184.24 | BF39: =IFERROR(BF16*ASSUMPTIONS!$F$43,0) -> 18902.52 | BG39: =IFERROR(BG16*ASSUMPTIONS!$F$43,0) -> 20792.88 | BH39: =IFERROR(BH16*ASSUMPTIONS!$F$43,0) -> 22872.24 | BI39: =IFERROR(BI16*ASSUMPTIONS!$F$43,0) -> 25159.32 | ... BM39: =IFERROR(BM16*ASSUMPTIONS!$F$43,0) -> 36835.2 | BN39: =SUM(BB39:BM39) -> 276087.24
A40: TOTAL COGS (£) | B40: =IFERROR(B35+B36+B37+B38+B39,0) -> 6945.5 | C40: =IFERROR(C35+C36+C37+C38+C39,0) -> 7007.08 | D40: =IFERROR(D35+D36+D37+D38+D39,0) -> 7294.74 | E40: =IFERROR(E35+E36+E37+E38+E39,0) -> 7637.5 | F40: =IFERROR(F35+F36+F37+F38+F39,0) -> 8025.36 | G40: =IFERROR(G35+G36+G37+G38+G39,0) -> 8458.32 | H40: =IFERROR(H35+H36+H37+H38+H39,0) -> 8936.38 | I40: =IFERROR(I35+I36+I37+I38+I39,0) -> 9477.58 | ... M40: =IFERROR(M35+M36+M37+M38+M39,0) -> 12309.86 | N40: =SUM(B40:M40) -> 108412.68 | O40: =IFERROR(O35+O36+O37+O38+O39,0) -> 13220.88 | P40: =IFERROR(P35+P36+P37+P38+P39,0) -> 14231.12 | Q40: =IFERROR(Q35+Q36+Q37+Q38+Q39,0) -> 15340.58 | R40: =IFERROR(R35+R36+R37+R38+R39,0) -> 16567.3 | S40: =IFERROR(S35+S36+S37+S38+S39,0) -> 17920.3 | T40: =IFERROR(T35+T36+T37+T38+T39,0) -> 19417.62 | U40: =IFERROR(U35+U36+U37+U38+U39,0) -> 21059.26 | V40: =IFERROR(V35+V36+V37+V38+V39,0) -> 22872.28 | ... Z40: =IFERROR(Z35+Z36+Z37+Z38+Z39,0) -> 32198.96 | AA40: =SUM(O40:Z40) -> 254307.66 | AB40: =IFERROR(AB35+AB36+AB37+AB38+AB39,0) -> 35157.52 | AC40: =IFERROR(AC35+AC36+AC37+AC38+AC39,0) -> 38413.74 | AD40: =IFERROR(AD35+AD36+AD37+AD38+AD39,0) -> 42003.7 | AE40: =IFERROR(AE35+AE36+AE37+AE38+AE39,0) -> 45954.46 | AF40: =IFERROR(AF35+AF36+AF37+AF38+AF39,0) -> 50302.1 | AG40: =IFERROR(AG35+AG36+AG37+AG38+AG39,0) -> 55091.72 | AH40: =IFERROR(AH35+AH36+AH37+AH38+AH39,0) -> 60368.42 | AI40: =IFERROR(AI35+AI36+AI37+AI38+AI39,0) -> 66168.28 | ... AM40: =IFERROR(AM35+AM36+AM37+AM38+AM39,0) -> 95817.02 | AN40: =SUM(AB40:AM40) -> 728723.58 | AO40: =IFERROR(AO35+AO36+AO37+AO38+AO39,0) -> 105179.78 | AP40: =IFERROR(AP35+AP36+AP37+AP38+AP39,0) -> 115480.62 | AQ40: =IFERROR(AQ35+AQ36+AQ37+AQ38+AQ39,0) -> 126809.74 | AR40: =IFERROR(AR35+AR36+AR37+AR38+AR39,0) -> 139275.38 | AS40: =IFERROR(AS35+AS36+AS37+AS38+AS39,0) -> 152985.78 | AT40: =IFERROR(AT35+AT36+AT37+AT38+AT39,0) -> 168067.22 | AU40: =IFERROR(AU35+AU36+AU37+AU38+AU39,0) -> 184655 | AV40: =IFERROR(AV35+AV36+AV37+AV38+AV39,0) -> 202902.46 | ... AZ40: =IFERROR(AZ35+AZ36+AZ37+AZ38+AZ39,0) -> 296097.1 | BA40: =SUM(AO40:AZ40) -> 2228875.9 | BB40: =IFERROR(BB35+BB36+BB37+BB38+BB39,0) -> 325502.3 | BC40: =IFERROR(BC35+BC36+BC37+BC38+BC39,0) -> 357848.02 | BD40: =IFERROR(BD35+BD36+BD37+BD38+BD39,0) -> 393422.9 | BE40: =IFERROR(BE35+BE36+BE37+BE38+BE39,0) -> 432560.68 | BF40: =IFERROR(BF35+BF36+BF37+BF38+BF39,0) -> 475613.14 | BG40: =IFERROR(BG35+BG36+BG37+BG38+BG39,0) -> 522977.16 | BH40: =IFERROR(BH35+BH36+BH37+BH38+BH39,0) -> 575076.68 | BI40: =IFERROR(BI35+BI36+BI37+BI38+BI39,0) -> 632380.74 | ... BM40: =IFERROR(BM35+BM36+BM37+BM38+BM39,0) -> 924926.4 | BN40: =SUM(BB40:BM40) -> 6941519.2
A42: GROSS PROFIT (£) | B42: =IFERROR(B31-B40,0) -> 16804.5 | C42: =IFERROR(C31-C40,0) -> 17020.92 | D42: =IFERROR(D31-D40,0) -> 19318.26 | E42: =IFERROR(E31-E40,0) -> 22094.5 | F42: =IFERROR(F31-F40,0) -> 25259.64 | G42: =IFERROR(G31-G40,0) -> 28813.68 | H42: =IFERROR(H31-H40,0) -> 33055.62 | I42: =IFERROR(I31-I40,0) -> 38021.42 | ... M42: =IFERROR(M31-M40,0) -> 64597.14 | N42: =SUM(B42:M42) -> 414606.32 | O42: =IFERROR(O31-O40,0) -> 73888.12 | P42: =IFERROR(P31-P40,0) -> 84273.88 | Q42: =IFERROR(Q31-Q40,0) -> 96352.42 | R42: =IFERROR(R31-R40,0) -> 110159.7 | S42: =IFERROR(S31-S40,0) -> 125713.7 | T42: =IFERROR(T31-T40,0) -> 143648.38 | U42: =IFERROR(U31-U40,0) -> 163963.74 | V42: =IFERROR(V31-V40,0) -> 187012.72 | ... Z42: =IFERROR(Z31-Z40,0) -> 318327.04 | AA42: =SUM(O42:Z42) -> 2039218.3 | AB42: =IFERROR(AB31-AB40,0) -> 363991.48 | AC42: =IFERROR(AC31-AC40,0) -> 416229.26 | AD42: =IFERROR(AD31-AD40,0) -> 476009.3 | AE42: =IFERROR(AE31-AE40,0) -> 544282.54 | AF42: =IFERROR(AF31-AF40,0) -> 622316.9 | AG42: =IFERROR(AG31-AG40,0) -> 711697.28 | AH42: =IFERROR(AH31-AH40,0) -> 813709.58 | AI42: =IFERROR(AI31-AI40,0) -> 930518.72 | ... AM42: =IFERROR(AM31-AM40,0) -> 1594496 | AN42: =SUM(AB42:AM42) -> 10148635 | AO42: =IFERROR(AO31-AO40,0) -> 1825150.2 | AP42: =IFERROR(AP31-AP40,0) -> 2089368.4 | AQ42: =IFERROR(AQ31-AQ40,0) -> 2391815.3 | AR42: =IFERROR(AR31-AR40,0) -> 2738686.6 | AS42: =IFERROR(AS31-AS40,0) -> 3136178.2 | AT42: =IFERROR(AT31-AT40,0) -> 3591717.8 | AU42: =IFERROR(AU31-AU40,0) -> 4114246 | AV42: =IFERROR(AV31-AV40,0) -> 4713337.5 | ... AZ42: =IFERROR(AZ31-AZ40,0) -> 8130399.9 | BA42: =SUM(AO42:AZ42) -> 51412755 | BB42: =IFERROR(BB31-BB40,0) -> 9321028.7 | BC42: =IFERROR(BC31-BC40,0) -> 10687650 | BD42: =IFERROR(BD31-BD40,0) -> 12255656 | BE42: =IFERROR(BE31-BE40,0) -> 14055313 | BF42: =IFERROR(BF31-BF40,0) -> 16121110 | BG42: =IFERROR(BG31-BG40,0) -> 18492707 | BH42: =IFERROR(BH31-BH40,0) -> 21215201 | BI42: =IFERROR(BI31-BI40,0) -> 24340956 | ... BM42: =IFERROR(BM31-BM40,0) -> 42217066 | BN42: =SUM(BB42:BM42) -> 2.654704e+08
A43: Gross Margin % | B43: =IFERROR(B42/B31,0) -> 0.70755789 | C43: =IFERROR(C42/C31,0) -> 0.70837856 | D43: =IFERROR(D42/D31,0) -> 0.72589561 | E43: =IFERROR(E42/E31,0) -> 0.74312189 | F43: =IFERROR(F42/F31,0) -> 0.75888959 | G43: =IFERROR(G42/G31,0) -> 0.77306504 | H43: =IFERROR(H42/H31,0) -> 0.78718851 | I43: =IFERROR(I42/I31,0) -> 0.8004678 | ... M43: =IFERROR(M42/M31,0) -> 0.83993837 | N43: =M43 -> 0.83993837 | O43: =IFERROR(O42/O31,0) -> 0.84822602 | P43: =IFERROR(P42/P31,0) -> 0.85552896 | Q43: =IFERROR(Q42/Q31,0) -> 0.86265406 | R43: =IFERROR(R42/R31,0) -> 0.8692678 | S43: =IFERROR(S42/S31,0) -> 0.87523636 | T43: =IFERROR(T42/T31,0) -> 0.88092171 | U43: =IFERROR(U42/U31,0) -> 0.88618031 | V43: =IFERROR(V42/V31,0) -> 0.8910247 | ... Z43: =IFERROR(Z42/Z31,0) -> 0.90814102 | AA43: =Z43 -> 0.90814102 | AB43: =IFERROR(AB42/AB31,0) -> 0.91191881 | AC43: =IFERROR(AC42/AC31,0) -> 0.9155079 | AD43: =IFERROR(AD42/AD31,0) -> 0.91891381 | AE43: =IFERROR(AE42/AE31,0) -> 0.92214236 | AF43: =IFERROR(AF42/AF31,0) -> 0.92521457 | AG43: =IFERROR(AG42/AG31,0) -> 0.9281527 | AH43: =IFERROR(AH42/AH31,0) -> 0.93093474 | AI43: =IFERROR(AI42/AI31,0) -> 0.93361178 | ... AM43: =IFERROR(AM42/AM31,0) -> 0.94331404 | AN43: =AM43 -> 0.94331404 | AO43: =IFERROR(AO42/AO31,0) -> 0.94551202 | AP43: =IFERROR(AP42/AP31,0) -> 0.94762425 | AQ43: =IFERROR(AQ42/AQ31,0) -> 0.9496512 | AR43: =IFERROR(AR42/AR31,0) -> 0.95160625 | AS43: =IFERROR(AS42/AS31,0) -> 0.95348794 | AT43: =IFERROR(AT42/AT31,0) -> 0.95529872 | AU43: =IFERROR(AU42/AU31,0) -> 0.957046 | AV43: =IFERROR(AV42/AV31,0) -> 0.95872812 | ... AZ43: =IFERROR(AZ42/AZ31,0) -> 0.96486119 | BA43: =AZ43 -> 0.96486119 | BB43: =IFERROR(BB42/BB31,0) -> 0.96625706 | BC43: =IFERROR(BC42/BC31,0) -> 0.96760236 | BD43: =IFERROR(BD42/BD31,0) -> 0.96889711 | BE43: =IFERROR(BE42/BE31,0) -> 0.97014326 | BF43: =IFERROR(BF42/BF31,0) -> 0.97134295 | BG43: =IFERROR(BG42/BG31,0) -> 0.97249759 | BH43: =IFERROR(BH42/BH31,0) -> 0.97360857 | BI43: =IFERROR(BI42/BI31,0) -> 0.97467776 | ... BM43: =IFERROR(BM42/BM31,0) -> 0.97856088 | BN43: =BM43 -> 0.97856088

Sheet HEADCOUNT
A1: HEADCOUNT — Staff Costs by Department
A2: All values auto-calculated from Assumptions Section 6. Edit roles, start months, and salaries there.
B4: YEAR 1 | N4: Y1 | O4: YEAR 2 | AA4: Y2 | AB4: YEAR 3 | AN4: Y3 | AO4: YEAR 4 | BA4: Y4 | BB4: YEAR 5 | BN4: Y5
B5: Jan | C5: Feb | D5: Mar | E5: Apr | F5: May | G5: Jun | H5: Jul | I5: Aug | J5: Sep | K5: Oct | L5: Nov | M5: Dec | N5: Y1 Total | O5: Jan | P5: Feb | Q5: Mar | R5: Apr | S5: May | T5: Jun | U5: Jul | V5: Aug | W5: Sep | X5: Oct | Y5: Nov | Z5: Dec | AA5: Y2 Total | AB5: Jan | AC5: Feb | AD5: Mar | AE5: Apr | AF5: May | AG5: Jun | AH5: Jul | AI5: Aug | AJ5: Sep | AK5: Oct | AL5: Nov | AM5: Dec | AN5: Y3 Total | AO5: Jan | AP5: Feb | AQ5: Mar | AR5: Apr | AS5: May | AT5: Jun | AU5: Jul | AV5: Aug | AW5: Sep | AX5: Oct | AY5: Nov | AZ5: Dec | BA5: Y4 Total | BB5: Jan | BC5: Feb | BD5: Mar | BE5: Apr | BF5: May | BG5: Jun | BH5: Jul | BI5: Aug | BJ5: Sep | BK5: Oct | BL5: Nov | BM5: Dec | BN5: Y5 Total
A7: ENGINEERING
A8: =IFERROR(ASSUMPTIONS!B47,"(empty)") -> Engineering | B8: =IFERROR(IF(1>=ASSUMPTIONS!$C$47,ASSUMPTIONS!$D$47*(1+ASSUMPTIONS!$B$66),0),0) -> 10242 | C8: =IFERROR(IF(2>=ASSUMPTIONS!$C$47,ASSUMPTIONS!$D$47*(1+ASSUMPTIONS!$B$66),0),0) -> 10242 | D8: =IFERROR(IF(3>=ASSUMPTIONS!$C$47,ASSUMPTIONS!$D$47*(1+ASSUMPTIONS!$B$66),0),0) -> 10242 | E8: =IFERROR(IF(4>=ASSUMPTIONS!$C$47,ASSUMPTIONS!$D$47*(1+ASSUMPTIONS!$B$66),0),0) -> 10242 | F8: =IFERROR(IF(5>=ASSUMPTIONS!$C$47,ASSUMPTIONS!$D$47*(1+ASSUMPTIONS!$B$66),0),0) -> 10242 | G8: =IFERROR(IF(6>=ASSUMPTIONS!$C$47,ASSUMPTIONS!$D$47*(1+ASSUMPTIONS!$B$66),0),0) -> 10242 | H8: =IFERROR(IF(7>=ASSUMPTIONS!$C$47,ASSUMPTIONS!$D$47*(1+ASSUMPTIONS!$B$66),0),0) -> 10242 | I8: =IFERROR(IF(8>=ASSUMPTIONS!$C$47,ASSUMPTIONS!$D$47*(1+ASSUMPTIONS!$B$66),0),0) -> 10242 | J8: =IFERROR(IF(9>=ASSUMPTIONS!$C$47,ASSUMPTIONS!$D$47*(1+ASSUMPTIONS!$B$66),0),0) -> 10242 | K8: =IFERROR(IF(10>=ASSUMPTIONS!$C$47,ASSUMPTIONS!$D$47*(1+ASSUMPTIONS!$B$66),0),0) -> 10242 | L8: =IFERROR(IF(11>=ASSUMPTIONS!$C$47,ASSUMPTIONS!$D$47*(1+ASSUMPTIONS!$B$66),0),0) -> 10242 | M8: =IFERROR(IF(12>=ASSUMPTIONS!$C$47,ASSUMPTIONS!$D$47*(1+ASSUMPTIONS!$B$66),0),0) -> 10242 | N8: =SUM(B8:M8) -> 122904 | O8: =IFERROR(IF(13>=ASSUMPTIONS!$C$47,ASSUMPTIONS!$D$47*(1+ASSUMPTIONS!$B$66),0),0) -> 10242 | P8: =IFERROR(IF(14>=ASSUMPTIONS!$C$47,ASSUMPTIONS!$D$47*(1+ASSUMPTIONS!$B$66),0),0) -> 10242 | Q8: =IFERROR(IF(15>=ASSUMPTIONS!$C$47,ASSUMPTIONS!$D$47*(1+ASSUMPTIONS!$B$66),0),0) -> 10242 | R8: =IFERROR(IF(16>=ASSUMPTIONS!$C$47,ASSUMPTIONS!$D$47*(1+ASSUMPTIONS!$B$66),0),0) -> 10242 | S8: =IFERROR(IF(17>=ASSUMPTIONS!$C$47,ASSUMPTIONS!$D$47*(1+ASSUMPTIONS!$B$66),0),0) -> 10242 | T8: =IFERROR(IF(18>=ASSUMPTIONS!$C$47,ASSUMPTIONS!$D$47*(1+ASSUMPTIONS!$B$66),0),0) -> 10242 | U8: =IFERROR(IF(19>=ASSUMPTIONS!$C$47,ASSUMPTIONS!$D$47*(1+ASSUMPTIONS!$B$66),0),0) -> 10242 | V8: =IFERROR(IF(20>=ASSUMPTIONS!$C$47,ASSUMPTIONS!$D$47*(1+ASSUMPTIONS!$B$66),0),0) -> 10242 | W8: =IFERROR(IF(21>=ASSUMPTIONS!$C$47,ASSUMPTIONS!$D$47*(1+ASSUMPTIONS!$B$66),0),0) -> 10242 | X8: =IFERROR(IF(22>=ASSUMPTIONS!$C$47,ASSUMPTIONS!$D$47*(1+ASSUMPTIONS!$B$66),0),0) -> 10242 | Y8: =IFERROR(IF(23>=ASSUMPTIONS!$C$47,ASSUMPTIONS!$D$47*(1+ASSUMPTIONS!$B$66),0),0) -> 10242 | Z8: =IFERROR(IF(24>=ASSUMPTIONS!$C$47,ASSUMPTIONS!$D$47*(1+ASSUMPTIONS!$B$66),0),0) -> 10242 | AA8: =SUM(O8:Z8) -> 122904 | AB8: =IFERROR(IF(25>=ASSUMPTIONS!$C$47,ASSUMPTIONS!$D$47*(1+ASSUMPTIONS!$B$66),0),0) -> 10242 | AC8: =IFERROR(IF(26>=ASSUMPTIONS!$C$47,ASSUMPTIONS!$D$47*(1+ASSUMPTIONS!$B$66),0),0) -> 10242 | AD8: =IFERROR(IF(27>=ASSUMPTIONS!$C$47,ASSUMPTIONS!$D$47*(1+ASSUMPTIONS!$B$66),0),0) -> 10242 | AE8: =IFERROR(IF(28>=ASSUMPTIONS!$C$47,ASSUMPTIONS!$D$47*(1+ASSUMPTIONS!$B$66),0),0) -> 10242 | AF8: =IFERROR(IF(29>=ASSUMPTIONS!$C$47,ASSUMPTIONS!$D$47*(1+ASSUMPTIONS!$B$66),0),0) -> 10242 | AG8: =IFERROR(IF(30>=ASSUMPTIONS!$C$47,ASSUMPTIONS!$D$47*(1+ASSUMPTIONS!$B$66),0),0) -> 10242 | AH8: =IFERROR(IF(31>=ASSUMPTIONS!$C$47,ASSUMPTIONS!$D$47*(1+ASSUMPTIONS!$B$66),0),0) -> 10242 | AI8: =IFERROR(IF(32>=ASSUMPTIONS!$C$47,ASSUMPTIONS!$D$47*(1+ASSUMPTIONS!$B$66),0),0) -> 10242 | AJ8: =IFERROR(IF(33>=ASSUMPTIONS!$C$47,ASSUMPTIONS!$D$47*(1+ASSUMPTIONS!$B$66),0),0) -> 10242 | AK8: =IFERROR(IF(34>=ASSUMPTIONS!$C$47,ASSUMPTIONS!$D$47*(1+ASSUMPTIONS!$B$66),0),0) -> 10242 | AL8: =IFERROR(IF(35>=ASSUMPTIONS!$C$47,ASSUMPTIONS!$D$47*(1+ASSUMPTIONS!$B$66),0),0) -> 10242 | AM8: =IFERROR(IF(36>=ASSUMPTIONS!$C$47,ASSUMPTIONS!$D$47*(1+ASSUMPTIONS!$B$66),0),0) -> 10242 | AN8: =SUM(AB8:AM8) -> 122904 | AO8: =IFERROR(IF(37>=ASSUMPTIONS!$C$47,ASSUMPTIONS!$D$47*(1+ASSUMPTIONS!$B$66),0),0) -> 10242 | AP8: =IFERROR(IF(38>=ASSUMPTIONS!$C$47,ASSUMPTIONS!$D$47*(1+ASSUMPTIONS!$B$66),0),0) -> 10242 | AQ8: =IFERROR(IF(39>=ASSUMPTIONS!$C$47,ASSUMPTIONS!$D$47*(1+ASSUMPTIONS!$B$66),0),0) -> 10242 | AR8: =IFERROR(IF(40>=ASSUMPTIONS!$C$47,ASSUMPTIONS!$D$47*(1+ASSUMPTIONS!$B$66),0),0) -> 10242 | AS8: =IFERROR(IF(41>=ASSUMPTIONS!$C$47,ASSUMPTIONS!$D$47*(1+ASSUMPTIONS!$B$66),0),0) -> 10242 | AT8: =IFERROR(IF(42>=ASSUMPTIONS!$C$47,ASSUMPTIONS!$D$47*(1+ASSUMPTIONS!$B$66),0),0) -> 10242 | AU8: =IFERROR(IF(43>=ASSUMPTIONS!$C$47,ASSUMPTIONS!$D$47*(1+ASSUMPTIONS!$B$66),0),0) -> 10242 | AV8: =IFERROR(IF(44>=ASSUMPTIONS!$C$47,ASSUMPTIONS!$D$47*(1+ASSUMPTIONS!$B$66),0),0) -> 10242 | AW8: =IFERROR(IF(45>=ASSUMPTIONS!$C$47,ASSUMPTIONS!$D$47*(1+ASSUMPTIONS!$B$66),0),0) -> 10242 | AX8: =IFERROR(IF(46>=ASSUMPTIONS!$C$47,ASSUMPTIONS!$D$47*(1+ASSUMPTIONS!$B$66),0),0) -> 10242 | AY8: =IFERROR(IF(47>=ASSUMPTIONS!$C$47,ASSUMPTIONS!$D$47*(1+ASSUMPTIONS!$B$66),0),0) -> 10242 | AZ8: =IFERROR(IF(48>=ASSUMPTIONS!$C$47,ASSUMPTIONS!$D$47*(1+ASSUMPTIONS!$B$66),0),0) -> 10242 | BA8: =SUM(AO8:AZ8) -> 122904 | BB8: =IFERROR(IF(49>=ASSUMPTIONS!$C$47,ASSUMPTIONS!$D$47*(1+ASSUMPTIONS!$B$66),0),0) -> 10242 | BC8: =IFERROR(IF(50>=ASSUMPTIONS!$C$47,ASSUMPTIONS!$D$47*(1+ASSUMPTIONS!$B$66),0),0) -> 10242 | BD8: =IFERROR(IF(51>=ASSUMPTIONS!$C$47,ASSUMPTIONS!$D$47*(1+ASSUMPTIONS!$B$66),0),0) -> 10242 | BE8: =IFERROR(IF(52>=ASSUMPTIONS!$C$47,ASSUMPTIONS!$D$47*(1+ASSUMPTIONS!$B$66),0),0) -> 10242 | BF8: =IFERROR(IF(53>=ASSUMPTIONS!$C$47,ASSUMPTIONS!$D$47*(1+ASSUMPTIONS!$B$66),0),0) -> 10242 | BG8: =IFERROR(IF(54>=ASSUMPTIONS!$C$47,ASSUMPTIONS!$D$47*(1+ASSUMPTIONS!$B$66),0),0) -> 10242 | BH8: =IFERROR(IF(55>=ASSUMPTIONS!$C$47,ASSUMPTIONS!$D$47*(1+ASSUMPTIONS!$B$66),0),0) -> 10242 | BI8: =IFERROR(IF(56>=ASSUMPTIONS!$C$47,ASSUMPTIONS!$D$47*(1+ASSUMPTIONS!$B$66),0),0) -> 10242 | BJ8: =IFERROR(IF(57>=ASSUMPTIONS!$C$47,ASSUMPTIONS!$D$47*(1+ASSUMPTIONS!$B$66),0),0) -> 10242 | BK8: =IFERROR(IF(58>=ASSUMPTIONS!$C$47,ASSUMPTIONS!$D$47*(1+ASSUMPTIONS!$B$66),0),0) -> 10242 | BL8: =IFERROR(IF(59>=ASSUMPTIONS!$C$47,ASSUMPTIONS!$D$47*(1+ASSUMPTIONS!$B$66),0),0) -> 10242 | BM8: =IFERROR(IF(60>=ASSUMPTIONS!$C$47,ASSUMPTIONS!$D$47*(1+ASSUMPTIONS!$B$66),0),0) -> 10242 | BN8: =SUM(BB8:BM8) -> 122904
A9: =IFERROR(ASSUMPTIONS!B48,"(empty)") -> Engineering | B9: =IFERROR(IF(1>=ASSUMPTIONS!$C$48,ASSUMPTIONS!$D$48*(1+ASSUMPTIONS!$B$66),0),0) -> 7966 | C9: =IFERROR(IF(2>=ASSUMPTIONS!$C$48,ASSUMPTIONS!$D$48*(1+ASSUMPTIONS!$B$66),0),0) -> 7966 | D9: =IFERROR(IF(3>=ASSUMPTIONS!$C$48,ASSUMPTIONS!$D$48*(1+ASSUMPTIONS!$B$66),0),0) -> 7966 | E9: =IFERROR(IF(4>=ASSUMPTIONS!$C$48,ASSUMPTIONS!$D$48*(1+ASSUMPTIONS!$B$66),0),0) -> 7966 | F9: =IFERROR(IF(5>=ASSUMPTIONS!$C$48,ASSUMPTIONS!$D$48*(1+ASSUMPTIONS!$B$66),0),0) -> 7966 | G9: =IFERROR(IF(6>=ASSUMPTIONS!$C$48,ASSUMPTIONS!$D$48*(1+ASSUMPTIONS!$B$66),0),0) -> 7966 | H9: =IFERROR(IF(7>=ASSUMPTIONS!$C$48,ASSUMPTIONS!$D$48*(1+ASSUMPTIONS!$B$66),0),0) -> 7966 | I9: =IFERROR(IF(8>=ASSUMPTIONS!$C$48,ASSUMPTIONS!$D$48*(1+ASSUMPTIONS!$B$66),0),0) -> 7966 | J9: =IFERROR(IF(9>=ASSUMPTIONS!$C$48,ASSUMPTIONS!$D$48*(1+ASSUMPTIONS!$B$66),0),0) -> 7966 | K9: =IFERROR(IF(10>=ASSUMPTIONS!$C$48,ASSUMPTIONS!$D$48*(1+ASSUMPTIONS!$B$66),0),0) -> 7966 | L9: =IFERROR(IF(11>=ASSUMPTIONS!$C$48,ASSUMPTIONS!$D$48*(1+ASSUMPTIONS!$B$66),0),0) -> 7966 | M9: =IFERROR(IF(12>=ASSUMPTIONS!$C$48,ASSUMPTIONS!$D$48*(1+ASSUMPTIONS!$B$66),0),0) -> 7966 | N9: =SUM(B9:M9) -> 95592 | O9: =IFERROR(IF(13>=ASSUMPTIONS!$C$48,ASSUMPTIONS!$D$48*(1+ASSUMPTIONS!$B$66),0),0) -> 7966 | P9: =IFERROR(IF(14>=ASSUMPTIONS!$C$48,ASSUMPTIONS!$D$48*(1+ASSUMPTIONS!$B$66),0),0) -> 7966 | Q9: =IFERROR(IF(15>=ASSUMPTIONS!$C$48,ASSUMPTIONS!$D$48*(1+ASSUMPTIONS!$B$66),0),0) -> 7966 | R9: =IFERROR(IF(16>=ASSUMPTIONS!$C$48,ASSUMPTIONS!$D$48*(1+ASSUMPTIONS!$B$66),0),0) -> 7966 | S9: =IFERROR(IF(17>=ASSUMPTIONS!$C$48,ASSUMPTIONS!$D$48*(1+ASSUMPTIONS!$B$66),0),0) -> 7966 | T9: =IFERROR(IF(18>=ASSUMPTIONS!$C$48,ASSUMPTIONS!$D$48*(1+ASSUMPTIONS!$B$66),0),0) -> 7966 | U9: =IFERROR(IF(19>=ASSUMPTIONS!$C$48,ASSUMPTIONS!$D$48*(1+ASSUMPTIONS!$B$66),0),0) -> 7966 | V9: =IFERROR(IF(20>=ASSUMPTIONS!$C$48,ASSUMPTIONS!$D$48*(1+ASSUMPTIONS!$B$66),0),0) -> 7966 | W9: =IFERROR(IF(21>=ASSUMPTIONS!$C$48,ASSUMPTIONS!$D$48*(1+ASSUMPTIONS!$B$66),0),0) -> 7966 | X9: =IFERROR(IF(22>=ASSUMPTIONS!$C$48,ASSUMPTIONS!$D$48*(1+ASSUMPTIONS!$B$66),0),0) -> 7966 | Y9: =IFERROR(IF(23>=ASSUMPTIONS!$C$48,ASSUMPTIONS!$D$48*(1+ASSUMPTIONS!$B$66),0),0) -> 7966 | Z9: =IFERROR(IF(24>=ASSUMPTIONS!$C$48,ASSUMPTIONS!$D$48*(1+ASSUMPTIONS!$B$66),0),0) -> 7966 | AA9: =SUM(O9:Z9) -> 95592 | AB9: =IFERROR(IF(25>=ASSUMPTIONS!$C$48,ASSUMPTIONS!$D$48*(1+ASSUMPTIONS!$B$66),0),0) -> 7966 | AC9: =IFERROR(IF(26>=ASSUMPTIONS!$C$48,ASSUMPTIONS!$D$48*(1+ASSUMPTIONS!$B$66),0),0) -> 7966 | AD9: =IFERROR(IF(27>=ASSUMPTIONS!$C$48,ASSUMPTIONS!$D$48*(1+ASSUMPTIONS!$B$66),0),0) -> 7966 | AE9: =IFERROR(IF(28>=ASSUMPTIONS!$C$48,ASSUMPTIONS!$D$48*(1+ASSUMPTIONS!$B$66),0),0) -> 7966 | AF9: =IFERROR(IF(29>=ASSUMPTIONS!$C$48,ASSUMPTIONS!$D$48*(1+ASSUMPTIONS!$B$66),0),0) -> 7966 | AG9: =IFERROR(IF(30>=ASSUMPTIONS!$C$48,ASSUMPTIONS!$D$48*(1+ASSUMPTIONS!$B$66),0),0) -> 7966 | AH9: =IFERROR(IF(31>=ASSUMPTIONS!$C$48,ASSUMPTIONS!$D$48*(1+ASSUMPTIONS!$B$66),0),0) -> 7966 | AI9: =IFERROR(IF(32>=ASSUMPTIONS!$C$48,ASSUMPTIONS!$D$48*(1+ASSUMPTIONS!$B$66),0),0) -> 7966 | AJ9: =IFERROR(IF(33>=ASSUMPTIONS!$C$48,ASSUMPTIONS!$D$48*(1+ASSUMPTIONS!$B$66),0),0) -> 7966 | AK9: =IFERROR(IF(34>=ASSUMPTIONS!$C$48,ASSUMPTIONS!$D$48*(1+ASSUMPTIONS!$B$66),0),0) -> 7966 | AL9: =IFERROR(IF(35>=ASSUMPTIONS!$C$48,ASSUMPTIONS!$D$48*(1+ASSUMPTIONS!$B$66),0),0) -> 7966 | AM9: =IFERROR(IF(36>=ASSUMPTIONS!$C$48,ASSUMPTIONS!$D$48*(1+ASSUMPTIONS!$B$66),0),0) -> 7966 | AN9: =SUM(AB9:AM9) -> 95592 | AO9: =IFERROR(IF(37>=ASSUMPTIONS!$C$48,ASSUMPTIONS!$D$48*(1+ASSUMPTIONS!$B$66),0),0) -> 7966 | AP9: =IFERROR(IF(38>=ASSUMPTIONS!$C$48,ASSUMPTIONS!$D$48*(1+ASSUMPTIONS!$B$66),0),0) -> 7966 | AQ9: =IFERROR(IF(39>=ASSUMPTIONS!$C$48,ASSUMPTIONS!$D$48*(1+ASSUMPTIONS!$B$66),0),0) -> 7966 | AR9: =IFERROR(IF(40>=ASSUMPTIONS!$C$48,ASSUMPTIONS!$D$48*(1+ASSUMPTIONS!$B$66),0),0) -> 7966 | AS9: =IFERROR(IF(41>=ASSUMPTIONS!$C$48,ASSUMPTIONS!$D$48*(1+ASSUMPTIONS!$B$66),0),0) -> 7966 | AT9: =IFERROR(IF(42>=ASSUMPTIONS!$C$48,ASSUMPTIONS!$D$48*(1+ASSUMPTIONS!$B$66),0),0) -> 7966 | AU9: =IFERROR(IF(43>=ASSUMPTIONS!$C$48,ASSUMPTIONS!$D$48*(1+ASSUMPTIONS!$B$66),0),0) -> 7966 | AV9: =IFERROR(IF(44>=ASSUMPTIONS!$C$48,ASSUMPTIONS!$D$48*(1+ASSUMPTIONS!$B$66),0),0) -> 7966 | AW9: =IFERROR(IF(45>=ASSUMPTIONS!$C$48,ASSUMPTIONS!$D$48*(1+ASSUMPTIONS!$B$66),0),0) -> 7966 | AX9: =IFERROR(IF(46>=ASSUMPTIONS!$C$48,ASSUMPTIONS!$D$48*(1+ASSUMPTIONS!$B$66),0),0) -> 7966 | AY9: =IFERROR(IF(47>=ASSUMPTIONS!$C$48,ASSUMPTIONS!$D$48*(1+ASSUMPTIONS!$B$66),0),0) -> 7966 | AZ9: =IFERROR(IF(48>=ASSUMPTIONS!$C$48,ASSUMPTIONS!$D$48*(1+ASSUMPTIONS!$B$66),0),0) -> 7966 | BA9: =SUM(AO9:AZ9) -> 95592 | BB9: =IFERROR(IF(49>=ASSUMPTIONS!$C$48,ASSUMPTIONS!$D$48*(1+ASSUMPTIONS!$B$66),0),0) -> 7966 | BC9: =IFERROR(IF(50>=ASSUMPTIONS!$C$48,ASSUMPTIONS!$D$48*(1+ASSUMPTIONS!$B$66),0),0) -> 7966 | BD9: =IFERROR(IF(51>=ASSUMPTIONS!$C$48,ASSUMPTIONS!$D$48*(1+ASSUMPTIONS!$B$66),0),0) -> 7966 | BE9: =IFERROR(IF(52>=ASSUMPTIONS!$C$48,ASSUMPTIONS!$D$48*(1+ASSUMPTIONS!$B$66),0),0) -> 7966 | BF9: =IFERROR(IF(53>=ASSUMPTIONS!$C$48,ASSUMPTIONS!$D$48*(1+ASSUMPTIONS!$B$66),0),0) -> 7966 | BG9: =IFERROR(IF(54>=ASSUMPTIONS!$C$48,ASSUMPTIONS!$D$48*(1+ASSUMPTIONS!$B$66),0),0) -> 7966 | BH9: =IFERROR(IF(55>=ASSUMPTIONS!$C$48,ASSUMPTIONS!$D$48*(1+ASSUMPTIONS!$B$66),0),0) -> 7966 | BI9: =IFERROR(IF(56>=ASSUMPTIONS!$C$48,ASSUMPTIONS!$D$48*(1+ASSUMPTIONS!$B$66),0),0) -> 7966 | BJ9: =IFERROR(IF(57>=ASSUMPTIONS!$C$48,ASSUMPTIONS!$D$48*(1+ASSUMPTIONS!$B$66),0),0) -> 7966 | BK9: =IFERROR(IF(58>=ASSUMPTIONS!$C$48,ASSUMPTIONS!$D$48*(1+ASSUMPTIONS!$B$66),0),0) -> 7966 | BL9: =IFERROR(IF(59>=ASSUMPTIONS!$C$48,ASSUMPTIONS!$D$48*(1+ASSUMPTIONS!$B$66),0),0) -> 7966 | BM9: =IFERROR(IF(60>=ASSUMPTIONS!$C$48,ASSUMPTIONS!$D$48*(1+ASSUMPTIONS!$B$66),0),0) -> 7966 | BN9: =SUM(BB9:BM9) -> 95592
A10: =IFERROR(ASSUMPTIONS!B49,"(empty)") -> Engineering | B10: =IFERROR(IF(1>=ASSUMPTIONS!$C$49,ASSUMPTIONS!$D$49*(1+ASSUMPTIONS!$B$66),0),0) -> 0 | C10: =IFERROR(IF(2>=ASSUMPTIONS!$C$49,ASSUMPTIONS!$D$49*(1+ASSUMPTIONS!$B$66),0),0) -> 0 | D10: =IFERROR(IF(3>=ASSUMPTIONS!$C$49,ASSUMPTIONS!$D$49*(1+ASSUMPTIONS!$B$66),0),0) -> 6259 | E10: =IFERROR(IF(4>=ASSUMPTIONS!$C$49,ASSUMPTIONS!$D$49*(1+ASSUMPTIONS!$B$66),0),0) -> 6259 | F10: =IFERROR(IF(5>=ASSUMPTIONS!$C$49,ASSUMPTIONS!$D$49*(1+ASSUMPTIONS!$B$66),0),0) -> 6259 | G10: =IFERROR(IF(6>=ASSUMPTIONS!$C$49,ASSUMPTIONS!$D$49*(1+ASSUMPTIONS!$B$66),0),0) -> 6259 | H10: =IFERROR(IF(7>=ASSUMPTIONS!$C$49,ASSUMPTIONS!$D$49*(1+ASSUMPTIONS!$B$66),0),0) -> 6259 | I10: =IFERROR(IF(8>=ASSUMPTIONS!$C$49,ASSUMPTIONS!$D$49*(1+ASSUMPTIONS!$B$66),0),0) -> 6259 | J10: =IFERROR(IF(9>=ASSUMPTIONS!$C$49,ASSUMPTIONS!$D$49*(1+ASSUMPTIONS!$B$66),0),0) -> 6259 | K10: =IFERROR(IF(10>=ASSUMPTIONS!$C$49,ASSUMPTIONS!$D$49*(1+ASSUMPTIONS!$B$66),0),0) -> 6259 | L10: =IFERROR(IF(11>=ASSUMPTIONS!$C$49,ASSUMPTIONS!$D$49*(1+ASSUMPTIONS!$B$66),0),0) -> 6259 | M10: =IFERROR(IF(12>=ASSUMPTIONS!$C$49,ASSUMPTIONS!$D$49*(1+ASSUMPTIONS!$B$66),0),0) -> 6259 | N10: =SUM(B10:M10) -> 62590 | O10: =IFERROR(IF(13>=ASSUMPTIONS!$C$49,ASSUMPTIONS!$D$49*(1+ASSUMPTIONS!$B$66),0),0) -> 6259 | P10: =IFERROR(IF(14>=ASSUMPTIONS!$C$49,ASSUMPTIONS!$D$49*(1+ASSUMPTIONS!$B$66),0),0) -> 6259 | Q10: =IFERROR(IF(15>=ASSUMPTIONS!$C$49,ASSUMPTIONS!$D$49*(1+ASSUMPTIONS!$B$66),0),0) -> 6259 | R10: =IFERROR(IF(16>=ASSUMPTIONS!$C$49,ASSUMPTIONS!$D$49*(1+ASSUMPTIONS!$B$66),0),0) -> 6259 | S10: =IFERROR(IF(17>=ASSUMPTIONS!$C$49,ASSUMPTIONS!$D$49*(1+ASSUMPTIONS!$B$66),0),0) -> 6259 | T10: =IFERROR(IF(18>=ASSUMPTIONS!$C$49,ASSUMPTIONS!$D$49*(1+ASSUMPTIONS!$B$66),0),0) -> 6259 | U10: =IFERROR(IF(19>=ASSUMPTIONS!$C$49,ASSUMPTIONS!$D$49*(1+ASSUMPTIONS!$B$66),0),0) -> 6259 | V10: =IFERROR(IF(20>=ASSUMPTIONS!$C$49,ASSUMPTIONS!$D$49*(1+ASSUMPTIONS!$B$66),0),0) -> 6259 | W10: =IFERROR(IF(21>=ASSUMPTIONS!$C$49,ASSUMPTIONS!$D$49*(1+ASSUMPTIONS!$B$66),0),0) -> 6259 | X10: =IFERROR(IF(22>=ASSUMPTIONS!$C$49,ASSUMPTIONS!$D$49*(1+ASSUMPTIONS!$B$66),0),0) -> 6259 | Y10: =IFERROR(IF(23>=ASSUMPTIONS!$C$49,ASSUMPTIONS!$D$49*(1+ASSUMPTIONS!$B$66),0),0) -> 6259 | Z10: =IFERROR(IF(24>=ASSUMPTIONS!$C$49,ASSUMPTIONS!$D$49*(1+ASSUMPTIONS!$B$66),0),0) -> 6259 | AA10: =SUM(O10:Z10) -> 75108 | AB10: =IFERROR(IF(25>=ASSUMPTIONS!$C$49,ASSUMPTIONS!$D$49*(1+ASSUMPTIONS!$B$66),0),0) -> 6259 | AC10: =IFERROR(IF(26>=ASSUMPTIONS!$C$49,ASSUMPTIONS!$D$49*(1+ASSUMPTIONS!$B$66),0),0) -> 6259 | AD10: =IFERROR(IF(27>=ASSUMPTIONS!$C$49,ASSUMPTIONS!$D$49*(1+ASSUMPTIONS!$B$66),0),0) -> 6259 | AE10: =IFERROR(IF(28>=ASSUMPTIONS!$C$49,ASSUMPTIONS!$D$49*(1+ASSUMPTIONS!$B$66),0),0) -> 6259 | AF10: =IFERROR(IF(29>=ASSUMPTIONS!$C$49,ASSUMPTIONS!$D$49*(1+ASSUMPTIONS!$B$66),0),0) -> 6259 | AG10: =IFERROR(IF(30>=ASSUMPTIONS!$C$49,ASSUMPTIONS!$D$49*(1+ASSUMPTIONS!$B$66),0),0) -> 6259 | AH10: =IFERROR(IF(31>=ASSUMPTIONS!$C$49,ASSUMPTIONS!$D$49*(1+ASSUMPTIONS!$B$66),0),0) -> 6259 | AI10: =IFERROR(IF(32>=ASSUMPTIONS!$C$49,ASSUMPTIONS!$D$49*(1+ASSUMPTIONS!$B$66),0),0) -> 6259 | AJ10: =IFERROR(IF(33>=ASSUMPTIONS!$C$49,ASSUMPTIONS!$D$49*(1+ASSUMPTIONS!$B$66),0),0) -> 6259 | AK10: =IFERROR(IF(34>=ASSUMPTIONS!$C$49,ASSUMPTIONS!$D$49*(1+ASSUMPTIONS!$B$66),0),0) -> 6259 | AL10: =IFERROR(IF(35>=ASSUMPTIONS!$C$49,ASSUMPTIONS!$D$49*(1+ASSUMPTIONS!$B$66),0),0) -> 6259 | AM10: =IFERROR(IF(36>=ASSUMPTIONS!$C$49,ASSUMPTIONS!$D$49*(1+ASSUMPTIONS!$B$66),0),0) -> 6259 | AN10: =SUM(AB10:AM10) -> 75108 | AO10: =IFERROR(IF(37>=ASSUMPTIONS!$C$49,ASSUMPTIONS!$D$49*(1+ASSUMPTIONS!$B$66),0),0) -> 6259 | AP10: =IFERROR(IF(38>=ASSUMPTIONS!$C$49,ASSUMPTIONS!$D$49*(1+ASSUMPTIONS!$B$66),0),0) -> 6259 | AQ10: =IFERROR(IF(39>=ASSUMPTIONS!$C$49,ASSUMPTIONS!$D$49*(1+ASSUMPTIONS!$B$66),0),0) -> 6259 | AR10: =IFERROR(IF(40>=ASSUMPTIONS!$C$49,ASSUMPTIONS!$D$49*(1+ASSUMPTIONS!$B$66),0),0) -> 6259 | AS10: =IFERROR(IF(41>=ASSUMPTIONS!$C$49,ASSUMPTIONS!$D$49*(1+ASSUMPTIONS!$B$66),0),0) -> 6259 | AT10: =IFERROR(IF(42>=ASSUMPTIONS!$C$49,ASSUMPTIONS!$D$49*(1+ASSUMPTIONS!$B$66),0),0) -> 6259 | AU10: =IFERROR(IF(43>=ASSUMPTIONS!$C$49,ASSUMPTIONS!$D$49*(1+ASSUMPTIONS!$B$66),0),0) -> 6259 | AV10: =IFERROR(IF(44>=ASSUMPTIONS!$C$49,ASSUMPTIONS!$D$49*(1+ASSUMPTIONS!$B$66),0),0) -> 6259 | AW10: =IFERROR(IF(45>=ASSUMPTIONS!$C$49,ASSUMPTIONS!$D$49*(1+ASSUMPTIONS!$B$66),0),0) -> 6259 | AX10: =IFERROR(IF(46>=ASSUMPTIONS!$C$49,ASSUMPTIONS!$D$49*(1+ASSUMPTIONS!$B$66),0),0) -> 6259 | AY10: =IFERROR(IF(47>=ASSUMPTIONS!$C$49,ASSUMPTIONS!$D$49*(1+ASSUMPTIONS!$B$66),0),0) -> 6259 | AZ10: =IFERROR(IF(48>=ASSUMPTIONS!$C$49,ASSUMPTIONS!$D$49*(1+ASSUMPTIONS!$B$66),0),0) -> 6259 | BA10: =SUM(AO10:AZ10) -> 75108 | BB10: =IFERROR(IF(49>=ASSUMPTIONS!$C$49,ASSUMPTIONS!$D$49*(1+ASSUMPTIONS!$B$66),0),0) -> 6259 | BC10: =IFERROR(IF(50>=ASSUMPTIONS!$C$49,ASSUMPTIONS!$D$49*(1+ASSUMPTIONS!$B$66),0),0) -> 6259 | BD10: =IFERROR(IF(51>=ASSUMPTIONS!$C$49,ASSUMPTIONS!$D$49*(1+ASSUMPTIONS!$B$66),0),0) -> 6259 | BE10: =IFERROR(IF(52>=ASSUMPTIONS!$C$49,ASSUMPTIONS!$D$49*(1+ASSUMPTIONS!$B$66),0),0) -> 6259 | BF10: =IFERROR(IF(53>=ASSUMPTIONS!$C$49,ASSUMPTIONS!$D$49*(1+ASSUMPTIONS!$B$66),0),0) -> 6259 | BG10: =IFERROR(IF(54>=ASSUMPTIONS!$C$49,ASSUMPTIONS!$D$49*(1+ASSUMPTIONS!$B$66),0),0) -> 6259 | BH10: =IFERROR(IF(55>=ASSUMPTIONS!$C$49,ASSUMPTIONS!$D$49*(1+ASSUMPTIONS!$B$66),0),0) -> 6259 | BI10: =IFERROR(IF(56>=ASSUMPTIONS!$C$49,ASSUMPTIONS!$D$49*(1+ASSUMPTIONS!$B$66),0),0) -> 6259 | BJ10: =IFERROR(IF(57>=ASSUMPTIONS!$C$49,ASSUMPTIONS!$D$49*(1+ASSUMPTIONS!$B$66),0),0) -> 6259 | BK10: =IFERROR(IF(58>=ASSUMPTIONS!$C$49,ASSUMPTIONS!$D$49*(1+ASSUMPTIONS!$B$66),0),0) -> 6259 | BL10: =IFERROR(IF(59>=ASSUMPTIONS!$C$49,ASSUMPTIONS!$D$49*(1+ASSUMPTIONS!$B$66),0),0) -> 6259 | BM10: =IFERROR(IF(60>=ASSUMPTIONS!$C$49,ASSUMPTIONS!$D$49*(1+ASSUMPTIONS!$B$66),0),0) -> 6259 | BN10: =SUM(BB10:BM10) -> 75108
A11: =IFERROR(ASSUMPTIONS!B50,"(empty)") -> Engineering | B11: =IFERROR(IF(1>=ASSUMPTIONS!$C$50,ASSUMPTIONS!$D$50*(1+ASSUMPTIONS!$B$66),0),0) -> 0 | C11: =IFERROR(IF(2>=ASSUMPTIONS!$C$50,ASSUMPTIONS!$D$50*(1+ASSUMPTIONS!$B$66),0),0) -> 0 | D11: =IFERROR(IF(3>=ASSUMPTIONS!$C$50,ASSUMPTIONS!$D$50*(1+ASSUMPTIONS!$B$66),0),0) -> 0 | E11: =IFERROR(IF(4>=ASSUMPTIONS!$C$50,ASSUMPTIONS!$D$50*(1+ASSUMPTIONS!$B$66),0),0) -> 0 | F11: =IFERROR(IF(5>=ASSUMPTIONS!$C$50,ASSUMPTIONS!$D$50*(1+ASSUMPTIONS!$B$66),0),0) -> 0 | G11: =IFERROR(IF(6>=ASSUMPTIONS!$C$50,ASSUMPTIONS!$D$50*(1+ASSUMPTIONS!$B$66),0),0) -> 6259 | H11: =IFERROR(IF(7>=ASSUMPTIONS!$C$50,ASSUMPTIONS!$D$50*(1+ASSUMPTIONS!$B$66),0),0) -> 6259 | I11: =IFERROR(IF(8>=ASSUMPTIONS!$C$50,ASSUMPTIONS!$D$50*(1+ASSUMPTIONS!$B$66),0),0) -> 6259 | J11: =IFERROR(IF(9>=ASSUMPTIONS!$C$50,ASSUMPTIONS!$D$50*(1+ASSUMPTIONS!$B$66),0),0) -> 6259 | K11: =IFERROR(IF(10>=ASSUMPTIONS!$C$50,ASSUMPTIONS!$D$50*(1+ASSUMPTIONS!$B$66),0),0) -> 6259 | L11: =IFERROR(IF(11>=ASSUMPTIONS!$C$50,ASSUMPTIONS!$D$50*(1+ASSUMPTIONS!$B$66),0),0) -> 6259 | M11: =IFERROR(IF(12>=ASSUMPTIONS!$C$50,ASSUMPTIONS!$D$50*(1+ASSUMPTIONS!$B$66),0),0) -> 6259 | N11: =SUM(B11:M11) -> 43813 | O11: =IFERROR(IF(13>=ASSUMPTIONS!$C$50,ASSUMPTIONS!$D$50*(1+ASSUMPTIONS!$B$66),0),0) -> 6259 | P11: =IFERROR(IF(14>=ASSUMPTIONS!$C$50,ASSUMPTIONS!$D$50*(1+ASSUMPTIONS!$B$66),0),0) -> 6259 | Q11: =IFERROR(IF(15>=ASSUMPTIONS!$C$50,ASSUMPTIONS!$D$50*(1+ASSUMPTIONS!$B$66),0),0) -> 6259 | R11: =IFERROR(IF(16>=ASSUMPTIONS!$C$50,ASSUMPTIONS!$D$50*(1+ASSUMPTIONS!$B$66),0),0) -> 6259 | S11: =IFERROR(IF(17>=ASSUMPTIONS!$C$50,ASSUMPTIONS!$D$50*(1+ASSUMPTIONS!$B$66),0),0) -> 6259 | T11: =IFERROR(IF(18>=ASSUMPTIONS!$C$50,ASSUMPTIONS!$D$50*(1+ASSUMPTIONS!$B$66),0),0) -> 6259 | U11: =IFERROR(IF(19>=ASSUMPTIONS!$C$50,ASSUMPTIONS!$D$50*(1+ASSUMPTIONS!$B$66),0),0) -> 6259 | V11: =IFERROR(IF(20>=ASSUMPTIONS!$C$50,ASSUMPTIONS!$D$50*(1+ASSUMPTIONS!$B$66),0),0) -> 6259 | W11: =IFERROR(IF(21>=ASSUMPTIONS!$C$50,ASSUMPTIONS!$D$50*(1+ASSUMPTIONS!$B$66),0),0) -> 6259 | X11: =IFERROR(IF(22>=ASSUMPTIONS!$C$50,ASSUMPTIONS!$D$50*(1+ASSUMPTIONS!$B$66),0),0) -> 6259 | Y11: =IFERROR(IF(23>=ASSUMPTIONS!$C$50,ASSUMPTIONS!$D$50*(1+ASSUMPTIONS!$B$66),0),0) -> 6259 | Z11: =IFERROR(IF(24>=ASSUMPTIONS!$C$50,ASSUMPTIONS!$D$50*(1+ASSUMPTIONS!$B$66),0),0) -> 6259 | AA11: =SUM(O11:Z11) -> 75108 | AB11: =IFERROR(IF(25>=ASSUMPTIONS!$C$50,ASSUMPTIONS!$D$50*(1+ASSUMPTIONS!$B$66),0),0) -> 6259 | AC11: =IFERROR(IF(26>=ASSUMPTIONS!$C$50,ASSUMPTIONS!$D$50*(1+ASSUMPTIONS!$B$66),0),0) -> 6259 | AD11: =IFERROR(IF(27>=ASSUMPTIONS!$C$50,ASSUMPTIONS!$D$50*(1+ASSUMPTIONS!$B$66),0),0) -> 6259 | AE11: =IFERROR(IF(28>=ASSUMPTIONS!$C$50,ASSUMPTIONS!$D$50*(1+ASSUMPTIONS!$B$66),0),0) -> 6259 | AF11: =IFERROR(IF(29>=ASSUMPTIONS!$C$50,ASSUMPTIONS!$D$50*(1+ASSUMPTIONS!$B$66),0),0) -> 6259 | AG11: =IFERROR(IF(30>=ASSUMPTIONS!$C$50,ASSUMPTIONS!$D$50*(1+ASSUMPTIONS!$B$66),0),0) -> 6259 | AH11: =IFERROR(IF(31>=ASSUMPTIONS!$C$50,ASSUMPTIONS!$D$50*(1+ASSUMPTIONS!$B$66),0),0) -> 6259 | AI11: =IFERROR(IF(32>=ASSUMPTIONS!$C$50,ASSUMPTIONS!$D$50*(1+ASSUMPTIONS!$B$66),0),0) -> 6259 | AJ11: =IFERROR(IF(33>=ASSUMPTIONS!$C$50,ASSUMPTIONS!$D$50*(1+ASSUMPTIONS!$B$66),0),0) -> 6259 | AK11: =IFERROR(IF(34>=ASSUMPTIONS!$C$50,ASSUMPTIONS!$D$50*(1+ASSUMPTIONS!$B$66),0),0) -> 6259 | AL11: =IFERROR(IF(35>=ASSUMPTIONS!$C$50,ASSUMPTIONS!$D$50*(1+ASSUMPTIONS!$B$66),0),0) -> 6259 | AM11: =IFERROR(IF(36>=ASSUMPTIONS!$C$50,ASSUMPTIONS!$D$50*(1+ASSUMPTIONS!$B$66),0),0) -> 6259 | AN11: =SUM(AB11:AM11) -> 75108 | AO11: =IFERROR(IF(37>=ASSUMPTIONS!$C$50,ASSUMPTIONS!$D$50*(1+ASSUMPTIONS!$B$66),0),0) -> 6259 | AP11: =IFERROR(IF(38>=ASSUMPTIONS!$C$50,ASSUMPTIONS!$D$50*(1+ASSUMPTIONS!$B$66),0),0) -> 6259 | AQ11: =IFERROR(IF(39>=ASSUMPTIONS!$C$50,ASSUMPTIONS!$D$50*(1+ASSUMPTIONS!$B$66),0),0) -> 6259 | AR11: =IFERROR(IF(40>=ASSUMPTIONS!$C$50,ASSUMPTIONS!$D$50*(1+ASSUMPTIONS!$B$66),0),0) -> 6259 | AS11: =IFERROR(IF(41>=ASSUMPTIONS!$C$50,ASSUMPTIONS!$D$50*(1+ASSUMPTIONS!$B$66),0),0) -> 6259 | AT11: =IFERROR(IF(42>=ASSUMPTIONS!$C$50,ASSUMPTIONS!$D$50*(1+ASSUMPTIONS!$B$66),0),0) -> 6259 | AU11: =IFERROR(IF(43>=ASSUMPTIONS!$C$50,ASSUMPTIONS!$D$50*(1+ASSUMPTIONS!$B$66),0),0) -> 6259 | AV11: =IFERROR(IF(44>=ASSUMPTIONS!$C$50,ASSUMPTIONS!$D$50*(1+ASSUMPTIONS!$B$66),0),0) -> 6259 | AW11: =IFERROR(IF(45>=ASSUMPTIONS!$C$50,ASSUMPTIONS!$D$50*(1+ASSUMPTIONS!$B$66),0),0) -> 6259 | AX11: =IFERROR(IF(46>=ASSUMPTIONS!$C$50,ASSUMPTIONS!$D$50*(1+ASSUMPTIONS!$B$66),0),0) -> 6259 | AY11: =IFERROR(IF(47>=ASSUMPTIONS!$C$50,ASSUMPTIONS!$D$50*(1+ASSUMPTIONS!$B$66),0),0) -> 6259 | AZ11: =IFERROR(IF(48>=ASSUMPTIONS!$C$50,ASSUMPTIONS!$D$50*(1+ASSUMPTIONS!$B$66),0),0) -> 6259 | BA11: =SUM(AO11:AZ11) -> 75108 | BB11: =IFERROR(IF(49>=ASSUMPTIONS!$C$50,ASSUMPTIONS!$D$50*(1+ASSUMPTIONS!$B$66),0),0) -> 6259 | BC11: =IFERROR(IF(50>=ASSUMPTIONS!$C$50,ASSUMPTIONS!$D$50*(1+ASSUMPTIONS!$B$66),0),0) -> 6259 | BD11: =IFERROR(IF(51>=ASSUMPTIONS!$C$50,ASSUMPTIONS!$D$50*(1+ASSUMPTIONS!$B$66),0),0) -> 6259 | BE11: =IFERROR(IF(52>=ASSUMPTIONS!$C$50,ASSUMPTIONS!$D$50*(1+ASSUMPTIONS!$B$66),0),0) -> 6259 | BF11: =IFERROR(IF(53>=ASSUMPTIONS!$C$50,ASSUMPTIONS!$D$50*(1+ASSUMPTIONS!$B$66),0),0) -> 6259 | BG11: =IFERROR(IF(54>=ASSUMPTIONS!$C$50,ASSUMPTIONS!$D$50*(1+ASSUMPTIONS!$B$66),0),0) -> 6259 | BH11: =IFERROR(IF(55>=ASSUMPTIONS!$C$50,ASSUMPTIONS!$D$50*(1+ASSUMPTIONS!$B$66),0),0) -> 6259 | BI11: =IFERROR(IF(56>=ASSUMPTIONS!$C$50,ASSUMPTIONS!$D$50*(1+ASSUMPTIONS!$B$66),0),0) -> 6259 | BJ11: =IFERROR(IF(57>=ASSUMPTIONS!$C$50,ASSUMPTIONS!$D$50*(1+ASSUMPTIONS!$B$66),0),0) -> 6259 | BK11: =IFERROR(IF(58>=ASSUMPTIONS!$C$50,ASSUMPTIONS!$D$50*(1+ASSUMPTIONS!$B$66),0),0) -> 6259 | BL11: =IFERROR(IF(59>=ASSUMPTIONS!$C$50,ASSUMPTIONS!$D$50*(1+ASSUMPTIONS!$B$66),0),0) -> 6259 | BM11: =IFERROR(IF(60>=ASSUMPTIONS!$C$50,ASSUMPTIONS!$D$50*(1+ASSUMPTIONS!$B$66),0),0) -> 6259 | BN11: =SUM(BB11:BM11) -> 75108
A12: =IFERROR(ASSUMPTIONS!B51,"(empty)") -> Engineering | B12: =IFERROR(IF(1>=ASSUMPTIONS!$C$51,ASSUMPTIONS!$D$51*(1+ASSUMPTIONS!$B$66),0),0) -> 0 | C12: =IFERROR(IF(2>=ASSUMPTIONS!$C$51,ASSUMPTIONS!$D$51*(1+ASSUMPTIONS!$B$66),0),0) -> 0 | D12: =IFERROR(IF(3>=ASSUMPTIONS!$C$51,ASSUMPTIONS!$D$51*(1+ASSUMPTIONS!$B$66),0),0) -> 0 | E12: =IFERROR(IF(4>=ASSUMPTIONS!$C$51,ASSUMPTIONS!$D$51*(1+ASSUMPTIONS!$B$66),0),0) -> 0 | F12: =IFERROR(IF(5>=ASSUMPTIONS!$C$51,ASSUMPTIONS!$D$51*(1+ASSUMPTIONS!$B$66),0),0) -> 0 | G12: =IFERROR(IF(6>=ASSUMPTIONS!$C$51,ASSUMPTIONS!$D$51*(1+ASSUMPTIONS!$B$66),0),0) -> 5121 | H12: =IFERROR(IF(7>=ASSUMPTIONS!$C$51,ASSUMPTIONS!$D$51*(1+ASSUMPTIONS!$B$66),0),0) -> 5121 | I12: =IFERROR(IF(8>=ASSUMPTIONS!$C$51,ASSUMPTIONS!$D$51*(1+ASSUMPTIONS!$B$66),0),0) -> 5121 | J12: =IFERROR(IF(9>=ASSUMPTIONS!$C$51,ASSUMPTIONS!$D$51*(1+ASSUMPTIONS!$B$66),0),0) -> 5121 | K12: =IFERROR(IF(10>=ASSUMPTIONS!$C$51,ASSUMPTIONS!$D$51*(1+ASSUMPTIONS!$B$66),0),0) -> 5121 | L12: =IFERROR(IF(11>=ASSUMPTIONS!$C$51,ASSUMPTIONS!$D$51*(1+ASSUMPTIONS!$B$66),0),0) -> 5121 | M12: =IFERROR(IF(12>=ASSUMPTIONS!$C$51,ASSUMPTIONS!$D$51*(1+ASSUMPTIONS!$B$66),0),0) -> 5121 | N12: =SUM(B12:M12) -> 35847 | O12: =IFERROR(IF(13>=ASSUMPTIONS!$C$51,ASSUMPTIONS!$D$51*(1+ASSUMPTIONS!$B$66),0),0) -> 5121 | P12: =IFERROR(IF(14>=ASSUMPTIONS!$C$51,ASSUMPTIONS!$D$51*(1+ASSUMPTIONS!$B$66),0),0) -> 5121 | Q12: =IFERROR(IF(15>=ASSUMPTIONS!$C$51,ASSUMPTIONS!$D$51*(1+ASSUMPTIONS!$B$66),0),0) -> 5121 | R12: =IFERROR(IF(16>=ASSUMPTIONS!$C$51,ASSUMPTIONS!$D$51*(1+ASSUMPTIONS!$B$66),0),0) -> 5121 | S12: =IFERROR(IF(17>=ASSUMPTIONS!$C$51,ASSUMPTIONS!$D$51*(1+ASSUMPTIONS!$B$66),0),0) -> 5121 | T12: =IFERROR(IF(18>=ASSUMPTIONS!$C$51,ASSUMPTIONS!$D$51*(1+ASSUMPTIONS!$B$66),0),0) -> 5121 | U12: =IFERROR(IF(19>=ASSUMPTIONS!$C$51,ASSUMPTIONS!$D$51*(1+ASSUMPTIONS!$B$66),0),0) -> 5121 | V12: =IFERROR(IF(20>=ASSUMPTIONS!$C$51,ASSUMPTIONS!$D$51*(1+ASSUMPTIONS!$B$66),0),0) -> 5121 | W12: =IFERROR(IF(21>=ASSUMPTIONS!$C$51,ASSUMPTIONS!$D$51*(1+ASSUMPTIONS!$B$66),0),0) -> 5121 | X12: =IFERROR(IF(22>=ASSUMPTIONS!$C$51,ASSUMPTIONS!$D$51*(1+ASSUMPTIONS!$B$66),0),0) -> 5121 | Y12: =IFERROR(IF(23>=ASSUMPTIONS!$C$51,ASSUMPTIONS!$D$51*(1+ASSUMPTIONS!$B$66),0),0) -> 5121 | Z12: =IFERROR(IF(24>=ASSUMPTIONS!$C$51,ASSUMPTIONS!$D$51*(1+ASSUMPTIONS!$B$66),0),0) -> 5121 | AA12: =SUM(O12:Z12) -> 61452 | AB12: =IFERROR(IF(25>=ASSUMPTIONS!$C$51,ASSUMPTIONS!$D$51*(1+ASSUMPTIONS!$B$66),0),0) -> 5121 | AC12: =IFERROR(IF(26>=ASSUMPTIONS!$C$51,ASSUMPTIONS!$D$51*(1+ASSUMPTIONS!$B$66),0),0) -> 5121 | AD12: =IFERROR(IF(27>=ASSUMPTIONS!$C$51,ASSUMPTIONS!$D$51*(1+ASSUMPTIONS!$B$66),0),0) -> 5121 | AE12: =IFERROR(IF(28>=ASSUMPTIONS!$C$51,ASSUMPTIONS!$D$51*(1+ASSUMPTIONS!$B$66),0),0) -> 5121 | AF12: =IFERROR(IF(29>=ASSUMPTIONS!$C$51,ASSUMPTIONS!$D$51*(1+ASSUMPTIONS!$B$66),0),0) -> 5121 | AG12: =IFERROR(IF(30>=ASSUMPTIONS!$C$51,ASSUMPTIONS!$D$51*(1+ASSUMPTIONS!$B$66),0),0) -> 5121 | AH12: =IFERROR(IF(31>=ASSUMPTIONS!$C$51,ASSUMPTIONS!$D$51*(1+ASSUMPTIONS!$B$66),0),0) -> 5121 | AI12: =IFERROR(IF(32>=ASSUMPTIONS!$C$51,ASSUMPTIONS!$D$51*(1+ASSUMPTIONS!$B$66),0),0) -> 5121 | AJ12: =IFERROR(IF(33>=ASSUMPTIONS!$C$51,ASSUMPTIONS!$D$51*(1+ASSUMPTIONS!$B$66),0),0) -> 5121 | AK12: =IFERROR(IF(34>=ASSUMPTIONS!$C$51,ASSUMPTIONS!$D$51*(1+ASSUMPTIONS!$B$66),0),0) -> 5121 | AL12: =IFERROR(IF(35>=ASSUMPTIONS!$C$51,ASSUMPTIONS!$D$51*(1+ASSUMPTIONS!$B$66),0),0) -> 5121 | AM12: =IFERROR(IF(36>=ASSUMPTIONS!$C$51,ASSUMPTIONS!$D$51*(1+ASSUMPTIONS!$B$66),0),0) -> 5121 | AN12: =SUM(AB12:AM12) -> 61452 | AO12: =IFERROR(IF(37>=ASSUMPTIONS!$C$51,ASSUMPTIONS!$D$51*(1+ASSUMPTIONS!$B$66),0),0) -> 5121 | AP12: =IFERROR(IF(38>=ASSUMPTIONS!$C$51,ASSUMPTIONS!$D$51*(1+ASSUMPTIONS!$B$66),0),0) -> 5121 | AQ12: =IFERROR(IF(39>=ASSUMPTIONS!$C$51,ASSUMPTIONS!$D$51*(1+ASSUMPTIONS!$B$66),0),0) -> 5121 | AR12: =IFERROR(IF(40>=ASSUMPTIONS!$C$51,ASSUMPTIONS!$D$51*(1+ASSUMPTIONS!$B$66),0),0) -> 5121 | AS12: =IFERROR(IF(41>=ASSUMPTIONS!$C$51,ASSUMPTIONS!$D$51*(1+ASSUMPTIONS!$B$66),0),0) -> 5121 | AT12: =IFERROR(IF(42>=ASSUMPTIONS!$C$51,ASSUMPTIONS!$D$51*(1+ASSUMPTIONS!$B$66),0),0) -> 5121 | AU12: =IFERROR(IF(43>=ASSUMPTIONS!$C$51,ASSUMPTIONS!$D$51*(1+ASSUMPTIONS!$B$66),0),0) -> 5121 | AV12: =IFERROR(IF(44>=ASSUMPTIONS!$C$51,ASSUMPTIONS!$D$51*(1+ASSUMPTIONS!$B$66),0),0) -> 5121 | AW12: =IFERROR(IF(45>=ASSUMPTIONS!$C$51,ASSUMPTIONS!$D$51*(1+ASSUMPTIONS!$B$66),0),0) -> 5121 | AX12: =IFERROR(IF(46>=ASSUMPTIONS!$C$51,ASSUMPTIONS!$D$51*(1+ASSUMPTIONS!$B$66),0),0) -> 5121 | AY12: =IFERROR(IF(47>=ASSUMPTIONS!$C$51,ASSUMPTIONS!$D$51*(1+ASSUMPTIONS!$B$66),0),0) -> 5121 | AZ12: =IFERROR(IF(48>=ASSUMPTIONS!$C$51,ASSUMPTIONS!$D$51*(1+ASSUMPTIONS!$B$66),0),0) -> 5121 | BA12: =SUM(AO12:AZ12) -> 61452 | BB12: =IFERROR(IF(49>=ASSUMPTIONS!$C$51,ASSUMPTIONS!$D$51*(1+ASSUMPTIONS!$B$66),0),0) -> 5121 | BC12: =IFERROR(IF(50>=ASSUMPTIONS!$C$51,ASSUMPTIONS!$D$51*(1+ASSUMPTIONS!$B$66),0),0) -> 5121 | BD12: =IFERROR(IF(51>=ASSUMPTIONS!$C$51,ASSUMPTIONS!$D$51*(1+ASSUMPTIONS!$B$66),0),0) -> 5121 | BE12: =IFERROR(IF(52>=ASSUMPTIONS!$C$51,ASSUMPTIONS!$D$51*(1+ASSUMPTIONS!$B$66),0),0) -> 5121 | BF12: =IFERROR(IF(53>=ASSUMPTIONS!$C$51,ASSUMPTIONS!$D$51*(1+ASSUMPTIONS!$B$66),0),0) -> 5121 | BG12: =IFERROR(IF(54>=ASSUMPTIONS!$C$51,ASSUMPTIONS!$D$51*(1+ASSUMPTIONS!$B$66),0),0) -> 5121 | BH12: =IFERROR(IF(55>=ASSUMPTIONS!$C$51,ASSUMPTIONS!$D$51*(1+ASSUMPTIONS!$B$66),0),0) -> 5121 | BI12: =IFERROR(IF(56>=ASSUMPTIONS!$C$51,ASSUMPTIONS!$D$51*(1+ASSUMPTIONS!$B$66),0),0) -> 5121 | BJ12: =IFERROR(IF(57>=ASSUMPTIONS!$C$51,ASSUMPTIONS!$D$51*(1+ASSUMPTIONS!$B$66),0),0) -> 5121 | BK12: =IFERROR(IF(58>=ASSUMPTIONS!$C$51,ASSUMPTIONS!$D$51*(1+ASSUMPTIONS!$B$66),0),0) -> 5121 | BL12: =IFERROR(IF(59>=ASSUMPTIONS!$C$51,ASSUMPTIONS!$D$51*(1+ASSUMPTIONS!$B$66),0),0) -> 5121 | BM12: =IFERROR(IF(60>=ASSUMPTIONS!$C$51,ASSUMPTIONS!$D$51*(1+ASSUMPTIONS!$B$66),0),0) -> 5121 | BN12: =SUM(BB12:BM12) -> 61452
A13: ENGINEERING — TOTAL (£) | B13: =SUM(B8:B12) -> 18208 | C13: =SUM(C8:C12) -> 18208 | D13: =SUM(D8:D12) -> 24467 | E13: =SUM(E8:E12) -> 24467 | F13: =SUM(F8:F12) -> 24467 | G13: =SUM(G8:G12) -> 35847 | H13: =SUM(H8:H12) -> 35847 | I13: =SUM(I8:I12) -> 35847 | ... M13: =SUM(M8:M12) -> 35847 | N13: =SUM(B13:M13) -> 360746 | O13: =SUM(O8:O12) -> 35847 | P13: =SUM(P8:P12) -> 35847 | Q13: =SUM(Q8:Q12) -> 35847 | R13: =SUM(R8:R12) -> 35847 | S13: =SUM(S8:S12) -> 35847 | T13: =SUM(T8:T12) -> 35847 | U13: =SUM(U8:U12) -> 35847 | V13: =SUM(V8:V12) -> 35847 | ... Z13: =SUM(Z8:Z12) -> 35847 | AA13: =SUM(O13:Z13) -> 430164 | AB13: =SUM(AB8:AB12) -> 35847 | AC13: =SUM(AC8:AC12) -> 35847 | AD13: =SUM(AD8:AD12) -> 35847 | AE13: =SUM(AE8:AE12) -> 35847 | AF13: =SUM(AF8:AF12) -> 35847 | AG13: =SUM(AG8:AG12) -> 35847 | AH13: =SUM(AH8:AH12) -> 35847 | AI13: =SUM(AI8:AI12) -> 35847 | ... AM13: =SUM(AM8:AM12) -> 35847 | AN13: =SUM(AB13:AM13) -> 430164 | AO13: =SUM(AO8:AO12) -> 35847 | AP13: =SUM(AP8:AP12) -> 35847 | AQ13: =SUM(AQ8:AQ12) -> 35847 | AR13: =SUM(AR8:AR12) -> 35847 | AS13: =SUM(AS8:AS12) -> 35847 | AT13: =SUM(AT8:AT12) -> 35847 | AU13: =SUM(AU8:AU12) -> 35847 | AV13: =SUM(AV8:AV12) -> 35847 | ... AZ13: =SUM(AZ8:AZ12) -> 35847 | BA13: =SUM(AO13:AZ13) -> 430164 | BB13: =SUM(BB8:BB12) -> 35847 | BC13: =SUM(BC8:BC12) -> 35847 | BD13: =SUM(BD8:BD12) -> 35847 | BE13: =SUM(BE8:BE12) -> 35847 | BF13: =SUM(BF8:BF12) -> 35847 | BG13: =SUM(BG8:BG12) -> 35847 | BH13: =SUM(BH8:BH12) -> 35847 | BI13: =SUM(BI8:BI12) -> 35847 | ... BM13: =SUM(BM8:BM12) -> 35847 | BN13: =SUM(BB13:BM13) -> 430164
A15: PRODUCT
A16: =IFERROR(ASSUMPTIONS!B52,"(empty)") -> Product | B16: =IFERROR(IF(1>=ASSUMPTIONS!$C$52,ASSUMPTIONS!$D$52*(1+ASSUMPTIONS!$B$66),0),0) -> 9104 | C16: =IFERROR(IF(2>=ASSUMPTIONS!$C$52,ASSUMPTIONS!$D$52*(1+ASSUMPTIONS!$B$66),0),0) -> 9104 | D16: =IFERROR(IF(3>=ASSUMPTIONS!$C$52,ASSUMPTIONS!$D$52*(1+ASSUMPTIONS!$B$66),0),0) -> 9104 | E16: =IFERROR(IF(4>=ASSUMPTIONS!$C$52,ASSUMPTIONS!$D$52*(1+ASSUMPTIONS!$B$66),0),0) -> 9104 | F16: =IFERROR(IF(5>=ASSUMPTIONS!$C$52,ASSUMPTIONS!$D$52*(1+ASSUMPTIONS!$B$66),0),0) -> 9104 | G16: =IFERROR(IF(6>=ASSUMPTIONS!$C$52,ASSUMPTIONS!$D$52*(1+ASSUMPTIONS!$B$66),0),0) -> 9104 | H16: =IFERROR(IF(7>=ASSUMPTIONS!$C$52,ASSUMPTIONS!$D$52*(1+ASSUMPTIONS!$B$66),0),0) -> 9104 | I16: =IFERROR(IF(8>=ASSUMPTIONS!$C$52,ASSUMPTIONS!$D$52*(1+ASSUMPTIONS!$B$66),0),0) -> 9104 | J16: =IFERROR(IF(9>=ASSUMPTIONS!$C$52,ASSUMPTIONS!$D$52*(1+ASSUMPTIONS!$B$66),0),0) -> 9104 | K16: =IFERROR(IF(10>=ASSUMPTIONS!$C$52,ASSUMPTIONS!$D$52*(1+ASSUMPTIONS!$B$66),0),0) -> 9104 | L16: =IFERROR(IF(11>=ASSUMPTIONS!$C$52,ASSUMPTIONS!$D$52*(1+ASSUMPTIONS!$B$66),0),0) -> 9104 | M16: =IFERROR(IF(12>=ASSUMPTIONS!$C$52,ASSUMPTIONS!$D$52*(1+ASSUMPTIONS!$B$66),0),0) -> 9104 | N16: =SUM(B16:M16) -> 109248 | O16: =IFERROR(IF(13>=ASSUMPTIONS!$C$52,ASSUMPTIONS!$D$52*(1+ASSUMPTIONS!$B$66),0),0) -> 9104 | P16: =IFERROR(IF(14>=ASSUMPTIONS!$C$52,ASSUMPTIONS!$D$52*(1+ASSUMPTIONS!$B$66),0),0) -> 9104 | Q16: =IFERROR(IF(15>=ASSUMPTIONS!$C$52,ASSUMPTIONS!$D$52*(1+ASSUMPTIONS!$B$66),0),0) -> 9104 | R16: =IFERROR(IF(16>=ASSUMPTIONS!$C$52,ASSUMPTIONS!$D$52*(1+ASSUMPTIONS!$B$66),0),0) -> 9104 | S16: =IFERROR(IF(17>=ASSUMPTIONS!$C$52,ASSUMPTIONS!$D$52*(1+ASSUMPTIONS!$B$66),0),0) -> 9104 | T16: =IFERROR(IF(18>=ASSUMPTIONS!$C$52,ASSUMPTIONS!$D$52*(1+ASSUMPTIONS!$B$66),0),0) -> 9104 | U16: =IFERROR(IF(19>=ASSUMPTIONS!$C$52,ASSUMPTIONS!$D$52*(1+ASSUMPTIONS!$B$66),0),0) -> 9104 | V16: =IFERROR(IF(20>=ASSUMPTIONS!$C$52,ASSUMPTIONS!$D$52*(1+ASSUMPTIONS!$B$66),0),0) -> 9104 | W16: =IFERROR(IF(21>=ASSUMPTIONS!$C$52,ASSUMPTIONS!$D$52*(1+ASSUMPTIONS!$B$66),0),0) -> 9104 | X16: =IFERROR(IF(22>=ASSUMPTIONS!$C$52,ASSUMPTIONS!$D$52*(1+ASSUMPTIONS!$B$66),0),0) -> 9104 | Y16: =IFERROR(IF(23>=ASSUMPTIONS!$C$52,ASSUMPTIONS!$D$52*(1+ASSUMPTIONS!$B$66),0),0) -> 9104 | Z16: =IFERROR(IF(24>=ASSUMPTIONS!$C$52,ASSUMPTIONS!$D$52*(1+ASSUMPTIONS!$B$66),0),0) -> 9104 | AA16: =SUM(O16:Z16) -> 109248 | AB16: =IFERROR(IF(25>=ASSUMPTIONS!$C$52,ASSUMPTIONS!$D$52*(1+ASSUMPTIONS!$B$66),0),0) -> 9104 | AC16: =IFERROR(IF(26>=ASSUMPTIONS!$C$52,ASSUMPTIONS!$D$52*(1+ASSUMPTIONS!$B$66),0),0) -> 9104 | AD16: =IFERROR(IF(27>=ASSUMPTIONS!$C$52,ASSUMPTIONS!$D$52*(1+ASSUMPTIONS!$B$66),0),0) -> 9104 | AE16: =IFERROR(IF(28>=ASSUMPTIONS!$C$52,ASSUMPTIONS!$D$52*(1+ASSUMPTIONS!$B$66),0),0) -> 9104 | AF16: =IFERROR(IF(29>=ASSUMPTIONS!$C$52,ASSUMPTIONS!$D$52*(1+ASSUMPTIONS!$B$66),0),0) -> 9104 | AG16: =IFERROR(IF(30>=ASSUMPTIONS!$C$52,ASSUMPTIONS!$D$52*(1+ASSUMPTIONS!$B$66),0),0) -> 9104 | AH16: =IFERROR(IF(31>=ASSUMPTIONS!$C$52,ASSUMPTIONS!$D$52*(1+ASSUMPTIONS!$B$66),0),0) -> 9104 | AI16: =IFERROR(IF(32>=ASSUMPTIONS!$C$52,ASSUMPTIONS!$D$52*(1+ASSUMPTIONS!$B$66),0),0) -> 9104 | AJ16: =IFERROR(IF(33>=ASSUMPTIONS!$C$52,ASSUMPTIONS!$D$52*(1+ASSUMPTIONS!$B$66),0),0) -> 9104 | AK16: =IFERROR(IF(34>=ASSUMPTIONS!$C$52,ASSUMPTIONS!$D$52*(1+ASSUMPTIONS!$B$66),0),0) -> 9104 | AL16: =IFERROR(IF(35>=ASSUMPTIONS!$C$52,ASSUMPTIONS!$D$52*(1+ASSUMPTIONS!$B$66),0),0) -> 9104 | AM16: =IFERROR(IF(36>=ASSUMPTIONS!$C$52,ASSUMPTIONS!$D$52*(1+ASSUMPTIONS!$B$66),0),0) -> 9104 | AN16: =SUM(AB16:AM16) -> 109248 | AO16: =IFERROR(IF(37>=ASSUMPTIONS!$C$52,ASSUMPTIONS!$D$52*(1+ASSUMPTIONS!$B$66),0),0) -> 9104 | AP16: =IFERROR(IF(38>=ASSUMPTIONS!$C$52,ASSUMPTIONS!$D$52*(1+ASSUMPTIONS!$B$66),0),0) -> 9104 | AQ16: =IFERROR(IF(39>=ASSUMPTIONS!$C$52,ASSUMPTIONS!$D$52*(1+ASSUMPTIONS!$B$66),0),0) -> 9104 | AR16: =IFERROR(IF(40>=ASSUMPTIONS!$C$52,ASSUMPTIONS!$D$52*(1+ASSUMPTIONS!$B$66),0),0) -> 9104 | AS16: =IFERROR(IF(41>=ASSUMPTIONS!$C$52,ASSUMPTIONS!$D$52*(1+ASSUMPTIONS!$B$66),0),0) -> 9104 | AT16: =IFERROR(IF(42>=ASSUMPTIONS!$C$52,ASSUMPTIONS!$D$52*(1+ASSUMPTIONS!$B$66),0),0) -> 9104 | AU16: =IFERROR(IF(43>=ASSUMPTIONS!$C$52,ASSUMPTIONS!$D$52*(1+ASSUMPTIONS!$B$66),0),0) -> 9104 | AV16: =IFERROR(IF(44>=ASSUMPTIONS!$C$52,ASSUMPTIONS!$D$52*(1+ASSUMPTIONS!$B$66),0),0) -> 9104 | AW16: =IFERROR(IF(45>=ASSUMPTIONS!$C$52,ASSUMPTIONS!$D$52*(1+ASSUMPTIONS!$B$66),0),0) -> 9104 | AX16: =IFERROR(IF(46>=ASSUMPTIONS!$C$52,ASSUMPTIONS!$D$52*(1+ASSUMPTIONS!$B$66),0),0) -> 9104 | AY16: =IFERROR(IF(47>=ASSUMPTIONS!$C$52,ASSUMPTIONS!$D$52*(1+ASSUMPTIONS!$B$66),0),0) -> 9104 | AZ16: =IFERROR(IF(48>=ASSUMPTIONS!$C$52,ASSUMPTIONS!$D$52*(1+ASSUMPTIONS!$B$66),0),0) -> 9104 | BA16: =SUM(AO16:AZ16) -> 109248 | BB16: =IFERROR(IF(49>=ASSUMPTIONS!$C$52,ASSUMPTIONS!$D$52*(1+ASSUMPTIONS!$B$66),0),0) -> 9104 | BC16: =IFERROR(IF(50>=ASSUMPTIONS!$C$52,ASSUMPTIONS!$D$52*(1+ASSUMPTIONS!$B$66),0),0) -> 9104 | BD16: =IFERROR(IF(51>=ASSUMPTIONS!$C$52,ASSUMPTIONS!$D$52*(1+ASSUMPTIONS!$B$66),0),0) -> 9104 | BE16: =IFERROR(IF(52>=ASSUMPTIONS!$C$52,ASSUMPTIONS!$D$52*(1+ASSUMPTIONS!$B$66),0),0) -> 9104 | BF16: =IFERROR(IF(53>=ASSUMPTIONS!$C$52,ASSUMPTIONS!$D$52*(1+ASSUMPTIONS!$B$66),0),0) -> 9104 | BG16: =IFERROR(IF(54>=ASSUMPTIONS!$C$52,ASSUMPTIONS!$D$52*(1+ASSUMPTIONS!$B$66),0),0) -> 9104 | BH16: =IFERROR(IF(55>=ASSUMPTIONS!$C$52,ASSUMPTIONS!$D$52*(1+ASSUMPTIONS!$B$66),0),0) -> 9104 | BI16: =IFERROR(IF(56>=ASSUMPTIONS!$C$52,ASSUMPTIONS!$D$52*(1+ASSUMPTIONS!$B$66),0),0) -> 9104 | BJ16: =IFERROR(IF(57>=ASSUMPTIONS!$C$52,ASSUMPTIONS!$D$52*(1+ASSUMPTIONS!$B$66),0),0) -> 9104 | BK16: =IFERROR(IF(58>=ASSUMPTIONS!$C$52,ASSUMPTIONS!$D$52*(1+ASSUMPTIONS!$B$66),0),0) -> 9104 | BL16: =IFERROR(IF(59>=ASSUMPTIONS!$C$52,ASSUMPTIONS!$D$52*(1+ASSUMPTIONS!$B$66),0),0) -> 9104 | BM16: =IFERROR(IF(60>=ASSUMPTIONS!$C$52,ASSUMPTIONS!$D$52*(1+ASSUMPTIONS!$B$66),0),0) -> 9104 | BN16: =SUM(BB16:BM16) -> 109248
A17: =IFERROR(ASSUMPTIONS!B53,"(empty)") -> Product | B17: =IFERROR(IF(1>=ASSUMPTIONS!$C$53,ASSUMPTIONS!$D$53*(1+ASSUMPTIONS!$B$66),0),0) -> 0 | C17: =IFERROR(IF(2>=ASSUMPTIONS!$C$53,ASSUMPTIONS!$D$53*(1+ASSUMPTIONS!$B$66),0),0) -> 0 | D17: =IFERROR(IF(3>=ASSUMPTIONS!$C$53,ASSUMPTIONS!$D$53*(1+ASSUMPTIONS!$B$66),0),0) -> 6828 | E17: =IFERROR(IF(4>=ASSUMPTIONS!$C$53,ASSUMPTIONS!$D$53*(1+ASSUMPTIONS!$B$66),0),0) -> 6828 | F17: =IFERROR(IF(5>=ASSUMPTIONS!$C$53,ASSUMPTIONS!$D$53*(1+ASSUMPTIONS!$B$66),0),0) -> 6828 | G17: =IFERROR(IF(6>=ASSUMPTIONS!$C$53,ASSUMPTIONS!$D$53*(1+ASSUMPTIONS!$B$66),0),0) -> 6828 | H17: =IFERROR(IF(7>=ASSUMPTIONS!$C$53,ASSUMPTIONS!$D$53*(1+ASSUMPTIONS!$B$66),0),0) -> 6828 | I17: =IFERROR(IF(8>=ASSUMPTIONS!$C$53,ASSUMPTIONS!$D$53*(1+ASSUMPTIONS!$B$66),0),0) -> 6828 | J17: =IFERROR(IF(9>=ASSUMPTIONS!$C$53,ASSUMPTIONS!$D$53*(1+ASSUMPTIONS!$B$66),0),0) -> 6828 | K17: =IFERROR(IF(10>=ASSUMPTIONS!$C$53,ASSUMPTIONS!$D$53*(1+ASSUMPTIONS!$B$66),0),0) -> 6828 | L17: =IFERROR(IF(11>=ASSUMPTIONS!$C$53,ASSUMPTIONS!$D$53*(1+ASSUMPTIONS!$B$66),0),0) -> 6828 | M17: =IFERROR(IF(12>=ASSUMPTIONS!$C$53,ASSUMPTIONS!$D$53*(1+ASSUMPTIONS!$B$66),0),0) -> 6828 | N17: =SUM(B17:M17) -> 68280 | O17: =IFERROR(IF(13>=ASSUMPTIONS!$C$53,ASSUMPTIONS!$D$53*(1+ASSUMPTIONS!$B$66),0),0) -> 6828 | P17: =IFERROR(IF(14>=ASSUMPTIONS!$C$53,ASSUMPTIONS!$D$53*(1+ASSUMPTIONS!$B$66),0),0) -> 6828 | Q17: =IFERROR(IF(15>=ASSUMPTIONS!$C$53,ASSUMPTIONS!$D$53*(1+ASSUMPTIONS!$B$66),0),0) -> 6828 | R17: =IFERROR(IF(16>=ASSUMPTIONS!$C$53,ASSUMPTIONS!$D$53*(1+ASSUMPTIONS!$B$66),0),0) -> 6828 | S17: =IFERROR(IF(17>=ASSUMPTIONS!$C$53,ASSUMPTIONS!$D$53*(1+ASSUMPTIONS!$B$66),0),0) -> 6828 | T17: =IFERROR(IF(18>=ASSUMPTIONS!$C$53,ASSUMPTIONS!$D$53*(1+ASSUMPTIONS!$B$66),0),0) -> 6828 | U17: =IFERROR(IF(19>=ASSUMPTIONS!$C$53,ASSUMPTIONS!$D$53*(1+ASSUMPTIONS!$B$66),0),0) -> 6828 | V17: =IFERROR(IF(20>=ASSUMPTIONS!$C$53,ASSUMPTIONS!$D$53*(1+ASSUMPTIONS!$B$66),0),0) -> 6828 | W17: =IFERROR(IF(21>=ASSUMPTIONS!$C$53,ASSUMPTIONS!$D$53*(1+ASSUMPTIONS!$B$66),0),0) -> 6828 | X17: =IFERROR(IF(22>=ASSUMPTIONS!$C$53,ASSUMPTIONS!$D$53*(1+ASSUMPTIONS!$B$66),0),0) -> 6828 | Y17: =IFERROR(IF(23>=ASSUMPTIONS!$C$53,ASSUMPTIONS!$D$53*(1+ASSUMPTIONS!$B$66),0),0) -> 6828 | Z17: =IFERROR(IF(24>=ASSUMPTIONS!$C$53,ASSUMPTIONS!$D$53*(1+ASSUMPTIONS!$B$66),0),0) -> 6828 | AA17: =SUM(O17:Z17) -> 81936 | AB17: =IFERROR(IF(25>=ASSUMPTIONS!$C$53,ASSUMPTIONS!$D$53*(1+ASSUMPTIONS!$B$66),0),0) -> 6828 | AC17: =IFERROR(IF(26>=ASSUMPTIONS!$C$53,ASSUMPTIONS!$D$53*(1+ASSUMPTIONS!$B$66),0),0) -> 6828 | AD17: =IFERROR(IF(27>=ASSUMPTIONS!$C$53,ASSUMPTIONS!$D$53*(1+ASSUMPTIONS!$B$66),0),0) -> 6828 | AE17: =IFERROR(IF(28>=ASSUMPTIONS!$C$53,ASSUMPTIONS!$D$53*(1+ASSUMPTIONS!$B$66),0),0) -> 6828 | AF17: =IFERROR(IF(29>=ASSUMPTIONS!$C$53,ASSUMPTIONS!$D$53*(1+ASSUMPTIONS!$B$66),0),0) -> 6828 | AG17: =IFERROR(IF(30>=ASSUMPTIONS!$C$53,ASSUMPTIONS!$D$53*(1+ASSUMPTIONS!$B$66),0),0) -> 6828 | AH17: =IFERROR(IF(31>=ASSUMPTIONS!$C$53,ASSUMPTIONS!$D$53*(1+ASSUMPTIONS!$B$66),0),0) -> 6828 | AI17: =IFERROR(IF(32>=ASSUMPTIONS!$C$53,ASSUMPTIONS!$D$53*(1+ASSUMPTIONS!$B$66),0),0) -> 6828 | AJ17: =IFERROR(IF(33>=ASSUMPTIONS!$C$53,ASSUMPTIONS!$D$53*(1+ASSUMPTIONS!$B$66),0),0) -> 6828 | AK17: =IFERROR(IF(34>=ASSUMPTIONS!$C$53,ASSUMPTIONS!$D$53*(1+ASSUMPTIONS!$B$66),0),0) -> 6828 | AL17: =IFERROR(IF(35>=ASSUMPTIONS!$C$53,ASSUMPTIONS!$D$53*(1+ASSUMPTIONS!$B$66),0),0) -> 6828 | AM17: =IFERROR(IF(36>=ASSUMPTIONS!$C$53,ASSUMPTIONS!$D$53*(1+ASSUMPTIONS!$B$66),0),0) -> 6828 | AN17: =SUM(AB17:AM17) -> 81936 | AO17: =IFERROR(IF(37>=ASSUMPTIONS!$C$53,ASSUMPTIONS!$D$53*(1+ASSUMPTIONS!$B$66),0),0) -> 6828 | AP17: =IFERROR(IF(38>=ASSUMPTIONS!$C$53,ASSUMPTIONS!$D$53*(1+ASSUMPTIONS!$B$66),0),0) -> 6828 | AQ17: =IFERROR(IF(39>=ASSUMPTIONS!$C$53,ASSUMPTIONS!$D$53*(1+ASSUMPTIONS!$B$66),0),0) -> 6828 | AR17: =IFERROR(IF(40>=ASSUMPTIONS!$C$53,ASSUMPTIONS!$D$53*(1+ASSUMPTIONS!$B$66),0),0) -> 6828 | AS17: =IFERROR(IF(41>=ASSUMPTIONS!$C$53,ASSUMPTIONS!$D$53*(1+ASSUMPTIONS!$B$66),0),0) -> 6828 | AT17: =IFERROR(IF(42>=ASSUMPTIONS!$C$53,ASSUMPTIONS!$D$53*(1+ASSUMPTIONS!$B$66),0),0) -> 6828 | AU17: =IFERROR(IF(43>=ASSUMPTIONS!$C$53,ASSUMPTIONS!$D$53*(1+ASSUMPTIONS!$B$66),0),0) -> 6828 | AV17: =IFERROR(IF(44>=ASSUMPTIONS!$C$53,ASSUMPTIONS!$D$53*(1+ASSUMPTIONS!$B$66),0),0) -> 6828 | AW17: =IFERROR(IF(45>=ASSUMPTIONS!$C$53,ASSUMPTIONS!$D$53*(1+ASSUMPTIONS!$B$66),0),0) -> 6828 | AX17: =IFERROR(IF(46>=ASSUMPTIONS!$C$53,ASSUMPTIONS!$D$53*(1+ASSUMPTIONS!$B$66),0),0) -> 6828 | AY17: =IFERROR(IF(47>=ASSUMPTIONS!$C$53,ASSUMPTIONS!$D$53*(1+ASSUMPTIONS!$B$66),0),0) -> 6828 | AZ17: =IFERROR(IF(48>=ASSUMPTIONS!$C$53,ASSUMPTIONS!$D$53*(1+ASSUMPTIONS!$B$66),0),0) -> 6828 | BA17: =SUM(AO17:AZ17) -> 81936 | BB17: =IFERROR(IF(49>=ASSUMPTIONS!$C$53,ASSUMPTIONS!$D$53*(1+ASSUMPTIONS!$B$66),0),0) -> 6828 | BC17: =IFERROR(IF(50>=ASSUMPTIONS!$C$53,ASSUMPTIONS!$D$53*(1+ASSUMPTIONS!$B$66),0),0) -> 6828 | BD17: =IFERROR(IF(51>=ASSUMPTIONS!$C$53,ASSUMPTIONS!$D$53*(1+ASSUMPTIONS!$B$66),0),0) -> 6828 | BE17: =IFERROR(IF(52>=ASSUMPTIONS!$C$53,ASSUMPTIONS!$D$53*(1+ASSUMPTIONS!$B$66),0),0) -> 6828 | BF17: =IFERROR(IF(53>=ASSUMPTIONS!$C$53,ASSUMPTIONS!$D$53*(1+ASSUMPTIONS!$B$66),0),0) -> 6828 | BG17: =IFERROR(IF(54>=ASSUMPTIONS!$C$53,ASSUMPTIONS!$D$53*(1+ASSUMPTIONS!$B$66),0),0) -> 6828 | BH17: =IFERROR(IF(55>=ASSUMPTIONS!$C$53,ASSUMPTIONS!$D$53*(1+ASSUMPTIONS!$B$66),0),0) -> 6828 | BI17: =IFERROR(IF(56>=ASSUMPTIONS!$C$53,ASSUMPTIONS!$D$53*(1+ASSUMPTIONS!$B$66),0),0) -> 6828 | BJ17: =IFERROR(IF(57>=ASSUMPTIONS!$C$53,ASSUMPTIONS!$D$53*(1+ASSUMPTIONS!$B$66),0),0) -> 6828 | BK17: =IFERROR(IF(58>=ASSUMPTIONS!$C$53,ASSUMPTIONS!$D$53*(1+ASSUMPTIONS!$B$66),0),0) -> 6828 | BL17: =IFERROR(IF(59>=ASSUMPTIONS!$C$53,ASSUMPTIONS!$D$53*(1+ASSUMPTIONS!$B$66),0),0) -> 6828 | BM17: =IFERROR(IF(60>=ASSUMPTIONS!$C$53,ASSUMPTIONS!$D$53*(1+ASSUMPTIONS!$B$66),0),0) -> 6828 | BN17: =SUM(BB17:BM17) -> 81936
A18: =IFERROR(ASSUMPTIONS!B54,"(empty)") -> Product | B18: =IFERROR(IF(1>=ASSUMPTIONS!$C$54,ASSUMPTIONS!$D$54*(1+ASSUMPTIONS!$B$66),0),0) -> 0 | C18: =IFERROR(IF(2>=ASSUMPTIONS!$C$54,ASSUMPTIONS!$D$54*(1+ASSUMPTIONS!$B$66),0),0) -> 0 | D18: =IFERROR(IF(3>=ASSUMPTIONS!$C$54,ASSUMPTIONS!$D$54*(1+ASSUMPTIONS!$B$66),0),0) -> 0 | E18: =IFERROR(IF(4>=ASSUMPTIONS!$C$54,ASSUMPTIONS!$D$54*(1+ASSUMPTIONS!$B$66),0),0) -> 0 | F18: =IFERROR(IF(5>=ASSUMPTIONS!$C$54,ASSUMPTIONS!$D$54*(1+ASSUMPTIONS!$B$66),0),0) -> 0 | G18: =IFERROR(IF(6>=ASSUMPTIONS!$C$54,ASSUMPTIONS!$D$54*(1+ASSUMPTIONS!$B$66),0),0) -> 5690 | H18: =IFERROR(IF(7>=ASSUMPTIONS!$C$54,ASSUMPTIONS!$D$54*(1+ASSUMPTIONS!$B$66),0),0) -> 5690 | I18: =IFERROR(IF(8>=ASSUMPTIONS!$C$54,ASSUMPTIONS!$D$54*(1+ASSUMPTIONS!$B$66),0),0) -> 5690 | J18: =IFERROR(IF(9>=ASSUMPTIONS!$C$54,ASSUMPTIONS!$D$54*(1+ASSUMPTIONS!$B$66),0),0) -> 5690 | K18: =IFERROR(IF(10>=ASSUMPTIONS!$C$54,ASSUMPTIONS!$D$54*(1+ASSUMPTIONS!$B$66),0),0) -> 5690 | L18: =IFERROR(IF(11>=ASSUMPTIONS!$C$54,ASSUMPTIONS!$D$54*(1+ASSUMPTIONS!$B$66),0),0) -> 5690 | M18: =IFERROR(IF(12>=ASSUMPTIONS!$C$54,ASSUMPTIONS!$D$54*(1+ASSUMPTIONS!$B$66),0),0) -> 5690 | N18: =SUM(B18:M18) -> 39830 | O18: =IFERROR(IF(13>=ASSUMPTIONS!$C$54,ASSUMPTIONS!$D$54*(1+ASSUMPTIONS!$B$66),0),0) -> 5690 | P18: =IFERROR(IF(14>=ASSUMPTIONS!$C$54,ASSUMPTIONS!$D$54*(1+ASSUMPTIONS!$B$66),0),0) -> 5690 | Q18: =IFERROR(IF(15>=ASSUMPTIONS!$C$54,ASSUMPTIONS!$D$54*(1+ASSUMPTIONS!$B$66),0),0) -> 5690 | R18: =IFERROR(IF(16>=ASSUMPTIONS!$C$54,ASSUMPTIONS!$D$54*(1+ASSUMPTIONS!$B$66),0),0) -> 5690 | S18: =IFERROR(IF(17>=ASSUMPTIONS!$C$54,ASSUMPTIONS!$D$54*(1+ASSUMPTIONS!$B$66),0),0) -> 5690 | T18: =IFERROR(IF(18>=ASSUMPTIONS!$C$54,ASSUMPTIONS!$D$54*(1+ASSUMPTIONS!$B$66),0),0) -> 5690 | U18: =IFERROR(IF(19>=ASSUMPTIONS!$C$54,ASSUMPTIONS!$D$54*(1+ASSUMPTIONS!$B$66),0),0) -> 5690 | V18: =IFERROR(IF(20>=ASSUMPTIONS!$C$54,ASSUMPTIONS!$D$54*(1+ASSUMPTIONS!$B$66),0),0) -> 5690 | W18: =IFERROR(IF(21>=ASSUMPTIONS!$C$54,ASSUMPTIONS!$D$54*(1+ASSUMPTIONS!$B$66),0),0) -> 5690 | X18: =IFERROR(IF(22>=ASSUMPTIONS!$C$54,ASSUMPTIONS!$D$54*(1+ASSUMPTIONS!$B$66),0),0) -> 5690 | Y18: =IFERROR(IF(23>=ASSUMPTIONS!$C$54,ASSUMPTIONS!$D$54*(1+ASSUMPTIONS!$B$66),0),0) -> 5690 | Z18: =IFERROR(IF(24>=ASSUMPTIONS!$C$54,ASSUMPTIONS!$D$54*(1+ASSUMPTIONS!$B$66),0),0) -> 5690 | AA18: =SUM(O18:Z18) -> 68280 | AB18: =IFERROR(IF(25>=ASSUMPTIONS!$C$54,ASSUMPTIONS!$D$54*(1+ASSUMPTIONS!$B$66),0),0) -> 5690 | AC18: =IFERROR(IF(26>=ASSUMPTIONS!$C$54,ASSUMPTIONS!$D$54*(1+ASSUMPTIONS!$B$66),0),0) -> 5690 | AD18: =IFERROR(IF(27>=ASSUMPTIONS!$C$54,ASSUMPTIONS!$D$54*(1+ASSUMPTIONS!$B$66),0),0) -> 5690 | AE18: =IFERROR(IF(28>=ASSUMPTIONS!$C$54,ASSUMPTIONS!$D$54*(1+ASSUMPTIONS!$B$66),0),0) -> 5690 | AF18: =IFERROR(IF(29>=ASSUMPTIONS!$C$54,ASSUMPTIONS!$D$54*(1+ASSUMPTIONS!$B$66),0),0) -> 5690 | AG18: =IFERROR(IF(30>=ASSUMPTIONS!$C$54,ASSUMPTIONS!$D$54*(1+ASSUMPTIONS!$B$66),0),0) -> 5690 | AH18: =IFERROR(IF(31>=ASSUMPTIONS!$C$54,ASSUMPTIONS!$D$54*(1+ASSUMPTIONS!$B$66),0),0) -> 5690 | AI18: =IFERROR(IF(32>=ASSUMPTIONS!$C$54,ASSUMPTIONS!$D$54*(1+ASSUMPTIONS!$B$66),0),0) -> 5690 | AJ18: =IFERROR(IF(33>=ASSUMPTIONS!$C$54,ASSUMPTIONS!$D$54*(1+ASSUMPTIONS!$B$66),0),0) -> 5690 | AK18: =IFERROR(IF(34>=ASSUMPTIONS!$C$54,ASSUMPTIONS!$D$54*(1+ASSUMPTIONS!$B$66),0),0) -> 5690 | AL18: =IFERROR(IF(35>=ASSUMPTIONS!$C$54,ASSUMPTIONS!$D$54*(1+ASSUMPTIONS!$B$66),0),0) -> 5690 | AM18: =IFERROR(IF(36>=ASSUMPTIONS!$C$54,ASSUMPTIONS!$D$54*(1+ASSUMPTIONS!$B$66),0),0) -> 5690 | AN18: =SUM(AB18:AM18) -> 68280 | AO18: =IFERROR(IF(37>=ASSUMPTIONS!$C$54,ASSUMPTIONS!$D$54*(1+ASSUMPTIONS!$B$66),0),0) -> 5690 | AP18: =IFERROR(IF(38>=ASSUMPTIONS!$C$54,ASSUMPTIONS!$D$54*(1+ASSUMPTIONS!$B$66),0),0) -> 5690 | AQ18: =IFERROR(IF(39>=ASSUMPTIONS!$C$54,ASSUMPTIONS!$D$54*(1+ASSUMPTIONS!$B$66),0),0) -> 5690 | AR18: =IFERROR(IF(40>=ASSUMPTIONS!$C$54,ASSUMPTIONS!$D$54*(1+ASSUMPTIONS!$B$66),0),0) -> 5690 | AS18: =IFERROR(IF(41>=ASSUMPTIONS!$C$54,ASSUMPTIONS!$D$54*(1+ASSUMPTIONS!$B$66),0),0) -> 5690 | AT18: =IFERROR(IF(42>=ASSUMPTIONS!$C$54,ASSUMPTIONS!$D$54*(1+ASSUMPTIONS!$B$66),0),0) -> 5690 | AU18: =IFERROR(IF(43>=ASSUMPTIONS!$C$54,ASSUMPTIONS!$D$54*(1+ASSUMPTIONS!$B$66),0),0) -> 5690 | AV18: =IFERROR(IF(44>=ASSUMPTIONS!$C$54,ASSUMPTIONS!$D$54*(1+ASSUMPTIONS!$B$66),0),0) -> 5690 | AW18: =IFERROR(IF(45>=ASSUMPTIONS!$C$54,ASSUMPTIONS!$D$54*(1+ASSUMPTIONS!$B$66),0),0) -> 5690 | AX18: =IFERROR(IF(46>=ASSUMPTIONS!$C$54,ASSUMPTIONS!$D$54*(1+ASSUMPTIONS!$B$66),0),0) -> 5690 | AY18: =IFERROR(IF(47>=ASSUMPTIONS!$C$54,ASSUMPTIONS!$D$54*(1+ASSUMPTIONS!$B$66),0),0) -> 5690 | AZ18: =IFERROR(IF(48>=ASSUMPTIONS!$C$54,ASSUMPTIONS!$D$54*(1+ASSUMPTIONS!$B$66),0),0) -> 5690 | BA18: =SUM(AO18:AZ18) -> 68280 | BB18: =IFERROR(IF(49>=ASSUMPTIONS!$C$54,ASSUMPTIONS!$D$54*(1+ASSUMPTIONS!$B$66),0),0) -> 5690 | BC18: =IFERROR(IF(50>=ASSUMPTIONS!$C$54,ASSUMPTIONS!$D$54*(1+ASSUMPTIONS!$B$66),0),0) -> 5690 | BD18: =IFERROR(IF(51>=ASSUMPTIONS!$C$54,ASSUMPTIONS!$D$54*(1+ASSUMPTIONS!$B$66),0),0) -> 5690 | BE18: =IFERROR(IF(52>=ASSUMPTIONS!$C$54,ASSUMPTIONS!$D$54*(1+ASSUMPTIONS!$B$66),0),0) -> 5690 | BF18: =IFERROR(IF(53>=ASSUMPTIONS!$C$54,ASSUMPTIONS!$D$54*(1+ASSUMPTIONS!$B$66),0),0) -> 5690 | BG18: =IFERROR(IF(54>=ASSUMPTIONS!$C$54,ASSUMPTIONS!$D$54*(1+ASSUMPTIONS!$B$66),0),0) -> 5690 | BH18: =IFERROR(IF(55>=ASSUMPTIONS!$C$54,ASSUMPTIONS!$D$54*(1+ASSUMPTIONS!$B$66),0),0) -> 5690 | BI18: =IFERROR(IF(56>=ASSUMPTIONS!$C$54,ASSUMPTIONS!$D$54*(1+ASSUMPTIONS!$B$66),0),0) -> 5690 | BJ18: =IFERROR(IF(57>=ASSUMPTIONS!$C$54,ASSUMPTIONS!$D$54*(1+ASSUMPTIONS!$B$66),0),0) -> 5690 | BK18: =IFERROR(IF(58>=ASSUMPTIONS!$C$54,ASSUMPTIONS!$D$54*(1+ASSUMPTIONS!$B$66),0),0) -> 5690 | BL18: =IFERROR(IF(59>=ASSUMPTIONS!$C$54,ASSUMPTIONS!$D$54*(1+ASSUMPTIONS!$B$66),0),0) -> 5690 | BM18: =IFERROR(IF(60>=ASSUMPTIONS!$C$54,ASSUMPTIONS!$D$54*(1+ASSUMPTIONS!$B$66),0),0) -> 5690 | BN18: =SUM(BB18:BM18) -> 68280
A19: PRODUCT — TOTAL (£) | B19: =SUM(B16:B18) -> 9104 | C19: =SUM(C16:C18) -> 9104 | D19: =SUM(D16:D18) -> 15932 | E19: =SUM(E16:E18) -> 15932 | F19: =SUM(F16:F18) -> 15932 | G19: =SUM(G16:G18) -> 21622 | H19: =SUM(H16:H18) -> 21622 | I19: =SUM(I16:I18) -> 21622 | ... M19: =SUM(M16:M18) -> 21622 | N19: =SUM(B19:M19) -> 217358 | O19: =SUM(O16:O18) -> 21622 | P19: =SUM(P16:P18) -> 21622 | Q19: =SUM(Q16:Q18) -> 21622 | R19: =SUM(R16:R18) -> 21622 | S19: =SUM(S16:S18) -> 21622 | T19: =SUM(T16:T18) -> 21622 | U19: =SUM(U16:U18) -> 21622 | V19: =SUM(V16:V18) -> 21622 | ... Z19: =SUM(Z16:Z18) -> 21622 | AA19: =SUM(O19:Z19) -> 259464 | AB19: =SUM(AB16:AB18) -> 21622 | AC19: =SUM(AC16:AC18) -> 21622 | AD19: =SUM(AD16:AD18) -> 21622 | AE19: =SUM(AE16:AE18) -> 21622 | AF19: =SUM(AF16:AF18) -> 21622 | AG19: =SUM(AG16:AG18) -> 21622 | AH19: =SUM(AH16:AH18) -> 21622 | AI19: =SUM(AI16:AI18) -> 21622 | ... AM19: =SUM(AM16:AM18) -> 21622 | AN19: =SUM(AB19:AM19) -> 259464 | AO19: =SUM(AO16:AO18) -> 21622 | AP19: =SUM(AP16:AP18) -> 21622 | AQ19: =SUM(AQ16:AQ18) -> 21622 | AR19: =SUM(AR16:AR18) -> 21622 | AS19: =SUM(AS16:AS18) -> 21622 | AT19: =SUM(AT16:AT18) -> 21622 | AU19: =SUM(AU16:AU18) -> 21622 | AV19: =SUM(AV16:AV18) -> 21622 | ... AZ19: =SUM(AZ16:AZ18) -> 21622 | BA19: =SUM(AO19:AZ19) -> 259464 | BB19: =SUM(BB16:BB18) -> 21622 | BC19: =SUM(BC16:BC18) -> 21622 | BD19: =SUM(BD16:BD18) -> 21622 | BE19: =SUM(BE16:BE18) -> 21622 | BF19: =SUM(BF16:BF18) -> 21622 | BG19: =SUM(BG16:BG18) -> 21622 | BH19: =SUM(BH16:BH18) -> 21622 | BI19: =SUM(BI16:BI18) -> 21622 | ... BM19: =SUM(BM16:BM18) -> 21622 | BN19: =SUM(BB19:BM19) -> 259464
A21: SALES
A22: =IFERROR(ASSUMPTIONS!B55,"(empty)") -> Sales | B22: =IFERROR(IF(1>=ASSUMPTIONS!$C$55,ASSUMPTIONS!$D$55*(1+ASSUMPTIONS!$B$66),0),0) -> 0 | C22: =IFERROR(IF(2>=ASSUMPTIONS!$C$55,ASSUMPTIONS!$D$55*(1+ASSUMPTIONS!$B$66),0),0) -> 0 | D22: =IFERROR(IF(3>=ASSUMPTIONS!$C$55,ASSUMPTIONS!$D$55*(1+ASSUMPTIONS!$B$66),0),0) -> 0 | E22: =IFERROR(IF(4>=ASSUMPTIONS!$C$55,ASSUMPTIONS!$D$55*(1+ASSUMPTIONS!$B$66),0),0) -> 0 | F22: =IFERROR(IF(5>=ASSUMPTIONS!$C$55,ASSUMPTIONS!$D$55*(1+ASSUMPTIONS!$B$66),0),0) -> 0 | G22: =IFERROR(IF(6>=ASSUMPTIONS!$C$55,ASSUMPTIONS!$D$55*(1+ASSUMPTIONS!$B$66),0),0) -> 10242 | H22: =IFERROR(IF(7>=ASSUMPTIONS!$C$55,ASSUMPTIONS!$D$55*(1+ASSUMPTIONS!$B$66),0),0) -> 10242 | I22: =IFERROR(IF(8>=ASSUMPTIONS!$C$55,ASSUMPTIONS!$D$55*(1+ASSUMPTIONS!$B$66),0),0) -> 10242 | J22: =IFERROR(IF(9>=ASSUMPTIONS!$C$55,ASSUMPTIONS!$D$55*(1+ASSUMPTIONS!$B$66),0),0) -> 10242 | K22: =IFERROR(IF(10>=ASSUMPTIONS!$C$55,ASSUMPTIONS!$D$55*(1+ASSUMPTIONS!$B$66),0),0) -> 10242 | L22: =IFERROR(IF(11>=ASSUMPTIONS!$C$55,ASSUMPTIONS!$D$55*(1+ASSUMPTIONS!$B$66),0),0) -> 10242 | M22: =IFERROR(IF(12>=ASSUMPTIONS!$C$55,ASSUMPTIONS!$D$55*(1+ASSUMPTIONS!$B$66),0),0) -> 10242 | N22: =SUM(B22:M22) -> 71694 | O22: =IFERROR(IF(13>=ASSUMPTIONS!$C$55,ASSUMPTIONS!$D$55*(1+ASSUMPTIONS!$B$66),0),0) -> 10242 | P22: =IFERROR(IF(14>=ASSUMPTIONS!$C$55,ASSUMPTIONS!$D$55*(1+ASSUMPTIONS!$B$66),0),0) -> 10242 | Q22: =IFERROR(IF(15>=ASSUMPTIONS!$C$55,ASSUMPTIONS!$D$55*(1+ASSUMPTIONS!$B$66),0),0) -> 10242 | R22: =IFERROR(IF(16>=ASSUMPTIONS!$C$55,ASSUMPTIONS!$D$55*(1+ASSUMPTIONS!$B$66),0),0) -> 10242 | S22: =IFERROR(IF(17>=ASSUMPTIONS!$C$55,ASSUMPTIONS!$D$55*(1+ASSUMPTIONS!$B$66),0),0) -> 10242 | T22: =IFERROR(IF(18>=ASSUMPTIONS!$C$55,ASSUMPTIONS!$D$55*(1+ASSUMPTIONS!$B$66),0),0) -> 10242 | U22: =IFERROR(IF(19>=ASSUMPTIONS!$C$55,ASSUMPTIONS!$D$55*(1+ASSUMPTIONS!$B$66),0),0) -> 10242 | V22: =IFERROR(IF(20>=ASSUMPTIONS!$C$55,ASSUMPTIONS!$D$55*(1+ASSUMPTIONS!$B$66),0),0) -> 10242 | W22: =IFERROR(IF(21>=ASSUMPTIONS!$C$55,ASSUMPTIONS!$D$55*(1+ASSUMPTIONS!$B$66),0),0) -> 10242 | X22: =IFERROR(IF(22>=ASSUMPTIONS!$C$55,ASSUMPTIONS!$D$55*(1+ASSUMPTIONS!$B$66),0),0) -> 10242 | Y22: =IFERROR(IF(23>=ASSUMPTIONS!$C$55,ASSUMPTIONS!$D$55*(1+ASSUMPTIONS!$B$66),0),0) -> 10242 | Z22: =IFERROR(IF(24>=ASSUMPTIONS!$C$55,ASSUMPTIONS!$D$55*(1+ASSUMPTIONS!$B$66),0),0) -> 10242 | AA22: =SUM(O22:Z22) -> 122904 | AB22: =IFERROR(IF(25>=ASSUMPTIONS!$C$55,ASSUMPTIONS!$D$55*(1+ASSUMPTIONS!$B$66),0),0) -> 10242 | AC22: =IFERROR(IF(26>=ASSUMPTIONS!$C$55,ASSUMPTIONS!$D$55*(1+ASSUMPTIONS!$B$66),0),0) -> 10242 | AD22: =IFERROR(IF(27>=ASSUMPTIONS!$C$55,ASSUMPTIONS!$D$55*(1+ASSUMPTIONS!$B$66),0),0) -> 10242 | AE22: =IFERROR(IF(28>=ASSUMPTIONS!$C$55,ASSUMPTIONS!$D$55*(1+ASSUMPTIONS!$B$66),0),0) -> 10242 | AF22: =IFERROR(IF(29>=ASSUMPTIONS!$C$55,ASSUMPTIONS!$D$55*(1+ASSUMPTIONS!$B$66),0),0) -> 10242 | AG22: =IFERROR(IF(30>=ASSUMPTIONS!$C$55,ASSUMPTIONS!$D$55*(1+ASSUMPTIONS!$B$66),0),0) -> 10242 | AH22: =IFERROR(IF(31>=ASSUMPTIONS!$C$55,ASSUMPTIONS!$D$55*(1+ASSUMPTIONS!$B$66),0),0) -> 10242 | AI22: =IFERROR(IF(32>=ASSUMPTIONS!$C$55,ASSUMPTIONS!$D$55*(1+ASSUMPTIONS!$B$66),0),0) -> 10242 | AJ22: =IFERROR(IF(33>=ASSUMPTIONS!$C$55,ASSUMPTIONS!$D$55*(1+ASSUMPTIONS!$B$66),0),0) -> 10242 | AK22: =IFERROR(IF(34>=ASSUMPTIONS!$C$55,ASSUMPTIONS!$D$55*(1+ASSUMPTIONS!$B$66),0),0) -> 10242 | AL22: =IFERROR(IF(35>=ASSUMPTIONS!$C$55,ASSUMPTIONS!$D$55*(1+ASSUMPTIONS!$B$66),0),0) -> 10242 | AM22: =IFERROR(IF(36>=ASSUMPTIONS!$C$55,ASSUMPTIONS!$D$55*(1+ASSUMPTIONS!$B$66),0),0) -> 10242 | AN22: =SUM(AB22:AM22) -> 122904 | AO22: =IFERROR(IF(37>=ASSUMPTIONS!$C$55,ASSUMPTIONS!$D$55*(1+ASSUMPTIONS!$B$66),0),0) -> 10242 | AP22: =IFERROR(IF(38>=ASSUMPTIONS!$C$55,ASSUMPTIONS!$D$55*(1+ASSUMPTIONS!$B$66),0),0) -> 10242 | AQ22: =IFERROR(IF(39>=ASSUMPTIONS!$C$55,ASSUMPTIONS!$D$55*(1+ASSUMPTIONS!$B$66),0),0) -> 10242 | AR22: =IFERROR(IF(40>=ASSUMPTIONS!$C$55,ASSUMPTIONS!$D$55*(1+ASSUMPTIONS!$B$66),0),0) -> 10242 | AS22: =IFERROR(IF(41>=ASSUMPTIONS!$C$55,ASSUMPTIONS!$D$55*(1+ASSUMPTIONS!$B$66),0),0) -> 10242 | AT22: =IFERROR(IF(42>=ASSUMPTIONS!$C$55,ASSUMPTIONS!$D$55*(1+ASSUMPTIONS!$B$66),0),0) -> 10242 | AU22: =IFERROR(IF(43>=ASSUMPTIONS!$C$55,ASSUMPTIONS!$D$55*(1+ASSUMPTIONS!$B$66),0),0) -> 10242 | AV22: =IFERROR(IF(44>=ASSUMPTIONS!$C$55,ASSUMPTIONS!$D$55*(1+ASSUMPTIONS!$B$66),0),0) -> 10242 | AW22: =IFERROR(IF(45>=ASSUMPTIONS!$C$55,ASSUMPTIONS!$D$55*(1+ASSUMPTIONS!$B$66),0),0) -> 10242 | AX22: =IFERROR(IF(46>=ASSUMPTIONS!$C$55,ASSUMPTIONS!$D$55*(1+ASSUMPTIONS!$B$66),0),0) -> 10242 | AY22: =IFERROR(IF(47>=ASSUMPTIONS!$C$55,ASSUMPTIONS!$D$55*(1+ASSUMPTIONS!$B$66),0),0) -> 10242 | AZ22: =IFERROR(IF(48>=ASSUMPTIONS!$C$55,ASSUMPTIONS!$D$55*(1+ASSUMPTIONS!$B$66),0),0) -> 10242 | BA22: =SUM(AO22:AZ22) -> 122904 | BB22: =IFERROR(IF(49>=ASSUMPTIONS!$C$55,ASSUMPTIONS!$D$55*(1+ASSUMPTIONS!$B$66),0),0) -> 10242 | BC22: =IFERROR(IF(50>=ASSUMPTIONS!$C$55,ASSUMPTIONS!$D$55*(1+ASSUMPTIONS!$B$66),0),0) -> 10242 | BD22: =IFERROR(IF(51>=ASSUMPTIONS!$C$55,ASSUMPTIONS!$D$55*(1+ASSUMPTIONS!$B$66),0),0) -> 10242 | BE22: =IFERROR(IF(52>=ASSUMPTIONS!$C$55,ASSUMPTIONS!$D$55*(1+ASSUMPTIONS!$B$66),0),0) -> 10242 | BF22: =IFERROR(IF(53>=ASSUMPTIONS!$C$55,ASSUMPTIONS!$D$55*(1+ASSUMPTIONS!$B$66),0),0) -> 10242 | BG22: =IFERROR(IF(54>=ASSUMPTIONS!$C$55,ASSUMPTIONS!$D$55*(1+ASSUMPTIONS!$B$66),0),0) -> 10242 | BH22: =IFERROR(IF(55>=ASSUMPTIONS!$C$55,ASSUMPTIONS!$D$55*(1+ASSUMPTIONS!$B$66),0),0) -> 10242 | BI22: =IFERROR(IF(56>=ASSUMPTIONS!$C$55,ASSUMPTIONS!$D$55*(1+ASSUMPTIONS!$B$66),0),0) -> 10242 | BJ22: =IFERROR(IF(57>=ASSUMPTIONS!$C$55,ASSUMPTIONS!$D$55*(1+ASSUMPTIONS!$B$66),0),0) -> 10242 | BK22: =IFERROR(IF(58>=ASSUMPTIONS!$C$55,ASSUMPTIONS!$D$55*(1+ASSUMPTIONS!$B$66),0),0) -> 10242 | BL22: =IFERROR(IF(59>=ASSUMPTIONS!$C$55,ASSUMPTIONS!$D$55*(1+ASSUMPTIONS!$B$66),0),0) -> 10242 | BM22: =IFERROR(IF(60>=ASSUMPTIONS!$C$55,ASSUMPTIONS!$D$55*(1+ASSUMPTIONS!$B$66),0),0) -> 10242 | BN22: =SUM(BB22:BM22) -> 122904
A23: =IFERROR(ASSUMPTIONS!B56,"(empty)") -> Sales | B23: =IFERROR(IF(1>=ASSUMPTIONS!$C$56,ASSUMPTIONS!$D$56*(1+ASSUMPTIONS!$B$66),0),0) -> 0 | C23: =IFERROR(IF(2>=ASSUMPTIONS!$C$56,ASSUMPTIONS!$D$56*(1+ASSUMPTIONS!$B$66),0),0) -> 0 | D23: =IFERROR(IF(3>=ASSUMPTIONS!$C$56,ASSUMPTIONS!$D$56*(1+ASSUMPTIONS!$B$66),0),0) -> 0 | E23: =IFERROR(IF(4>=ASSUMPTIONS!$C$56,ASSUMPTIONS!$D$56*(1+ASSUMPTIONS!$B$66),0),0) -> 0 | F23: =IFERROR(IF(5>=ASSUMPTIONS!$C$56,ASSUMPTIONS!$D$56*(1+ASSUMPTIONS!$B$66),0),0) -> 0 | G23: =IFERROR(IF(6>=ASSUMPTIONS!$C$56,ASSUMPTIONS!$D$56*(1+ASSUMPTIONS!$B$66),0),0) -> 0 | H23: =IFERROR(IF(7>=ASSUMPTIONS!$C$56,ASSUMPTIONS!$D$56*(1+ASSUMPTIONS!$B$66),0),0) -> 0 | I23: =IFERROR(IF(8>=ASSUMPTIONS!$C$56,ASSUMPTIONS!$D$56*(1+ASSUMPTIONS!$B$66),0),0) -> 0 | J23: =IFERROR(IF(9>=ASSUMPTIONS!$C$56,ASSUMPTIONS!$D$56*(1+ASSUMPTIONS!$B$66),0),0) -> 5690 | K23: =IFERROR(IF(10>=ASSUMPTIONS!$C$56,ASSUMPTIONS!$D$56*(1+ASSUMPTIONS!$B$66),0),0) -> 5690 | L23: =IFERROR(IF(11>=ASSUMPTIONS!$C$56,ASSUMPTIONS!$D$56*(1+ASSUMPTIONS!$B$66),0),0) -> 5690 | M23: =IFERROR(IF(12>=ASSUMPTIONS!$C$56,ASSUMPTIONS!$D$56*(1+ASSUMPTIONS!$B$66),0),0) -> 5690 | N23: =SUM(B23:M23) -> 22760 | O23: =IFERROR(IF(13>=ASSUMPTIONS!$C$56,ASSUMPTIONS!$D$56*(1+ASSUMPTIONS!$B$66),0),0) -> 5690 | P23: =IFERROR(IF(14>=ASSUMPTIONS!$C$56,ASSUMPTIONS!$D$56*(1+ASSUMPTIONS!$B$66),0),0) -> 5690 | Q23: =IFERROR(IF(15>=ASSUMPTIONS!$C$56,ASSUMPTIONS!$D$56*(1+ASSUMPTIONS!$B$66),0),0) -> 5690 | R23: =IFERROR(IF(16>=ASSUMPTIONS!$C$56,ASSUMPTIONS!$D$56*(1+ASSUMPTIONS!$B$66),0),0) -> 5690 | S23: =IFERROR(IF(17>=ASSUMPTIONS!$C$56,ASSUMPTIONS!$D$56*(1+ASSUMPTIONS!$B$66),0),0) -> 5690 | T23: =IFERROR(IF(18>=ASSUMPTIONS!$C$56,ASSUMPTIONS!$D$56*(1+ASSUMPTIONS!$B$66),0),0) -> 5690 | U23: =IFERROR(IF(19>=ASSUMPTIONS!$C$56,ASSUMPTIONS!$D$56*(1+ASSUMPTIONS!$B$66),0),0) -> 5690 | V23: =IFERROR(IF(20>=ASSUMPTIONS!$C$56,ASSUMPTIONS!$D$56*(1+ASSUMPTIONS!$B$66),0),0) -> 5690 | W23: =IFERROR(IF(21>=ASSUMPTIONS!$C$56,ASSUMPTIONS!$D$56*(1+ASSUMPTIONS!$B$66),0),0) -> 5690 | X23: =IFERROR(IF(22>=ASSUMPTIONS!$C$56,ASSUMPTIONS!$D$56*(1+ASSUMPTIONS!$B$66),0),0) -> 5690 | Y23: =IFERROR(IF(23>=ASSUMPTIONS!$C$56,ASSUMPTIONS!$D$56*(1+ASSUMPTIONS!$B$66),0),0) -> 5690 | Z23: =IFERROR(IF(24>=ASSUMPTIONS!$C$56,ASSUMPTIONS!$D$56*(1+ASSUMPTIONS!$B$66),0),0) -> 5690 | AA23: =SUM(O23:Z23) -> 68280 | AB23: =IFERROR(IF(25>=ASSUMPTIONS!$C$56,ASSUMPTIONS!$D$56*(1+ASSUMPTIONS!$B$66),0),0) -> 5690 | AC23: =IFERROR(IF(26>=ASSUMPTIONS!$C$56,ASSUMPTIONS!$D$56*(1+ASSUMPTIONS!$B$66),0),0) -> 5690 | AD23: =IFERROR(IF(27>=ASSUMPTIONS!$C$56,ASSUMPTIONS!$D$56*(1+ASSUMPTIONS!$B$66),0),0) -> 5690 | AE23: =IFERROR(IF(28>=ASSUMPTIONS!$C$56,ASSUMPTIONS!$D$56*(1+ASSUMPTIONS!$B$66),0),0) -> 5690 | AF23: =IFERROR(IF(29>=ASSUMPTIONS!$C$56,ASSUMPTIONS!$D$56*(1+ASSUMPTIONS!$B$66),0),0) -> 5690 | AG23: =IFERROR(IF(30>=ASSUMPTIONS!$C$56,ASSUMPTIONS!$D$56*(1+ASSUMPTIONS!$B$66),0),0) -> 5690 | AH23: =IFERROR(IF(31>=ASSUMPTIONS!$C$56,ASSUMPTIONS!$D$56*(1+ASSUMPTIONS!$B$66),0),0) -> 5690 | AI23: =IFERROR(IF(32>=ASSUMPTIONS!$C$56,ASSUMPTIONS!$D$56*(1+ASSUMPTIONS!$B$66),0),0) -> 5690 | AJ23: =IFERROR(IF(33>=ASSUMPTIONS!$C$56,ASSUMPTIONS!$D$56*(1+ASSUMPTIONS!$B$66),0),0) -> 5690 | AK23: =IFERROR(IF(34>=ASSUMPTIONS!$C$56,ASSUMPTIONS!$D$56*(1+ASSUMPTIONS!$B$66),0),0) -> 5690 | AL23: =IFERROR(IF(35>=ASSUMPTIONS!$C$56,ASSUMPTIONS!$D$56*(1+ASSUMPTIONS!$B$66),0),0) -> 5690 | AM23: =IFERROR(IF(36>=ASSUMPTIONS!$C$56,ASSUMPTIONS!$D$56*(1+ASSUMPTIONS!$B$66),0),0) -> 5690 | AN23: =SUM(AB23:AM23) -> 68280 | AO23: =IFERROR(IF(37>=ASSUMPTIONS!$C$56,ASSUMPTIONS!$D$56*(1+ASSUMPTIONS!$B$66),0),0) -> 5690 | AP23: =IFERROR(IF(38>=ASSUMPTIONS!$C$56,ASSUMPTIONS!$D$56*(1+ASSUMPTIONS!$B$66),0),0) -> 5690 | AQ23: =IFERROR(IF(39>=ASSUMPTIONS!$C$56,ASSUMPTIONS!$D$56*(1+ASSUMPTIONS!$B$66),0),0) -> 5690 | AR23: =IFERROR(IF(40>=ASSUMPTIONS!$C$56,ASSUMPTIONS!$D$56*(1+ASSUMPTIONS!$B$66),0),0) -> 5690 | AS23: =IFERROR(IF(41>=ASSUMPTIONS!$C$56,ASSUMPTIONS!$D$56*(1+ASSUMPTIONS!$B$66),0),0) -> 5690 | AT23: =IFERROR(IF(42>=ASSUMPTIONS!$C$56,ASSUMPTIONS!$D$56*(1+ASSUMPTIONS!$B$66),0),0) -> 5690 | AU23: =IFERROR(IF(43>=ASSUMPTIONS!$C$56,ASSUMPTIONS!$D$56*(1+ASSUMPTIONS!$B$66),0),0) -> 5690 | AV23: =IFERROR(IF(44>=ASSUMPTIONS!$C$56,ASSUMPTIONS!$D$56*(1+ASSUMPTIONS!$B$66),0),0) -> 5690 | AW23: =IFERROR(IF(45>=ASSUMPTIONS!$C$56,ASSUMPTIONS!$D$56*(1+ASSUMPTIONS!$B$66),0),0) -> 5690 | AX23: =IFERROR(IF(46>=ASSUMPTIONS!$C$56,ASSUMPTIONS!$D$56*(1+ASSUMPTIONS!$B$66),0),0) -> 5690 | AY23: =IFERROR(IF(47>=ASSUMPTIONS!$C$56,ASSUMPTIONS!$D$56*(1+ASSUMPTIONS!$B$66),0),0) -> 5690 | AZ23: =IFERROR(IF(48>=ASSUMPTIONS!$C$56,ASSUMPTIONS!$D$56*(1+ASSUMPTIONS!$B$66),0),0) -> 5690 | BA23: =SUM(AO23:AZ23) -> 68280 | BB23: =IFERROR(IF(49>=ASSUMPTIONS!$C$56,ASSUMPTIONS!$D$56*(1+ASSUMPTIONS!$B$66),0),0) -> 5690 | BC23: =IFERROR(IF(50>=ASSUMPTIONS!$C$56,ASSUMPTIONS!$D$56*(1+ASSUMPTIONS!$B$66),0),0) -> 5690 | BD23: =IFERROR(IF(51>=ASSUMPTIONS!$C$56,ASSUMPTIONS!$D$56*(1+ASSUMPTIONS!$B$66),0),0) -> 5690 | BE23: =IFERROR(IF(52>=ASSUMPTIONS!$C$56,ASSUMPTIONS!$D$56*(1+ASSUMPTIONS!$B$66),0),0) -> 5690 | BF23: =IFERROR(IF(53>=ASSUMPTIONS!$C$56,ASSUMPTIONS!$D$56*(1+ASSUMPTIONS!$B$66),0),0) -> 5690 | BG23: =IFERROR(IF(54>=ASSUMPTIONS!$C$56,ASSUMPTIONS!$D$56*(1+ASSUMPTIONS!$B$66),0),0) -> 5690 | BH23: =IFERROR(IF(55>=ASSUMPTIONS!$C$56,ASSUMPTIONS!$D$56*(1+ASSUMPTIONS!$B$66),0),0) -> 5690 | BI23: =IFERROR(IF(56>=ASSUMPTIONS!$C$56,ASSUMPTIONS!$D$56*(1+ASSUMPTIONS!$B$66),0),0) -> 5690 | BJ23: =IFERROR(IF(57>=ASSUMPTIONS!$C$56,ASSUMPTIONS!$D$56*(1+ASSUMPTIONS!$B$66),0),0) -> 5690 | BK23: =IFERROR(IF(58>=ASSUMPTIONS!$C$56,ASSUMPTIONS!$D$56*(1+ASSUMPTIONS!$B$66),0),0) -> 5690 | BL23: =IFERROR(IF(59>=ASSUMPTIONS!$C$56,ASSUMPTIONS!$D$56*(1+ASSUMPTIONS!$B$66),0),0) -> 5690 | BM23: =IFERROR(IF(60>=ASSUMPTIONS!$C$56,ASSUMPTIONS!$D$56*(1+ASSUMPTIONS!$B$66),0),0) -> 5690 | BN23: =SUM(BB23:BM23) -> 68280
A24: =IFERROR(ASSUMPTIONS!B57,"(empty)") -> Sales | B24: =IFERROR(IF(1>=ASSUMPTIONS!$C$57,ASSUMPTIONS!$D$57*(1+ASSUMPTIONS!$B$66),0),0) -> 0 | C24: =IFERROR(IF(2>=ASSUMPTIONS!$C$57,ASSUMPTIONS!$D$57*(1+ASSUMPTIONS!$B$66),0),0) -> 0 | D24: =IFERROR(IF(3>=ASSUMPTIONS!$C$57,ASSUMPTIONS!$D$57*(1+ASSUMPTIONS!$B$66),0),0) -> 0 | E24: =IFERROR(IF(4>=ASSUMPTIONS!$C$57,ASSUMPTIONS!$D$57*(1+ASSUMPTIONS!$B$66),0),0) -> 0 | F24: =IFERROR(IF(5>=ASSUMPTIONS!$C$57,ASSUMPTIONS!$D$57*(1+ASSUMPTIONS!$B$66),0),0) -> 0 | G24: =IFERROR(IF(6>=ASSUMPTIONS!$C$57,ASSUMPTIONS!$D$57*(1+ASSUMPTIONS!$B$66),0),0) -> 0 | H24: =IFERROR(IF(7>=ASSUMPTIONS!$C$57,ASSUMPTIONS!$D$57*(1+ASSUMPTIONS!$B$66),0),0) -> 0 | I24: =IFERROR(IF(8>=ASSUMPTIONS!$C$57,ASSUMPTIONS!$D$57*(1+ASSUMPTIONS!$B$66),0),0) -> 0 | J24: =IFERROR(IF(9>=ASSUMPTIONS!$C$57,ASSUMPTIONS!$D$57*(1+ASSUMPTIONS!$B$66),0),0) -> 0 | K24: =IFERROR(IF(10>=ASSUMPTIONS!$C$57,ASSUMPTIONS!$D$57*(1+ASSUMPTIONS!$B$66),0),0) -> 0 | L24: =IFERROR(IF(11>=ASSUMPTIONS!$C$57,ASSUMPTIONS!$D$57*(1+ASSUMPTIONS!$B$66),0),0) -> 0 | M24: =IFERROR(IF(12>=ASSUMPTIONS!$C$57,ASSUMPTIONS!$D$57*(1+ASSUMPTIONS!$B$66),0),0) -> 5690 | N24: =SUM(B24:M24) -> 5690 | O24: =IFERROR(IF(13>=ASSUMPTIONS!$C$57,ASSUMPTIONS!$D$57*(1+ASSUMPTIONS!$B$66),0),0) -> 5690 | P24: =IFERROR(IF(14>=ASSUMPTIONS!$C$57,ASSUMPTIONS!$D$57*(1+ASSUMPTIONS!$B$66),0),0) -> 5690 | Q24: =IFERROR(IF(15>=ASSUMPTIONS!$C$57,ASSUMPTIONS!$D$57*(1+ASSUMPTIONS!$B$66),0),0) -> 5690 | R24: =IFERROR(IF(16>=ASSUMPTIONS!$C$57,ASSUMPTIONS!$D$57*(1+ASSUMPTIONS!$B$66),0),0) -> 5690 | S24: =IFERROR(IF(17>=ASSUMPTIONS!$C$57,ASSUMPTIONS!$D$57*(1+ASSUMPTIONS!$B$66),0),0) -> 5690 | T24: =IFERROR(IF(18>=ASSUMPTIONS!$C$57,ASSUMPTIONS!$D$57*(1+ASSUMPTIONS!$B$66),0),0) -> 5690 | U24: =IFERROR(IF(19>=ASSUMPTIONS!$C$57,ASSUMPTIONS!$D$57*(1+ASSUMPTIONS!$B$66),0),0) -> 5690 | V24: =IFERROR(IF(20>=ASSUMPTIONS!$C$57,ASSUMPTIONS!$D$57*(1+ASSUMPTIONS!$B$66),0),0) -> 5690 | W24: =IFERROR(IF(21>=ASSUMPTIONS!$C$57,ASSUMPTIONS!$D$57*(1+ASSUMPTIONS!$B$66),0),0) -> 5690 | X24: =IFERROR(IF(22>=ASSUMPTIONS!$C$57,ASSUMPTIONS!$D$57*(1+ASSUMPTIONS!$B$66),0),0) -> 5690 | Y24: =IFERROR(IF(23>=ASSUMPTIONS!$C$57,ASSUMPTIONS!$D$57*(1+ASSUMPTIONS!$B$66),0),0) -> 5690 | Z24: =IFERROR(IF(24>=ASSUMPTIONS!$C$57,ASSUMPTIONS!$D$57*(1+ASSUMPTIONS!$B$66),0),0) -> 5690 | AA24: =SUM(O24:Z24) -> 68280 | AB24: =IFERROR(IF(25>=ASSUMPTIONS!$C$57,ASSUMPTIONS!$D$57*(1+ASSUMPTIONS!$B$66),0),0) -> 5690 | AC24: =IFERROR(IF(26>=ASSUMPTIONS!$C$57,ASSUMPTIONS!$D$57*(1+ASSUMPTIONS!$B$66),0),0) -> 5690 | AD24: =IFERROR(IF(27>=ASSUMPTIONS!$C$57,ASSUMPTIONS!$D$57*(1+ASSUMPTIONS!$B$66),0),0) -> 5690 | AE24: =IFERROR(IF(28>=ASSUMPTIONS!$C$57,ASSUMPTIONS!$D$57*(1+ASSUMPTIONS!$B$66),0),0) -> 5690 | AF24: =IFERROR(IF(29>=ASSUMPTIONS!$C$57,ASSUMPTIONS!$D$57*(1+ASSUMPTIONS!$B$66),0),0) -> 5690 | AG24: =IFERROR(IF(30>=ASSUMPTIONS!$C$57,ASSUMPTIONS!$D$57*(1+ASSUMPTIONS!$B$66),0),0) -> 5690 | AH24: =IFERROR(IF(31>=ASSUMPTIONS!$C$57,ASSUMPTIONS!$D$57*(1+ASSUMPTIONS!$B$66),0),0) -> 5690 | AI24: =IFERROR(IF(32>=ASSUMPTIONS!$C$57,ASSUMPTIONS!$D$57*(1+ASSUMPTIONS!$B$66),0),0) -> 5690 | AJ24: =IFERROR(IF(33>=ASSUMPTIONS!$C$57,ASSUMPTIONS!$D$57*(1+ASSUMPTIONS!$B$66),0),0) -> 5690 | AK24: =IFERROR(IF(34>=ASSUMPTIONS!$C$57,ASSUMPTIONS!$D$57*(1+ASSUMPTIONS!$B$66),0),0) -> 5690 | AL24: =IFERROR(IF(35>=ASSUMPTIONS!$C$57,ASSUMPTIONS!$D$57*(1+ASSUMPTIONS!$B$66),0),0) -> 5690 | AM24: =IFERROR(IF(36>=ASSUMPTIONS!$C$57,ASSUMPTIONS!$D$57*(1+ASSUMPTIONS!$B$66),0),0) -> 5690 | AN24: =SUM(AB24:AM24) -> 68280 | AO24: =IFERROR(IF(37>=ASSUMPTIONS!$C$57,ASSUMPTIONS!$D$57*(1+ASSUMPTIONS!$B$66),0),0) -> 5690 | AP24: =IFERROR(IF(38>=ASSUMPTIONS!$C$57,ASSUMPTIONS!$D$57*(1+ASSUMPTIONS!$B$66),0),0) -> 5690 | AQ24: =IFERROR(IF(39>=ASSUMPTIONS!$C$57,ASSUMPTIONS!$D$57*(1+ASSUMPTIONS!$B$66),0),0) -> 5690 | AR24: =IFERROR(IF(40>=ASSUMPTIONS!$C$57,ASSUMPTIONS!$D$57*(1+ASSUMPTIONS!$B$66),0),0) -> 5690 | AS24: =IFERROR(IF(41>=ASSUMPTIONS!$C$57,ASSUMPTIONS!$D$57*(1+ASSUMPTIONS!$B$66),0),0) -> 5690 | AT24: =IFERROR(IF(42>=ASSUMPTIONS!$C$57,ASSUMPTIONS!$D$57*(1+ASSUMPTIONS!$B$66),0),0) -> 5690 | AU24: =IFERROR(IF(43>=ASSUMPTIONS!$C$57,ASSUMPTIONS!$D$57*(1+ASSUMPTIONS!$B$66),0),0) -> 5690 | AV24: =IFERROR(IF(44>=ASSUMPTIONS!$C$57,ASSUMPTIONS!$D$57*(1+ASSUMPTIONS!$B$66),0),0) -> 5690 | AW24: =IFERROR(IF(45>=ASSUMPTIONS!$C$57,ASSUMPTIONS!$D$57*(1+ASSUMPTIONS!$B$66),0),0) -> 5690 | AX24: =IFERROR(IF(46>=ASSUMPTIONS!$C$57,ASSUMPTIONS!$D$57*(1+ASSUMPTIONS!$B$66),0),0) -> 5690 | AY24: =IFERROR(IF(47>=ASSUMPTIONS!$C$57,ASSUMPTIONS!$D$57*(1+ASSUMPTIONS!$B$66),0),0) -> 5690 | AZ24: =IFERROR(IF(48>=ASSUMPTIONS!$C$57,ASSUMPTIONS!$D$57*(1+ASSUMPTIONS!$B$66),0),0) -> 5690 | BA24: =SUM(AO24:AZ24) -> 68280 | BB24: =IFERROR(IF(49>=ASSUMPTIONS!$C$57,ASSUMPTIONS!$D$57*(1+ASSUMPTIONS!$B$66),0),0) -> 5690 | BC24: =IFERROR(IF(50>=ASSUMPTIONS!$C$57,ASSUMPTIONS!$D$57*(1+ASSUMPTIONS!$B$66),0),0) -> 5690 | BD24: =IFERROR(IF(51>=ASSUMPTIONS!$C$57,ASSUMPTIONS!$D$57*(1+ASSUMPTIONS!$B$66),0),0) -> 5690 | BE24: =IFERROR(IF(52>=ASSUMPTIONS!$C$57,ASSUMPTIONS!$D$57*(1+ASSUMPTIONS!$B$66),0),0) -> 5690 | BF24: =IFERROR(IF(53>=ASSUMPTIONS!$C$57,ASSUMPTIONS!$D$57*(1+ASSUMPTIONS!$B$66),0),0) -> 5690 | BG24: =IFERROR(IF(54>=ASSUMPTIONS!$C$57,ASSUMPTIONS!$D$57*(1+ASSUMPTIONS!$B$66),0),0) -> 5690 | BH24: =IFERROR(IF(55>=ASSUMPTIONS!$C$57,ASSUMPTIONS!$D$57*(1+ASSUMPTIONS!$B$66),0),0) -> 5690 | BI24: =IFERROR(IF(56>=ASSUMPTIONS!$C$57,ASSUMPTIONS!$D$57*(1+ASSUMPTIONS!$B$66),0),0) -> 5690 | BJ24: =IFERROR(IF(57>=ASSUMPTIONS!$C$57,ASSUMPTIONS!$D$57*(1+ASSUMPTIONS!$B$66),0),0) -> 5690 | BK24: =IFERROR(IF(58>=ASSUMPTIONS!$C$57,ASSUMPTIONS!$D$57*(1+ASSUMPTIONS!$B$66),0),0) -> 5690 | BL24: =IFERROR(IF(59>=ASSUMPTIONS!$C$57,ASSUMPTIONS!$D$57*(1+ASSUMPTIONS!$B$66),0),0) -> 5690 | BM24: =IFERROR(IF(60>=ASSUMPTIONS!$C$57,ASSUMPTIONS!$D$57*(1+ASSUMPTIONS!$B$66),0),0) -> 5690 | BN24: =SUM(BB24:BM24) -> 68280
A25: =IFERROR(ASSUMPTIONS!B58,"(empty)") -> Sales | B25: =IFERROR(IF(1>=ASSUMPTIONS!$C$58,ASSUMPTIONS!$D$58*(1+ASSUMPTIONS!$B$66),0),0) -> 0 | C25: =IFERROR(IF(2>=ASSUMPTIONS!$C$58,ASSUMPTIONS!$D$58*(1+ASSUMPTIONS!$B$66),0),0) -> 0 | D25: =IFERROR(IF(3>=ASSUMPTIONS!$C$58,ASSUMPTIONS!$D$58*(1+ASSUMPTIONS!$B$66),0),0) -> 0 | E25: =IFERROR(IF(4>=ASSUMPTIONS!$C$58,ASSUMPTIONS!$D$58*(1+ASSUMPTIONS!$B$66),0),0) -> 0 | F25: =IFERROR(IF(5>=ASSUMPTIONS!$C$58,ASSUMPTIONS!$D$58*(1+ASSUMPTIONS!$B$66),0),0) -> 0 | G25: =IFERROR(IF(6>=ASSUMPTIONS!$C$58,ASSUMPTIONS!$D$58*(1+ASSUMPTIONS!$B$66),0),0) -> 0 | H25: =IFERROR(IF(7>=ASSUMPTIONS!$C$58,ASSUMPTIONS!$D$58*(1+ASSUMPTIONS!$B$66),0),0) -> 0 | I25: =IFERROR(IF(8>=ASSUMPTIONS!$C$58,ASSUMPTIONS!$D$58*(1+ASSUMPTIONS!$B$66),0),0) -> 0 | J25: =IFERROR(IF(9>=ASSUMPTIONS!$C$58,ASSUMPTIONS!$D$58*(1+ASSUMPTIONS!$B$66),0),0) -> 3983 | K25: =IFERROR(IF(10>=ASSUMPTIONS!$C$58,ASSUMPTIONS!$D$58*(1+ASSUMPTIONS!$B$66),0),0) -> 3983 | L25: =IFERROR(IF(11>=ASSUMPTIONS!$C$58,ASSUMPTIONS!$D$58*(1+ASSUMPTIONS!$B$66),0),0) -> 3983 | M25: =IFERROR(IF(12>=ASSUMPTIONS!$C$58,ASSUMPTIONS!$D$58*(1+ASSUMPTIONS!$B$66),0),0) -> 3983 | N25: =SUM(B25:M25) -> 15932 | O25: =IFERROR(IF(13>=ASSUMPTIONS!$C$58,ASSUMPTIONS!$D$58*(1+ASSUMPTIONS!$B$66),0),0) -> 3983 | P25: =IFERROR(IF(14>=ASSUMPTIONS!$C$58,ASSUMPTIONS!$D$58*(1+ASSUMPTIONS!$B$66),0),0) -> 3983 | Q25: =IFERROR(IF(15>=ASSUMPTIONS!$C$58,ASSUMPTIONS!$D$58*(1+ASSUMPTIONS!$B$66),0),0) -> 3983 | R25: =IFERROR(IF(16>=ASSUMPTIONS!$C$58,ASSUMPTIONS!$D$58*(1+ASSUMPTIONS!$B$66),0),0) -> 3983 | S25: =IFERROR(IF(17>=ASSUMPTIONS!$C$58,ASSUMPTIONS!$D$58*(1+ASSUMPTIONS!$B$66),0),0) -> 3983 | T25: =IFERROR(IF(18>=ASSUMPTIONS!$C$58,ASSUMPTIONS!$D$58*(1+ASSUMPTIONS!$B$66),0),0) -> 3983 | U25: =IFERROR(IF(19>=ASSUMPTIONS!$C$58,ASSUMPTIONS!$D$58*(1+ASSUMPTIONS!$B$66),0),0) -> 3983 | V25: =IFERROR(IF(20>=ASSUMPTIONS!$C$58,ASSUMPTIONS!$D$58*(1+ASSUMPTIONS!$B$66),0),0) -> 3983 | W25: =IFERROR(IF(21>=ASSUMPTIONS!$C$58,ASSUMPTIONS!$D$58*(1+ASSUMPTIONS!$B$66),0),0) -> 3983 | X25: =IFERROR(IF(22>=ASSUMPTIONS!$C$58,ASSUMPTIONS!$D$58*(1+ASSUMPTIONS!$B$66),0),0) -> 3983 | Y25: =IFERROR(IF(23>=ASSUMPTIONS!$C$58,ASSUMPTIONS!$D$58*(1+ASSUMPTIONS!$B$66),0),0) -> 3983 | Z25: =IFERROR(IF(24>=ASSUMPTIONS!$C$58,ASSUMPTIONS!$D$58*(1+ASSUMPTIONS!$B$66),0),0) -> 3983 | AA25: =SUM(O25:Z25) -> 47796 | AB25: =IFERROR(IF(25>=ASSUMPTIONS!$C$58,ASSUMPTIONS!$D$58*(1+ASSUMPTIONS!$B$66),0),0) -> 3983 | AC25: =IFERROR(IF(26>=ASSUMPTIONS!$C$58,ASSUMPTIONS!$D$58*(1+ASSUMPTIONS!$B$66),0),0) -> 3983 | AD25: =IFERROR(IF(27>=ASSUMPTIONS!$C$58,ASSUMPTIONS!$D$58*(1+ASSUMPTIONS!$B$66),0),0) -> 3983 | AE25: =IFERROR(IF(28>=ASSUMPTIONS!$C$58,ASSUMPTIONS!$D$58*(1+ASSUMPTIONS!$B$66),0),0) -> 3983 | AF25: =IFERROR(IF(29>=ASSUMPTIONS!$C$58,ASSUMPTIONS!$D$58*(1+ASSUMPTIONS!$B$66),0),0) -> 3983 | AG25: =IFERROR(IF(30>=ASSUMPTIONS!$C$58,ASSUMPTIONS!$D$58*(1+ASSUMPTIONS!$B$66),0),0) -> 3983 | AH25: =IFERROR(IF(31>=ASSUMPTIONS!$C$58,ASSUMPTIONS!$D$58*(1+ASSUMPTIONS!$B$66),0),0) -> 3983 | AI25: =IFERROR(IF(32>=ASSUMPTIONS!$C$58,ASSUMPTIONS!$D$58*(1+ASSUMPTIONS!$B$66),0),0) -> 3983 | AJ25: =IFERROR(IF(33>=ASSUMPTIONS!$C$58,ASSUMPTIONS!$D$58*(1+ASSUMPTIONS!$B$66),0),0) -> 3983 | AK25: =IFERROR(IF(34>=ASSUMPTIONS!$C$58,ASSUMPTIONS!$D$58*(1+ASSUMPTIONS!$B$66),0),0) -> 3983 | AL25: =IFERROR(IF(35>=ASSUMPTIONS!$C$58,ASSUMPTIONS!$D$58*(1+ASSUMPTIONS!$B$66),0),0) -> 3983 | AM25: =IFERROR(IF(36>=ASSUMPTIONS!$C$58,ASSUMPTIONS!$D$58*(1+ASSUMPTIONS!$B$66),0),0) -> 3983 | AN25: =SUM(AB25:AM25) -> 47796 | AO25: =IFERROR(IF(37>=ASSUMPTIONS!$C$58,ASSUMPTIONS!$D$58*(1+ASSUMPTIONS!$B$66),0),0) -> 3983 | AP25: =IFERROR(IF(38>=ASSUMPTIONS!$C$58,ASSUMPTIONS!$D$58*(1+ASSUMPTIONS!$B$66),0),0) -> 3983 | AQ25: =IFERROR(IF(39>=ASSUMPTIONS!$C$58,ASSUMPTIONS!$D$58*(1+ASSUMPTIONS!$B$66),0),0) -> 3983 | AR25: =IFERROR(IF(40>=ASSUMPTIONS!$C$58,ASSUMPTIONS!$D$58*(1+ASSUMPTIONS!$B$66),0),0) -> 3983 | AS25: =IFERROR(IF(41>=ASSUMPTIONS!$C$58,ASSUMPTIONS!$D$58*(1+ASSUMPTIONS!$B$66),0),0) -> 3983 | AT25: =IFERROR(IF(42>=ASSUMPTIONS!$C$58,ASSUMPTIONS!$D$58*(1+ASSUMPTIONS!$B$66),0),0) -> 3983 | AU25: =IFERROR(IF(43>=ASSUMPTIONS!$C$58,ASSUMPTIONS!$D$58*(1+ASSUMPTIONS!$B$66),0),0) -> 3983 | AV25: =IFERROR(IF(44>=ASSUMPTIONS!$C$58,ASSUMPTIONS!$D$58*(1+ASSUMPTIONS!$B$66),0),0) -> 3983 | AW25: =IFERROR(IF(45>=ASSUMPTIONS!$C$58,ASSUMPTIONS!$D$58*(1+ASSUMPTIONS!$B$66),0),0) -> 3983 | AX25: =IFERROR(IF(46>=ASSUMPTIONS!$C$58,ASSUMPTIONS!$D$58*(1+ASSUMPTIONS!$B$66),0),0) -> 3983 | AY25: =IFERROR(IF(47>=ASSUMPTIONS!$C$58,ASSUMPTIONS!$D$58*(1+ASSUMPTIONS!$B$66),0),0) -> 3983 | AZ25: =IFERROR(IF(48>=ASSUMPTIONS!$C$58,ASSUMPTIONS!$D$58*(1+ASSUMPTIONS!$B$66),0),0) -> 3983 | BA25: =SUM(AO25:AZ25) -> 47796 | BB25: =IFERROR(IF(49>=ASSUMPTIONS!$C$58,ASSUMPTIONS!$D$58*(1+ASSUMPTIONS!$B$66),0),0) -> 3983 | BC25: =IFERROR(IF(50>=ASSUMPTIONS!$C$58,ASSUMPTIONS!$D$58*(1+ASSUMPTIONS!$B$66),0),0) -> 3983 | BD25: =IFERROR(IF(51>=ASSUMPTIONS!$C$58,ASSUMPTIONS!$D$58*(1+ASSUMPTIONS!$B$66),0),0) -> 3983 | BE25: =IFERROR(IF(52>=ASSUMPTIONS!$C$58,ASSUMPTIONS!$D$58*(1+ASSUMPTIONS!$B$66),0),0) -> 3983 | BF25: =IFERROR(IF(53>=ASSUMPTIONS!$C$58,ASSUMPTIONS!$D$58*(1+ASSUMPTIONS!$B$66),0),0) -> 3983 | BG25: =IFERROR(IF(54>=ASSUMPTIONS!$C$58,ASSUMPTIONS!$D$58*(1+ASSUMPTIONS!$B$66),0),0) -> 3983 | BH25: =IFERROR(IF(55>=ASSUMPTIONS!$C$58,ASSUMPTIONS!$D$58*(1+ASSUMPTIONS!$B$66),0),0) -> 3983 | BI25: =IFERROR(IF(56>=ASSUMPTIONS!$C$58,ASSUMPTIONS!$D$58*(1+ASSUMPTIONS!$B$66),0),0) -> 3983 | BJ25: =IFERROR(IF(57>=ASSUMPTIONS!$C$58,ASSUMPTIONS!$D$58*(1+ASSUMPTIONS!$B$66),0),0) -> 3983 | BK25: =IFERROR(IF(58>=ASSUMPTIONS!$C$58,ASSUMPTIONS!$D$58*(1+ASSUMPTIONS!$B$66),0),0) -> 3983 | BL25: =IFERROR(IF(59>=ASSUMPTIONS!$C$58,ASSUMPTIONS!$D$58*(1+ASSUMPTIONS!$B$66),0),0) -> 3983 | BM25: =IFERROR(IF(60>=ASSUMPTIONS!$C$58,ASSUMPTIONS!$D$58*(1+ASSUMPTIONS!$B$66),0),0) -> 3983 | BN25: =SUM(BB25:BM25) -> 47796
A26: SALES — TOTAL (£) | B26: =SUM(B22:B25) -> 0 | C26: =SUM(C22:C25) -> 0 | D26: =SUM(D22:D25) -> 0 | E26: =SUM(E22:E25) -> 0 | F26: =SUM(F22:F25) -> 0 | G26: =SUM(G22:G25) -> 10242 | H26: =SUM(H22:H25) -> 10242 | I26: =SUM(I22:I25) -> 10242 | ... M26: =SUM(M22:M25) -> 25605 | N26: =SUM(B26:M26) -> 116076 | O26: =SUM(O22:O25) -> 25605 | P26: =SUM(P22:P25) -> 25605 | Q26: =SUM(Q22:Q25) -> 25605 | R26: =SUM(R22:R25) -> 25605 | S26: =SUM(S22:S25) -> 25605 | T26: =SUM(T22:T25) -> 25605 | U26: =SUM(U22:U25) -> 25605 | V26: =SUM(V22:V25) -> 25605 | ... Z26: =SUM(Z22:Z25) -> 25605 | AA26: =SUM(O26:Z26) -> 307260 | AB26: =SUM(AB22:AB25) -> 25605 | AC26: =SUM(AC22:AC25) -> 25605 | AD26: =SUM(AD22:AD25) -> 25605 | AE26: =SUM(AE22:AE25) -> 25605 | AF26: =SUM(AF22:AF25) -> 25605 | AG26: =SUM(AG22:AG25) -> 25605 | AH26: =SUM(AH22:AH25) -> 25605 | AI26: =SUM(AI22:AI25) -> 25605 | ... AM26: =SUM(AM22:AM25) -> 25605 | AN26: =SUM(AB26:AM26) -> 307260 | AO26: =SUM(AO22:AO25) -> 25605 | AP26: =SUM(AP22:AP25) -> 25605 | AQ26: =SUM(AQ22:AQ25) -> 25605 | AR26: =SUM(AR22:AR25) -> 25605 | AS26: =SUM(AS22:AS25) -> 25605 | AT26: =SUM(AT22:AT25) -> 25605 | AU26: =SUM(AU22:AU25) -> 25605 | AV26: =SUM(AV22:AV25) -> 25605 | ... AZ26: =SUM(AZ22:AZ25) -> 25605 | BA26: =SUM(AO26:AZ26) -> 307260 | BB26: =SUM(BB22:BB25) -> 25605 | BC26: =SUM(BC22:BC25) -> 25605 | BD26: =SUM(BD22:BD25) -> 25605 | BE26: =SUM(BE22:BE25) -> 25605 | BF26: =SUM(BF22:BF25) -> 25605 | BG26: =SUM(BG22:BG25) -> 25605 | BH26: =SUM(BH22:BH25) -> 25605 | BI26: =SUM(BI22:BI25) -> 25605 | ... BM26: =SUM(BM22:BM25) -> 25605 | BN26: =SUM(BB26:BM26) -> 307260
A28: MARKETING
A29: =IFERROR(ASSUMPTIONS!B59,"(empty)") -> Marketing | B29: =IFERROR(IF(1>=ASSUMPTIONS!$C$59,ASSUMPTIONS!$D$59*(1+ASSUMPTIONS!$B$66),0),0) -> 0 | C29: =IFERROR(IF(2>=ASSUMPTIONS!$C$59,ASSUMPTIONS!$D$59*(1+ASSUMPTIONS!$B$66),0),0) -> 0 | D29: =IFERROR(IF(3>=ASSUMPTIONS!$C$59,ASSUMPTIONS!$D$59*(1+ASSUMPTIONS!$B$66),0),0) -> 0 | E29: =IFERROR(IF(4>=ASSUMPTIONS!$C$59,ASSUMPTIONS!$D$59*(1+ASSUMPTIONS!$B$66),0),0) -> 0 | F29: =IFERROR(IF(5>=ASSUMPTIONS!$C$59,ASSUMPTIONS!$D$59*(1+ASSUMPTIONS!$B$66),0),0) -> 0 | G29: =IFERROR(IF(6>=ASSUMPTIONS!$C$59,ASSUMPTIONS!$D$59*(1+ASSUMPTIONS!$B$66),0),0) -> 9104 | H29: =IFERROR(IF(7>=ASSUMPTIONS!$C$59,ASSUMPTIONS!$D$59*(1+ASSUMPTIONS!$B$66),0),0) -> 9104 | I29: =IFERROR(IF(8>=ASSUMPTIONS!$C$59,ASSUMPTIONS!$D$59*(1+ASSUMPTIONS!$B$66),0),0) -> 9104 | J29: =IFERROR(IF(9>=ASSUMPTIONS!$C$59,ASSUMPTIONS!$D$59*(1+ASSUMPTIONS!$B$66),0),0) -> 9104 | K29: =IFERROR(IF(10>=ASSUMPTIONS!$C$59,ASSUMPTIONS!$D$59*(1+ASSUMPTIONS!$B$66),0),0) -> 9104 | L29: =IFERROR(IF(11>=ASSUMPTIONS!$C$59,ASSUMPTIONS!$D$59*(1+ASSUMPTIONS!$B$66),0),0) -> 9104 | M29: =IFERROR(IF(12>=ASSUMPTIONS!$C$59,ASSUMPTIONS!$D$59*(1+ASSUMPTIONS!$B$66),0),0) -> 9104 | N29: =SUM(B29:M29) -> 63728 | O29: =IFERROR(IF(13>=ASSUMPTIONS!$C$59,ASSUMPTIONS!$D$59*(1+ASSUMPTIONS!$B$66),0),0) -> 9104 | P29: =IFERROR(IF(14>=ASSUMPTIONS!$C$59,ASSUMPTIONS!$D$59*(1+ASSUMPTIONS!$B$66),0),0) -> 9104 | Q29: =IFERROR(IF(15>=ASSUMPTIONS!$C$59,ASSUMPTIONS!$D$59*(1+ASSUMPTIONS!$B$66),0),0) -> 9104 | R29: =IFERROR(IF(16>=ASSUMPTIONS!$C$59,ASSUMPTIONS!$D$59*(1+ASSUMPTIONS!$B$66),0),0) -> 9104 | S29: =IFERROR(IF(17>=ASSUMPTIONS!$C$59,ASSUMPTIONS!$D$59*(1+ASSUMPTIONS!$B$66),0),0) -> 9104 | T29: =IFERROR(IF(18>=ASSUMPTIONS!$C$59,ASSUMPTIONS!$D$59*(1+ASSUMPTIONS!$B$66),0),0) -> 9104 | U29: =IFERROR(IF(19>=ASSUMPTIONS!$C$59,ASSUMPTIONS!$D$59*(1+ASSUMPTIONS!$B$66),0),0) -> 9104 | V29: =IFERROR(IF(20>=ASSUMPTIONS!$C$59,ASSUMPTIONS!$D$59*(1+ASSUMPTIONS!$B$66),0),0) -> 9104 | W29: =IFERROR(IF(21>=ASSUMPTIONS!$C$59,ASSUMPTIONS!$D$59*(1+ASSUMPTIONS!$B$66),0),0) -> 9104 | X29: =IFERROR(IF(22>=ASSUMPTIONS!$C$59,ASSUMPTIONS!$D$59*(1+ASSUMPTIONS!$B$66),0),0) -> 9104 | Y29: =IFERROR(IF(23>=ASSUMPTIONS!$C$59,ASSUMPTIONS!$D$59*(1+ASSUMPTIONS!$B$66),0),0) -> 9104 | Z29: =IFERROR(IF(24>=ASSUMPTIONS!$C$59,ASSUMPTIONS!$D$59*(1+ASSUMPTIONS!$B$66),0),0) -> 9104 | AA29: =SUM(O29:Z29) -> 109248 | AB29: =IFERROR(IF(25>=ASSUMPTIONS!$C$59,ASSUMPTIONS!$D$59*(1+ASSUMPTIONS!$B$66),0),0) -> 9104 | AC29: =IFERROR(IF(26>=ASSUMPTIONS!$C$59,ASSUMPTIONS!$D$59*(1+ASSUMPTIONS!$B$66),0),0) -> 9104 | AD29: =IFERROR(IF(27>=ASSUMPTIONS!$C$59,ASSUMPTIONS!$D$59*(1+ASSUMPTIONS!$B$66),0),0) -> 9104 | AE29: =IFERROR(IF(28>=ASSUMPTIONS!$C$59,ASSUMPTIONS!$D$59*(1+ASSUMPTIONS!$B$66),0),0) -> 9104 | AF29: =IFERROR(IF(29>=ASSUMPTIONS!$C$59,ASSUMPTIONS!$D$59*(1+ASSUMPTIONS!$B$66),0),0) -> 9104 | AG29: =IFERROR(IF(30>=ASSUMPTIONS!$C$59,ASSUMPTIONS!$D$59*(1+ASSUMPTIONS!$B$66),0),0) -> 9104 | AH29: =IFERROR(IF(31>=ASSUMPTIONS!$C$59,ASSUMPTIONS!$D$59*(1+ASSUMPTIONS!$B$66),0),0) -> 9104 | AI29: =IFERROR(IF(32>=ASSUMPTIONS!$C$59,ASSUMPTIONS!$D$59*(1+ASSUMPTIONS!$B$66),0),0) -> 9104 | AJ29: =IFERROR(IF(33>=ASSUMPTIONS!$C$59,ASSUMPTIONS!$D$59*(1+ASSUMPTIONS!$B$66),0),0) -> 9104 | AK29: =IFERROR(IF(34>=ASSUMPTIONS!$C$59,ASSUMPTIONS!$D$59*(1+ASSUMPTIONS!$B$66),0),0) -> 9104 | AL29: =IFERROR(IF(35>=ASSUMPTIONS!$C$59,ASSUMPTIONS!$D$59*(1+ASSUMPTIONS!$B$66),0),0) -> 9104 | AM29: =IFERROR(IF(36>=ASSUMPTIONS!$C$59,ASSUMPTIONS!$D$59*(1+ASSUMPTIONS!$B$66),0),0) -> 9104 | AN29: =SUM(AB29:AM29) -> 109248 | AO29: =IFERROR(IF(37>=ASSUMPTIONS!$C$59,ASSUMPTIONS!$D$59*(1+ASSUMPTIONS!$B$66),0),0) -> 9104 | AP29: =IFERROR(IF(38>=ASSUMPTIONS!$C$59,ASSUMPTIONS!$D$59*(1+ASSUMPTIONS!$B$66),0),0) -> 9104 | AQ29: =IFERROR(IF(39>=ASSUMPTIONS!$C$59,ASSUMPTIONS!$D$59*(1+ASSUMPTIONS!$B$66),0),0) -> 9104 | AR29: =IFERROR(IF(40>=ASSUMPTIONS!$C$59,ASSUMPTIONS!$D$59*(1+ASSUMPTIONS!$B$66),0),0) -> 9104 | AS29: =IFERROR(IF(41>=ASSUMPTIONS!$C$59,ASSUMPTIONS!$D$59*(1+ASSUMPTIONS!$B$66),0),0) -> 9104 | AT29: =IFERROR(IF(42>=ASSUMPTIONS!$C$59,ASSUMPTIONS!$D$59*(1+ASSUMPTIONS!$B$66),0),0) -> 9104 | AU29: =IFERROR(IF(43>=ASSUMPTIONS!$C$59,ASSUMPTIONS!$D$59*(1+ASSUMPTIONS!$B$66),0),0) -> 9104 | AV29: =IFERROR(IF(44>=ASSUMPTIONS!$C$59,ASSUMPTIONS!$D$59*(1+ASSUMPTIONS!$B$66),0),0) -> 9104 | AW29: =IFERROR(IF(45>=ASSUMPTIONS!$C$59,ASSUMPTIONS!$D$59*(1+ASSUMPTIONS!$B$66),0),0) -> 9104 | AX29: =IFERROR(IF(46>=ASSUMPTIONS!$C$59,ASSUMPTIONS!$D$59*(1+ASSUMPTIONS!$B$66),0),0) -> 9104 | AY29: =IFERROR(IF(47>=ASSUMPTIONS!$C$59,ASSUMPTIONS!$D$59*(1+ASSUMPTIONS!$B$66),0),0) -> 9104 | AZ29: =IFERROR(IF(48>=ASSUMPTIONS!$C$59,ASSUMPTIONS!$D$59*(1+ASSUMPTIONS!$B$66),0),0) -> 9104 | BA29: =SUM(AO29:AZ29) -> 109248 | BB29: =IFERROR(IF(49>=ASSUMPTIONS!$C$59,ASSUMPTIONS!$D$59*(1+ASSUMPTIONS!$B$66),0),0) -> 9104 | BC29: =IFERROR(IF(50>=ASSUMPTIONS!$C$59,ASSUMPTIONS!$D$59*(1+ASSUMPTIONS!$B$66),0),0) -> 9104 | BD29: =IFERROR(IF(51>=ASSUMPTIONS!$C$59,ASSUMPTIONS!$D$59*(1+ASSUMPTIONS!$B$66),0),0) -> 9104 | BE29: =IFERROR(IF(52>=ASSUMPTIONS!$C$59,ASSUMPTIONS!$D$59*(1+ASSUMPTIONS!$B$66),0),0) -> 9104 | BF29: =IFERROR(IF(53>=ASSUMPTIONS!$C$59,ASSUMPTIONS!$D$59*(1+ASSUMPTIONS!$B$66),0),0) -> 9104 | BG29: =IFERROR(IF(54>=ASSUMPTIONS!$C$59,ASSUMPTIONS!$D$59*(1+ASSUMPTIONS!$B$66),0),0) -> 9104 | BH29: =IFERROR(IF(55>=ASSUMPTIONS!$C$59,ASSUMPTIONS!$D$59*(1+ASSUMPTIONS!$B$66),0),0) -> 9104 | BI29: =IFERROR(IF(56>=ASSUMPTIONS!$C$59,ASSUMPTIONS!$D$59*(1+ASSUMPTIONS!$B$66),0),0) -> 9104 | BJ29: =IFERROR(IF(57>=ASSUMPTIONS!$C$59,ASSUMPTIONS!$D$59*(1+ASSUMPTIONS!$B$66),0),0) -> 9104 | BK29: =IFERROR(IF(58>=ASSUMPTIONS!$C$59,ASSUMPTIONS!$D$59*(1+ASSUMPTIONS!$B$66),0),0) -> 9104 | BL29: =IFERROR(IF(59>=ASSUMPTIONS!$C$59,ASSUMPTIONS!$D$59*(1+ASSUMPTIONS!$B$66),0),0) -> 9104 | BM29: =IFERROR(IF(60>=ASSUMPTIONS!$C$59,ASSUMPTIONS!$D$59*(1+ASSUMPTIONS!$B$66),0),0) -> 9104 | BN29: =SUM(BB29:BM29) -> 109248
A30: =IFERROR(ASSUMPTIONS!B60,"(empty)") -> Marketing | B30: =IFERROR(IF(1>=ASSUMPTIONS!$C$60,ASSUMPTIONS!$D$60*(1+ASSUMPTIONS!$B$66),0),0) -> 0 | C30: =IFERROR(IF(2>=ASSUMPTIONS!$C$60,ASSUMPTIONS!$D$60*(1+ASSUMPTIONS!$B$66),0),0) -> 0 | D30: =IFERROR(IF(3>=ASSUMPTIONS!$C$60,ASSUMPTIONS!$D$60*(1+ASSUMPTIONS!$B$66),0),0) -> 0 | E30: =IFERROR(IF(4>=ASSUMPTIONS!$C$60,ASSUMPTIONS!$D$60*(1+ASSUMPTIONS!$B$66),0),0) -> 0 | F30: =IFERROR(IF(5>=ASSUMPTIONS!$C$60,ASSUMPTIONS!$D$60*(1+ASSUMPTIONS!$B$66),0),0) -> 0 | G30: =IFERROR(IF(6>=ASSUMPTIONS!$C$60,ASSUMPTIONS!$D$60*(1+ASSUMPTIONS!$B$66),0),0) -> 0 | H30: =IFERROR(IF(7>=ASSUMPTIONS!$C$60,ASSUMPTIONS!$D$60*(1+ASSUMPTIONS!$B$66),0),0) -> 0 | I30: =IFERROR(IF(8>=ASSUMPTIONS!$C$60,ASSUMPTIONS!$D$60*(1+ASSUMPTIONS!$B$66),0),0) -> 0 | J30: =IFERROR(IF(9>=ASSUMPTIONS!$C$60,ASSUMPTIONS!$D$60*(1+ASSUMPTIONS!$B$66),0),0) -> 5121 | K30: =IFERROR(IF(10>=ASSUMPTIONS!$C$60,ASSUMPTIONS!$D$60*(1+ASSUMPTIONS!$B$66),0),0) -> 5121 | L30: =IFERROR(IF(11>=ASSUMPTIONS!$C$60,ASSUMPTIONS!$D$60*(1+ASSUMPTIONS!$B$66),0),0) -> 5121 | M30: =IFERROR(IF(12>=ASSUMPTIONS!$C$60,ASSUMPTIONS!$D$60*(1+ASSUMPTIONS!$B$66),0),0) -> 5121 | N30: =SUM(B30:M30) -> 20484 | O30: =IFERROR(IF(13>=ASSUMPTIONS!$C$60,ASSUMPTIONS!$D$60*(1+ASSUMPTIONS!$B$66),0),0) -> 5121 | P30: =IFERROR(IF(14>=ASSUMPTIONS!$C$60,ASSUMPTIONS!$D$60*(1+ASSUMPTIONS!$B$66),0),0) -> 5121 | Q30: =IFERROR(IF(15>=ASSUMPTIONS!$C$60,ASSUMPTIONS!$D$60*(1+ASSUMPTIONS!$B$66),0),0) -> 5121 | R30: =IFERROR(IF(16>=ASSUMPTIONS!$C$60,ASSUMPTIONS!$D$60*(1+ASSUMPTIONS!$B$66),0),0) -> 5121 | S30: =IFERROR(IF(17>=ASSUMPTIONS!$C$60,ASSUMPTIONS!$D$60*(1+ASSUMPTIONS!$B$66),0),0) -> 5121 | T30: =IFERROR(IF(18>=ASSUMPTIONS!$C$60,ASSUMPTIONS!$D$60*(1+ASSUMPTIONS!$B$66),0),0) -> 5121 | U30: =IFERROR(IF(19>=ASSUMPTIONS!$C$60,ASSUMPTIONS!$D$60*(1+ASSUMPTIONS!$B$66),0),0) -> 5121 | V30: =IFERROR(IF(20>=ASSUMPTIONS!$C$60,ASSUMPTIONS!$D$60*(1+ASSUMPTIONS!$B$66),0),0) -> 5121 | W30: =IFERROR(IF(21>=ASSUMPTIONS!$C$60,ASSUMPTIONS!$D$60*(1+ASSUMPTIONS!$B$66),0),0) -> 5121 | X30: =IFERROR(IF(22>=ASSUMPTIONS!$C$60,ASSUMPTIONS!$D$60*(1+ASSUMPTIONS!$B$66),0),0) -> 5121 | Y30: =IFERROR(IF(23>=ASSUMPTIONS!$C$60,ASSUMPTIONS!$D$60*(1+ASSUMPTIONS!$B$66),0),0) -> 5121 | Z30: =IFERROR(IF(24>=ASSUMPTIONS!$C$60,ASSUMPTIONS!$D$60*(1+ASSUMPTIONS!$B$66),0),0) -> 5121 | AA30: =SUM(O30:Z30) -> 61452 | AB30: =IFERROR(IF(25>=ASSUMPTIONS!$C$60,ASSUMPTIONS!$D$60*(1+ASSUMPTIONS!$B$66),0),0) -> 5121 | AC30: =IFERROR(IF(26>=ASSUMPTIONS!$C$60,ASSUMPTIONS!$D$60*(1+ASSUMPTIONS!$B$66),0),0) -> 5121 | AD30: =IFERROR(IF(27>=ASSUMPTIONS!$C$60,ASSUMPTIONS!$D$60*(1+ASSUMPTIONS!$B$66),0),0) -> 5121 | AE30: =IFERROR(IF(28>=ASSUMPTIONS!$C$60,ASSUMPTIONS!$D$60*(1+ASSUMPTIONS!$B$66),0),0) -> 5121 | AF30: =IFERROR(IF(29>=ASSUMPTIONS!$C$60,ASSUMPTIONS!$D$60*(1+ASSUMPTIONS!$B$66),0),0) -> 5121 | AG30: =IFERROR(IF(30>=ASSUMPTIONS!$C$60,ASSUMPTIONS!$D$60*(1+ASSUMPTIONS!$B$66),0),0) -> 5121 | AH30: =IFERROR(IF(31>=ASSUMPTIONS!$C$60,ASSUMPTIONS!$D$60*(1+ASSUMPTIONS!$B$66),0),0) -> 5121 | AI30: =IFERROR(IF(32>=ASSUMPTIONS!$C$60,ASSUMPTIONS!$D$60*(1+ASSUMPTIONS!$B$66),0),0) -> 5121 | AJ30: =IFERROR(IF(33>=ASSUMPTIONS!$C$60,ASSUMPTIONS!$D$60*(1+ASSUMPTIONS!$B$66),0),0) -> 5121 | AK30: =IFERROR(IF(34>=ASSUMPTIONS!$C$60,ASSUMPTIONS!$D$60*(1+ASSUMPTIONS!$B$66),0),0) -> 5121 | AL30: =IFERROR(IF(35>=ASSUMPTIONS!$C$60,ASSUMPTIONS!$D$60*(1+ASSUMPTIONS!$B$66),0),0) -> 5121 | AM30: =IFERROR(IF(36>=ASSUMPTIONS!$C$60,ASSUMPTIONS!$D$60*(1+ASSUMPTIONS!$B$66),0),0) -> 5121 | AN30: =SUM(AB30:AM30) -> 61452 | AO30: =IFERROR(IF(37>=ASSUMPTIONS!$C$60,ASSUMPTIONS!$D$60*(1+ASSUMPTIONS!$B$66),0),0) -> 5121 | AP30: =IFERROR(IF(38>=ASSUMPTIONS!$C$60,ASSUMPTIONS!$D$60*(1+ASSUMPTIONS!$B$66),0),0) -> 5121 | AQ30: =IFERROR(IF(39>=ASSUMPTIONS!$C$60,ASSUMPTIONS!$D$60*(1+ASSUMPTIONS!$B$66),0),0) -> 5121 | AR30: =IFERROR(IF(40>=ASSUMPTIONS!$C$60,ASSUMPTIONS!$D$60*(1+ASSUMPTIONS!$B$66),0),0) -> 5121 | AS30: =IFERROR(IF(41>=ASSUMPTIONS!$C$60,ASSUMPTIONS!$D$60*(1+ASSUMPTIONS!$B$66),0),0) -> 5121 | AT30: =IFERROR(IF(42>=ASSUMPTIONS!$C$60,ASSUMPTIONS!$D$60*(1+ASSUMPTIONS!$B$66),0),0) -> 5121 | AU30: =IFERROR(IF(43>=ASSUMPTIONS!$C$60,ASSUMPTIONS!$D$60*(1+ASSUMPTIONS!$B$66),0),0) -> 5121 | AV30: =IFERROR(IF(44>=ASSUMPTIONS!$C$60,ASSUMPTIONS!$D$60*(1+ASSUMPTIONS!$B$66),0),0) -> 5121 | AW30: =IFERROR(IF(45>=ASSUMPTIONS!$C$60,ASSUMPTIONS!$D$60*(1+ASSUMPTIONS!$B$66),0),0) -> 5121 | AX30: =IFERROR(IF(46>=ASSUMPTIONS!$C$60,ASSUMPTIONS!$D$60*(1+ASSUMPTIONS!$B$66),0),0) -> 5121 | AY30: =IFERROR(IF(47>=ASSUMPTIONS!$C$60,ASSUMPTIONS!$D$60*(1+ASSUMPTIONS!$B$66),0),0) -> 5121 | AZ30: =IFERROR(IF(48>=ASSUMPTIONS!$C$60,ASSUMPTIONS!$D$60*(1+ASSUMPTIONS!$B$66),0),0) -> 5121 | BA30: =SUM(AO30:AZ30) -> 61452 | BB30: =IFERROR(IF(49>=ASSUMPTIONS!$C$60,ASSUMPTIONS!$D$60*(1+ASSUMPTIONS!$B$66),0),0) -> 5121 | BC30: =IFERROR(IF(50>=ASSUMPTIONS!$C$60,ASSUMPTIONS!$D$60*(1+ASSUMPTIONS!$B$66),0),0) -> 5121 | BD30: =IFERROR(IF(51>=ASSUMPTIONS!$C$60,ASSUMPTIONS!$D$60*(1+ASSUMPTIONS!$B$66),0),0) -> 5121 | BE30: =IFERROR(IF(52>=ASSUMPTIONS!$C$60,ASSUMPTIONS!$D$60*(1+ASSUMPTIONS!$B$66),0),0) -> 5121 | BF30: =IFERROR(IF(53>=ASSUMPTIONS!$C$60,ASSUMPTIONS!$D$60*(1+ASSUMPTIONS!$B$66),0),0) -> 5121 | BG30: =IFERROR(IF(54>=ASSUMPTIONS!$C$60,ASSUMPTIONS!$D$60*(1+ASSUMPTIONS!$B$66),0),0) -> 5121 | BH30: =IFERROR(IF(55>=ASSUMPTIONS!$C$60,ASSUMPTIONS!$D$60*(1+ASSUMPTIONS!$B$66),0),0) -> 5121 | BI30: =IFERROR(IF(56>=ASSUMPTIONS!$C$60,ASSUMPTIONS!$D$60*(1+ASSUMPTIONS!$B$66),0),0) -> 5121 | BJ30: =IFERROR(IF(57>=ASSUMPTIONS!$C$60,ASSUMPTIONS!$D$60*(1+ASSUMPTIONS!$B$66),0),0) -> 5121 | BK30: =IFERROR(IF(58>=ASSUMPTIONS!$C$60,ASSUMPTIONS!$D$60*(1+ASSUMPTIONS!$B$66),0),0) -> 5121 | BL30: =IFERROR(IF(59>=ASSUMPTIONS!$C$60,ASSUMPTIONS!$D$60*(1+ASSUMPTIONS!$B$66),0),0) -> 5121 | BM30: =IFERROR(IF(60>=ASSUMPTIONS!$C$60,ASSUMPTIONS!$D$60*(1+ASSUMPTIONS!$B$66),0),0) -> 5121 | BN30: =SUM(BB30:BM30) -> 61452
A31: =IFERROR(ASSUMPTIONS!B61,"(empty)") -> Marketing | B31: =IFERROR(IF(1>=ASSUMPTIONS!$C$61,ASSUMPTIONS!$D$61*(1+ASSUMPTIONS!$B$66),0),0) -> 0 | C31: =IFERROR(IF(2>=ASSUMPTIONS!$C$61,ASSUMPTIONS!$D$61*(1+ASSUMPTIONS!$B$66),0),0) -> 0 | D31: =IFERROR(IF(3>=ASSUMPTIONS!$C$61,ASSUMPTIONS!$D$61*(1+ASSUMPTIONS!$B$66),0),0) -> 0 | E31: =IFERROR(IF(4>=ASSUMPTIONS!$C$61,ASSUMPTIONS!$D$61*(1+ASSUMPTIONS!$B$66),0),0) -> 0 | F31: =IFERROR(IF(5>=ASSUMPTIONS!$C$61,ASSUMPTIONS!$D$61*(1+ASSUMPTIONS!$B$66),0),0) -> 0 | G31: =IFERROR(IF(6>=ASSUMPTIONS!$C$61,ASSUMPTIONS!$D$61*(1+ASSUMPTIONS!$B$66),0),0) -> 0 | H31: =IFERROR(IF(7>=ASSUMPTIONS!$C$61,ASSUMPTIONS!$D$61*(1+ASSUMPTIONS!$B$66),0),0) -> 0 | I31: =IFERROR(IF(8>=ASSUMPTIONS!$C$61,ASSUMPTIONS!$D$61*(1+ASSUMPTIONS!$B$66),0),0) -> 0 | J31: =IFERROR(IF(9>=ASSUMPTIONS!$C$61,ASSUMPTIONS!$D$61*(1+ASSUMPTIONS!$B$66),0),0) -> 0 | K31: =IFERROR(IF(10>=ASSUMPTIONS!$C$61,ASSUMPTIONS!$D$61*(1+ASSUMPTIONS!$B$66),0),0) -> 0 | L31: =IFERROR(IF(11>=ASSUMPTIONS!$C$61,ASSUMPTIONS!$D$61*(1+ASSUMPTIONS!$B$66),0),0) -> 0 | M31: =IFERROR(IF(12>=ASSUMPTIONS!$C$61,ASSUMPTIONS!$D$61*(1+ASSUMPTIONS!$B$66),0),0) -> 6259 | N31: =SUM(B31:M31) -> 6259 | O31: =IFERROR(IF(13>=ASSUMPTIONS!$C$61,ASSUMPTIONS!$D$61*(1+ASSUMPTIONS!$B$66),0),0) -> 6259 | P31: =IFERROR(IF(14>=ASSUMPTIONS!$C$61,ASSUMPTIONS!$D$61*(1+ASSUMPTIONS!$B$66),0),0) -> 6259 | Q31: =IFERROR(IF(15>=ASSUMPTIONS!$C$61,ASSUMPTIONS!$D$61*(1+ASSUMPTIONS!$B$66),0),0) -> 6259 | R31: =IFERROR(IF(16>=ASSUMPTIONS!$C$61,ASSUMPTIONS!$D$61*(1+ASSUMPTIONS!$B$66),0),0) -> 6259 | S31: =IFERROR(IF(17>=ASSUMPTIONS!$C$61,ASSUMPTIONS!$D$61*(1+ASSUMPTIONS!$B$66),0),0) -> 6259 | T31: =IFERROR(IF(18>=ASSUMPTIONS!$C$61,ASSUMPTIONS!$D$61*(1+ASSUMPTIONS!$B$66),0),0) -> 6259 | U31: =IFERROR(IF(19>=ASSUMPTIONS!$C$61,ASSUMPTIONS!$D$61*(1+ASSUMPTIONS!$B$66),0),0) -> 6259 | V31: =IFERROR(IF(20>=ASSUMPTIONS!$C$61,ASSUMPTIONS!$D$61*(1+ASSUMPTIONS!$B$66),0),0) -> 6259 | W31: =IFERROR(IF(21>=ASSUMPTIONS!$C$61,ASSUMPTIONS!$D$61*(1+ASSUMPTIONS!$B$66),0),0) -> 6259 | X31: =IFERROR(IF(22>=ASSUMPTIONS!$C$61,ASSUMPTIONS!$D$61*(1+ASSUMPTIONS!$B$66),0),0) -> 6259 | Y31: =IFERROR(IF(23>=ASSUMPTIONS!$C$61,ASSUMPTIONS!$D$61*(1+ASSUMPTIONS!$B$66),0),0) -> 6259 | Z31: =IFERROR(IF(24>=ASSUMPTIONS!$C$61,ASSUMPTIONS!$D$61*(1+ASSUMPTIONS!$B$66),0),0) -> 6259 | AA31: =SUM(O31:Z31) -> 75108 | AB31: =IFERROR(IF(25>=ASSUMPTIONS!$C$61,ASSUMPTIONS!$D$61*(1+ASSUMPTIONS!$B$66),0),0) -> 6259 | AC31: =IFERROR(IF(26>=ASSUMPTIONS!$C$61,ASSUMPTIONS!$D$61*(1+ASSUMPTIONS!$B$66),0),0) -> 6259 | AD31: =IFERROR(IF(27>=ASSUMPTIONS!$C$61,ASSUMPTIONS!$D$61*(1+ASSUMPTIONS!$B$66),0),0) -> 6259 | AE31: =IFERROR(IF(28>=ASSUMPTIONS!$C$61,ASSUMPTIONS!$D$61*(1+ASSUMPTIONS!$B$66),0),0) -> 6259 | AF31: =IFERROR(IF(29>=ASSUMPTIONS!$C$61,ASSUMPTIONS!$D$61*(1+ASSUMPTIONS!$B$66),0),0) -> 6259 | AG31: =IFERROR(IF(30>=ASSUMPTIONS!$C$61,ASSUMPTIONS!$D$61*(1+ASSUMPTIONS!$B$66),0),0) -> 6259 | AH31: =IFERROR(IF(31>=ASSUMPTIONS!$C$61,ASSUMPTIONS!$D$61*(1+ASSUMPTIONS!$B$66),0),0) -> 6259 | AI31: =IFERROR(IF(32>=ASSUMPTIONS!$C$61,ASSUMPTIONS!$D$61*(1+ASSUMPTIONS!$B$66),0),0) -> 6259 | AJ31: =IFERROR(IF(33>=ASSUMPTIONS!$C$61,ASSUMPTIONS!$D$61*(1+ASSUMPTIONS!$B$66),0),0) -> 6259 | AK31: =IFERROR(IF(34>=ASSUMPTIONS!$C$61,ASSUMPTIONS!$D$61*(1+ASSUMPTIONS!$B$66),0),0) -> 6259 | AL31: =IFERROR(IF(35>=ASSUMPTIONS!$C$61,ASSUMPTIONS!$D$61*(1+ASSUMPTIONS!$B$66),0),0) -> 6259 | AM31: =IFERROR(IF(36>=ASSUMPTIONS!$C$61,ASSUMPTIONS!$D$61*(1+ASSUMPTIONS!$B$66),0),0) -> 6259 | AN31: =SUM(AB31:AM31) -> 75108 | AO31: =IFERROR(IF(37>=ASSUMPTIONS!$C$61,ASSUMPTIONS!$D$61*(1+ASSUMPTIONS!$B$66),0),0) -> 6259 | AP31: =IFERROR(IF(38>=ASSUMPTIONS!$C$61,ASSUMPTIONS!$D$61*(1+ASSUMPTIONS!$B$66),0),0) -> 6259 | AQ31: =IFERROR(IF(39>=ASSUMPTIONS!$C$61,ASSUMPTIONS!$D$61*(1+ASSUMPTIONS!$B$66),0),0) -> 6259 | AR31: =IFERROR(IF(40>=ASSUMPTIONS!$C$61,ASSUMPTIONS!$D$61*(1+ASSUMPTIONS!$B$66),0),0) -> 6259 | AS31: =IFERROR(IF(41>=ASSUMPTIONS!$C$61,ASSUMPTIONS!$D$61*(1+ASSUMPTIONS!$B$66),0),0) -> 6259 | AT31: =IFERROR(IF(42>=ASSUMPTIONS!$C$61,ASSUMPTIONS!$D$61*(1+ASSUMPTIONS!$B$66),0),0) -> 6259 | AU31: =IFERROR(IF(43>=ASSUMPTIONS!$C$61,ASSUMPTIONS!$D$61*(1+ASSUMPTIONS!$B$66),0),0) -> 6259 | AV31: =IFERROR(IF(44>=ASSUMPTIONS!$C$61,ASSUMPTIONS!$D$61*(1+ASSUMPTIONS!$B$66),0),0) -> 6259 | AW31: =IFERROR(IF(45>=ASSUMPTIONS!$C$61,ASSUMPTIONS!$D$61*(1+ASSUMPTIONS!$B$66),0),0) -> 6259 | AX31: =IFERROR(IF(46>=ASSUMPTIONS!$C$61,ASSUMPTIONS!$D$61*(1+ASSUMPTIONS!$B$66),0),0) -> 6259 | AY31: =IFERROR(IF(47>=ASSUMPTIONS!$C$61,ASSUMPTIONS!$D$61*(1+ASSUMPTIONS!$B$66),0),0) -> 6259 | AZ31: =IFERROR(IF(48>=ASSUMPTIONS!$C$61,ASSUMPTIONS!$D$61*(1+ASSUMPTIONS!$B$66),0),0) -> 6259 | BA31: =SUM(AO31:AZ31) -> 75108 | BB31: =IFERROR(IF(49>=ASSUMPTIONS!$C$61,ASSUMPTIONS!$D$61*(1+ASSUMPTIONS!$B$66),0),0) -> 6259 | BC31: =IFERROR(IF(50>=ASSUMPTIONS!$C$61,ASSUMPTIONS!$D$61*(1+ASSUMPTIONS!$B$66),0),0) -> 6259 | BD31: =IFERROR(IF(51>=ASSUMPTIONS!$C$61,ASSUMPTIONS!$D$61*(1+ASSUMPTIONS!$B$66),0),0) -> 6259 | BE31: =IFERROR(IF(52>=ASSUMPTIONS!$C$61,ASSUMPTIONS!$D$61*(1+ASSUMPTIONS!$B$66),0),0) -> 6259 | BF31: =IFERROR(IF(53>=ASSUMPTIONS!$C$61,ASSUMPTIONS!$D$61*(1+ASSUMPTIONS!$B$66),0),0) -> 6259 | BG31: =IFERROR(IF(54>=ASSUMPTIONS!$C$61,ASSUMPTIONS!$D$61*(1+ASSUMPTIONS!$B$66),0),0) -> 6259 | BH31: =IFERROR(IF(55>=ASSUMPTIONS!$C$61,ASSUMPTIONS!$D$61*(1+ASSUMPTIONS!$B$66),0),0) -> 6259 | BI31: =IFERROR(IF(56>=ASSUMPTIONS!$C$61,ASSUMPTIONS!$D$61*(1+ASSUMPTIONS!$B$66),0),0) -> 6259 | BJ31: =IFERROR(IF(57>=ASSUMPTIONS!$C$61,ASSUMPTIONS!$D$61*(1+ASSUMPTIONS!$B$66),0),0) -> 6259 | BK31: =IFERROR(IF(58>=ASSUMPTIONS!$C$61,ASSUMPTIONS!$D$61*(1+ASSUMPTIONS!$B$66),0),0) -> 6259 | BL31: =IFERROR(IF(59>=ASSUMPTIONS!$C$61,ASSUMPTIONS!$D$61*(1+ASSUMPTIONS!$B$66),0),0) -> 6259 | BM31: =IFERROR(IF(60>=ASSUMPTIONS!$C$61,ASSUMPTIONS!$D$61*(1+ASSUMPTIONS!$B$66),0),0) -> 6259 | BN31: =SUM(BB31:BM31) -> 75108
A32: MARKETING — TOTAL (£) | B32: =SUM(B29:B31) -> 0 | C32: =SUM(C29:C31) -> 0 | D32: =SUM(D29:D31) -> 0 | E32: =SUM(E29:E31) -> 0 | F32: =SUM(F29:F31) -> 0 | G32: =SUM(G29:G31) -> 9104 | H32: =SUM(H29:H31) -> 9104 | I32: =SUM(I29:I31) -> 9104 | ... M32: =SUM(M29:M31) -> 20484 | N32: =SUM(B32:M32) -> 90471 | O32: =SUM(O29:O31) -> 20484 | P32: =SUM(P29:P31) -> 20484 | Q32: =SUM(Q29:Q31) -> 20484 | R32: =SUM(R29:R31) -> 20484 | S32: =SUM(S29:S31) -> 20484 | T32: =SUM(T29:T31) -> 20484 | U32: =SUM(U29:U31) -> 20484 | V32: =SUM(V29:V31) -> 20484 | ... Z32: =SUM(Z29:Z31) -> 20484 | AA32: =SUM(O32:Z32) -> 245808 | AB32: =SUM(AB29:AB31) -> 20484 | AC32: =SUM(AC29:AC31) -> 20484 | AD32: =SUM(AD29:AD31) -> 20484 | AE32: =SUM(AE29:AE31) -> 20484 | AF32: =SUM(AF29:AF31) -> 20484 | AG32: =SUM(AG29:AG31) -> 20484 | AH32: =SUM(AH29:AH31) -> 20484 | AI32: =SUM(AI29:AI31) -> 20484 | ... AM32: =SUM(AM29:AM31) -> 20484 | AN32: =SUM(AB32:AM32) -> 245808 | AO32: =SUM(AO29:AO31) -> 20484 | AP32: =SUM(AP29:AP31) -> 20484 | AQ32: =SUM(AQ29:AQ31) -> 20484 | AR32: =SUM(AR29:AR31) -> 20484 | AS32: =SUM(AS29:AS31) -> 20484 | AT32: =SUM(AT29:AT31) -> 20484 | AU32: =SUM(AU29:AU31) -> 20484 | AV32: =SUM(AV29:AV31) -> 20484 | ... AZ32: =SUM(AZ29:AZ31) -> 20484 | BA32: =SUM(AO32:AZ32) -> 245808 | BB32: =SUM(BB29:BB31) -> 20484 | BC32: =SUM(BC29:BC31) -> 20484 | BD32: =SUM(BD29:BD31) -> 20484 | BE32: =SUM(BE29:BE31) -> 20484 | BF32: =SUM(BF29:BF31) -> 20484 | BG32: =SUM(BG29:BG31) -> 20484 | BH32: =SUM(BH29:BH31) -> 20484 | BI32: =SUM(BI29:BI31) -> 20484 | ... BM32: =SUM(BM29:BM31) -> 20484 | BN32: =SUM(BB32:BM32) -> 245808
A34: CUSTOMER SUCCESS
A35: =IFERROR(ASSUMPTIONS!B62,"(empty)") -> CS | B35: =IFERROR(IF(1>=ASSUMPTIONS!$C$62,ASSUMPTIONS!$D$62*(1+ASSUMPTIONS!$B$66),0),0) -> 0 | C35: =IFERROR(IF(2>=ASSUMPTIONS!$C$62,ASSUMPTIONS!$D$62*(1+ASSUMPTIONS!$B$66),0),0) -> 0 | D35: =IFERROR(IF(3>=ASSUMPTIONS!$C$62,ASSUMPTIONS!$D$62*(1+ASSUMPTIONS!$B$66),0),0) -> 6828 | E35: =IFERROR(IF(4>=ASSUMPTIONS!$C$62,ASSUMPTIONS!$D$62*(1+ASSUMPTIONS!$B$66),0),0) -> 6828 | F35: =IFERROR(IF(5>=ASSUMPTIONS!$C$62,ASSUMPTIONS!$D$62*(1+ASSUMPTIONS!$B$66),0),0) -> 6828 | G35: =IFERROR(IF(6>=ASSUMPTIONS!$C$62,ASSUMPTIONS!$D$62*(1+ASSUMPTIONS!$B$66),0),0) -> 6828 | H35: =IFERROR(IF(7>=ASSUMPTIONS!$C$62,ASSUMPTIONS!$D$62*(1+ASSUMPTIONS!$B$66),0),0) -> 6828 | I35: =IFERROR(IF(8>=ASSUMPTIONS!$C$62,ASSUMPTIONS!$D$62*(1+ASSUMPTIONS!$B$66),0),0) -> 6828 | J35: =IFERROR(IF(9>=ASSUMPTIONS!$C$62,ASSUMPTIONS!$D$62*(1+ASSUMPTIONS!$B$66),0),0) -> 6828 | K35: =IFERROR(IF(10>=ASSUMPTIONS!$C$62,ASSUMPTIONS!$D$62*(1+ASSUMPTIONS!$B$66),0),0) -> 6828 | L35: =IFERROR(IF(11>=ASSUMPTIONS!$C$62,ASSUMPTIONS!$D$62*(1+ASSUMPTIONS!$B$66),0),0) -> 6828 | M35: =IFERROR(IF(12>=ASSUMPTIONS!$C$62,ASSUMPTIONS!$D$62*(1+ASSUMPTIONS!$B$66),0),0) -> 6828 | N35: =SUM(B35:M35) -> 68280 | O35: =IFERROR(IF(13>=ASSUMPTIONS!$C$62,ASSUMPTIONS!$D$62*(1+ASSUMPTIONS!$B$66),0),0) -> 6828 | P35: =IFERROR(IF(14>=ASSUMPTIONS!$C$62,ASSUMPTIONS!$D$62*(1+ASSUMPTIONS!$B$66),0),0) -> 6828 | Q35: =IFERROR(IF(15>=ASSUMPTIONS!$C$62,ASSUMPTIONS!$D$62*(1+ASSUMPTIONS!$B$66),0),0) -> 6828 | R35: =IFERROR(IF(16>=ASSUMPTIONS!$C$62,ASSUMPTIONS!$D$62*(1+ASSUMPTIONS!$B$66),0),0) -> 6828 | S35: =IFERROR(IF(17>=ASSUMPTIONS!$C$62,ASSUMPTIONS!$D$62*(1+ASSUMPTIONS!$B$66),0),0) -> 6828 | T35: =IFERROR(IF(18>=ASSUMPTIONS!$C$62,ASSUMPTIONS!$D$62*(1+ASSUMPTIONS!$B$66),0),0) -> 6828 | U35: =IFERROR(IF(19>=ASSUMPTIONS!$C$62,ASSUMPTIONS!$D$62*(1+ASSUMPTIONS!$B$66),0),0) -> 6828 | V35: =IFERROR(IF(20>=ASSUMPTIONS!$C$62,ASSUMPTIONS!$D$62*(1+ASSUMPTIONS!$B$66),0),0) -> 6828 | W35: =IFERROR(IF(21>=ASSUMPTIONS!$C$62,ASSUMPTIONS!$D$62*(1+ASSUMPTIONS!$B$66),0),0) -> 6828 | X35: =IFERROR(IF(22>=ASSUMPTIONS!$C$62,ASSUMPTIONS!$D$62*(1+ASSUMPTIONS!$B$66),0),0) -> 6828 | Y35: =IFERROR(IF(23>=ASSUMPTIONS!$C$62,ASSUMPTIONS!$D$62*(1+ASSUMPTIONS!$B$66),0),0) -> 6828 | Z35: =IFERROR(IF(24>=ASSUMPTIONS!$C$62,ASSUMPTIONS!$D$62*(1+ASSUMPTIONS!$B$66),0),0) -> 6828 | AA35: =SUM(O35:Z35) -> 81936 | AB35: =IFERROR(IF(25>=ASSUMPTIONS!$C$62,ASSUMPTIONS!$D$62*(1+ASSUMPTIONS!$B$66),0),0) -> 6828 | AC35: =IFERROR(IF(26>=ASSUMPTIONS!$C$62,ASSUMPTIONS!$D$62*(1+ASSUMPTIONS!$B$66),0),0) -> 6828 | AD35: =IFERROR(IF(27>=ASSUMPTIONS!$C$62,ASSUMPTIONS!$D$62*(1+ASSUMPTIONS!$B$66),0),0) -> 6828 | AE35: =IFERROR(IF(28>=ASSUMPTIONS!$C$62,ASSUMPTIONS!$D$62*(1+ASSUMPTIONS!$B$66),0),0) -> 6828 | AF35: =IFERROR(IF(29>=ASSUMPTIONS!$C$62,ASSUMPTIONS!$D$62*(1+ASSUMPTIONS!$B$66),0),0) -> 6828 | AG35: =IFERROR(IF(30>=ASSUMPTIONS!$C$62,ASSUMPTIONS!$D$62*(1+ASSUMPTIONS!$B$66),0),0) -> 6828 | AH35: =IFERROR(IF(31>=ASSUMPTIONS!$C$62,ASSUMPTIONS!$D$62*(1+ASSUMPTIONS!$B$66),0),0) -> 6828 | AI35: =IFERROR(IF(32>=ASSUMPTIONS!$C$62,ASSUMPTIONS!$D$62*(1+ASSUMPTIONS!$B$66),0),0) -> 6828 | AJ35: =IFERROR(IF(33>=ASSUMPTIONS!$C$62,ASSUMPTIONS!$D$62*(1+ASSUMPTIONS!$B$66),0),0) -> 6828 | AK35: =IFERROR(IF(34>=ASSUMPTIONS!$C$62,ASSUMPTIONS!$D$62*(1+ASSUMPTIONS!$B$66),0),0) -> 6828 | AL35: =IFERROR(IF(35>=ASSUMPTIONS!$C$62,ASSUMPTIONS!$D$62*(1+ASSUMPTIONS!$B$66),0),0) -> 6828 | AM35: =IFERROR(IF(36>=ASSUMPTIONS!$C$62,ASSUMPTIONS!$D$62*(1+ASSUMPTIONS!$B$66),0),0) -> 6828 | AN35: =SUM(AB35:AM35) -> 81936 | AO35: =IFERROR(IF(37>=ASSUMPTIONS!$C$62,ASSUMPTIONS!$D$62*(1+ASSUMPTIONS!$B$66),0),0) -> 6828 | AP35: =IFERROR(IF(38>=ASSUMPTIONS!$C$62,ASSUMPTIONS!$D$62*(1+ASSUMPTIONS!$B$66),0),0) -> 6828 | AQ35: =IFERROR(IF(39>=ASSUMPTIONS!$C$62,ASSUMPTIONS!$D$62*(1+ASSUMPTIONS!$B$66),0),0) -> 6828 | AR35: =IFERROR(IF(40>=ASSUMPTIONS!$C$62,ASSUMPTIONS!$D$62*(1+ASSUMPTIONS!$B$66),0),0) -> 6828 | AS35: =IFERROR(IF(41>=ASSUMPTIONS!$C$62,ASSUMPTIONS!$D$62*(1+ASSUMPTIONS!$B$66),0),0) -> 6828 | AT35: =IFERROR(IF(42>=ASSUMPTIONS!$C$62,ASSUMPTIONS!$D$62*(1+ASSUMPTIONS!$B$66),0),0) -> 6828 | AU35: =IFERROR(IF(43>=ASSUMPTIONS!$C$62,ASSUMPTIONS!$D$62*(1+ASSUMPTIONS!$B$66),0),0) -> 6828 | AV35: =IFERROR(IF(44>=ASSUMPTIONS!$C$62,ASSUMPTIONS!$D$62*(1+ASSUMPTIONS!$B$66),0),0) -> 6828 | AW35: =IFERROR(IF(45>=ASSUMPTIONS!$C$62,ASSUMPTIONS!$D$62*(1+ASSUMPTIONS!$B$66),0),0) -> 6828 | AX35: =IFERROR(IF(46>=ASSUMPTIONS!$C$62,ASSUMPTIONS!$D$62*(1+ASSUMPTIONS!$B$66),0),0) -> 6828 | AY35: =IFERROR(IF(47>=ASSUMPTIONS!$C$62,ASSUMPTIONS!$D$62*(1+ASSUMPTIONS!$B$66),0),0) -> 6828 | AZ35: =IFERROR(IF(48>=ASSUMPTIONS!$C$62,ASSUMPTIONS!$D$62*(1+ASSUMPTIONS!$B$66),0),0) -> 6828 | BA35: =SUM(AO35:AZ35) -> 81936 | BB35: =IFERROR(IF(49>=ASSUMPTIONS!$C$62,ASSUMPTIONS!$D$62*(1+ASSUMPTIONS!$B$66),0),0) -> 6828 | BC35: =IFERROR(IF(50>=ASSUMPTIONS!$C$62,ASSUMPTIONS!$D$62*(1+ASSUMPTIONS!$B$66),0),0) -> 6828 | BD35: =IFERROR(IF(51>=ASSUMPTIONS!$C$62,ASSUMPTIONS!$D$62*(1+ASSUMPTIONS!$B$66),0),0) -> 6828 | BE35: =IFERROR(IF(52>=ASSUMPTIONS!$C$62,ASSUMPTIONS!$D$62*(1+ASSUMPTIONS!$B$66),0),0) -> 6828 | BF35: =IFERROR(IF(53>=ASSUMPTIONS!$C$62,ASSUMPTIONS!$D$62*(1+ASSUMPTIONS!$B$66),0),0) -> 6828 | BG35: =IFERROR(IF(54>=ASSUMPTIONS!$C$62,ASSUMPTIONS!$D$62*(1+ASSUMPTIONS!$B$66),0),0) -> 6828 | BH35: =IFERROR(IF(55>=ASSUMPTIONS!$C$62,ASSUMPTIONS!$D$62*(1+ASSUMPTIONS!$B$66),0),0) -> 6828 | BI35: =IFERROR(IF(56>=ASSUMPTIONS!$C$62,ASSUMPTIONS!$D$62*(1+ASSUMPTIONS!$B$66),0),0) -> 6828 | BJ35: =IFERROR(IF(57>=ASSUMPTIONS!$C$62,ASSUMPTIONS!$D$62*(1+ASSUMPTIONS!$B$66),0),0) -> 6828 | BK35: =IFERROR(IF(58>=ASSUMPTIONS!$C$62,ASSUMPTIONS!$D$62*(1+ASSUMPTIONS!$B$66),0),0) -> 6828 | BL35: =IFERROR(IF(59>=ASSUMPTIONS!$C$62,ASSUMPTIONS!$D$62*(1+ASSUMPTIONS!$B$66),0),0) -> 6828 | BM35: =IFERROR(IF(60>=ASSUMPTIONS!$C$62,ASSUMPTIONS!$D$62*(1+ASSUMPTIONS!$B$66),0),0) -> 6828 | BN35: =SUM(BB35:BM35) -> 81936
A36: =IFERROR(ASSUMPTIONS!B63,"(empty)") -> CS | B36: =IFERROR(IF(1>=ASSUMPTIONS!$C$63,ASSUMPTIONS!$D$63*(1+ASSUMPTIONS!$B$66),0),0) -> 0 | C36: =IFERROR(IF(2>=ASSUMPTIONS!$C$63,ASSUMPTIONS!$D$63*(1+ASSUMPTIONS!$B$66),0),0) -> 0 | D36: =IFERROR(IF(3>=ASSUMPTIONS!$C$63,ASSUMPTIONS!$D$63*(1+ASSUMPTIONS!$B$66),0),0) -> 0 | E36: =IFERROR(IF(4>=ASSUMPTIONS!$C$63,ASSUMPTIONS!$D$63*(1+ASSUMPTIONS!$B$66),0),0) -> 0 | F36: =IFERROR(IF(5>=ASSUMPTIONS!$C$63,ASSUMPTIONS!$D$63*(1+ASSUMPTIONS!$B$66),0),0) -> 0 | G36: =IFERROR(IF(6>=ASSUMPTIONS!$C$63,ASSUMPTIONS!$D$63*(1+ASSUMPTIONS!$B$66),0),0) -> 0 | H36: =IFERROR(IF(7>=ASSUMPTIONS!$C$63,ASSUMPTIONS!$D$63*(1+ASSUMPTIONS!$B$66),0),0) -> 0 | I36: =IFERROR(IF(8>=ASSUMPTIONS!$C$63,ASSUMPTIONS!$D$63*(1+ASSUMPTIONS!$B$66),0),0) -> 0 | J36: =IFERROR(IF(9>=ASSUMPTIONS!$C$63,ASSUMPTIONS!$D$63*(1+ASSUMPTIONS!$B$66),0),0) -> 5121 | K36: =IFERROR(IF(10>=ASSUMPTIONS!$C$63,ASSUMPTIONS!$D$63*(1+ASSUMPTIONS!$B$66),0),0) -> 5121 | L36: =IFERROR(IF(11>=ASSUMPTIONS!$C$63,ASSUMPTIONS!$D$63*(1+ASSUMPTIONS!$B$66),0),0) -> 5121 | M36: =IFERROR(IF(12>=ASSUMPTIONS!$C$63,ASSUMPTIONS!$D$63*(1+ASSUMPTIONS!$B$66),0),0) -> 5121 | N36: =SUM(B36:M36) -> 20484 | O36: =IFERROR(IF(13>=ASSUMPTIONS!$C$63,ASSUMPTIONS!$D$63*(1+ASSUMPTIONS!$B$66),0),0) -> 5121 | P36: =IFERROR(IF(14>=ASSUMPTIONS!$C$63,ASSUMPTIONS!$D$63*(1+ASSUMPTIONS!$B$66),0),0) -> 5121 | Q36: =IFERROR(IF(15>=ASSUMPTIONS!$C$63,ASSUMPTIONS!$D$63*(1+ASSUMPTIONS!$B$66),0),0) -> 5121 | R36: =IFERROR(IF(16>=ASSUMPTIONS!$C$63,ASSUMPTIONS!$D$63*(1+ASSUMPTIONS!$B$66),0),0) -> 5121 | S36: =IFERROR(IF(17>=ASSUMPTIONS!$C$63,ASSUMPTIONS!$D$63*(1+ASSUMPTIONS!$B$66),0),0) -> 5121 | T36: =IFERROR(IF(18>=ASSUMPTIONS!$C$63,ASSUMPTIONS!$D$63*(1+ASSUMPTIONS!$B$66),0),0) -> 5121 | U36: =IFERROR(IF(19>=ASSUMPTIONS!$C$63,ASSUMPTIONS!$D$63*(1+ASSUMPTIONS!$B$66),0),0) -> 5121 | V36: =IFERROR(IF(20>=ASSUMPTIONS!$C$63,ASSUMPTIONS!$D$63*(1+ASSUMPTIONS!$B$66),0),0) -> 5121 | W36: =IFERROR(IF(21>=ASSUMPTIONS!$C$63,ASSUMPTIONS!$D$63*(1+ASSUMPTIONS!$B$66),0),0) -> 5121 | X36: =IFERROR(IF(22>=ASSUMPTIONS!$C$63,ASSUMPTIONS!$D$63*(1+ASSUMPTIONS!$B$66),0),0) -> 5121 | Y36: =IFERROR(IF(23>=ASSUMPTIONS!$C$63,ASSUMPTIONS!$D$63*(1+ASSUMPTIONS!$B$66),0),0) -> 5121 | Z36: =IFERROR(IF(24>=ASSUMPTIONS!$C$63,ASSUMPTIONS!$D$63*(1+ASSUMPTIONS!$B$66),0),0) -> 5121 | AA36: =SUM(O36:Z36) -> 61452 | AB36: =IFERROR(IF(25>=ASSUMPTIONS!$C$63,ASSUMPTIONS!$D$63*(1+ASSUMPTIONS!$B$66),0),0) -> 5121 | AC36: =IFERROR(IF(26>=ASSUMPTIONS!$C$63,ASSUMPTIONS!$D$63*(1+ASSUMPTIONS!$B$66),0),0) -> 5121 | AD36: =IFERROR(IF(27>=ASSUMPTIONS!$C$63,ASSUMPTIONS!$D$63*(1+ASSUMPTIONS!$B$66),0),0) -> 5121 | AE36: =IFERROR(IF(28>=ASSUMPTIONS!$C$63,ASSUMPTIONS!$D$63*(1+ASSUMPTIONS!$B$66),0),0) -> 5121 | AF36: =IFERROR(IF(29>=ASSUMPTIONS!$C$63,ASSUMPTIONS!$D$63*(1+ASSUMPTIONS!$B$66),0),0) -> 5121 | AG36: =IFERROR(IF(30>=ASSUMPTIONS!$C$63,ASSUMPTIONS!$D$63*(1+ASSUMPTIONS!$B$66),0),0) -> 5121 | AH36: =IFERROR(IF(31>=ASSUMPTIONS!$C$63,ASSUMPTIONS!$D$63*(1+ASSUMPTIONS!$B$66),0),0) -> 5121 | AI36: =IFERROR(IF(32>=ASSUMPTIONS!$C$63,ASSUMPTIONS!$D$63*(1+ASSUMPTIONS!$B$66),0),0) -> 5121 | AJ36: =IFERROR(IF(33>=ASSUMPTIONS!$C$63,ASSUMPTIONS!$D$63*(1+ASSUMPTIONS!$B$66),0),0) -> 5121 | AK36: =IFERROR(IF(34>=ASSUMPTIONS!$C$63,ASSUMPTIONS!$D$63*(1+ASSUMPTIONS!$B$66),0),0) -> 5121 | AL36: =IFERROR(IF(35>=ASSUMPTIONS!$C$63,ASSUMPTIONS!$D$63*(1+ASSUMPTIONS!$B$66),0),0) -> 5121 | AM36: =IFERROR(IF(36>=ASSUMPTIONS!$C$63,ASSUMPTIONS!$D$63*(1+ASSUMPTIONS!$B$66),0),0) -> 5121 | AN36: =SUM(AB36:AM36) -> 61452 | AO36: =IFERROR(IF(37>=ASSUMPTIONS!$C$63,ASSUMPTIONS!$D$63*(1+ASSUMPTIONS!$B$66),0),0) -> 5121 | AP36: =IFERROR(IF(38>=ASSUMPTIONS!$C$63,ASSUMPTIONS!$D$63*(1+ASSUMPTIONS!$B$66),0),0) -> 5121 | AQ36: =IFERROR(IF(39>=ASSUMPTIONS!$C$63,ASSUMPTIONS!$D$63*(1+ASSUMPTIONS!$B$66),0),0) -> 5121 | AR36: =IFERROR(IF(40>=ASSUMPTIONS!$C$63,ASSUMPTIONS!$D$63*(1+ASSUMPTIONS!$B$66),0),0) -> 5121 | AS36: =IFERROR(IF(41>=ASSUMPTIONS!$C$63,ASSUMPTIONS!$D$63*(1+ASSUMPTIONS!$B$66),0),0) -> 5121 | AT36: =IFERROR(IF(42>=ASSUMPTIONS!$C$63,ASSUMPTIONS!$D$63*(1+ASSUMPTIONS!$B$66),0),0) -> 5121 | AU36: =IFERROR(IF(43>=ASSUMPTIONS!$C$63,ASSUMPTIONS!$D$63*(1+ASSUMPTIONS!$B$66),0),0) -> 5121 | AV36: =IFERROR(IF(44>=ASSUMPTIONS!$C$63,ASSUMPTIONS!$D$63*(1+ASSUMPTIONS!$B$66),0),0) -> 5121 | AW36: =IFERROR(IF(45>=ASSUMPTIONS!$C$63,ASSUMPTIONS!$D$63*(1+ASSUMPTIONS!$B$66),0),0) -> 5121 | AX36: =IFERROR(IF(46>=ASSUMPTIONS!$C$63,ASSUMPTIONS!$D$63*(1+ASSUMPTIONS!$B$66),0),0) -> 5121 | AY36: =IFERROR(IF(47>=ASSUMPTIONS!$C$63,ASSUMPTIONS!$D$63*(1+ASSUMPTIONS!$B$66),0),0) -> 5121 | AZ36: =IFERROR(IF(48>=ASSUMPTIONS!$C$63,ASSUMPTIONS!$D$63*(1+ASSUMPTIONS!$B$66),0),0) -> 5121 | BA36: =SUM(AO36:AZ36) -> 61452 | BB36: =IFERROR(IF(49>=ASSUMPTIONS!$C$63,ASSUMPTIONS!$D$63*(1+ASSUMPTIONS!$B$66),0),0) -> 5121 | BC36: =IFERROR(IF(50>=ASSUMPTIONS!$C$63,ASSUMPTIONS!$D$63*(1+ASSUMPTIONS!$B$66),0),0) -> 5121 | BD36: =IFERROR(IF(51>=ASSUMPTIONS!$C$63,ASSUMPTIONS!$D$63*(1+ASSUMPTIONS!$B$66),0),0) -> 5121 | BE36: =IFERROR(IF(52>=ASSUMPTIONS!$C$63,ASSUMPTIONS!$D$63*(1+ASSUMPTIONS!$B$66),0),0) -> 5121 | BF36: =IFERROR(IF(53>=ASSUMPTIONS!$C$63,ASSUMPTIONS!$D$63*(1+ASSUMPTIONS!$B$66),0),0) -> 5121 | BG36: =IFERROR(IF(54>=ASSUMPTIONS!$C$63,ASSUMPTIONS!$D$63*(1+ASSUMPTIONS!$B$66),0),0) -> 5121 | BH36: =IFERROR(IF(55>=ASSUMPTIONS!$C$63,ASSUMPTIONS!$D$63*(1+ASSUMPTIONS!$B$66),0),0) -> 5121 | BI36: =IFERROR(IF(56>=ASSUMPTIONS!$C$63,ASSUMPTIONS!$D$63*(1+ASSUMPTIONS!$B$66),0),0) -> 5121 | BJ36: =IFERROR(IF(57>=ASSUMPTIONS!$C$63,ASSUMPTIONS!$D$63*(1+ASSUMPTIONS!$B$66),0),0) -> 5121 | BK36: =IFERROR(IF(58>=ASSUMPTIONS!$C$63,ASSUMPTIONS!$D$63*(1+ASSUMPTIONS!$B$66),0),0) -> 5121 | BL36: =IFERROR(IF(59>=ASSUMPTIONS!$C$63,ASSUMPTIONS!$D$63*(1+ASSUMPTIONS!$B$66),0),0) -> 5121 | BM36: =IFERROR(IF(60>=ASSUMPTIONS!$C$63,ASSUMPTIONS!$D$63*(1+ASSUMPTIONS!$B$66),0),0) -> 5121 | BN36: =SUM(BB36:BM36) -> 61452
A37: =IFERROR(ASSUMPTIONS!B64,"(empty)") -> CS | B37: =IFERROR(IF(1>=ASSUMPTIONS!$C$64,ASSUMPTIONS!$D$64*(1+ASSUMPTIONS!$B$66),0),0) -> 0 | C37: =IFERROR(IF(2>=ASSUMPTIONS!$C$64,ASSUMPTIONS!$D$64*(1+ASSUMPTIONS!$B$66),0),0) -> 0 | D37: =IFERROR(IF(3>=ASSUMPTIONS!$C$64,ASSUMPTIONS!$D$64*(1+ASSUMPTIONS!$B$66),0),0) -> 0 | E37: =IFERROR(IF(4>=ASSUMPTIONS!$C$64,ASSUMPTIONS!$D$64*(1+ASSUMPTIONS!$B$66),0),0) -> 0 | F37: =IFERROR(IF(5>=ASSUMPTIONS!$C$64,ASSUMPTIONS!$D$64*(1+ASSUMPTIONS!$B$66),0),0) -> 0 | G37: =IFERROR(IF(6>=ASSUMPTIONS!$C$64,ASSUMPTIONS!$D$64*(1+ASSUMPTIONS!$B$66),0),0) -> 0 | H37: =IFERROR(IF(7>=ASSUMPTIONS!$C$64,ASSUMPTIONS!$D$64*(1+ASSUMPTIONS!$B$66),0),0) -> 0 | I37: =IFERROR(IF(8>=ASSUMPTIONS!$C$64,ASSUMPTIONS!$D$64*(1+ASSUMPTIONS!$B$66),0),0) -> 0 | J37: =IFERROR(IF(9>=ASSUMPTIONS!$C$64,ASSUMPTIONS!$D$64*(1+ASSUMPTIONS!$B$66),0),0) -> 0 | K37: =IFERROR(IF(10>=ASSUMPTIONS!$C$64,ASSUMPTIONS!$D$64*(1+ASSUMPTIONS!$B$66),0),0) -> 0 | L37: =IFERROR(IF(11>=ASSUMPTIONS!$C$64,ASSUMPTIONS!$D$64*(1+ASSUMPTIONS!$B$66),0),0) -> 0 | M37: =IFERROR(IF(12>=ASSUMPTIONS!$C$64,ASSUMPTIONS!$D$64*(1+ASSUMPTIONS!$B$66),0),0) -> 3983 | N37: =SUM(B37:M37) -> 3983 | O37: =IFERROR(IF(13>=ASSUMPTIONS!$C$64,ASSUMPTIONS!$D$64*(1+ASSUMPTIONS!$B$66),0),0) -> 3983 | P37: =IFERROR(IF(14>=ASSUMPTIONS!$C$64,ASSUMPTIONS!$D$64*(1+ASSUMPTIONS!$B$66),0),0) -> 3983 | Q37: =IFERROR(IF(15>=ASSUMPTIONS!$C$64,ASSUMPTIONS!$D$64*(1+ASSUMPTIONS!$B$66),0),0) -> 3983 | R37: =IFERROR(IF(16>=ASSUMPTIONS!$C$64,ASSUMPTIONS!$D$64*(1+ASSUMPTIONS!$B$66),0),0) -> 3983 | S37: =IFERROR(IF(17>=ASSUMPTIONS!$C$64,ASSUMPTIONS!$D$64*(1+ASSUMPTIONS!$B$66),0),0) -> 3983 | T37: =IFERROR(IF(18>=ASSUMPTIONS!$C$64,ASSUMPTIONS!$D$64*(1+ASSUMPTIONS!$B$66),0),0) -> 3983 | U37: =IFERROR(IF(19>=ASSUMPTIONS!$C$64,ASSUMPTIONS!$D$64*(1+ASSUMPTIONS!$B$66),0),0) -> 3983 | V37: =IFERROR(IF(20>=ASSUMPTIONS!$C$64,ASSUMPTIONS!$D$64*(1+ASSUMPTIONS!$B$66),0),0) -> 3983 | W37: =IFERROR(IF(21>=ASSUMPTIONS!$C$64,ASSUMPTIONS!$D$64*(1+ASSUMPTIONS!$B$66),0),0) -> 3983 | X37: =IFERROR(IF(22>=ASSUMPTIONS!$C$64,ASSUMPTIONS!$D$64*(1+ASSUMPTIONS!$B$66),0),0) -> 3983 | Y37: =IFERROR(IF(23>=ASSUMPTIONS!$C$64,ASSUMPTIONS!$D$64*(1+ASSUMPTIONS!$B$66),0),0) -> 3983 | Z37: =IFERROR(IF(24>=ASSUMPTIONS!$C$64,ASSUMPTIONS!$D$64*(1+ASSUMPTIONS!$B$66),0),0) -> 3983 | AA37: =SUM(O37:Z37) -> 47796 | AB37: =IFERROR(IF(25>=ASSUMPTIONS!$C$64,ASSUMPTIONS!$D$64*(1+ASSUMPTIONS!$B$66),0),0) -> 3983 | AC37: =IFERROR(IF(26>=ASSUMPTIONS!$C$64,ASSUMPTIONS!$D$64*(1+ASSUMPTIONS!$B$66),0),0) -> 3983 | AD37: =IFERROR(IF(27>=ASSUMPTIONS!$C$64,ASSUMPTIONS!$D$64*(1+ASSUMPTIONS!$B$66),0),0) -> 3983 | AE37: =IFERROR(IF(28>=ASSUMPTIONS!$C$64,ASSUMPTIONS!$D$64*(1+ASSUMPTIONS!$B$66),0),0) -> 3983 | AF37: =IFERROR(IF(29>=ASSUMPTIONS!$C$64,ASSUMPTIONS!$D$64*(1+ASSUMPTIONS!$B$66),0),0) -> 3983 | AG37: =IFERROR(IF(30>=ASSUMPTIONS!$C$64,ASSUMPTIONS!$D$64*(1+ASSUMPTIONS!$B$66),0),0) -> 3983 | AH37: =IFERROR(IF(31>=ASSUMPTIONS!$C$64,ASSUMPTIONS!$D$64*(1+ASSUMPTIONS!$B$66),0),0) -> 3983 | AI37: =IFERROR(IF(32>=ASSUMPTIONS!$C$64,ASSUMPTIONS!$D$64*(1+ASSUMPTIONS!$B$66),0),0) -> 3983 | AJ37: =IFERROR(IF(33>=ASSUMPTIONS!$C$64,ASSUMPTIONS!$D$64*(1+ASSUMPTIONS!$B$66),0),0) -> 3983 | AK37: =IFERROR(IF(34>=ASSUMPTIONS!$C$64,ASSUMPTIONS!$D$64*(1+ASSUMPTIONS!$B$66),0),0) -> 3983 | AL37: =IFERROR(IF(35>=ASSUMPTIONS!$C$64,ASSUMPTIONS!$D$64*(1+ASSUMPTIONS!$B$66),0),0) -> 3983 | AM37: =IFERROR(IF(36>=ASSUMPTIONS!$C$64,ASSUMPTIONS!$D$64*(1+ASSUMPTIONS!$B$66),0),0) -> 3983 | AN37: =SUM(AB37:AM37) -> 47796 | AO37: =IFERROR(IF(37>=ASSUMPTIONS!$C$64,ASSUMPTIONS!$D$64*(1+ASSUMPTIONS!$B$66),0),0) -> 3983 | AP37: =IFERROR(IF(38>=ASSUMPTIONS!$C$64,ASSUMPTIONS!$D$64*(1+ASSUMPTIONS!$B$66),0),0) -> 3983 | AQ37: =IFERROR(IF(39>=ASSUMPTIONS!$C$64,ASSUMPTIONS!$D$64*(1+ASSUMPTIONS!$B$66),0),0) -> 3983 | AR37: =IFERROR(IF(40>=ASSUMPTIONS!$C$64,ASSUMPTIONS!$D$64*(1+ASSUMPTIONS!$B$66),0),0) -> 3983 | AS37: =IFERROR(IF(41>=ASSUMPTIONS!$C$64,ASSUMPTIONS!$D$64*(1+ASSUMPTIONS!$B$66),0),0) -> 3983 | AT37: =IFERROR(IF(42>=ASSUMPTIONS!$C$64,ASSUMPTIONS!$D$64*(1+ASSUMPTIONS!$B$66),0),0) -> 3983 | AU37: =IFERROR(IF(43>=ASSUMPTIONS!$C$64,ASSUMPTIONS!$D$64*(1+ASSUMPTIONS!$B$66),0),0) -> 3983 | AV37: =IFERROR(IF(44>=ASSUMPTIONS!$C$64,ASSUMPTIONS!$D$64*(1+ASSUMPTIONS!$B$66),0),0) -> 3983 | AW37: =IFERROR(IF(45>=ASSUMPTIONS!$C$64,ASSUMPTIONS!$D$64*(1+ASSUMPTIONS!$B$66),0),0) -> 3983 | AX37: =IFERROR(IF(46>=ASSUMPTIONS!$C$64,ASSUMPTIONS!$D$64*(1+ASSUMPTIONS!$B$66),0),0) -> 3983 | AY37: =IFERROR(IF(47>=ASSUMPTIONS!$C$64,ASSUMPTIONS!$D$64*(1+ASSUMPTIONS!$B$66),0),0) -> 3983 | AZ37: =IFERROR(IF(48>=ASSUMPTIONS!$C$64,ASSUMPTIONS!$D$64*(1+ASSUMPTIONS!$B$66),0),0) -> 3983 | BA37: =SUM(AO37:AZ37) -> 47796 | BB37: =IFERROR(IF(49>=ASSUMPTIONS!$C$64,ASSUMPTIONS!$D$64*(1+ASSUMPTIONS!$B$66),0),0) -> 3983 | BC37: =IFERROR(IF(50>=ASSUMPTIONS!$C$64,ASSUMPTIONS!$D$64*(1+ASSUMPTIONS!$B$66),0),0) -> 3983 | BD37: =IFERROR(IF(51>=ASSUMPTIONS!$C$64,ASSUMPTIONS!$D$64*(1+ASSUMPTIONS!$B$66),0),0) -> 3983 | BE37: =IFERROR(IF(52>=ASSUMPTIONS!$C$64,ASSUMPTIONS!$D$64*(1+ASSUMPTIONS!$B$66),0),0) -> 3983 | BF37: =IFERROR(IF(53>=ASSUMPTIONS!$C$64,ASSUMPTIONS!$D$64*(1+ASSUMPTIONS!$B$66),0),0) -> 3983 | BG37: =IFERROR(IF(54>=ASSUMPTIONS!$C$64,ASSUMPTIONS!$D$64*(1+ASSUMPTIONS!$B$66),0),0) -> 3983 | BH37: =IFERROR(IF(55>=ASSUMPTIONS!$C$64,ASSUMPTIONS!$D$64*(1+ASSUMPTIONS!$B$66),0),0) -> 3983 | BI37: =IFERROR(IF(56>=ASSUMPTIONS!$C$64,ASSUMPTIONS!$D$64*(1+ASSUMPTIONS!$B$66),0),0) -> 3983 | BJ37: =IFERROR(IF(57>=ASSUMPTIONS!$C$64,ASSUMPTIONS!$D$64*(1+ASSUMPTIONS!$B$66),0),0) -> 3983 | BK37: =IFERROR(IF(58>=ASSUMPTIONS!$C$64,ASSUMPTIONS!$D$64*(1+ASSUMPTIONS!$B$66),0),0) -> 3983 | BL37: =IFERROR(IF(59>=ASSUMPTIONS!$C$64,ASSUMPTIONS!$D$64*(1+ASSUMPTIONS!$B$66),0),0) -> 3983 | BM37: =IFERROR(IF(60>=ASSUMPTIONS!$C$64,ASSUMPTIONS!$D$64*(1+ASSUMPTIONS!$B$66),0),0) -> 3983 | BN37: =SUM(BB37:BM37) -> 47796
A38: CUSTOMER SUCCESS — TOTAL (£) | B38: =SUM(B35:B37) -> 0 | C38: =SUM(C35:C37) -> 0 | D38: =SUM(D35:D37) -> 6828 | E38: =SUM(E35:E37) -> 6828 | F38: =SUM(F35:F37) -> 6828 | G38: =SUM(G35:G37) -> 6828 | H38: =SUM(H35:H37) -> 6828 | I38: =SUM(I35:I37) -> 6828 | ... M38: =SUM(M35:M37) -> 15932 | N38: =SUM(B38:M38) -> 92747 | O38: =SUM(O35:O37) -> 15932 | P38: =SUM(P35:P37) -> 15932 | Q38: =SUM(Q35:Q37) -> 15932 | R38: =SUM(R35:R37) -> 15932 | S38: =SUM(S35:S37) -> 15932 | T38: =SUM(T35:T37) -> 15932 | U38: =SUM(U35:U37) -> 15932 | V38: =SUM(V35:V37) -> 15932 | ... Z38: =SUM(Z35:Z37) -> 15932 | AA38: =SUM(O38:Z38) -> 191184 | AB38: =SUM(AB35:AB37) -> 15932 | AC38: =SUM(AC35:AC37) -> 15932 | AD38: =SUM(AD35:AD37) -> 15932 | AE38: =SUM(AE35:AE37) -> 15932 | AF38: =SUM(AF35:AF37) -> 15932 | AG38: =SUM(AG35:AG37) -> 15932 | AH38: =SUM(AH35:AH37) -> 15932 | AI38: =SUM(AI35:AI37) -> 15932 | ... AM38: =SUM(AM35:AM37) -> 15932 | AN38: =SUM(AB38:AM38) -> 191184 | AO38: =SUM(AO35:AO37) -> 15932 | AP38: =SUM(AP35:AP37) -> 15932 | AQ38: =SUM(AQ35:AQ37) -> 15932 | AR38: =SUM(AR35:AR37) -> 15932 | AS38: =SUM(AS35:AS37) -> 15932 | AT38: =SUM(AT35:AT37) -> 15932 | AU38: =SUM(AU35:AU37) -> 15932 | AV38: =SUM(AV35:AV37) -> 15932 | ... AZ38: =SUM(AZ35:AZ37) -> 15932 | BA38: =SUM(AO38:AZ38) -> 191184 | BB38: =SUM(BB35:BB37) -> 15932 | BC38: =SUM(BC35:BC37) -> 15932 | BD38: =SUM(BD35:BD37) -> 15932 | BE38: =SUM(BE35:BE37) -> 15932 | BF38: =SUM(BF35:BF37) -> 15932 | BG38: =SUM(BG35:BG37) -> 15932 | BH38: =SUM(BH35:BH37) -> 15932 | BI38: =SUM(BI35:BI37) -> 15932 | ... BM38: =SUM(BM35:BM37) -> 15932 | BN38: =SUM(BB38:BM38) -> 191184
A40: G&A
