Workbook

Sheet COVER
B2: Raise Ready
B3: Pre-Seed Financial Model — Foundation
B5: HOW TO USE THIS MODEL
B7: Step 01: ASSUMPTIONS | C7: Enter company info, revenue drivers, and costs. Yellow cells = your inputs (blue text).
B9: Step 02: REVENUE | C9: Auto-calculated from your drivers. Monthly new customers × ARPU.
B11: Step 03: HEADCOUNT | C11: Staff costs by role. Edit roles and salaries in Assumptions.
B13: Step 04: P&L | C13: Full profit & loss. All formulas — do not edit.
B15: Step 05: CASH FLOW | C15: Runway projection. Shows months of cash remaining.

Sheet ASSUMPTIONS
A1: ASSUMPTIONS — All Model Inputs
A2: Yellow cells = your inputs (blue text). Replace example values with your own data. Do not edit white cells — these are formulas.
A4: SECTION 1 — COMPANY INFORMATION
A5: Company Name | B5: My Startup Ltd | C5: Your legal trading name
A6: Reporting Currency | B6: $ | C6: Currency symbol used throughout
A7: Model Start | B7: Jan 2025 | C7: Start month label for display
A9: SECTION 2 — REVENUE DRIVERS
A10: Starting Customers (Month 1) | B10: 10 | C10: Customers at model start
A11: New Customers per Month | B11: 15 | C11: Average monthly acquisition
A12: Monthly Customer Growth Rate | B12: 0.08 | C12: Growth in new customer adds (MoM)
A13: Monthly Churn Rate | B13: 0.05 | C13: Percentage of customers lost per month
A14: Average Revenue Per User (ARPU) | B14: 99 | C14: Monthly ARPU ($)
A15: ARPU Annual Increase | B15: 0 | C15: Annual price increase %
A17: SECTION 3 — COST OF GOODS SOLD
A18: Hosting Cost per Customer | B18: 5 | C18: Monthly infrastructure cost per user ($)
A19: Payment Processing (% of Revenue) | B19: 0.029 | C19: Stripe/payment fees
A20: Support Cost per Customer | B20: 3 | C20: Monthly support cost per user ($)
A22: SECTION 4 — HEADCOUNT PLAN
A23: Role / Start Month / Annual Salary | B23: Role Name | C23: Start Month # | D23: Annual Salary ($)
A24: CEO / Co-Founder | B24: CEO / Co-Founder | C24: 1 | D24: 60000
A25: CTO / Co-Founder | B25: CTO / Co-Founder | C25: 1 | D25: 60000
A26: Engineer #1 | B26: Engineer #1 | C26: 3 | D26: 95000
A27: Engineer #2 | B27: Engineer #2 | C27: 6 | D27: 95000
A28: Designer | B28: Designer | C28: 4 | D28: 75000
A29: Sales / Growth | B29: Sales / Growth | C29: 6 | D29: 70000
A30: (empty)
A31: (empty)
A33: Payroll Overhead Multiplier | B33: 1.25 | C33: Benefits, tax, insurance multiplier
A35: SECTION 5 — OPERATING EXPENSES
A36: Marketing Spend (Monthly) | B36: 2000 | C36: Monthly marketing budget ($)
A37: Marketing Spend Growth (Monthly) | B37: 0.05 | C37: MoM increase in marketing
A38: Software & Tools (Monthly) | B38: 800 | C38: SaaS tools, subscriptions ($)
A39: Office / Rent (Monthly) | B39: 0 | C39: Office costs ($)
A40: Legal & Professional (Monthly) | B40: 500 | C40: Legal, accounting, compliance ($)
A41: Other OpEx (Monthly) | B41: 300 | C41: Miscellaneous costs ($)
A43: SECTION 6 — CASH & FUNDING
A44: Starting Cash Balance | B44: 50000 | C44: Cash at model start ($)
A45: Pre-Seed Raise Amount | B45: 250000 | C45: Expected raise ($)
A46: Pre-Seed Close Month | B46: 3 | C46: Month # when funds arrive

Sheet REVENUE
A1: REVENUE MODEL
A2: Driver-based model. All inputs flow from ASSUMPTIONS tab. White cells = formulas (do not edit).
B4: YEAR 1 | N4: YEAR 2
B5: Jan | C5: Feb | D5: Mar | E5: Apr | F5: May | G5: Jun | H5: Jul | I5: Aug | J5: Sep | K5: Oct | L5: Nov | M5: Dec | N5: Jan | O5: Feb | P5: Mar | Q5: Apr | R5: May | S5: Jun | T5: Y1 Total
A6: CUSTOMER ACQUISITION
A7: New Customers Added | B7: =IFERROR(ASSUMPTIONS!$B$11,0) -> 15 | C7: =IFERROR(ROUND(B7*(1+ASSUMPTIONS!$B$12),0),0) -> 16 | D7: =IFERROR(ROUND(C7*(1+ASSUMPTIONS!$B$12),0),0) -> 17 | E7: =IFERROR(ROUND(D7*(1+ASSUMPTIONS!$B$12),0),0) -> 18 | F7: =IFERROR(ROUND(E7*(1+ASSUMPTIONS!$B$12),0),0) -> 19 | G7: =IFERROR(ROUND(F7*(1+ASSUMPTIONS!$B$12),0),0) -> 21 | H7: =IFERROR(ROUND(G7*(1+ASSUMPTIONS!$B$12),0),0) -> 23 | I7: =IFERROR(ROUND(H7*(1+ASSUMPTIONS!$B$12),0),0) -> 25 | J7: =IFERROR(ROUND(I7*(1+ASSUMPTIONS!$B$12),0),0) -> 27 | ... S7: =IFERROR(ROUND(R7*(1+ASSUMPTIONS!$B$12),0),0) -> 53
A8: Customers Churned | B8: =IFERROR(ROUND(ASSUMPTIONS!$B$10*ASSUMPTIONS!$B$13,0),0) -> 1 | C8: =IFERROR(ROUND(B9*ASSUMPTIONS!$B$13,0),0) -> 1 | D8: =IFERROR(ROUND(C9*ASSUMPTIONS!$B$13,0),0) -> 2 | E8: =IFERROR(ROUND(D9*ASSUMPTIONS!$B$13,0),0) -> 3 | F8: =IFERROR(ROUND(E9*ASSUMPTIONS!$B$13,0),0) -> 3 | G8: =IFERROR(ROUND(F9*ASSUMPTIONS!$B$13,0),0) -> 4 | H8: =IFERROR(ROUND(G9*ASSUMPTIONS!$B$13,0),0) -> 5 | I8: =IFERROR(ROUND(H9*ASSUMPTIONS!$B$13,0),0) -> 6 | J8: =IFERROR(ROUND(I9*ASSUMPTIONS!$B$13,0),0) -> 7 | ... S8: =IFERROR(ROUND(R9*ASSUMPTIONS!$B$13,0),0) -> 18
A9: Active Customers — End of Month | B9: =IFERROR(ASSUMPTIONS!$B$10+B7-B8,0) -> 24 | C9: =IFERROR(B9+C7-C8,0) -> 39 | D9: =IFERROR(C9+D7-D8,0) -> 54 | E9: =IFERROR(D9+E7-E8,0) -> 69 | F9: =IFERROR(E9+F7-F8,0) -> 85 | G9: =IFERROR(F9+G7-G8,0) -> 102 | H9: =IFERROR(G9+H7-H8,0) -> 120 | I9: =IFERROR(H9+I7-I8,0) -> 139 | J9: =IFERROR(I9+J7-J8,0) -> 159 | ... S9: =IFERROR(R9+S7-S8,0) -> 401
A11: MONTHLY REVENUE
A12: Monthly ARPU ($) | B12: =IFERROR(ASSUMPTIONS!$B$14,0) -> 99 | C12: =IFERROR(ASSUMPTIONS!$B$14,0) -> 99 | D12: =IFERROR(ASSUMPTIONS!$B$14,0) -> 99 | E12: =IFERROR(ASSUMPTIONS!$B$14,0) -> 99 | F12: =IFERROR(ASSUMPTIONS!$B$14,0) -> 99 | G12: =IFERROR(ASSUMPTIONS!$B$14,0) -> 99 | H12: =IFERROR(ASSUMPTIONS!$B$14,0) -> 99 | I12: =IFERROR(ASSUMPTIONS!$B$14,0) -> 99 | ... S12: =IFERROR(ASSUMPTIONS!$B$14,0) -> 99
A13: TOTAL REVENUE ($) | B13: =IFERROR(B9*B12,0) -> 2376 | C13: =IFERROR(C9*C12,0) -> 3861 | D13: =IFERROR(D9*D12,0) -> 5346 | E13: =IFERROR(E9*E12,0) -> 6831 | F13: =IFERROR(F9*F12,0) -> 8415 | G13: =IFERROR(G9*G12,0) -> 10098 | H13: =IFERROR(H9*H12,0) -> 11880 | I13: =IFERROR(I9*I12,0) -> 13761 | ... M13: =IFERROR(M9*M12,0) -> 22275 | N13: =SUM(B13:M13) -> 138402 | O13: =IFERROR(O9*O12,0) -> 27324 | P13: =IFERROR(P9*P12,0) -> 30096 | Q13: =IFERROR(Q9*Q12,0) -> 33066 | R13: =IFERROR(R9*R12,0) -> 36234 | S13: =IFERROR(S9*S12,0) -> 39699
A14: Month-on-Month Revenue Growth % | C14: =IFERROR((C13-B13)/B13,0) -> 0.625 | D14: =IFERROR((D13-C13)/C13,0) -> 0.38461538 | E14: =IFERROR((E13-D13)/D13,0) -> 0.27777778 | F14: =IFERROR((F13-E13)/E13,0) -> 0.23188406 | G14: =IFERROR((G13-F13)/F13,0) -> 0.2 | H14: =IFERROR((H13-G13)/G13,0) -> 0.17647059 | I14: =IFERROR((I13-H13)/H13,0) -> 0.15833333 | J14: =IFERROR((J13-I13)/I13,0) -> 0.14388489 | ... S14: =IFERROR((S13-R13)/R13,0) -> 0.095628415

Sheet HEADCOUNT
A1: HEADCOUNT — Staff Costs by Role
A2: All values auto-calculated from Assumptions. Edit roles, start months, and salaries there.
B4: YEAR 1 | N4: YEAR 2
B5: Jan | C5: Feb | D5: Mar | E5: Apr | F5: May | G5: Jun | H5: Jul | I5: Aug | J5: Sep | K5: Oct | L5: Nov | M5: Dec | N5: Jan | O5: Feb | P5: Mar | Q5: Apr | R5: May | S5: Jun | T5: Y1 Total
A7: =IFERROR(ASSUMPTIONS!B24,"(empty)") -> CEO / Co-Founder | B7: =IFERROR(IF(AND(1>=ASSUMPTIONS!$C$24,ASSUMPTIONS!$C$24>0),ASSUMPTIONS!$D$24/12*(ASSUMPTIONS!$B$33),0),0) -> 6250 | C7: =IFERROR(IF(AND(2>=ASSUMPTIONS!$C$24,ASSUMPTIONS!$C$24>0),ASSUMPTIONS!$D$24/12*(ASSUMPTIONS!$B$33),0),0) -> 6250 | D7: =IFERROR(IF(AND(3>=ASSUMPTIONS!$C$24,ASSUMPTIONS!$C$24>0),ASSUMPTIONS!$D$24/12*(ASSUMPTIONS!$B$33),0),0) -> 6250 | E7: =IFERROR(IF(AND(4>=ASSUMPTIONS!$C$24,ASSUMPTIONS!$C$24>0),ASSUMPTIONS!$D$24/12*(ASSUMPTIONS!$B$33),0),0) -> 6250 | F7: =IFERROR(IF(AND(5>=ASSUMPTIONS!$C$24,ASSUMPTIONS!$C$24>0),ASSUMPTIONS!$D$24/12*(ASSUMPTIONS!$B$33),0),0) -> 6250 | G7: =IFERROR(IF(AND(6>=ASSUMPTIONS!$C$24,ASSUMPTIONS!$C$24>0),ASSUMPTIONS!$D$24/12*(ASSUMPTIONS!$B$33),0),0) -> 6250 | H7: =IFERROR(IF(AND(7>=ASSUMPTIONS!$C$24,ASSUMPTIONS!$C$24>0),ASSUMPTIONS!$D$24/12*(ASSUMPTIONS!$B$33),0),0) -> 6250 | I7: =IFERROR(IF(AND(8>=ASSUMPTIONS!$C$24,ASSUMPTIONS!$C$24>0),ASSUMPTIONS!$D$24/12*(ASSUMPTIONS!$B$33),0),0) -> 6250 | J7: =IFERROR(IF(AND(9>=ASSUMPTIONS!$C$24,ASSUMPTIONS!$C$24>0),ASSUMPTIONS!$D$24/12*(ASSUMPTIONS!$B$33),0),0) -> 6250 | K7: =IFERROR(IF(AND(10>=ASSUMPTIONS!$C$24,ASSUMPTIONS!$C$24>0),ASSUMPTIONS!$D$24/12*(ASSUMPTIONS!$B$33),0),0) -> 6250 | L7: =IFERROR(IF(AND(11>=ASSUMPTIONS!$C$24,ASSUMPTIONS!$C$24>0),ASSUMPTIONS!$D$24/12*(ASSUMPTIONS!$B$33),0),0) -> 6250 | M7: =IFERROR(IF(AND(12>=ASSUMPTIONS!$C$24,ASSUMPTIONS!$C$24>0),ASSUMPTIONS!$D$24/12*(ASSUMPTIONS!$B$33),0),0) -> 6250 | N7: =IFERROR(IF(AND(13>=ASSUMPTIONS!$C$24,ASSUMPTIONS!$C$24>0),ASSUMPTIONS!$D$24/12*(ASSUMPTIONS!$B$33),0),0) -> 6250 | O7: =IFERROR(IF(AND(14>=ASSUMPTIONS!$C$24,ASSUMPTIONS!$C$24>0),ASSUMPTIONS!$D$24/12*(ASSUMPTIONS!$B$33),0),0) -> 6250 | P7: =IFERROR(IF(AND(15>=ASSUMPTIONS!$C$24,ASSUMPTIONS!$C$24>0),ASSUMPTIONS!$D$24/12*(ASSUMPTIONS!$B$33),0),0) -> 6250 | Q7: =IFERROR(IF(AND(16>=ASSUMPTIONS!$C$24,ASSUMPTIONS!$C$24>0),ASSUMPTIONS!$D$24/12*(ASSUMPTIONS!$B$33),0),0) -> 6250 | R7: =IFERROR(IF(AND(17>=ASSUMPTIONS!$C$24,ASSUMPTIONS!$C$24>0),ASSUMPTIONS!$D$24/12*(ASSUMPTIONS!$B$33),0),0) -> 6250 | S7: =IFERROR(IF(AND(18>=ASSUMPTIONS!$C$24,ASSUMPTIONS!$C$24>0),ASSUMPTIONS!$D$24/12*(ASSUMPTIONS!$B$33),0),0) -> 6250
A8: =IFERROR(ASSUMPTIONS!B25,"(empty)") -> CTO / Co-Founder | B8: =IFERROR(IF(AND(1>=ASSUMPTIONS!$C$25,ASSUMPTIONS!$C$25>0),ASSUMPTIONS!$D$25/12*(ASSUMPTIONS!$B$33),0),0) -> 6250 | C8: =IFERROR(IF(AND(2>=ASSUMPTIONS!$C$25,ASSUMPTIONS!$C$25>0),ASSUMPTIONS!$D$25/12*(ASSUMPTIONS!$B$33),0),0) -> 6250 | D8: =IFERROR(IF(AND(3>=ASSUMPTIONS!$C$25,ASSUMPTIONS!$C$25>0),ASSUMPTIONS!$D$25/12*(ASSUMPTIONS!$B$33),0),0) -> 6250 | E8: =IFERROR(IF(AND(4>=ASSUMPTIONS!$C$25,ASSUMPTIONS!$C$25>0),ASSUMPTIONS!$D$25/12*(ASSUMPTIONS!$B$33),0),0) -> 6250 | F8: =IFERROR(IF(AND(5>=ASSUMPTIONS!$C$25,ASSUMPTIONS!$C$25>0),ASSUMPTIONS!$D$25/12*(ASSUMPTIONS!$B$33),0),0) -> 6250 | G8: =IFERROR(IF(AND(6>=ASSUMPTIONS!$C$25,ASSUMPTIONS!$C$25>0),ASSUMPTIONS!$D$25/12*(ASSUMPTIONS!$B$33),0),0) -> 6250 | H8: =IFERROR(IF(AND(7>=ASSUMPTIONS!$C$25,ASSUMPTIONS!$C$25>0),ASSUMPTIONS!$D$25/12*(ASSUMPTIONS!$B$33),0),0) -> 6250 | I8: =IFERROR(IF(AND(8>=ASSUMPTIONS!$C$25,ASSUMPTIONS!$C$25>0),ASSUMPTIONS!$D$25/12*(ASSUMPTIONS!$B$33),0),0) -> 6250 | J8: =IFERROR(IF(AND(9>=ASSUMPTIONS!$C$25,ASSUMPTIONS!$C$25>0),ASSUMPTIONS!$D$25/12*(ASSUMPTIONS!$B$33),0),0) -> 6250 | K8: =IFERROR(IF(AND(10>=ASSUMPTIONS!$C$25,ASSUMPTIONS!$C$25>0),ASSUMPTIONS!$D$25/12*(ASSUMPTIONS!$B$33),0),0) -> 6250 | L8: =IFERROR(IF(AND(11>=ASSUMPTIONS!$C$25,ASSUMPTIONS!$C$25>0),ASSUMPTIONS!$D$25/12*(ASSUMPTIONS!$B$33),0),0) -> 6250 | M8: =IFERROR(IF(AND(12>=ASSUMPTIONS!$C$25,ASSUMPTIONS!$C$25>0),ASSUMPTIONS!$D$25/12*(ASSUMPTIONS!$B$33),0),0) -> 6250 | N8: =IFERROR(IF(AND(13>=ASSUMPTIONS!$C$25,ASSUMPTIONS!$C$25>0),ASSUMPTIONS!$D$25/12*(ASSUMPTIONS!$B$33),0),0) -> 6250 | O8: =IFERROR(IF(AND(14>=ASSUMPTIONS!$C$25,ASSUMPTIONS!$C$25>0),ASSUMPTIONS!$D$25/12*(ASSUMPTIONS!$B$33),0),0) -> 6250 | P8: =IFERROR(IF(AND(15>=ASSUMPTIONS!$C$25,ASSUMPTIONS!$C$25>0),ASSUMPTIONS!$D$25/12*(ASSUMPTIONS!$B$33),0),0) -> 6250 | Q8: =IFERROR(IF(AND(16>=ASSUMPTIONS!$C$25,ASSUMPTIONS!$C$25>0),ASSUMPTIONS!$D$25/12*(ASSUMPTIONS!$B$33),0),0) -> 6250 | R8: =IFERROR(IF(AND(17>=ASSUMPTIONS!$C$25,ASSUMPTIONS!$C$25>0),ASSUMPTIONS!$D$25/12*(ASSUMPTIONS!$B$33),0),0) -> 6250 | S8: =IFERROR(IF(AND(18>=ASSUMPTIONS!$C$25,ASSUMPTIONS!$C$25>0),ASSUMPTIONS!$D$25/12*(ASSUMPTIONS!$B$33),0),0) -> 6250
A9: =IFERROR(ASSUMPTIONS!B26,"(empty)") -> Engineer #1 | B9: =IFERROR(IF(AND(1>=ASSUMPTIONS!$C$26,ASSUMPTIONS!$C$26>0),ASSUMPTIONS!$D$26/12*(ASSUMPTIONS!$B$33),0),0) -> 0 | C9: =IFERROR(IF(AND(2>=ASSUMPTIONS!$C$26,ASSUMPTIONS!$C$26>0),ASSUMPTIONS!$D$26/12*(ASSUMPTIONS!$B$33),0),0) -> 0 | D9: =IFERROR(IF(AND(3>=ASSUMPTIONS!$C$26,ASSUMPTIONS!$C$26>0),ASSUMPTIONS!$D$26/12*(ASSUMPTIONS!$B$33),0),0) -> 9895.8333 | E9: =IFERROR(IF(AND(4>=ASSUMPTIONS!$C$26,ASSUMPTIONS!$C$26>0),ASSUMPTIONS!$D$26/12*(ASSUMPTIONS!$B$33),0),0) -> 9895.8333 | F9: =IFERROR(IF(AND(5>=ASSUMPTIONS!$C$26,ASSUMPTIONS!$C$26>0),ASSUMPTIONS!$D$26/12*(ASSUMPTIONS!$B$33),0),0) -> 9895.8333 | G9: =IFERROR(IF(AND(6>=ASSUMPTIONS!$C$26,ASSUMPTIONS!$C$26>0),ASSUMPTIONS!$D$26/12*(ASSUMPTIONS!$B$33),0),0) -> 9895.8333 | H9: =IFERROR(IF(AND(7>=ASSUMPTIONS!$C$26,ASSUMPTIONS!$C$26>0),ASSUMPTIONS!$D$26/12*(ASSUMPTIONS!$B$33),0),0) -> 9895.8333 | I9: =IFERROR(IF(AND(8>=ASSUMPTIONS!$C$26,ASSUMPTIONS!$C$26>0),ASSUMPTIONS!$D$26/12*(ASSUMPTIONS!$B$33),0),0) -> 9895.8333 | J9: =IFERROR(IF(AND(9>=ASSUMPTIONS!$C$26,ASSUMPTIONS!$C$26>0),ASSUMPTIONS!$D$26/12*(ASSUMPTIONS!$B$33),0),0) -> 9895.8333 | K9: =IFERROR(IF(AND(10>=ASSUMPTIONS!$C$26,ASSUMPTIONS!$C$26>0),ASSUMPTIONS!$D$26/12*(ASSUMPTIONS!$B$33),0),0) -> 9895.8333 | L9: =IFERROR(IF(AND(11>=ASSUMPTIONS!$C$26,ASSUMPTIONS!$C$26>0),ASSUMPTIONS!$D$26/12*(ASSUMPTIONS!$B$33),0),0) -> 9895.8333 | M9: =IFERROR(IF(AND(12>=ASSUMPTIONS!$C$26,ASSUMPTIONS!$C$26>0),ASSUMPTIONS!$D$26/12*(ASSUMPTIONS!$B$33),0),0) -> 9895.8333 | N9: =IFERROR(IF(AND(13>=ASSUMPTIONS!$C$26,ASSUMPTIONS!$C$26>0),ASSUMPTIONS!$D$26/12*(ASSUMPTIONS!$B$33),0),0) -> 9895.8333 | O9: =IFERROR(IF(AND(14>=ASSUMPTIONS!$C$26,ASSUMPTIONS!$C$26>0),ASSUMPTIONS!$D$26/12*(ASSUMPTIONS!$B$33),0),0) -> 9895.8333 | P9: =IFERROR(IF(AND(15>=ASSUMPTIONS!$C$26,ASSUMPTIONS!$C$26>0),ASSUMPTIONS!$D$26/12*(ASSUMPTIONS!$B$33),0),0) -> 9895.8333 | Q9: =IFERROR(IF(AND(16>=ASSUMPTIONS!$C$26,ASSUMPTIONS!$C$26>0),ASSUMPTIONS!$D$26/12*(ASSUMPTIONS!$B$33),0),0) -> 9895.8333 | R9: =IFERROR(IF(AND(17>=ASSUMPTIONS!$C$26,ASSUMPTIONS!$C$26>0),ASSUMPTIONS!$D$26/12*(ASSUMPTIONS!$B$33),0),0) -> 9895.8333 | S9: =IFERROR(IF(AND(18>=ASSUMPTIONS!$C$26,ASSUMPTIONS!$C$26>0),ASSUMPTIONS!$D$26/12*(ASSUMPTIONS!$B$33),0),0) -> 9895.8333
A10: =IFERROR(ASSUMPTIONS!B27,"(empty)") -> Engineer #2 | B10: =IFERROR(IF(AND(1>=ASSUMPTIONS!$C$27,ASSUMPTIONS!$C$27>0),ASSUMPTIONS!$D$27/12*(ASSUMPTIONS!$B$33),0),0) -> 0 | C10: =IFERROR(IF(AND(2>=ASSUMPTIONS!$C$27,ASSUMPTIONS!$C$27>0),ASSUMPTIONS!$D$27/12*(ASSUMPTIONS!$B$33),0),0) -> 0 | D10: =IFERROR(IF(AND(3>=ASSUMPTIONS!$C$27,ASSUMPTIONS!$C$27>0),ASSUMPTIONS!$D$27/12*(ASSUMPTIONS!$B$33),0),0) -> 0 | E10: =IFERROR(IF(AND(4>=ASSUMPTIONS!$C$27,ASSUMPTIONS!$C$27>0),ASSUMPTIONS!$D$27/12*(ASSUMPTIONS!$B$33),0),0) -> 0 | F10: =IFERROR(IF(AND(5>=ASSUMPTIONS!$C$27,ASSUMPTIONS!$C$27>0),ASSUMPTIONS!$D$27/12*(ASSUMPTIONS!$B$33),0),0) -> 0 | G10: =IFERROR(IF(AND(6>=ASSUMPTIONS!$C$27,ASSUMPTIONS!$C$27>0),ASSUMPTIONS!$D$27/12*(ASSUMPTIONS!$B$33),0),0) -> 9895.8333 | H10: =IFERROR(IF(AND(7>=ASSUMPTIONS!$C$27,ASSUMPTIONS!$C$27>0),ASSUMPTIONS!$D$27/12*(ASSUMPTIONS!$B$33),0),0) -> 9895.8333 | I10: =IFERROR(IF(AND(8>=ASSUMPTIONS!$C$27,ASSUMPTIONS!$C$27>0),ASSUMPTIONS!$D$27/12*(ASSUMPTIONS!$B$33),0),0) -> 9895.8333 | J10: =IFERROR(IF(AND(9>=ASSUMPTIONS!$C$27,ASSUMPTIONS!$C$27>0),ASSUMPTIONS!$D$27/12*(ASSUMPTIONS!$B$33),0),0) -> 9895.8333 | K10: =IFERROR(IF(AND(10>=ASSUMPTIONS!$C$27,ASSUMPTIONS!$C$27>0),ASSUMPTIONS!$D$27/12*(ASSUMPTIONS!$B$33),0),0) -> 9895.8333 | L10: =IFERROR(IF(AND(11>=ASSUMPTIONS!$C$27,ASSUMPTIONS!$C$27>0),ASSUMPTIONS!$D$27/12*(ASSUMPTIONS!$B$33),0),0) -> 9895.8333 | M10: =IFERROR(IF(AND(12>=ASSUMPTIONS!$C$27,ASSUMPTIONS!$C$27>0),ASSUMPTIONS!$D$27/12*(ASSUMPTIONS!$B$33),0),0) -> 9895.8333 | N10: =IFERROR(IF(AND(13>=ASSUMPTIONS!$C$27,ASSUMPTIONS!$C$27>0),ASSUMPTIONS!$D$27/12*(ASSUMPTIONS!$B$33),0),0) -> 9895.8333 | O10: =IFERROR(IF(AND(14>=ASSUMPTIONS!$C$27,ASSUMPTIONS!$C$27>0),ASSUMPTIONS!$D$27/12*(ASSUMPTIONS!$B$33),0),0) -> 9895.8333 | P10: =IFERROR(IF(AND(15>=ASSUMPTIONS!$C$27,ASSUMPTIONS!$C$27>0),ASSUMPTIONS!$D$27/12*(ASSUMPTIONS!$B$33),0),0) -> 9895.8333 | Q10: =IFERROR(IF(AND(16>=ASSUMPTIONS!$C$27,ASSUMPTIONS!$C$27>0),ASSUMPTIONS!$D$27/12*(ASSUMPTIONS!$B$33),0),0) -> 9895.8333 | R10: =IFERROR(IF(AND(17>=ASSUMPTIONS!$C$27,ASSUMPTIONS!$C$27>0),ASSUMPTIONS!$D$27/12*(ASSUMPTIONS!$B$33),0),0) -> 9895.8333 | S10: =IFERROR(IF(AND(18>=ASSUMPTIONS!$C$27,ASSUMPTIONS!$C$27>0),ASSUMPTIONS!$D$27/12*(ASSUMPTIONS!$B$33),0),0) -> 9895.8333
A11: =IFERROR(ASSUMPTIONS!B28,"(empty)") -> Designer | B11: =IFERROR(IF(AND(1>=ASSUMPTIONS!$C$28,ASSUMPTIONS!$C$28>0),ASSUMPTIONS!$D$28/12*(ASSUMPTIONS!$B$33),0),0) -> 0 | C11: =IFERROR(IF(AND(2>=ASSUMPTIONS!$C$28,ASSUMPTIONS!$C$28>0),ASSUMPTIONS!$D$28/12*(ASSUMPTIONS!$B$33),0),0) -> 0 | D11: =IFERROR(IF(AND(3>=ASSUMPTIONS!$C$28,ASSUMPTIONS!$C$28>0),ASSUMPTIONS!$D$28/12*(ASSUMPTIONS!$B$33),0),0) -> 0 | E11: =IFERROR(IF(AND(4>=ASSUMPTIONS!$C$28,ASSUMPTIONS!$C$28>0),ASSUMPTIONS!$D$28/12*(ASSUMPTIONS!$B$33),0),0) -> 7812.5 | F11: =IFERROR(IF(AND(5>=ASSUMPTIONS!$C$28,ASSUMPTIONS!$C$28>0),ASSUMPTIONS!$D$28/12*(ASSUMPTIONS!$B$33),0),0) -> 7812.5 | G11: =IFERROR(IF(AND(6>=ASSUMPTIONS!$C$28,ASSUMPTIONS!$C$28>0),ASSUMPTIONS!$D$28/12*(ASSUMPTIONS!$B$33),0),0) -> 7812.5 | H11: =IFERROR(IF(AND(7>=ASSUMPTIONS!$C$28,ASSUMPTIONS!$C$28>0),ASSUMPTIONS!$D$28/12*(ASSUMPTIONS!$B$33),0),0) -> 7812.5 | I11: =IFERROR(IF(AND(8>=ASSUMPTIONS!$C$28,ASSUMPTIONS!$C$28>0),ASSUMPTIONS!$D$28/12*(ASSUMPTIONS!$B$33),0),0) -> 7812.5 | J11: =IFERROR(IF(AND(9>=ASSUMPTIONS!$C$28,ASSUMPTIONS!$C$28>0),ASSUMPTIONS!$D$28/12*(ASSUMPTIONS!$B$33),0),0) -> 7812.5 | K11: =IFERROR(IF(AND(10>=ASSUMPTIONS!$C$28,ASSUMPTIONS!$C$28>0),ASSUMPTIONS!$D$28/12*(ASSUMPTIONS!$B$33),0),0) -> 7812.5 | L11: =IFERROR(IF(AND(11>=ASSUMPTIONS!$C$28,ASSUMPTIONS!$C$28>0),ASSUMPTIONS!$D$28/12*(ASSUMPTIONS!$B$33),0),0) -> 7812.5 | M11: =IFERROR(IF(AND(12>=ASSUMPTIONS!$C$28,ASSUMPTIONS!$C$28>0),ASSUMPTIONS!$D$28/12*(ASSUMPTIONS!$B$33),0),0) -> 7812.5 | N11: =IFERROR(IF(AND(13>=ASSUMPTIONS!$C$28,ASSUMPTIONS!$C$28>0),ASSUMPTIONS!$D$28/12*(ASSUMPTIONS!$B$33),0),0) -> 7812.5 | O11: =IFERROR(IF(AND(14>=ASSUMPTIONS!$C$28,ASSUMPTIONS!$C$28>0),ASSUMPTIONS!$D$28/12*(ASSUMPTIONS!$B$33),0),0) -> 7812.5 | P11: =IFERROR(IF(AND(15>=ASSUMPTIONS!$C$28,ASSUMPTIONS!$C$28>0),ASSUMPTIONS!$D$28/12*(ASSUMPTIONS!$B$33),0),0) -> 7812.5 | Q11: =IFERROR(IF(AND(16>=ASSUMPTIONS!$C$28,ASSUMPTIONS!$C$28>0),ASSUMPTIONS!$D$28/12*(ASSUMPTIONS!$B$33),0),0) -> 7812.5 | R11: =IFERROR(IF(AND(17>=ASSUMPTIONS!$C$28,ASSUMPTIONS!$C$28>0),ASSUMPTIONS!$D$28/12*(ASSUMPTIONS!$B$33),0),0) -> 7812.5 | S11: =IFERROR(IF(AND(18>=ASSUMPTIONS!$C$28,ASSUMPTIONS!$C$28>0),ASSUMPTIONS!$D$28/12*(ASSUMPTIONS!$B$33),0),0) -> 7812.5
A12: =IFERROR(ASSUMPTIONS!B29,"(empty)") -> Sales / Growth | B12: =IFERROR(IF(AND(1>=ASSUMPTIONS!$C$29,ASSUMPTIONS!$C$29>0),ASSUMPTIONS!$D$29/12*(ASSUMPTIONS!$B$33),0),0) -> 0 | C12: =IFERROR(IF(AND(2>=ASSUMPTIONS!$C$29,ASSUMPTIONS!$C$29>0),ASSUMPTIONS!$D$29/12*(ASSUMPTIONS!$B$33),0),0) -> 0 | D12: =IFERROR(IF(AND(3>=ASSUMPTIONS!$C$29,ASSUMPTIONS!$C$29>0),ASSUMPTIONS!$D$29/12*(ASSUMPTIONS!$B$33),0),0) -> 0 | E12: =IFERROR(IF(AND(4>=ASSUMPTIONS!$C$29,ASSUMPTIONS!$C$29>0),ASSUMPTIONS!$D$29/12*(ASSUMPTIONS!$B$33),0),0) -> 0 | F12: =IFERROR(IF(AND(5>=ASSUMPTIONS!$C$29,ASSUMPTIONS!$C$29>0),ASSUMPTIONS!$D$29/12*(ASSUMPTIONS!$B$33),0),0) -> 0 | G12: =IFERROR(IF(AND(6>=ASSUMPTIONS!$C$29,ASSUMPTIONS!$C$29>0),ASSUMPTIONS!$D$29/12*(ASSUMPTIONS!$B$33),0),0) -> 7291.6667 | H12: =IFERROR(IF(AND(7>=ASSUMPTIONS!$C$29,ASSUMPTIONS!$C$29>0),ASSUMPTIONS!$D$29/12*(ASSUMPTIONS!$B$33),0),0) -> 7291.6667 | I12: =IFERROR(IF(AND(8>=ASSUMPTIONS!$C$29,ASSUMPTIONS!$C$29>0),ASSUMPTIONS!$D$29/12*(ASSUMPTIONS!$B$33),0),0) -> 7291.6667 | J12: =IFERROR(IF(AND(9>=ASSUMPTIONS!$C$29,ASSUMPTIONS!$C$29>0),ASSUMPTIONS!$D$29/12*(ASSUMPTIONS!$B$33),0),0) -> 7291.6667 | K12: =IFERROR(IF(AND(10>=ASSUMPTIONS!$C$29,ASSUMPTIONS!$C$29>0),ASSUMPTIONS!$D$29/12*(ASSUMPTIONS!$B$33),0),0) -> 7291.6667 | L12: =IFERROR(IF(AND(11>=ASSUMPTIONS!$C$29,ASSUMPTIONS!$C$29>0),ASSUMPTIONS!$D$29/12*(ASSUMPTIONS!$B$33),0),0) -> 7291.6667 | M12: =IFERROR(IF(AND(12>=ASSUMPTIONS!$C$29,ASSUMPTIONS!$C$29>0),ASSUMPTIONS!$D$29/12*(ASSUMPTIONS!$B$33),0),0) -> 7291.6667 | N12: =IFERROR(IF(AND(13>=ASSUMPTIONS!$C$29,ASSUMPTIONS!$C$29>0),ASSUMPTIONS!$D$29/12*(ASSUMPTIONS!$B$33),0),0) -> 7291.6667 | O12: =IFERROR(IF(AND(14>=ASSUMPTIONS!$C$29,ASSUMPTIONS!$C$29>0),ASSUMPTIONS!$D$29/12*(ASSUMPTIONS!$B$33),0),0) -> 7291.6667 | P12: =IFERROR(IF(AND(15>=ASSUMPTIONS!$C$29,ASSUMPTIONS!$C$29>0),ASSUMPTIONS!$D$29/12*(ASSUMPTIONS!$B$33),0),0) -> 7291.6667 | Q12: =IFERROR(IF(AND(16>=ASSUMPTIONS!$C$29,ASSUMPTIONS!$C$29>0),ASSUMPTIONS!$D$29/12*(ASSUMPTIONS!$B$33),0),0) -> 7291.6667 | R12: =IFERROR(IF(AND(17>=ASSUMPTIONS!$C$29,ASSUMPTIONS!$C$29>0),ASSUMPTIONS!$D$29/12*(ASSUMPTIONS!$B$33),0),0) -> 7291.6667 | S12: =IFERROR(IF(AND(18>=ASSUMPTIONS!$C$29,ASSUMPTIONS!$C$29>0),ASSUMPTIONS!$D$29/12*(ASSUMPTIONS!$B$33),0),0) -> 7291.6667
A13: =IFERROR(ASSUMPTIONS!B30,"(empty)") -> 0 | B13: =IFERROR(IF(AND(1>=ASSUMPTIONS!$C$30,ASSUMPTIONS!$C$30>0),ASSUMPTIONS!$D$30/12*(ASSUMPTIONS!$B$33),0),0) -> 0 | C13: =IFERROR(IF(AND(2>=ASSUMPTIONS!$C$30,ASSUMPTIONS!$C$30>0),ASSUMPTIONS!$D$30/12*(ASSUMPTIONS!$B$33),0),0) -> 0 | D13: =IFERROR(IF(AND(3>=ASSUMPTIONS!$C$30,ASSUMPTIONS!$C$30>0),ASSUMPTIONS!$D$30/12*(ASSUMPTIONS!$B$33),0),0) -> 0 | E13: =IFERROR(IF(AND(4>=ASSUMPTIONS!$C$30,ASSUMPTIONS!$C$30>0),ASSUMPTIONS!$D$30/12*(ASSUMPTIONS!$B$33),0),0) -> 0 | F13: =IFERROR(IF(AND(5>=ASSUMPTIONS!$C$30,ASSUMPTIONS!$C$30>0),ASSUMPTIONS!$D$30/12*(ASSUMPTIONS!$B$33),0),0) -> 0 | G13: =IFERROR(IF(AND(6>=ASSUMPTIONS!$C$30,ASSUMPTIONS!$C$30>0),ASSUMPTIONS!$D$30/12*(ASSUMPTIONS!$B$33),0),0) -> 0 | H13: =IFERROR(IF(AND(7>=ASSUMPTIONS!$C$30,ASSUMPTIONS!$C$30>0),ASSUMPTIONS!$D$30/12*(ASSUMPTIONS!$B$33),0),0) -> 0 | I13: =IFERROR(IF(AND(8>=ASSUMPTIONS!$C$30,ASSUMPTIONS!$C$30>0),ASSUMPTIONS!$D$30/12*(ASSUMPTIONS!$B$33),0),0) -> 0 | J13: =IFERROR(IF(AND(9>=ASSUMPTIONS!$C$30,ASSUMPTIONS!$C$30>0),ASSUMPTIONS!$D$30/12*(ASSUMPTIONS!$B$33),0),0) -> 0 | K13: =IFERROR(IF(AND(10>=ASSUMPTIONS!$C$30,ASSUMPTIONS!$C$30>0),ASSUMPTIONS!$D$30/12*(ASSUMPTIONS!$B$33),0),0) -> 0 | L13: =IFERROR(IF(AND(11>=ASSUMPTIONS!$C$30,ASSUMPTIONS!$C$30>0),ASSUMPTIONS!$D$30/12*(ASSUMPTIONS!$B$33),0),0) -> 0 | M13: =IFERROR(IF(AND(12>=ASSUMPTIONS!$C$30,ASSUMPTIONS!$C$30>0),ASSUMPTIONS!$D$30/12*(ASSUMPTIONS!$B$33),0),0) -> 0 | N13: =IFERROR(IF(AND(13>=ASSUMPTIONS!$C$30,ASSUMPTIONS!$C$30>0),ASSUMPTIONS!$D$30/12*(ASSUMPTIONS!$B$33),0),0) -> 0 | O13: =IFERROR(IF(AND(14>=ASSUMPTIONS!$C$30,ASSUMPTIONS!$C$30>0),ASSUMPTIONS!$D$30/12*(ASSUMPTIONS!$B$33),0),0) -> 0 | P13: =IFERROR(IF(AND(15>=ASSUMPTIONS!$C$30,ASSUMPTIONS!$C$30>0),ASSUMPTIONS!$D$30/12*(ASSUMPTIONS!$B$33),0),0) -> 0 | Q13: =IFERROR(IF(AND(16>=ASSUMPTIONS!$C$30,ASSUMPTIONS!$C$30>0),ASSUMPTIONS!$D$30/12*(ASSUMPTIONS!$B$33),0),0) -> 0 | R13: =IFERROR(IF(AND(17>=ASSUMPTIONS!$C$30,ASSUMPTIONS!$C$30>0),ASSUMPTIONS!$D$30/12*(ASSUMPTIONS!$B$33),0),0) -> 0 | S13: =IFERROR(IF(AND(18>=ASSUMPTIONS!$C$30,ASSUMPTIONS!$C$30>0),ASSUMPTIONS!$D$30/12*(ASSUMPTIONS!$B$33),0),0) -> 0
A14: =IFERROR(ASSUMPTIONS!B31,"(empty)") -> 0 | B14: =IFERROR(IF(AND(1>=ASSUMPTIONS!$C$31,ASSUMPTIONS!$C$31>0),ASSUMPTIONS!$D$31/12*(ASSUMPTIONS!$B$33),0),0) -> 0 | C14: =IFERROR(IF(AND(2>=ASSUMPTIONS!$C$31,ASSUMPTIONS!$C$31>0),ASSUMPTIONS!$D$31/12*(ASSUMPTIONS!$B$33),0),0) -> 0 | D14: =IFERROR(IF(AND(3>=ASSUMPTIONS!$C$31,ASSUMPTIONS!$C$31>0),ASSUMPTIONS!$D$31/12*(ASSUMPTIONS!$B$33),0),0) -> 0 | E14: =IFERROR(IF(AND(4>=ASSUMPTIONS!$C$31,ASSUMPTIONS!$C$31>0),ASSUMPTIONS!$D$31/12*(ASSUMPTIONS!$B$33),0),0) -> 0 | F14: =IFERROR(IF(AND(5>=ASSUMPTIONS!$C$31,ASSUMPTIONS!$C$31>0),ASSUMPTIONS!$D$31/12*(ASSUMPTIONS!$B$33),0),0) -> 0 | G14: =IFERROR(IF(AND(6>=ASSUMPTIONS!$C$31,ASSUMPTIONS!$C$31>0),ASSUMPTIONS!$D$31/12*(ASSUMPTIONS!$B$33),0),0) -> 0 | H14: =IFERROR(IF(AND(7>=ASSUMPTIONS!$C$31,ASSUMPTIONS!$C$31>0),ASSUMPTIONS!$D$31/12*(ASSUMPTIONS!$B$33),0),0) -> 0 | I14: =IFERROR(IF(AND(8>=ASSUMPTIONS!$C$31,ASSUMPTIONS!$C$31>0),ASSUMPTIONS!$D$31/12*(ASSUMPTIONS!$B$33),0),0) -> 0 | J14: =IFERROR(IF(AND(9>=ASSUMPTIONS!$C$31,ASSUMPTIONS!$C$31>0),ASSUMPTIONS!$D$31/12*(ASSUMPTIONS!$B$33),0),0) -> 0 | K14: =IFERROR(IF(AND(10>=ASSUMPTIONS!$C$31,ASSUMPTIONS!$C$31>0),ASSUMPTIONS!$D$31/12*(ASSUMPTIONS!$B$33),0),0) -> 0 | L14: =IFERROR(IF(AND(11>=ASSUMPTIONS!$C$31,ASSUMPTIONS!$C$31>0),ASSUMPTIONS!$D$31/12*(ASSUMPTIONS!$B$33),0),0) -> 0 | M14: =IFERROR(IF(AND(12>=ASSUMPTIONS!$C$31,ASSUMPTIONS!$C$31>0),ASSUMPTIONS!$D$31/12*(ASSUMPTIONS!$B$33),0),0) -> 0 | N14: =IFERROR(IF(AND(13>=ASSUMPTIONS!$C$31,ASSUMPTIONS!$C$31>0),ASSUMPTIONS!$D$31/12*(ASSUMPTIONS!$B$33),0),0) -> 0 | O14: =IFERROR(IF(AND(14>=ASSUMPTIONS!$C$31,ASSUMPTIONS!$C$31>0),ASSUMPTIONS!$D$31/12*(ASSUMPTIONS!$B$33),0),0) -> 0 | P14: =IFERROR(IF(AND(15>=ASSUMPTIONS!$C$31,ASSUMPTIONS!$C$31>0),ASSUMPTIONS!$D$31/12*(ASSUMPTIONS!$B$33),0),0) -> 0 | Q14: =IFERROR(IF(AND(16>=ASSUMPTIONS!$C$31,ASSUMPTIONS!$C$31>0),ASSUMPTIONS!$D$31/12*(ASSUMPTIONS!$B$33),0),0) -> 0 | R14: =IFERROR(IF(AND(17>=ASSUMPTIONS!$C$31,ASSUMPTIONS!$C$31>0),ASSUMPTIONS!$D$31/12*(ASSUMPTIONS!$B$33),0),0) -> 0 | S14: =IFERROR(IF(AND(18>=ASSUMPTIONS!$C$31,ASSUMPTIONS!$C$31>0),ASSUMPTIONS!$D$31/12*(ASSUMPTIONS!$B$33),0),0) -> 0
A16: TOTAL HEADCOUNT COST ($) | B16: =SUM(B7:B14) -> 12500 | C16: =SUM(C7:C14) -> 12500 | D16: =SUM(D7:D14) -> 22395.833 | E16: =SUM(E7:E14) -> 30208.333 | F16: =SUM(F7:F14) -> 30208.333 | G16: =SUM(G7:G14) -> 47395.833 | H16: =SUM(H7:H14) -> 47395.833 | I16: =SUM(I7:I14) -> 47395.833 | ... S16: =SUM(S7:S14) -> 47395.833
A17: Headcount (#) | B17: =COUNTIF(B7:B14,">"&0) -> 2 | C17: =COUNTIF(C7:C14,">"&0) -> 2 | D17: =COUNTIF(D7:D14,">"&0) -> 3 | E17: =COUNTIF(E7:E14,">"&0) -> 4 | F17: =COUNTIF(F7:F14,">"&0) -> 4 | G17: =COUNTIF(G7:G14,">"&0) -> 6 | H17: =COUNTIF(H7:H14,">"&0) -> 6 | I17: =COUNTIF(I7:I14,">"&0) -> 6 | ... S17: =COUNTIF(S7:S14,">"&0) -> 6

Sheet P&L
A1: PROFIT & LOSS STATEMENT
A2: All figures auto-populated from REVENUE and HEADCOUNT sheets. Green text = cross-sheet links. Do not edit.
B4: YEAR 1 | N4: YEAR 2
B5: Jan | C5: Feb | D5: Mar | E5: Apr | F5: May | G5: Jun | H5: Jul | I5: Aug | J5: Sep | K5: Oct | L5: Nov | M5: Dec | N5: Jan | O5: Feb | P5: Mar | Q5: Apr | R5: May | S5: Jun | T5: Y1 Total
A6: REVENUE
A8: Total Revenue ($) | B8: =IFERROR(REVENUE!B13,0) -> 2376 | C8: =IFERROR(REVENUE!C13,0) -> 3861 | D8: =IFERROR(REVENUE!D13,0) -> 5346 | E8: =IFERROR(REVENUE!E13,0) -> 6831 | F8: =IFERROR(REVENUE!F13,0) -> 8415 | G8: =IFERROR(REVENUE!G13,0) -> 10098 | H8: =IFERROR(REVENUE!H13,0) -> 11880 | I8: =IFERROR(REVENUE!I13,0) -> 13761 | ... S8: =IFERROR(REVENUE!S13,0) -> 39699
A10: COST OF GOODS SOLD
A11: Hosting Costs ($) | B11: =IFERROR(REVENUE!B9*ASSUMPTIONS!$B$18,0) -> 120 | C11: =IFERROR(REVENUE!C9*ASSUMPTIONS!$B$18,0) -> 195 | D11: =IFERROR(REVENUE!D9*ASSUMPTIONS!$B$18,0) -> 270 | E11: =IFERROR(REVENUE!E9*ASSUMPTIONS!$B$18,0) -> 345 | F11: =IFERROR(REVENUE!F9*ASSUMPTIONS!$B$18,0) -> 425 | G11: =IFERROR(REVENUE!G9*ASSUMPTIONS!$B$18,0) -> 510 | H11: =IFERROR(REVENUE!H9*ASSUMPTIONS!$B$18,0) -> 600 | I11: =IFERROR(REVENUE!I9*ASSUMPTIONS!$B$18,0) -> 695 | ... S11: =IFERROR(REVENUE!S9*ASSUMPTIONS!$B$18,0) -> 2005
A12: Payment Processing ($) | B12: =IFERROR(B8*ASSUMPTIONS!$B$19,0) -> 68.904 | C12: =IFERROR(C8*ASSUMPTIONS!$B$19,0) -> 111.969 | D12: =IFERROR(D8*ASSUMPTIONS!$B$19,0) -> 155.034 | E12: =IFERROR(E8*ASSUMPTIONS!$B$19,0) -> 198.099 | F12: =IFERROR(F8*ASSUMPTIONS!$B$19,0) -> 244.035 | G12: =IFERROR(G8*ASSUMPTIONS!$B$19,0) -> 292.842 | H12: =IFERROR(H8*ASSUMPTIONS!$B$19,0) -> 344.52 | I12: =IFERROR(I8*ASSUMPTIONS!$B$19,0) -> 399.069 | ... S12: =IFERROR(S8*ASSUMPTIONS!$B$19,0) -> 1151.271
A13: Support Costs ($) | B13: =IFERROR(REVENUE!B9*ASSUMPTIONS!$B$20,0) -> 72 | C13: =IFERROR(REVENUE!C9*ASSUMPTIONS!$B$20,0) -> 117 | D13: =IFERROR(REVENUE!D9*ASSUMPTIONS!$B$20,0) -> 162 | E13: =IFERROR(REVENUE!E9*ASSUMPTIONS!$B$20,0) -> 207 | F13: =IFERROR(REVENUE!F9*ASSUMPTIONS!$B$20,0) -> 255 | G13: =IFERROR(REVENUE!G9*ASSUMPTIONS!$B$20,0) -> 306 | H13: =IFERROR(REVENUE!H9*ASSUMPTIONS!$B$20,0) -> 360 | I13: =IFERROR(REVENUE!I9*ASSUMPTIONS!$B$20,0) -> 417 | ... S13: =IFERROR(REVENUE!S9*ASSUMPTIONS!$B$20,0) -> 1203
A14: TOTAL COGS ($) | B14: =SUM(B11:B13) -> 260.904 | C14: =SUM(C11:C13) -> 423.969 | D14: =SUM(D11:D13) -> 587.034 | E14: =SUM(E11:E13) -> 750.099 | F14: =SUM(F11:F13) -> 924.035 | G14: =SUM(G11:G13) -> 1108.842 | H14: =SUM(H11:H13) -> 1304.52 | I14: =SUM(I11:I13) -> 1511.069 | ... S14: =SUM(S11:S13) -> 4359.271
A15: GROSS PROFIT ($) | B15: =B8-B14 -> 2115.096 | C15: =C8-C14 -> 3437.031 | D15: =D8-D14 -> 4758.966 | E15: =E8-E14 -> 6080.901 | F15: =F8-F14 -> 7490.965 | G15: =G8-G14 -> 8989.158 | H15: =H8-H14 -> 10575.48 | I15: =I8-I14 -> 12249.931 | ... S15: =S8-S14 -> 35339.729
A16: Gross Margin % | B16: =IFERROR(B15/B8,0) -> 0.89019192 | C16: =IFERROR(C15/C8,0) -> 0.89019192 | D16: =IFERROR(D15/D8,0) -> 0.89019192 | E16: =IFERROR(E15/E8,0) -> 0.89019192 | F16: =IFERROR(F15/F8,0) -> 0.89019192 | G16: =IFERROR(G15/G8,0) -> 0.89019192 | H16: =IFERROR(H15/H8,0) -> 0.89019192 | I16: =IFERROR(I15/I8,0) -> 0.89019192 | ... S16: =IFERROR(S15/S8,0) -> 0.89019192
A18: OPERATING EXPENSES
A19: Total Headcount ($) | B19: =IFERROR(HEADCOUNT!B16,0) -> 12500 | C19: =IFERROR(HEADCOUNT!C16,0) -> 12500 | D19: =IFERROR(HEADCOUNT!D16,0) -> 22395.833 | E19: =IFERROR(HEADCOUNT!E16,0) -> 30208.333 | F19: =IFERROR(HEADCOUNT!F16,0) -> 30208.333 | G19: =IFERROR(HEADCOUNT!G16,0) -> 47395.833 | H19: =IFERROR(HEADCOUNT!H16,0) -> 47395.833 | I19: =IFERROR(HEADCOUNT!I16,0) -> 47395.833 | ... S19: =IFERROR(HEADCOUNT!S16,0) -> 47395.833
A20: Marketing ($) | B20: =IFERROR(ASSUMPTIONS!$B$36,0) -> 2000 | C20: =IFERROR(ROUND(B20*(1+ASSUMPTIONS!$B$37),0),0) -> 2100 | D20: =IFERROR(ROUND(C20*(1+ASSUMPTIONS!$B$37),0),0) -> 2205 | E20: =IFERROR(ROUND(D20*(1+ASSUMPTIONS!$B$37),0),0) -> 2315 | F20: =IFERROR(ROUND(E20*(1+ASSUMPTIONS!$B$37),0),0) -> 2431 | G20: =IFERROR(ROUND(F20*(1+ASSUMPTIONS!$B$37),0),0) -> 2553 | H20: =IFERROR(ROUND(G20*(1+ASSUMPTIONS!$B$37),0),0) -> 2681 | I20: =IFERROR(ROUND(H20*(1+ASSUMPTIONS!$B$37),0),0) -> 2815 | J20: =IFERROR(ROUND(I20*(1+ASSUMPTIONS!$B$37),0),0) -> 2956 | ... S20: =IFERROR(ROUND(R20*(1+ASSUMPTIONS!$B$37),0),0) -> 4586
A21: Software & Tools ($) | B21: =IFERROR(ASSUMPTIONS!$B$38,0) -> 800 | C21: =IFERROR(ASSUMPTIONS!$B$38,0) -> 800 | D21: =IFERROR(ASSUMPTIONS!$B$38,0) -> 800 | E21: =IFERROR(ASSUMPTIONS!$B$38,0) -> 800 | F21: =IFERROR(ASSUMPTIONS!$B$38,0) -> 800 | G21: =IFERROR(ASSUMPTIONS!$B$38,0) -> 800 | H21: =IFERROR(ASSUMPTIONS!$B$38,0) -> 800 | I21: =IFERROR(ASSUMPTIONS!$B$38,0) -> 800 | ... S21: =IFERROR(ASSUMPTIONS!$B$38,0) -> 800
A22: Office / Rent ($) | B22: =IFERROR(ASSUMPTIONS!$B$39,0) -> 0 | C22: =IFERROR(ASSUMPTIONS!$B$39,0) -> 0 | D22: =IFERROR(ASSUMPTIONS!$B$39,0) -> 0 | E22: =IFERROR(ASSUMPTIONS!$B$39,0) -> 0 | F22: =IFERROR(ASSUMPTIONS!$B$39,0) -> 0 | G22: =IFERROR(ASSUMPTIONS!$B$39,0) -> 0 | H22: =IFERROR(ASSUMPTIONS!$B$39,0) -> 0 | I22: =IFERROR(ASSUMPTIONS!$B$39,0) -> 0 | ... S22: =IFERROR(ASSUMPTIONS!$B$39,0) -> 0
A23: Legal & Professional ($) | B23: =IFERROR(ASSUMPTIONS!$B$40,0) -> 500 | C23: =IFERROR(ASSUMPTIONS!$B$40,0) -> 500 | D23: =IFERROR(ASSUMPTIONS!$B$40,0) -> 500 | E23: =IFERROR(ASSUMPTIONS!$B$40,0) -> 500 | F23: =IFERROR(ASSUMPTIONS!$B$40,0) -> 500 | G23: =IFERROR(ASSUMPTIONS!$B$40,0) -> 500 | H23: =IFERROR(ASSUMPTIONS!$B$40,0) -> 500 | I23: =IFERROR(ASSUMPTIONS!$B$40,0) -> 500 | ... S23: =IFERROR(ASSUMPTIONS!$B$40,0) -> 500
A24: Other OpEx ($) | B24: =IFERROR(ASSUMPTIONS!$B$41,0) -> 300 | C24: =IFERROR(ASSUMPTIONS!$B$41,0) -> 300 | D24: =IFERROR(ASSUMPTIONS!$B$41,0) -> 300 | E24: =IFERROR(ASSUMPTIONS!$B$41,0) -> 300 | F24: =IFERROR(ASSUMPTIONS!$B$41,0) -> 300 | G24: =IFERROR(ASSUMPTIONS!$B$41,0) -> 300 | H24: =IFERROR(ASSUMPTIONS!$B$41,0) -> 300 | I24: =IFERROR(ASSUMPTIONS!$B$41,0) -> 300 | ... S24: =IFERROR(ASSUMPTIONS!$B$41,0) -> 300
A25: TOTAL OPERATING EXPENSES ($) | B25: =SUM(B19:B24) -> 16100 | C25: =SUM(C19:C24) -> 16200 | D25: =SUM(D19:D24) -> 26200.833 | E25: =SUM(E19:E24) -> 34123.333 | F25: =SUM(F19:F24) -> 34239.333 | G25: =SUM(G19:G24) -> 51548.833 | H25: =SUM(H19:H24) -> 51676.833 | I25: =SUM(I19:I24) -> 51810.833 | ... S25: =SUM(S19:S24) -> 53581.833
A27: EBITDA ($) | B27: =B15-B25 -> -13984.904 | C27: =C15-C25 -> -12762.969 | D27: =D15-D25 -> -21441.867 | E27: =E15-E25 -> -28042.432 | F27: =F15-F25 -> -26748.368 | G27: =G15-G25 -> -42559.675 | H27: =H15-H25 -> -41101.353 | I27: =I15-I25 -> -39560.902 | ... S27: =S15-S25 -> -18242.104
A28: EBITDA Margin % | B28: =IFERROR(B27/B8,0) -> -5.8859024 | C28: =IFERROR(C27/C8,0) -> -3.3056123 | D28: =IFERROR(D27/D8,0) -> -4.0108244 | E28: =IFERROR(E27/E8,0) -> -4.1051724 | F28: =IFERROR(F27/F8,0) -> -3.1786534 | G28: =IFERROR(G27/G8,0) -> -4.2146638 | H28: =IFERROR(H27/H8,0) -> -3.4597099 | I28: =IFERROR(I27/I8,0) -> -2.8748566 | ... S28: =IFERROR(S27/S8,0) -> -0.45951042

Sheet CASH FLOW
A1: CASH FLOW STATEMENT
A2: Monthly cash in/out. Shows runway remaining. Yellow = your inputs (CAPEX). Everything else auto-calculated.
B4: YEAR 1 | N4: YEAR 2
B5: Jan | C5: Feb | D5: Mar | E5: Apr | F5: May | G5: Jun | H5: Jul | I5: Aug | J5: Sep | K5: Oct | L5: Nov | M5: Dec | N5: Jan | O5: Feb | P5: Mar | Q5: Apr | R5: May | S5: Jun | T5: Y1 Total
A6: OPENING CASH BALANCE
A7: Opening Cash Balance ($) | B7: =ASSUMPTIONS!$B$44 -> 50000 | C7: =IFERROR(B18,0) -> 36015.096 | D7: =IFERROR(C18,0) -> 23252.127 | E7: =IFERROR(D18,0) -> 251810.26 | F7: =IFERROR(E18,0) -> 223767.83 | G7: =IFERROR(F18,0) -> 197019.46 | H7: =IFERROR(G18,0) -> 154459.78 | I7: =IFERROR(H18,0) -> 113358.43 | J7: =IFERROR(I18,0) -> 73797.528 | ... S7: =IFERROR(R18,0) -> -87061.696
A9: OPERATING ACTIVITIES
A10: EBITDA (from P&L) | B10: =IFERROR('P&L'!B27,0) -> -13984.904 | C10: =IFERROR('P&L'!C27,0) -> -12762.969 | D10: =IFERROR('P&L'!D27,0) -> -21441.867 | E10: =IFERROR('P&L'!E27,0) -> -28042.432 | F10: =IFERROR('P&L'!F27,0) -> -26748.368 | G10: =IFERROR('P&L'!G27,0) -> -42559.675 | H10: =IFERROR('P&L'!H27,0) -> -41101.353 | I10: =IFERROR('P&L'!I27,0) -> -39560.902 | ... S10: =IFERROR('P&L'!S27,0) -> -18242.104
A11: CASH FROM OPERATIONS ($) | B11: =B10 -> -13984.904 | C11: =C10 -> -12762.969 | D11: =D10 -> -21441.867 | E11: =E10 -> -28042.432 | F11: =F10 -> -26748.368 | G11: =G10 -> -42559.675 | H11: =H10 -> -41101.353 | I11: =I10 -> -39560.902 | ... S11: =S10 -> -18242.104
A13: FINANCING ACTIVITIES
A14: Pre-Seed Raise ($) | B14: =IF(1=ASSUMPTIONS!$B$46,ASSUMPTIONS!$B$45,0) -> 0 | C14: =IF(2=ASSUMPTIONS!$B$46,ASSUMPTIONS!$B$45,0) -> 0 | D14: =IF(3=ASSUMPTIONS!$B$46,ASSUMPTIONS!$B$45,0) -> 250000 | E14: =IF(4=ASSUMPTIONS!$B$46,ASSUMPTIONS!$B$45,0) -> 0 | F14: =IF(5=ASSUMPTIONS!$B$46,ASSUMPTIONS!$B$45,0) -> 0 | G14: =IF(6=ASSUMPTIONS!$B$46,ASSUMPTIONS!$B$45,0) -> 0 | H14: =IF(7=ASSUMPTIONS!$B$46,ASSUMPTIONS!$B$45,0) -> 0 | I14: =IF(8=ASSUMPTIONS!$B$46,ASSUMPTIONS!$B$45,0) -> 0 | J14: =IF(9=ASSUMPTIONS!$B$46,ASSUMPTIONS!$B$45,0) -> 0 | K14: =IF(10=ASSUMPTIONS!$B$46,ASSUMPTIONS!$B$45,0) -> 0 | L14: =IF(11=ASSUMPTIONS!$B$46,ASSUMPTIONS!$B$45,0) -> 0 | M14: =IF(12=ASSUMPTIONS!$B$46,ASSUMPTIONS!$B$45,0) -> 0 | N14: =IF(13=ASSUMPTIONS!$B$46,ASSUMPTIONS!$B$45,0) -> 0 | O14: =IF(14=ASSUMPTIONS!$B$46,ASSUMPTIONS!$B$45,0) -> 0 | P14: =IF(15=ASSUMPTIONS!$B$46,ASSUMPTIONS!$B$45,0) -> 0 | Q14: =IF(16=ASSUMPTIONS!$B$46,ASSUMPTIONS!$B$45,0) -> 0 | R14: =IF(17=ASSUMPTIONS!$B$46,ASSUMPTIONS!$B$45,0) -> 0 | S14: =IF(18=ASSUMPTIONS!$B$46,ASSUMPTIONS!$B$45,0) -> 0
A15: CASH FROM FINANCING ($) | B15: =B14 -> 0 | C15: =C14 -> 0 | D15: =D14 -> 250000 | E15: =E14 -> 0 | F15: =F14 -> 0 | G15: =G14 -> 0 | H15: =H14 -> 0 | I15: =I14 -> 0 | ... S15: =S14 -> 0
A17: NET CASH MOVEMENT ($) | B17: =B11+B15 -> -13984.904 | C17: =C11+C15 -> -12762.969 | D17: =D11+D15 -> 228558.13 | E17: =E11+E15 -> -28042.432 | F17: =F11+F15 -> -26748.368 | G17: =G11+G15 -> -42559.675 | H17: =H11+H15 -> -41101.353 | I17: =I11+I15 -> -39560.902 | ... S17: =S11+S15 -> -18242.104
A18: CLOSING CASH BALANCE ($) | B18: =B7+B17 -> 36015.096 | C18: =C7+C17 -> 23252.127 | D18: =D7+D17 -> 251810.26 | E18: =E7+E17 -> 223767.83 | F18: =F7+F17 -> 197019.46 | G18: =G7+G17 -> 154459.78 | H18: =H7+H17 -> 113358.43 | I18: =I7+I17 -> 73797.528 | ... S18: =S7+S17 -> -105303.8
A20: Monthly Cash Burn ($) | B20: =IFERROR(B11,0) -> -13984.904 | C20: =IFERROR(C11,0) -> -12762.969 | D20: =IFERROR(D11,0) -> -21441.867 | E20: =IFERROR(E11,0) -> -28042.432 | F20: =IFERROR(F11,0) -> -26748.368 | G20: =IFERROR(G11,0) -> -42559.675 | H20: =IFERROR(H11,0) -> -41101.353 | I20: =IFERROR(I11,0) -> -39560.902 | ... S20: =IFERROR(S11,0) -> -18242.104
A21: Runway — Months Remaining | B21: =IFERROR(IF(B20<0,B18/ABS(B20),"∞"),0) -> 2.5752837 | C21: =IFERROR(IF(C20<0,C18/ABS(C20),"∞"),0) -> 1.8218431 | D21: =IFERROR(IF(D20<0,D18/ABS(D20),"∞"),0) -> 11.743859 | E21: =IFERROR(IF(E20<0,E18/ABS(E20),"∞"),0) -> 7.9796155 | F21: =IFERROR(IF(F20<0,F18/ABS(F20),"∞"),0) -> 7.3656627 | G21: =IFERROR(IF(G20<0,G18/ABS(G20),"∞"),0) -> 3.6292519 | H21: =IFERROR(IF(H20<0,H18/ABS(H20),"∞"),0) -> 2.7580218 | I21: =IFERROR(IF(I20<0,I18/ABS(I20),"∞"),0) -> 1.8654157 | ... S21: =IFERROR(IF(S20<0,S18/ABS(S20),"∞"),0) -> -5.7725687
