Workbook

Sheet COVER
B2: Raise Ready
B3: Series A Financial Model — Popular
B5: Includes: Marketplace + SaaS revenue, departmental headcount, unit economics, sensitivity analysis, balance sheet, KPI dashboard. 36-month horizon.
B7: ASSUMPTIONS | C7: All model inputs, 3 scenarios, CAC channels
B8: REVENUE | C8: Marketplace + SaaS dual-revenue model
B9: HEADCOUNT | C9: Departmental: Engineering, Product, Sales, Marketing, CS, G&A
B10: P&L | C10: Full profit & loss
B11: CASH FLOW | C11: Cash flow + runway
B12: BALANCE SHEET | C12: Assets, liabilities, equity, balance check
B13: UNIT ECONOMICS | C13: CAC, LTV, LTV:CAC, payback by segment
B14: SENSITIVITY | C14: What-if analysis on key drivers
B15: KPI DASHBOARD | C15: Year-end summary metrics

Sheet ASSUMPTIONS
A1: ASSUMPTIONS — Series A Model
A2: Yellow = inputs (blue text). Scenarios: Conservative / Base / Aggressive.
A4: SECTION 1 — COMPANY
A5: Company Name | B5: SeriesA Co
A6: Currency | B6: $
A7: Model Start | B7: Jan 2025
A9: SCENARIO SELECTOR
A10: Active Scenario (1/2/3) | B10: 2
A12: SECTION 2 — MARKETPLACE REVENUE
B13: Conservative | C13: Base | D13: Aggressive
A14: Starting Buyers | B14: 20 | C14: 40 | D14: 60
A15: New Buyers/Mo | B15: 8 | C15: 15 | D15: 25
A16: Buyer Growth MoM | B16: 0.04 | C16: 0.08 | D16: 0.12
A17: Buyer Churn | B17: 0.06 | C17: 0.045 | D17: 0.03
A18: Starting Sellers | B18: 10 | C18: 20 | D18: 30
A19: New Sellers/Mo | B19: 3 | C19: 6 | D19: 10
A20: Seller Growth MoM | B20: 0.03 | C20: 0.06 | D20: 0.1
A21: Seller Churn | B21: 0.04 | C21: 0.03 | D21: 0.02
A22: Avg Transactions/Buyer/Mo | B22: 2 | C22: 3 | D22: 4
A23: Avg Transaction Value ($) | B23: 150 | C23: 200 | D23: 250
A24: Take Rate % | B24: 0.12 | C24: 0.15 | D24: 0.18
A25: Seller Subscription ($/Mo) | B25: 0 | C25: 49 | D25: 99
A26: Active Marketplace Values
A27: → Starting Buyers | B27: =CHOOSE($B$10,B14,C14,D14) -> 40
A28: → New Buyers/Mo | B28: =CHOOSE($B$10,B15,C15,D15) -> 15
A29: → Buyer Growth MoM | B29: =CHOOSE($B$10,B16,C16,D16) -> 0.08
A30: → Buyer Churn | B30: =CHOOSE($B$10,B17,C17,D17) -> 0.045
A31: → Starting Sellers | B31: =CHOOSE($B$10,B18,C18,D18) -> 20
A32: → New Sellers/Mo | B32: =CHOOSE($B$10,B19,C19,D19) -> 6
A33: → Seller Growth MoM | B33: =CHOOSE($B$10,B20,C20,D20) -> 0.06
A34: → Seller Churn | B34: =CHOOSE($B$10,B21,C21,D21) -> 0.03
A35: → Avg Transactions/Buyer/Mo | B35: =CHOOSE($B$10,B22,C22,D22) -> 3
A36: → Avg Transaction Value ($) | B36: =CHOOSE($B$10,B23,C23,D23) -> 200
A37: → Take Rate % | B37: =CHOOSE($B$10,B24,C24,D24) -> 0.15
A38: → Seller Subscription ($/Mo) | B38: =CHOOSE($B$10,B25,C25,D25) -> 49
A40: SECTION 3 — SAAS SUBSCRIPTION REVENUE
B41: Conservative | C41: Base | D41: Aggressive
A42: Starting SaaS Subscribers | B42: 5 | C42: 15 | D42: 30
A43: New SaaS Subs/Mo | B43: 3 | C43: 8 | D43: 15
A44: SaaS Sub Growth MoM | B44: 0.04 | C44: 0.08 | D44: 0.12
A45: SaaS Monthly Churn | B45: 0.05 | C45: 0.035 | D45: 0.025
A46: SaaS ARPU ($/Mo) | B46: 79 | C46: 129 | D46: 199
A47: Active SaaS Values
A48: → Starting SaaS Subscribers | B48: =CHOOSE($B$10,B42,C42,D42) -> 15
A49: → New SaaS Subs/Mo | B49: =CHOOSE($B$10,B43,C43,D43) -> 8
A50: → SaaS Sub Growth MoM | B50: =CHOOSE($B$10,B44,C44,D44) -> 0.08
A51: → SaaS Monthly Churn | B51: =CHOOSE($B$10,B45,C45,D45) -> 0.035
A52: → SaaS ARPU ($/Mo) | B52: =CHOOSE($B$10,B46,C46,D46) -> 129
A54: SECTION 4 — UNIT ECONOMICS
A55: Blended CAC ($) | B55: 120 | C55: Cost to acquire one customer
A56: SaaS Gross Margin % | B56: 0.8
A57: Marketplace Gross Margin % | B57: 0.65
A59: SECTION 5 — COGS
A60: Hosting/User ($) | B60: 4
A61: Payment Processing (%) | B61: 0.025
A62: Support/User ($) | B62: 3
A64: SECTION 6 — HEADCOUNT PLAN
B65: Role | C65: Start Mo | D65: Salary ($)
A66: ENGINEERING
A67: CTO | B67: CTO | C67: 1 | D67: 140000
A68: Sr Eng | B68: Sr Eng | C68: 1 | D68: 130000
A69: Eng #2 | B69: Eng #2 | C69: 3 | D69: 120000
A70: Eng #3 | B70: Eng #3 | C70: 6 | D70: 120000
A71: Eng #4 | B71: Eng #4 | C71: 9 | D71: 120000
A72: Eng #5 | B72: Eng #5 | C72: 12 | D72: 120000
A73: PRODUCT
A74: VP Product | B74: VP Product | C74: 3 | D74: 130000
A75: PM | B75: PM | C75: 6 | D75: 110000
A76: Designer | B76: Designer | C76: 4 | D76: 95000
A77: SALES
A78: Sales Lead | B78: Sales Lead | C78: 1 | D78: 100000
A79: AE #1 | B79: AE #1 | C79: 4 | D79: 85000
A80: AE #2 | B80: AE #2 | C80: 8 | D80: 85000
A81: SDR | B81: SDR | C81: 6 | D81: 55000
A82: MARKETING
A83: Marketing Lead | B83: Marketing Lead | C83: 3 | D83: 95000
A84: Growth | B84: Growth | C84: 6 | D84: 80000
A85: CUSTOMER SUCCESS
A86: CS Lead | B86: CS Lead | C86: 4 | D86: 80000
A87: CS #1 | B87: CS #1 | C87: 8 | D87: 60000
A88: G&A
A89: CEO | B89: CEO | C89: 1 | D89: 120000
A90: Ops/Finance | B90: Ops/Finance | C90: 6 | D90: 90000
A92: Overhead Multiplier | B92: 1.3
A94: SECTION 7 — OPEX
A95: Marketing (Mo $) | B95: 8000
A96: Mktg Growth MoM | B96: 0.06
A97: Software ($) | B97: 2000
A98: Office ($) | B98: 3000
A99: Legal ($) | B99: 1500
A100: Other ($) | B100: 1000
A102: SECTION 8 — CASH & FUNDING
A103: Starting Cash | B103: 500000
A104: Series A Amount | B104: 5000000
A105: Series A Month | B105: 6

Sheet REVENUE
A1: REVENUE — Marketplace + SaaS
A2: Dual revenue model. All from ASSUMPTIONS.
B4: YEAR 1 | N4: YEAR 2 | Z4: YEAR 3
B5: Jan | C5: Feb | D5: Mar | E5: Apr | F5: May | G5: Jun | H5: Jul | I5: Aug | J5: Sep | K5: Oct | L5: Nov | M5: Dec | N5: Jan | O5: Feb | P5: Mar | Q5: Apr | R5: May | S5: Jun | T5: Jul | U5: Aug | V5: Sep | W5: Oct | X5: Nov | Y5: Dec | Z5: Jan | AA5: Feb | AB5: Mar | AC5: Apr | AD5: May | AE5: Jun | AF5: Jul | AG5: Aug | AH5: Sep | AI5: Oct | AJ5: Nov | AK5: Dec | AL5: Y1 Total | AM5: Y2 Total | AN5: Y3 Total
A6: MARKETPLACE — BUYERS & SELLERS
A7: New Buyers | B7: =IFERROR(ASSUMPTIONS!$B$28,0) -> 15 | C7: =IFERROR(ROUND(B7*(1+ASSUMPTIONS!$B$29),0),0) -> 16 | D7: =IFERROR(ROUND(C7*(1+ASSUMPTIONS!$B$29),0),0) -> 17 | E7: =IFERROR(ROUND(D7*(1+ASSUMPTIONS!$B$29),0),0) -> 18 | F7: =IFERROR(ROUND(E7*(1+ASSUMPTIONS!$B$29),0),0) -> 19 | G7: =IFERROR(ROUND(F7*(1+ASSUMPTIONS!$B$29),0),0) -> 21 | H7: =IFERROR(ROUND(G7*(1+ASSUMPTIONS!$B$29),0),0) -> 23 | I7: =IFERROR(ROUND(H7*(1+ASSUMPTIONS!$B$29),0),0) -> 25 | J7: =IFERROR(ROUND(I7*(1+ASSUMPTIONS!$B$29),0),0) -> 27 | ... AK7: =IFERROR(ROUND(AJ7*(1+ASSUMPTIONS!$B$29),0),0) -> 211
A8: Buyers Churned | B8: =IFERROR(ROUND(ASSUMPTIONS!$B$27*ASSUMPTIONS!$B$30,0),0) -> 2 | C8: =IFERROR(ROUND(B9*ASSUMPTIONS!$B$30,0),0) -> 2 | D8: =IFERROR(ROUND(C9*ASSUMPTIONS!$B$30,0),0) -> 3 | E8: =IFERROR(ROUND(D9*ASSUMPTIONS!$B$30,0),0) -> 4 | F8: =IFERROR(ROUND(E9*ASSUMPTIONS!$B$30,0),0) -> 4 | G8: =IFERROR(ROUND(F9*ASSUMPTIONS!$B$30,0),0) -> 5 | H8: =IFERROR(ROUND(G9*ASSUMPTIONS!$B$30,0),0) -> 6 | I8: =IFERROR(ROUND(H9*ASSUMPTIONS!$B$30,0),0) -> 6 | J8: =IFERROR(ROUND(I9*ASSUMPTIONS!$B$30,0),0) -> 7 | ... AK8: =IFERROR(ROUND(AJ9*ASSUMPTIONS!$B$30,0),0) -> 75
A9: Active Buyers EOM | B9: =IFERROR(ASSUMPTIONS!$B$27+B7-B8,0) -> 53 | C9: =IFERROR(B9+C7-C8,0) -> 67 | D9: =IFERROR(C9+D7-D8,0) -> 81 | E9: =IFERROR(D9+E7-E8,0) -> 95 | F9: =IFERROR(E9+F7-F8,0) -> 110 | G9: =IFERROR(F9+G7-G8,0) -> 126 | H9: =IFERROR(G9+H7-H8,0) -> 143 | I9: =IFERROR(H9+I7-I8,0) -> 162 | J9: =IFERROR(I9+J7-J8,0) -> 182 | ... AK9: =IFERROR(AJ9+AK7-AK8,0) -> 1812
A11: New Sellers | B11: =IFERROR(ASSUMPTIONS!$B$32,0) -> 6 | C11: =IFERROR(ROUND(B11*(1+ASSUMPTIONS!$B$33),0),0) -> 6 | D11: =IFERROR(ROUND(C11*(1+ASSUMPTIONS!$B$33),0),0) -> 6 | E11: =IFERROR(ROUND(D11*(1+ASSUMPTIONS!$B$33),0),0) -> 6 | F11: =IFERROR(ROUND(E11*(1+ASSUMPTIONS!$B$33),0),0) -> 6 | G11: =IFERROR(ROUND(F11*(1+ASSUMPTIONS!$B$33),0),0) -> 6 | H11: =IFERROR(ROUND(G11*(1+ASSUMPTIONS!$B$33),0),0) -> 6 | I11: =IFERROR(ROUND(H11*(1+ASSUMPTIONS!$B$33),0),0) -> 6 | J11: =IFERROR(ROUND(I11*(1+ASSUMPTIONS!$B$33),0),0) -> 6 | ... AK11: =IFERROR(ROUND(AJ11*(1+ASSUMPTIONS!$B$33),0),0) -> 6
A12: Sellers Churned | B12: =IFERROR(ROUND(ASSUMPTIONS!$B$31*ASSUMPTIONS!$B$34,0),0) -> 1 | C12: =IFERROR(ROUND(B13*ASSUMPTIONS!$B$34,0),0) -> 1 | D12: =IFERROR(ROUND(C13*ASSUMPTIONS!$B$34,0),0) -> 1 | E12: =IFERROR(ROUND(D13*ASSUMPTIONS!$B$34,0),0) -> 1 | F12: =IFERROR(ROUND(E13*ASSUMPTIONS!$B$34,0),0) -> 1 | G12: =IFERROR(ROUND(F13*ASSUMPTIONS!$B$34,0),0) -> 1 | H12: =IFERROR(ROUND(G13*ASSUMPTIONS!$B$34,0),0) -> 2 | I12: =IFERROR(ROUND(H13*ASSUMPTIONS!$B$34,0),0) -> 2 | J12: =IFERROR(ROUND(I13*ASSUMPTIONS!$B$34,0),0) -> 2 | ... AK12: =IFERROR(ROUND(AJ13*ASSUMPTIONS!$B$34,0),0) -> 4
A13: Active Sellers EOM | B13: =IFERROR(ASSUMPTIONS!$B$31+B11-B12,0) -> 25 | C13: =IFERROR(B13+C11-C12,0) -> 30 | D13: =IFERROR(C13+D11-D12,0) -> 35 | E13: =IFERROR(D13+E11-E12,0) -> 40 | F13: =IFERROR(E13+F11-F12,0) -> 45 | G13: =IFERROR(F13+G11-G12,0) -> 50 | H13: =IFERROR(G13+H11-H12,0) -> 54 | I13: =IFERROR(H13+I11-I12,0) -> 58 | J13: =IFERROR(I13+J11-J12,0) -> 62 | ... AK13: =IFERROR(AJ13+AK11-AK12,0) -> 139
A15: MARKETPLACE REVENUE
A16: GMV ($) | B16: =IFERROR(B9*ASSUMPTIONS!$B$35*ASSUMPTIONS!$B$36,0) -> 31800 | C16: =IFERROR(C9*ASSUMPTIONS!$B$35*ASSUMPTIONS!$B$36,0) -> 40200 | D16: =IFERROR(D9*ASSUMPTIONS!$B$35*ASSUMPTIONS!$B$36,0) -> 48600 | E16: =IFERROR(E9*ASSUMPTIONS!$B$35*ASSUMPTIONS!$B$36,0) -> 57000 | F16: =IFERROR(F9*ASSUMPTIONS!$B$35*ASSUMPTIONS!$B$36,0) -> 66000 | G16: =IFERROR(G9*ASSUMPTIONS!$B$35*ASSUMPTIONS!$B$36,0) -> 75600 | H16: =IFERROR(H9*ASSUMPTIONS!$B$35*ASSUMPTIONS!$B$36,0) -> 85800 | I16: =IFERROR(I9*ASSUMPTIONS!$B$35*ASSUMPTIONS!$B$36,0) -> 97200 | ... AK16: =IFERROR(AK9*ASSUMPTIONS!$B$35*ASSUMPTIONS!$B$36,0) -> 1087200
A17: Transaction Revenue (GMV × Take Rate) | B17: =IFERROR(B16*ASSUMPTIONS!$B$37,0) -> 4770 | C17: =IFERROR(C16*ASSUMPTIONS!$B$37,0) -> 6030 | D17: =IFERROR(D16*ASSUMPTIONS!$B$37,0) -> 7290 | E17: =IFERROR(E16*ASSUMPTIONS!$B$37,0) -> 8550 | F17: =IFERROR(F16*ASSUMPTIONS!$B$37,0) -> 9900 | G17: =IFERROR(G16*ASSUMPTIONS!$B$37,0) -> 11340 | H17: =IFERROR(H16*ASSUMPTIONS!$B$37,0) -> 12870 | I17: =IFERROR(I16*ASSUMPTIONS!$B$37,0) -> 14580 | ... AK17: =IFERROR(AK16*ASSUMPTIONS!$B$37,0) -> 163080
A18: Seller Subscription Revenue ($) | B18: =IFERROR(B13*ASSUMPTIONS!$B$38,0) -> 1225 | C18: =IFERROR(C13*ASSUMPTIONS!$B$38,0) -> 1470 | D18: =IFERROR(D13*ASSUMPTIONS!$B$38,0) -> 1715 | E18: =IFERROR(E13*ASSUMPTIONS!$B$38,0) -> 1960 | F18: =IFERROR(F13*ASSUMPTIONS!$B$38,0) -> 2205 | G18: =IFERROR(G13*ASSUMPTIONS!$B$38,0) -> 2450 | H18: =IFERROR(H13*ASSUMPTIONS!$B$38,0) -> 2646 | I18: =IFERROR(I13*ASSUMPTIONS!$B$38,0) -> 2842 | ... AK18: =IFERROR(AK13*ASSUMPTIONS!$B$38,0) -> 6811
A19: TOTAL MARKETPLACE REVENUE ($) | B19: =B17+B18 -> 5995 | C19: =C17+C18 -> 7500 | D19: =D17+D18 -> 9005 | E19: =E17+E18 -> 10510 | F19: =F17+F18 -> 12105 | G19: =G17+G18 -> 13790 | H19: =H17+H18 -> 15516 | I19: =I17+I18 -> 17422 | ... AK19: =AK17+AK18 -> 169891 | AL19: =SUM(B19:M19) -> 182391 | AM19: =SUM(N19:Y19) -> 555105 | AN19: =SUM(Z19:AK19) -> 1394165
A21: SAAS SUBSCRIPTION REVENUE
A22: New SaaS Subs | B22: =IFERROR(ASSUMPTIONS!$B$49,0) -> 8 | C22: =IFERROR(ROUND(B22*(1+ASSUMPTIONS!$B$50),0),0) -> 9 | D22: =IFERROR(ROUND(C22*(1+ASSUMPTIONS!$B$50),0),0) -> 10 | E22: =IFERROR(ROUND(D22*(1+ASSUMPTIONS!$B$50),0),0) -> 11 | F22: =IFERROR(ROUND(E22*(1+ASSUMPTIONS!$B$50),0),0) -> 12 | G22: =IFERROR(ROUND(F22*(1+ASSUMPTIONS!$B$50),0),0) -> 13 | H22: =IFERROR(ROUND(G22*(1+ASSUMPTIONS!$B$50),0),0) -> 14 | I22: =IFERROR(ROUND(H22*(1+ASSUMPTIONS!$B$50),0),0) -> 15 | J22: =IFERROR(ROUND(I22*(1+ASSUMPTIONS!$B$50),0),0) -> 16 | ... AK22: =IFERROR(ROUND(AJ22*(1+ASSUMPTIONS!$B$50),0),0) -> 123
A23: SaaS Churned | B23: =IFERROR(ROUND(ASSUMPTIONS!$B$48*ASSUMPTIONS!$B$51,0),0) -> 1 | C23: =IFERROR(ROUND(B24*ASSUMPTIONS!$B$51,0),0) -> 1 | D23: =IFERROR(ROUND(C24*ASSUMPTIONS!$B$51,0),0) -> 1 | E23: =IFERROR(ROUND(D24*ASSUMPTIONS!$B$51,0),0) -> 1 | F23: =IFERROR(ROUND(E24*ASSUMPTIONS!$B$51,0),0) -> 2 | G23: =IFERROR(ROUND(F24*ASSUMPTIONS!$B$51,0),0) -> 2 | H23: =IFERROR(ROUND(G24*ASSUMPTIONS!$B$51,0),0) -> 2 | I23: =IFERROR(ROUND(H24*ASSUMPTIONS!$B$51,0),0) -> 3 | J23: =IFERROR(ROUND(I24*ASSUMPTIONS!$B$51,0),0) -> 3 | ... AK23: =IFERROR(ROUND(AJ24*ASSUMPTIONS!$B$51,0),0) -> 37
A24: Active SaaS Subs EOM | B24: =IFERROR(ASSUMPTIONS!$B$48+B22-B23,0) -> 22 | C24: =IFERROR(B24+C22-C23,0) -> 30 | D24: =IFERROR(C24+D22-D23,0) -> 39 | E24: =IFERROR(D24+E22-E23,0) -> 49 | F24: =IFERROR(E24+F22-F23,0) -> 59 | G24: =IFERROR(F24+G22-G23,0) -> 70 | H24: =IFERROR(G24+H22-H23,0) -> 82 | I24: =IFERROR(H24+I22-I23,0) -> 94 | J24: =IFERROR(I24+J22-J23,0) -> 107 | ... AK24: =IFERROR(AJ24+AK22-AK23,0) -> 1146
A25: TOTAL SAAS REVENUE ($) | B25: =IFERROR(B24*ASSUMPTIONS!$B$52,0) -> 2838 | C25: =IFERROR(C24*ASSUMPTIONS!$B$52,0) -> 3870 | D25: =IFERROR(D24*ASSUMPTIONS!$B$52,0) -> 5031 | E25: =IFERROR(E24*ASSUMPTIONS!$B$52,0) -> 6321 | F25: =IFERROR(F24*ASSUMPTIONS!$B$52,0) -> 7611 | G25: =IFERROR(G24*ASSUMPTIONS!$B$52,0) -> 9030 | H25: =IFERROR(H24*ASSUMPTIONS!$B$52,0) -> 10578 | I25: =IFERROR(I24*ASSUMPTIONS!$B$52,0) -> 12126 | ... AK25: =IFERROR(AK24*ASSUMPTIONS!$B$52,0) -> 147834 | AL25: =SUM(B25:M25) -> 123066 | AM25: =SUM(N25:Y25) -> 442341 | AN25: =SUM(Z25:AK25) -> 1191702
A27: TOTAL REVENUE SUMMARY
A28: TOTAL REVENUE ($) | B28: =B19+B25 -> 8833 | C28: =C19+C25 -> 11370 | D28: =D19+D25 -> 14036 | E28: =E19+E25 -> 16831 | F28: =F19+F25 -> 19716 | G28: =G19+G25 -> 22820 | H28: =H19+H25 -> 26094 | I28: =I19+I25 -> 29548 | ... AK28: =AK19+AK25 -> 317725 | AL28: =SUM(B28:M28) -> 305457 | AM28: =SUM(N28:Y28) -> 997446 | AN28: =SUM(Z28:AK28) -> 2585867
A29: MoM Revenue Growth % | C29: =IFERROR((C28-B28)/B28,0) -> 0.28721839 | D29: =IFERROR((D28-C28)/C28,0) -> 0.23447669 | E29: =IFERROR((E28-D28)/D28,0) -> 0.19913081 | F29: =IFERROR((F28-E28)/E28,0) -> 0.1714099 | G29: =IFERROR((G28-F28)/F28,0) -> 0.15743559 | H29: =IFERROR((H28-G28)/G28,0) -> 0.14347064 | I29: =IFERROR((I28-H28)/H28,0) -> 0.13236759 | J29: =IFERROR((J28-I28)/I28,0) -> 0.12430621 | ... AK29: =IFERROR((AK28-AJ28)/AJ28,0) -> 0.07962133

Sheet HEADCOUNT
A1: HEADCOUNT — Departmental
A2: Auto-calculated from Assumptions Section 6.
B4: YEAR 1 | N4: YEAR 2 | Z4: YEAR 3
B5: Jan | C5: Feb | D5: Mar | E5: Apr | F5: May | G5: Jun | H5: Jul | I5: Aug | J5: Sep | K5: Oct | L5: Nov | M5: Dec | N5: Jan | O5: Feb | P5: Mar | Q5: Apr | R5: May | S5: Jun | T5: Jul | U5: Aug | V5: Sep | W5: Oct | X5: Nov | Y5: Dec | Z5: Jan | AA5: Feb | AB5: Mar | AC5: Apr | AD5: May | AE5: Jun | AF5: Jul | AG5: Aug | AH5: Sep | AI5: Oct | AJ5: Nov | AK5: Dec | AL5: Y1 Total | AM5: Y2 Total | AN5: Y3 Total
A7: ENGINEERING
A8: CTO | B8: =IFERROR(IF(1>=1,ROUND(140000/12*ASSUMPTIONS!$B$92,0),0),0) -> 15167 | C8: =IFERROR(IF(2>=1,ROUND(140000/12*ASSUMPTIONS!$B$92,0),0),0) -> 15167 | D8: =IFERROR(IF(3>=1,ROUND(140000/12*ASSUMPTIONS!$B$92,0),0),0) -> 15167 | E8: =IFERROR(IF(4>=1,ROUND(140000/12*ASSUMPTIONS!$B$92,0),0),0) -> 15167 | F8: =IFERROR(IF(5>=1,ROUND(140000/12*ASSUMPTIONS!$B$92,0),0),0) -> 15167 | G8: =IFERROR(IF(6>=1,ROUND(140000/12*ASSUMPTIONS!$B$92,0),0),0) -> 15167 | H8: =IFERROR(IF(7>=1,ROUND(140000/12*ASSUMPTIONS!$B$92,0),0),0) -> 15167 | I8: =IFERROR(IF(8>=1,ROUND(140000/12*ASSUMPTIONS!$B$92,0),0),0) -> 15167 | J8: =IFERROR(IF(9>=1,ROUND(140000/12*ASSUMPTIONS!$B$92,0),0),0) -> 15167 | K8: =IFERROR(IF(10>=1,ROUND(140000/12*ASSUMPTIONS!$B$92,0),0),0) -> 15167 | L8: =IFERROR(IF(11>=1,ROUND(140000/12*ASSUMPTIONS!$B$92,0),0),0) -> 15167 | M8: =IFERROR(IF(12>=1,ROUND(140000/12*ASSUMPTIONS!$B$92,0),0),0) -> 15167 | N8: =IFERROR(IF(13>=1,ROUND(140000/12*ASSUMPTIONS!$B$92,0),0),0) -> 15167 | O8: =IFERROR(IF(14>=1,ROUND(140000/12*ASSUMPTIONS!$B$92,0),0),0) -> 15167 | P8: =IFERROR(IF(15>=1,ROUND(140000/12*ASSUMPTIONS!$B$92,0),0),0) -> 15167 | Q8: =IFERROR(IF(16>=1,ROUND(140000/12*ASSUMPTIONS!$B$92,0),0),0) -> 15167 | R8: =IFERROR(IF(17>=1,ROUND(140000/12*ASSUMPTIONS!$B$92,0),0),0) -> 15167 | S8: =IFERROR(IF(18>=1,ROUND(140000/12*ASSUMPTIONS!$B$92,0),0),0) -> 15167 | T8: =IFERROR(IF(19>=1,ROUND(140000/12*ASSUMPTIONS!$B$92,0),0),0) -> 15167 | U8: =IFERROR(IF(20>=1,ROUND(140000/12*ASSUMPTIONS!$B$92,0),0),0) -> 15167 | V8: =IFERROR(IF(21>=1,ROUND(140000/12*ASSUMPTIONS!$B$92,0),0),0) -> 15167 | W8: =IFERROR(IF(22>=1,ROUND(140000/12*ASSUMPTIONS!$B$92,0),0),0) -> 15167 | X8: =IFERROR(IF(23>=1,ROUND(140000/12*ASSUMPTIONS!$B$92,0),0),0) -> 15167 | Y8: =IFERROR(IF(24>=1,ROUND(140000/12*ASSUMPTIONS!$B$92,0),0),0) -> 15167 | Z8: =IFERROR(IF(25>=1,ROUND(140000/12*ASSUMPTIONS!$B$92,0),0),0) -> 15167 | AA8: =IFERROR(IF(26>=1,ROUND(140000/12*ASSUMPTIONS!$B$92,0),0),0) -> 15167 | AB8: =IFERROR(IF(27>=1,ROUND(140000/12*ASSUMPTIONS!$B$92,0),0),0) -> 15167 | AC8: =IFERROR(IF(28>=1,ROUND(140000/12*ASSUMPTIONS!$B$92,0),0),0) -> 15167 | AD8: =IFERROR(IF(29>=1,ROUND(140000/12*ASSUMPTIONS!$B$92,0),0),0) -> 15167 | AE8: =IFERROR(IF(30>=1,ROUND(140000/12*ASSUMPTIONS!$B$92,0),0),0) -> 15167 | AF8: =IFERROR(IF(31>=1,ROUND(140000/12*ASSUMPTIONS!$B$92,0),0),0) -> 15167 | AG8: =IFERROR(IF(32>=1,ROUND(140000/12*ASSUMPTIONS!$B$92,0),0),0) -> 15167 | AH8: =IFERROR(IF(33>=1,ROUND(140000/12*ASSUMPTIONS!$B$92,0),0),0) -> 15167 | AI8: =IFERROR(IF(34>=1,ROUND(140000/12*ASSUMPTIONS!$B$92,0),0),0) -> 15167 | AJ8: =IFERROR(IF(35>=1,ROUND(140000/12*ASSUMPTIONS!$B$92,0),0),0) -> 15167 | AK8: =IFERROR(IF(36>=1,ROUND(140000/12*ASSUMPTIONS!$B$92,0),0),0) -> 15167
A9: Sr Eng | B9: =IFERROR(IF(1>=1,ROUND(130000/12*ASSUMPTIONS!$B$92,0),0),0) -> 14083 | C9: =IFERROR(IF(2>=1,ROUND(130000/12*ASSUMPTIONS!$B$92,0),0),0) -> 14083 | D9: =IFERROR(IF(3>=1,ROUND(130000/12*ASSUMPTIONS!$B$92,0),0),0) -> 14083 | E9: =IFERROR(IF(4>=1,ROUND(130000/12*ASSUMPTIONS!$B$92,0),0),0) -> 14083 | F9: =IFERROR(IF(5>=1,ROUND(130000/12*ASSUMPTIONS!$B$92,0),0),0) -> 14083 | G9: =IFERROR(IF(6>=1,ROUND(130000/12*ASSUMPTIONS!$B$92,0),0),0) -> 14083 | H9: =IFERROR(IF(7>=1,ROUND(130000/12*ASSUMPTIONS!$B$92,0),0),0) -> 14083 | I9: =IFERROR(IF(8>=1,ROUND(130000/12*ASSUMPTIONS!$B$92,0),0),0) -> 14083 | J9: =IFERROR(IF(9>=1,ROUND(130000/12*ASSUMPTIONS!$B$92,0),0),0) -> 14083 | K9: =IFERROR(IF(10>=1,ROUND(130000/12*ASSUMPTIONS!$B$92,0),0),0) -> 14083 | L9: =IFERROR(IF(11>=1,ROUND(130000/12*ASSUMPTIONS!$B$92,0),0),0) -> 14083 | M9: =IFERROR(IF(12>=1,ROUND(130000/12*ASSUMPTIONS!$B$92,0),0),0) -> 14083 | N9: =IFERROR(IF(13>=1,ROUND(130000/12*ASSUMPTIONS!$B$92,0),0),0) -> 14083 | O9: =IFERROR(IF(14>=1,ROUND(130000/12*ASSUMPTIONS!$B$92,0),0),0) -> 14083 | P9: =IFERROR(IF(15>=1,ROUND(130000/12*ASSUMPTIONS!$B$92,0),0),0) -> 14083 | Q9: =IFERROR(IF(16>=1,ROUND(130000/12*ASSUMPTIONS!$B$92,0),0),0) -> 14083 | R9: =IFERROR(IF(17>=1,ROUND(130000/12*ASSUMPTIONS!$B$92,0),0),0) -> 14083 | S9: =IFERROR(IF(18>=1,ROUND(130000/12*ASSUMPTIONS!$B$92,0),0),0) -> 14083 | T9: =IFERROR(IF(19>=1,ROUND(130000/12*ASSUMPTIONS!$B$92,0),0),0) -> 14083 | U9: =IFERROR(IF(20>=1,ROUND(130000/12*ASSUMPTIONS!$B$92,0),0),0) -> 14083 | V9: =IFERROR(IF(21>=1,ROUND(130000/12*ASSUMPTIONS!$B$92,0),0),0) -> 14083 | W9: =IFERROR(IF(22>=1,ROUND(130000/12*ASSUMPTIONS!$B$92,0),0),0) -> 14083 | X9: =IFERROR(IF(23>=1,ROUND(130000/12*ASSUMPTIONS!$B$92,0),0),0) -> 14083 | Y9: =IFERROR(IF(24>=1,ROUND(130000/12*ASSUMPTIONS!$B$92,0),0),0) -> 14083 | Z9: =IFERROR(IF(25>=1,ROUND(130000/12*ASSUMPTIONS!$B$92,0),0),0) -> 14083 | AA9: =IFERROR(IF(26>=1,ROUND(130000/12*ASSUMPTIONS!$B$92,0),0),0) -> 14083 | AB9: =IFERROR(IF(27>=1,ROUND(130000/12*ASSUMPTIONS!$B$92,0),0),0) -> 14083 | AC9: =IFERROR(IF(28>=1,ROUND(130000/12*ASSUMPTIONS!$B$92,0),0),0) -> 14083 | AD9: =IFERROR(IF(29>=1,ROUND(130000/12*ASSUMPTIONS!$B$92,0),0),0) -> 14083 | AE9: =IFERROR(IF(30>=1,ROUND(130000/12*ASSUMPTIONS!$B$92,0),0),0) -> 14083 | AF9: =IFERROR(IF(31>=1,ROUND(130000/12*ASSUMPTIONS!$B$92,0),0),0) -> 14083 | AG9: =IFERROR(IF(32>=1,ROUND(130000/12*ASSUMPTIONS!$B$92,0),0),0) -> 14083 | AH9: =IFERROR(IF(33>=1,ROUND(130000/12*ASSUMPTIONS!$B$92,0),0),0) -> 14083 | AI9: =IFERROR(IF(34>=1,ROUND(130000/12*ASSUMPTIONS!$B$92,0),0),0) -> 14083 | AJ9: =IFERROR(IF(35>=1,ROUND(130000/12*ASSUMPTIONS!$B$92,0),0),0) -> 14083 | AK9: =IFERROR(IF(36>=1,ROUND(130000/12*ASSUMPTIONS!$B$92,0),0),0) -> 14083
A10: Eng #2 | B10: =IFERROR(IF(1>=3,ROUND(120000/12*ASSUMPTIONS!$B$92,0),0),0) -> 0 | C10: =IFERROR(IF(2>=3,ROUND(120000/12*ASSUMPTIONS!$B$92,0),0),0) -> 0 | D10: =IFERROR(IF(3>=3,ROUND(120000/12*ASSUMPTIONS!$B$92,0),0),0) -> 13000 | E10: =IFERROR(IF(4>=3,ROUND(120000/12*ASSUMPTIONS!$B$92,0),0),0) -> 13000 | F10: =IFERROR(IF(5>=3,ROUND(120000/12*ASSUMPTIONS!$B$92,0),0),0) -> 13000 | G10: =IFERROR(IF(6>=3,ROUND(120000/12*ASSUMPTIONS!$B$92,0),0),0) -> 13000 | H10: =IFERROR(IF(7>=3,ROUND(120000/12*ASSUMPTIONS!$B$92,0),0),0) -> 13000 | I10: =IFERROR(IF(8>=3,ROUND(120000/12*ASSUMPTIONS!$B$92,0),0),0) -> 13000 | J10: =IFERROR(IF(9>=3,ROUND(120000/12*ASSUMPTIONS!$B$92,0),0),0) -> 13000 | K10: =IFERROR(IF(10>=3,ROUND(120000/12*ASSUMPTIONS!$B$92,0),0),0) -> 13000 | L10: =IFERROR(IF(11>=3,ROUND(120000/12*ASSUMPTIONS!$B$92,0),0),0) -> 13000 | M10: =IFERROR(IF(12>=3,ROUND(120000/12*ASSUMPTIONS!$B$92,0),0),0) -> 13000 | N10: =IFERROR(IF(13>=3,ROUND(120000/12*ASSUMPTIONS!$B$92,0),0),0) -> 13000 | O10: =IFERROR(IF(14>=3,ROUND(120000/12*ASSUMPTIONS!$B$92,0),0),0) -> 13000 | P10: =IFERROR(IF(15>=3,ROUND(120000/12*ASSUMPTIONS!$B$92,0),0),0) -> 13000 | Q10: =IFERROR(IF(16>=3,ROUND(120000/12*ASSUMPTIONS!$B$92,0),0),0) -> 13000 | R10: =IFERROR(IF(17>=3,ROUND(120000/12*ASSUMPTIONS!$B$92,0),0),0) -> 13000 | S10: =IFERROR(IF(18>=3,ROUND(120000/12*ASSUMPTIONS!$B$92,0),0),0) -> 13000 | T10: =IFERROR(IF(19>=3,ROUND(120000/12*ASSUMPTIONS!$B$92,0),0),0) -> 13000 | U10: =IFERROR(IF(20>=3,ROUND(120000/12*ASSUMPTIONS!$B$92,0),0),0) -> 13000 | V10: =IFERROR(IF(21>=3,ROUND(120000/12*ASSUMPTIONS!$B$92,0),0),0) -> 13000 | W10: =IFERROR(IF(22>=3,ROUND(120000/12*ASSUMPTIONS!$B$92,0),0),0) -> 13000 | X10: =IFERROR(IF(23>=3,ROUND(120000/12*ASSUMPTIONS!$B$92,0),0),0) -> 13000 | Y10: =IFERROR(IF(24>=3,ROUND(120000/12*ASSUMPTIONS!$B$92,0),0),0) -> 13000 | Z10: =IFERROR(IF(25>=3,ROUND(120000/12*ASSUMPTIONS!$B$92,0),0),0) -> 13000 | AA10: =IFERROR(IF(26>=3,ROUND(120000/12*ASSUMPTIONS!$B$92,0),0),0) -> 13000 | AB10: =IFERROR(IF(27>=3,ROUND(120000/12*ASSUMPTIONS!$B$92,0),0),0) -> 13000 | AC10: =IFERROR(IF(28>=3,ROUND(120000/12*ASSUMPTIONS!$B$92,0),0),0) -> 13000 | AD10: =IFERROR(IF(29>=3,ROUND(120000/12*ASSUMPTIONS!$B$92,0),0),0) -> 13000 | AE10: =IFERROR(IF(30>=3,ROUND(120000/12*ASSUMPTIONS!$B$92,0),0),0) -> 13000 | AF10: =IFERROR(IF(31>=3,ROUND(120000/12*ASSUMPTIONS!$B$92,0),0),0) -> 13000 | AG10: =IFERROR(IF(32>=3,ROUND(120000/12*ASSUMPTIONS!$B$92,0),0),0) -> 13000 | AH10: =IFERROR(IF(33>=3,ROUND(120000/12*ASSUMPTIONS!$B$92,0),0),0) -> 13000 | AI10: =IFERROR(IF(34>=3,ROUND(120000/12*ASSUMPTIONS!$B$92,0),0),0) -> 13000 | AJ10: =IFERROR(IF(35>=3,ROUND(120000/12*ASSUMPTIONS!$B$92,0),0),0) -> 13000 | AK10: =IFERROR(IF(36>=3,ROUND(120000/12*ASSUMPTIONS!$B$92,0),0),0) -> 13000
A11: Eng #3 | B11: =IFERROR(IF(1>=6,ROUND(120000/12*ASSUMPTIONS!$B$92,0),0),0) -> 0 | C11: =IFERROR(IF(2>=6,ROUND(120000/12*ASSUMPTIONS!$B$92,0),0),0) -> 0 | D11: =IFERROR(IF(3>=6,ROUND(120000/12*ASSUMPTIONS!$B$92,0),0),0) -> 0 | E11: =IFERROR(IF(4>=6,ROUND(120000/12*ASSUMPTIONS!$B$92,0),0),0) -> 0 | F11: =IFERROR(IF(5>=6,ROUND(120000/12*ASSUMPTIONS!$B$92,0),0),0) -> 0 | G11: =IFERROR(IF(6>=6,ROUND(120000/12*ASSUMPTIONS!$B$92,0),0),0) -> 13000 | H11: =IFERROR(IF(7>=6,ROUND(120000/12*ASSUMPTIONS!$B$92,0),0),0) -> 13000 | I11: =IFERROR(IF(8>=6,ROUND(120000/12*ASSUMPTIONS!$B$92,0),0),0) -> 13000 | J11: =IFERROR(IF(9>=6,ROUND(120000/12*ASSUMPTIONS!$B$92,0),0),0) -> 13000 | K11: =IFERROR(IF(10>=6,ROUND(120000/12*ASSUMPTIONS!$B$92,0),0),0) -> 13000 | L11: =IFERROR(IF(11>=6,ROUND(120000/12*ASSUMPTIONS!$B$92,0),0),0) -> 13000 | M11: =IFERROR(IF(12>=6,ROUND(120000/12*ASSUMPTIONS!$B$92,0),0),0) -> 13000 | N11: =IFERROR(IF(13>=6,ROUND(120000/12*ASSUMPTIONS!$B$92,0),0),0) -> 13000 | O11: =IFERROR(IF(14>=6,ROUND(120000/12*ASSUMPTIONS!$B$92,0),0),0) -> 13000 | P11: =IFERROR(IF(15>=6,ROUND(120000/12*ASSUMPTIONS!$B$92,0),0),0) -> 13000 | Q11: =IFERROR(IF(16>=6,ROUND(120000/12*ASSUMPTIONS!$B$92,0),0),0) -> 13000 | R11: =IFERROR(IF(17>=6,ROUND(120000/12*ASSUMPTIONS!$B$92,0),0),0) -> 13000 | S11: =IFERROR(IF(18>=6,ROUND(120000/12*ASSUMPTIONS!$B$92,0),0),0) -> 13000 | T11: =IFERROR(IF(19>=6,ROUND(120000/12*ASSUMPTIONS!$B$92,0),0),0) -> 13000 | U11: =IFERROR(IF(20>=6,ROUND(120000/12*ASSUMPTIONS!$B$92,0),0),0) -> 13000 | V11: =IFERROR(IF(21>=6,ROUND(120000/12*ASSUMPTIONS!$B$92,0),0),0) -> 13000 | W11: =IFERROR(IF(22>=6,ROUND(120000/12*ASSUMPTIONS!$B$92,0),0),0) -> 13000 | X11: =IFERROR(IF(23>=6,ROUND(120000/12*ASSUMPTIONS!$B$92,0),0),0) -> 13000 | Y11: =IFERROR(IF(24>=6,ROUND(120000/12*ASSUMPTIONS!$B$92,0),0),0) -> 13000 | Z11: =IFERROR(IF(25>=6,ROUND(120000/12*ASSUMPTIONS!$B$92,0),0),0) -> 13000 | AA11: =IFERROR(IF(26>=6,ROUND(120000/12*ASSUMPTIONS!$B$92,0),0),0) -> 13000 | AB11: =IFERROR(IF(27>=6,ROUND(120000/12*ASSUMPTIONS!$B$92,0),0),0) -> 13000 | AC11: =IFERROR(IF(28>=6,ROUND(120000/12*ASSUMPTIONS!$B$92,0),0),0) -> 13000 | AD11: =IFERROR(IF(29>=6,ROUND(120000/12*ASSUMPTIONS!$B$92,0),0),0) -> 13000 | AE11: =IFERROR(IF(30>=6,ROUND(120000/12*ASSUMPTIONS!$B$92,0),0),0) -> 13000 | AF11: =IFERROR(IF(31>=6,ROUND(120000/12*ASSUMPTIONS!$B$92,0),0),0) -> 13000 | AG11: =IFERROR(IF(32>=6,ROUND(120000/12*ASSUMPTIONS!$B$92,0),0),0) -> 13000 | AH11: =IFERROR(IF(33>=6,ROUND(120000/12*ASSUMPTIONS!$B$92,0),0),0) -> 13000 | AI11: =IFERROR(IF(34>=6,ROUND(120000/12*ASSUMPTIONS!$B$92,0),0),0) -> 13000 | AJ11: =IFERROR(IF(35>=6,ROUND(120000/12*ASSUMPTIONS!$B$92,0),0),0) -> 13000 | AK11: =IFERROR(IF(36>=6,ROUND(120000/12*ASSUMPTIONS!$B$92,0),0),0) -> 13000
A12: Eng #4 | B12: =IFERROR(IF(1>=9,ROUND(120000/12*ASSUMPTIONS!$B$92,0),0),0) -> 0 | C12: =IFERROR(IF(2>=9,ROUND(120000/12*ASSUMPTIONS!$B$92,0),0),0) -> 0 | D12: =IFERROR(IF(3>=9,ROUND(120000/12*ASSUMPTIONS!$B$92,0),0),0) -> 0 | E12: =IFERROR(IF(4>=9,ROUND(120000/12*ASSUMPTIONS!$B$92,0),0),0) -> 0 | F12: =IFERROR(IF(5>=9,ROUND(120000/12*ASSUMPTIONS!$B$92,0),0),0) -> 0 | G12: =IFERROR(IF(6>=9,ROUND(120000/12*ASSUMPTIONS!$B$92,0),0),0) -> 0 | H12: =IFERROR(IF(7>=9,ROUND(120000/12*ASSUMPTIONS!$B$92,0),0),0) -> 0 | I12: =IFERROR(IF(8>=9,ROUND(120000/12*ASSUMPTIONS!$B$92,0),0),0) -> 0 | J12: =IFERROR(IF(9>=9,ROUND(120000/12*ASSUMPTIONS!$B$92,0),0),0) -> 13000 | K12: =IFERROR(IF(10>=9,ROUND(120000/12*ASSUMPTIONS!$B$92,0),0),0) -> 13000 | L12: =IFERROR(IF(11>=9,ROUND(120000/12*ASSUMPTIONS!$B$92,0),0),0) -> 13000 | M12: =IFERROR(IF(12>=9,ROUND(120000/12*ASSUMPTIONS!$B$92,0),0),0) -> 13000 | N12: =IFERROR(IF(13>=9,ROUND(120000/12*ASSUMPTIONS!$B$92,0),0),0) -> 13000 | O12: =IFERROR(IF(14>=9,ROUND(120000/12*ASSUMPTIONS!$B$92,0),0),0) -> 13000 | P12: =IFERROR(IF(15>=9,ROUND(120000/12*ASSUMPTIONS!$B$92,0),0),0) -> 13000 | Q12: =IFERROR(IF(16>=9,ROUND(120000/12*ASSUMPTIONS!$B$92,0),0),0) -> 13000 | R12: =IFERROR(IF(17>=9,ROUND(120000/12*ASSUMPTIONS!$B$92,0),0),0) -> 13000 | S12: =IFERROR(IF(18>=9,ROUND(120000/12*ASSUMPTIONS!$B$92,0),0),0) -> 13000 | T12: =IFERROR(IF(19>=9,ROUND(120000/12*ASSUMPTIONS!$B$92,0),0),0) -> 13000 | U12: =IFERROR(IF(20>=9,ROUND(120000/12*ASSUMPTIONS!$B$92,0),0),0) -> 13000 | V12: =IFERROR(IF(21>=9,ROUND(120000/12*ASSUMPTIONS!$B$92,0),0),0) -> 13000 | W12: =IFERROR(IF(22>=9,ROUND(120000/12*ASSUMPTIONS!$B$92,0),0),0) -> 13000 | X12: =IFERROR(IF(23>=9,ROUND(120000/12*ASSUMPTIONS!$B$92,0),0),0) -> 13000 | Y12: =IFERROR(IF(24>=9,ROUND(120000/12*ASSUMPTIONS!$B$92,0),0),0) -> 13000 | Z12: =IFERROR(IF(25>=9,ROUND(120000/12*ASSUMPTIONS!$B$92,0),0),0) -> 13000 | AA12: =IFERROR(IF(26>=9,ROUND(120000/12*ASSUMPTIONS!$B$92,0),0),0) -> 13000 | AB12: =IFERROR(IF(27>=9,ROUND(120000/12*ASSUMPTIONS!$B$92,0),0),0) -> 13000 | AC12: =IFERROR(IF(28>=9,ROUND(120000/12*ASSUMPTIONS!$B$92,0),0),0) -> 13000 | AD12: =IFERROR(IF(29>=9,ROUND(120000/12*ASSUMPTIONS!$B$92,0),0),0) -> 13000 | AE12: =IFERROR(IF(30>=9,ROUND(120000/12*ASSUMPTIONS!$B$92,0),0),0) -> 13000 | AF12: =IFERROR(IF(31>=9,ROUND(120000/12*ASSUMPTIONS!$B$92,0),0),0) -> 13000 | AG12: =IFERROR(IF(32>=9,ROUND(120000/12*ASSUMPTIONS!$B$92,0),0),0) -> 13000 | AH12: =IFERROR(IF(33>=9,ROUND(120000/12*ASSUMPTIONS!$B$92,0),0),0) -> 13000 | AI12: =IFERROR(IF(34>=9,ROUND(120000/12*ASSUMPTIONS!$B$92,0),0),0) -> 13000 | AJ12: =IFERROR(IF(35>=9,ROUND(120000/12*ASSUMPTIONS!$B$92,0),0),0) -> 13000 | AK12: =IFERROR(IF(36>=9,ROUND(120000/12*ASSUMPTIONS!$B$92,0),0),0) -> 13000
A13: Eng #5 | B13: =IFERROR(IF(1>=12,ROUND(120000/12*ASSUMPTIONS!$B$92,0),0),0) -> 0 | C13: =IFERROR(IF(2>=12,ROUND(120000/12*ASSUMPTIONS!$B$92,0),0),0) -> 0 | D13: =IFERROR(IF(3>=12,ROUND(120000/12*ASSUMPTIONS!$B$92,0),0),0) -> 0 | E13: =IFERROR(IF(4>=12,ROUND(120000/12*ASSUMPTIONS!$B$92,0),0),0) -> 0 | F13: =IFERROR(IF(5>=12,ROUND(120000/12*ASSUMPTIONS!$B$92,0),0),0) -> 0 | G13: =IFERROR(IF(6>=12,ROUND(120000/12*ASSUMPTIONS!$B$92,0),0),0) -> 0 | H13: =IFERROR(IF(7>=12,ROUND(120000/12*ASSUMPTIONS!$B$92,0),0),0) -> 0 | I13: =IFERROR(IF(8>=12,ROUND(120000/12*ASSUMPTIONS!$B$92,0),0),0) -> 0 | J13: =IFERROR(IF(9>=12,ROUND(120000/12*ASSUMPTIONS!$B$92,0),0),0) -> 0 | K13: =IFERROR(IF(10>=12,ROUND(120000/12*ASSUMPTIONS!$B$92,0),0),0) -> 0 | L13: =IFERROR(IF(11>=12,ROUND(120000/12*ASSUMPTIONS!$B$92,0),0),0) -> 0 | M13: =IFERROR(IF(12>=12,ROUND(120000/12*ASSUMPTIONS!$B$92,0),0),0) -> 13000 | N13: =IFERROR(IF(13>=12,ROUND(120000/12*ASSUMPTIONS!$B$92,0),0),0) -> 13000 | O13: =IFERROR(IF(14>=12,ROUND(120000/12*ASSUMPTIONS!$B$92,0),0),0) -> 13000 | P13: =IFERROR(IF(15>=12,ROUND(120000/12*ASSUMPTIONS!$B$92,0),0),0) -> 13000 | Q13: =IFERROR(IF(16>=12,ROUND(120000/12*ASSUMPTIONS!$B$92,0),0),0) -> 13000 | R13: =IFERROR(IF(17>=12,ROUND(120000/12*ASSUMPTIONS!$B$92,0),0),0) -> 13000 | S13: =IFERROR(IF(18>=12,ROUND(120000/12*ASSUMPTIONS!$B$92,0),0),0) -> 13000 | T13: =IFERROR(IF(19>=12,ROUND(120000/12*ASSUMPTIONS!$B$92,0),0),0) -> 13000 | U13: =IFERROR(IF(20>=12,ROUND(120000/12*ASSUMPTIONS!$B$92,0),0),0) -> 13000 | V13: =IFERROR(IF(21>=12,ROUND(120000/12*ASSUMPTIONS!$B$92,0),0),0) -> 13000 | W13: =IFERROR(IF(22>=12,ROUND(120000/12*ASSUMPTIONS!$B$92,0),0),0) -> 13000 | X13: =IFERROR(IF(23>=12,ROUND(120000/12*ASSUMPTIONS!$B$92,0),0),0) -> 13000 | Y13: =IFERROR(IF(24>=12,ROUND(120000/12*ASSUMPTIONS!$B$92,0),0),0) -> 13000 | Z13: =IFERROR(IF(25>=12,ROUND(120000/12*ASSUMPTIONS!$B$92,0),0),0) -> 13000 | AA13: =IFERROR(IF(26>=12,ROUND(120000/12*ASSUMPTIONS!$B$92,0),0),0) -> 13000 | AB13: =IFERROR(IF(27>=12,ROUND(120000/12*ASSUMPTIONS!$B$92,0),0),0) -> 13000 | AC13: =IFERROR(IF(28>=12,ROUND(120000/12*ASSUMPTIONS!$B$92,0),0),0) -> 13000 | AD13: =IFERROR(IF(29>=12,ROUND(120000/12*ASSUMPTIONS!$B$92,0),0),0) -> 13000 | AE13: =IFERROR(IF(30>=12,ROUND(120000/12*ASSUMPTIONS!$B$92,0),0),0) -> 13000 | AF13: =IFERROR(IF(31>=12,ROUND(120000/12*ASSUMPTIONS!$B$92,0),0),0) -> 13000 | AG13: =IFERROR(IF(32>=12,ROUND(120000/12*ASSUMPTIONS!$B$92,0),0),0) -> 13000 | AH13: =IFERROR(IF(33>=12,ROUND(120000/12*ASSUMPTIONS!$B$92,0),0),0) -> 13000 | AI13: =IFERROR(IF(34>=12,ROUND(120000/12*ASSUMPTIONS!$B$92,0),0),0) -> 13000 | AJ13: =IFERROR(IF(35>=12,ROUND(120000/12*ASSUMPTIONS!$B$92,0),0),0) -> 13000 | AK13: =IFERROR(IF(36>=12,ROUND(120000/12*ASSUMPTIONS!$B$92,0),0),0) -> 13000
A14: Total ENGINEERING ($) | B14: =SUM(B8:B13) -> 29250 | C14: =SUM(C8:C13) -> 29250 | D14: =SUM(D8:D13) -> 42250 | E14: =SUM(E8:E13) -> 42250 | F14: =SUM(F8:F13) -> 42250 | G14: =SUM(G8:G13) -> 55250 | H14: =SUM(H8:H13) -> 55250 | I14: =SUM(I8:I13) -> 55250 | ... AK14: =SUM(AK8:AK13) -> 81250
A15: PRODUCT
A16: VP Product | B16: =IFERROR(IF(1>=3,ROUND(130000/12*ASSUMPTIONS!$B$92,0),0),0) -> 0 | C16: =IFERROR(IF(2>=3,ROUND(130000/12*ASSUMPTIONS!$B$92,0),0),0) -> 0 | D16: =IFERROR(IF(3>=3,ROUND(130000/12*ASSUMPTIONS!$B$92,0),0),0) -> 14083 | E16: =IFERROR(IF(4>=3,ROUND(130000/12*ASSUMPTIONS!$B$92,0),0),0) -> 14083 | F16: =IFERROR(IF(5>=3,ROUND(130000/12*ASSUMPTIONS!$B$92,0),0),0) -> 14083 | G16: =IFERROR(IF(6>=3,ROUND(130000/12*ASSUMPTIONS!$B$92,0),0),0) -> 14083 | H16: =IFERROR(IF(7>=3,ROUND(130000/12*ASSUMPTIONS!$B$92,0),0),0) -> 14083 | I16: =IFERROR(IF(8>=3,ROUND(130000/12*ASSUMPTIONS!$B$92,0),0),0) -> 14083 | J16: =IFERROR(IF(9>=3,ROUND(130000/12*ASSUMPTIONS!$B$92,0),0),0) -> 14083 | K16: =IFERROR(IF(10>=3,ROUND(130000/12*ASSUMPTIONS!$B$92,0),0),0) -> 14083 | L16: =IFERROR(IF(11>=3,ROUND(130000/12*ASSUMPTIONS!$B$92,0),0),0) -> 14083 | M16: =IFERROR(IF(12>=3,ROUND(130000/12*ASSUMPTIONS!$B$92,0),0),0) -> 14083 | N16: =IFERROR(IF(13>=3,ROUND(130000/12*ASSUMPTIONS!$B$92,0),0),0) -> 14083 | O16: =IFERROR(IF(14>=3,ROUND(130000/12*ASSUMPTIONS!$B$92,0),0),0) -> 14083 | P16: =IFERROR(IF(15>=3,ROUND(130000/12*ASSUMPTIONS!$B$92,0),0),0) -> 14083 | Q16: =IFERROR(IF(16>=3,ROUND(130000/12*ASSUMPTIONS!$B$92,0),0),0) -> 14083 | R16: =IFERROR(IF(17>=3,ROUND(130000/12*ASSUMPTIONS!$B$92,0),0),0) -> 14083 | S16: =IFERROR(IF(18>=3,ROUND(130000/12*ASSUMPTIONS!$B$92,0),0),0) -> 14083 | T16: =IFERROR(IF(19>=3,ROUND(130000/12*ASSUMPTIONS!$B$92,0),0),0) -> 14083 | U16: =IFERROR(IF(20>=3,ROUND(130000/12*ASSUMPTIONS!$B$92,0),0),0) -> 14083 | V16: =IFERROR(IF(21>=3,ROUND(130000/12*ASSUMPTIONS!$B$92,0),0),0) -> 14083 | W16: =IFERROR(IF(22>=3,ROUND(130000/12*ASSUMPTIONS!$B$92,0),0),0) -> 14083 | X16: =IFERROR(IF(23>=3,ROUND(130000/12*ASSUMPTIONS!$B$92,0),0),0) -> 14083 | Y16: =IFERROR(IF(24>=3,ROUND(130000/12*ASSUMPTIONS!$B$92,0),0),0) -> 14083 | Z16: =IFERROR(IF(25>=3,ROUND(130000/12*ASSUMPTIONS!$B$92,0),0),0) -> 14083 | AA16: =IFERROR(IF(26>=3,ROUND(130000/12*ASSUMPTIONS!$B$92,0),0),0) -> 14083 | AB16: =IFERROR(IF(27>=3,ROUND(130000/12*ASSUMPTIONS!$B$92,0),0),0) -> 14083 | AC16: =IFERROR(IF(28>=3,ROUND(130000/12*ASSUMPTIONS!$B$92,0),0),0) -> 14083 | AD16: =IFERROR(IF(29>=3,ROUND(130000/12*ASSUMPTIONS!$B$92,0),0),0) -> 14083 | AE16: =IFERROR(IF(30>=3,ROUND(130000/12*ASSUMPTIONS!$B$92,0),0),0) -> 14083 | AF16: =IFERROR(IF(31>=3,ROUND(130000/12*ASSUMPTIONS!$B$92,0),0),0) -> 14083 | AG16: =IFERROR(IF(32>=3,ROUND(130000/12*ASSUMPTIONS!$B$92,0),0),0) -> 14083 | AH16: =IFERROR(IF(33>=3,ROUND(130000/12*ASSUMPTIONS!$B$92,0),0),0) -> 14083 | AI16: =IFERROR(IF(34>=3,ROUND(130000/12*ASSUMPTIONS!$B$92,0),0),0) -> 14083 | AJ16: =IFERROR(IF(35>=3,ROUND(130000/12*ASSUMPTIONS!$B$92,0),0),0) -> 14083 | AK16: =IFERROR(IF(36>=3,ROUND(130000/12*ASSUMPTIONS!$B$92,0),0),0) -> 14083
A17: PM | B17: =IFERROR(IF(1>=6,ROUND(110000/12*ASSUMPTIONS!$B$92,0),0),0) -> 0 | C17: =IFERROR(IF(2>=6,ROUND(110000/12*ASSUMPTIONS!$B$92,0),0),0) -> 0 | D17: =IFERROR(IF(3>=6,ROUND(110000/12*ASSUMPTIONS!$B$92,0),0),0) -> 0 | E17: =IFERROR(IF(4>=6,ROUND(110000/12*ASSUMPTIONS!$B$92,0),0),0) -> 0 | F17: =IFERROR(IF(5>=6,ROUND(110000/12*ASSUMPTIONS!$B$92,0),0),0) -> 0 | G17: =IFERROR(IF(6>=6,ROUND(110000/12*ASSUMPTIONS!$B$92,0),0),0) -> 11917 | H17: =IFERROR(IF(7>=6,ROUND(110000/12*ASSUMPTIONS!$B$92,0),0),0) -> 11917 | I17: =IFERROR(IF(8>=6,ROUND(110000/12*ASSUMPTIONS!$B$92,0),0),0) -> 11917 | J17: =IFERROR(IF(9>=6,ROUND(110000/12*ASSUMPTIONS!$B$92,0),0),0) -> 11917 | K17: =IFERROR(IF(10>=6,ROUND(110000/12*ASSUMPTIONS!$B$92,0),0),0) -> 11917 | L17: =IFERROR(IF(11>=6,ROUND(110000/12*ASSUMPTIONS!$B$92,0),0),0) -> 11917 | M17: =IFERROR(IF(12>=6,ROUND(110000/12*ASSUMPTIONS!$B$92,0),0),0) -> 11917 | N17: =IFERROR(IF(13>=6,ROUND(110000/12*ASSUMPTIONS!$B$92,0),0),0) -> 11917 | O17: =IFERROR(IF(14>=6,ROUND(110000/12*ASSUMPTIONS!$B$92,0),0),0) -> 11917 | P17: =IFERROR(IF(15>=6,ROUND(110000/12*ASSUMPTIONS!$B$92,0),0),0) -> 11917 | Q17: =IFERROR(IF(16>=6,ROUND(110000/12*ASSUMPTIONS!$B$92,0),0),0) -> 11917 | R17: =IFERROR(IF(17>=6,ROUND(110000/12*ASSUMPTIONS!$B$92,0),0),0) -> 11917 | S17: =IFERROR(IF(18>=6,ROUND(110000/12*ASSUMPTIONS!$B$92,0),0),0) -> 11917 | T17: =IFERROR(IF(19>=6,ROUND(110000/12*ASSUMPTIONS!$B$92,0),0),0) -> 11917 | U17: =IFERROR(IF(20>=6,ROUND(110000/12*ASSUMPTIONS!$B$92,0),0),0) -> 11917 | V17: =IFERROR(IF(21>=6,ROUND(110000/12*ASSUMPTIONS!$B$92,0),0),0) -> 11917 | W17: =IFERROR(IF(22>=6,ROUND(110000/12*ASSUMPTIONS!$B$92,0),0),0) -> 11917 | X17: =IFERROR(IF(23>=6,ROUND(110000/12*ASSUMPTIONS!$B$92,0),0),0) -> 11917 | Y17: =IFERROR(IF(24>=6,ROUND(110000/12*ASSUMPTIONS!$B$92,0),0),0) -> 11917 | Z17: =IFERROR(IF(25>=6,ROUND(110000/12*ASSUMPTIONS!$B$92,0),0),0) -> 11917 | AA17: =IFERROR(IF(26>=6,ROUND(110000/12*ASSUMPTIONS!$B$92,0),0),0) -> 11917 | AB17: =IFERROR(IF(27>=6,ROUND(110000/12*ASSUMPTIONS!$B$92,0),0),0) -> 11917 | AC17: =IFERROR(IF(28>=6,ROUND(110000/12*ASSUMPTIONS!$B$92,0),0),0) -> 11917 | AD17: =IFERROR(IF(29>=6,ROUND(110000/12*ASSUMPTIONS!$B$92,0),0),0) -> 11917 | AE17: =IFERROR(IF(30>=6,ROUND(110000/12*ASSUMPTIONS!$B$92,0),0),0) -> 11917 | AF17: =IFERROR(IF(31>=6,ROUND(110000/12*ASSUMPTIONS!$B$92,0),0),0) -> 11917 | AG17: =IFERROR(IF(32>=6,ROUND(110000/12*ASSUMPTIONS!$B$92,0),0),0) -> 11917 | AH17: =IFERROR(IF(33>=6,ROUND(110000/12*ASSUMPTIONS!$B$92,0),0),0) -> 11917 | AI17: =IFERROR(IF(34>=6,ROUND(110000/12*ASSUMPTIONS!$B$92,0),0),0) -> 11917 | AJ17: =IFERROR(IF(35>=6,ROUND(110000/12*ASSUMPTIONS!$B$92,0),0),0) -> 11917 | AK17: =IFERROR(IF(36>=6,ROUND(110000/12*ASSUMPTIONS!$B$92,0),0),0) -> 11917
A18: Designer | B18: =IFERROR(IF(1>=4,ROUND(95000/12*ASSUMPTIONS!$B$92,0),0),0) -> 0 | C18: =IFERROR(IF(2>=4,ROUND(95000/12*ASSUMPTIONS!$B$92,0),0),0) -> 0 | D18: =IFERROR(IF(3>=4,ROUND(95000/12*ASSUMPTIONS!$B$92,0),0),0) -> 0 | E18: =IFERROR(IF(4>=4,ROUND(95000/12*ASSUMPTIONS!$B$92,0),0),0) -> 10292 | F18: =IFERROR(IF(5>=4,ROUND(95000/12*ASSUMPTIONS!$B$92,0),0),0) -> 10292 | G18: =IFERROR(IF(6>=4,ROUND(95000/12*ASSUMPTIONS!$B$92,0),0),0) -> 10292 | H18: =IFERROR(IF(7>=4,ROUND(95000/12*ASSUMPTIONS!$B$92,0),0),0) -> 10292 | I18: =IFERROR(IF(8>=4,ROUND(95000/12*ASSUMPTIONS!$B$92,0),0),0) -> 10292 | J18: =IFERROR(IF(9>=4,ROUND(95000/12*ASSUMPTIONS!$B$92,0),0),0) -> 10292 | K18: =IFERROR(IF(10>=4,ROUND(95000/12*ASSUMPTIONS!$B$92,0),0),0) -> 10292 | L18: =IFERROR(IF(11>=4,ROUND(95000/12*ASSUMPTIONS!$B$92,0),0),0) -> 10292 | M18: =IFERROR(IF(12>=4,ROUND(95000/12*ASSUMPTIONS!$B$92,0),0),0) -> 10292 | N18: =IFERROR(IF(13>=4,ROUND(95000/12*ASSUMPTIONS!$B$92,0),0),0) -> 10292 | O18: =IFERROR(IF(14>=4,ROUND(95000/12*ASSUMPTIONS!$B$92,0),0),0) -> 10292 | P18: =IFERROR(IF(15>=4,ROUND(95000/12*ASSUMPTIONS!$B$92,0),0),0) -> 10292 | Q18: =IFERROR(IF(16>=4,ROUND(95000/12*ASSUMPTIONS!$B$92,0),0),0) -> 10292 | R18: =IFERROR(IF(17>=4,ROUND(95000/12*ASSUMPTIONS!$B$92,0),0),0) -> 10292 | S18: =IFERROR(IF(18>=4,ROUND(95000/12*ASSUMPTIONS!$B$92,0),0),0) -> 10292 | T18: =IFERROR(IF(19>=4,ROUND(95000/12*ASSUMPTIONS!$B$92,0),0),0) -> 10292 | U18: =IFERROR(IF(20>=4,ROUND(95000/12*ASSUMPTIONS!$B$92,0),0),0) -> 10292 | V18: =IFERROR(IF(21>=4,ROUND(95000/12*ASSUMPTIONS!$B$92,0),0),0) -> 10292 | W18: =IFERROR(IF(22>=4,ROUND(95000/12*ASSUMPTIONS!$B$92,0),0),0) -> 10292 | X18: =IFERROR(IF(23>=4,ROUND(95000/12*ASSUMPTIONS!$B$92,0),0),0) -> 10292 | Y18: =IFERROR(IF(24>=4,ROUND(95000/12*ASSUMPTIONS!$B$92,0),0),0) -> 10292 | Z18: =IFERROR(IF(25>=4,ROUND(95000/12*ASSUMPTIONS!$B$92,0),0),0) -> 10292 | AA18: =IFERROR(IF(26>=4,ROUND(95000/12*ASSUMPTIONS!$B$92,0),0),0) -> 10292 | AB18: =IFERROR(IF(27>=4,ROUND(95000/12*ASSUMPTIONS!$B$92,0),0),0) -> 10292 | AC18: =IFERROR(IF(28>=4,ROUND(95000/12*ASSUMPTIONS!$B$92,0),0),0) -> 10292 | AD18: =IFERROR(IF(29>=4,ROUND(95000/12*ASSUMPTIONS!$B$92,0),0),0) -> 10292 | AE18: =IFERROR(IF(30>=4,ROUND(95000/12*ASSUMPTIONS!$B$92,0),0),0) -> 10292 | AF18: =IFERROR(IF(31>=4,ROUND(95000/12*ASSUMPTIONS!$B$92,0),0),0) -> 10292 | AG18: =IFERROR(IF(32>=4,ROUND(95000/12*ASSUMPTIONS!$B$92,0),0),0) -> 10292 | AH18: =IFERROR(IF(33>=4,ROUND(95000/12*ASSUMPTIONS!$B$92,0),0),0) -> 10292 | AI18: =IFERROR(IF(34>=4,ROUND(95000/12*ASSUMPTIONS!$B$92,0),0),0) -> 10292 | AJ18: =IFERROR(IF(35>=4,ROUND(95000/12*ASSUMPTIONS!$B$92,0),0),0) -> 10292 | AK18: =IFERROR(IF(36>=4,ROUND(95000/12*ASSUMPTIONS!$B$92,0),0),0) -> 10292
A19: Total PRODUCT ($) | B19: =SUM(B16:B18) -> 0 | C19: =SUM(C16:C18) -> 0 | D19: =SUM(D16:D18) -> 14083 | E19: =SUM(E16:E18) -> 24375 | F19: =SUM(F16:F18) -> 24375 | G19: =SUM(G16:G18) -> 36292 | H19: =SUM(H16:H18) -> 36292 | I19: =SUM(I16:I18) -> 36292 | ... AK19: =SUM(AK16:AK18) -> 36292
A20: SALES
A21: Sales Lead | B21: =IFERROR(IF(1>=1,ROUND(100000/12*ASSUMPTIONS!$B$92,0),0),0) -> 10833 | C21: =IFERROR(IF(2>=1,ROUND(100000/12*ASSUMPTIONS!$B$92,0),0),0) -> 10833 | D21: =IFERROR(IF(3>=1,ROUND(100000/12*ASSUMPTIONS!$B$92,0),0),0) -> 10833 | E21: =IFERROR(IF(4>=1,ROUND(100000/12*ASSUMPTIONS!$B$92,0),0),0) -> 10833 | F21: =IFERROR(IF(5>=1,ROUND(100000/12*ASSUMPTIONS!$B$92,0),0),0) -> 10833 | G21: =IFERROR(IF(6>=1,ROUND(100000/12*ASSUMPTIONS!$B$92,0),0),0) -> 10833 | H21: =IFERROR(IF(7>=1,ROUND(100000/12*ASSUMPTIONS!$B$92,0),0),0) -> 10833 | I21: =IFERROR(IF(8>=1,ROUND(100000/12*ASSUMPTIONS!$B$92,0),0),0) -> 10833 | J21: =IFERROR(IF(9>=1,ROUND(100000/12*ASSUMPTIONS!$B$92,0),0),0) -> 10833 | K21: =IFERROR(IF(10>=1,ROUND(100000/12*ASSUMPTIONS!$B$92,0),0),0) -> 10833 | L21: =IFERROR(IF(11>=1,ROUND(100000/12*ASSUMPTIONS!$B$92,0),0),0) -> 10833 | M21: =IFERROR(IF(12>=1,ROUND(100000/12*ASSUMPTIONS!$B$92,0),0),0) -> 10833 | N21: =IFERROR(IF(13>=1,ROUND(100000/12*ASSUMPTIONS!$B$92,0),0),0) -> 10833 | O21: =IFERROR(IF(14>=1,ROUND(100000/12*ASSUMPTIONS!$B$92,0),0),0) -> 10833 | P21: =IFERROR(IF(15>=1,ROUND(100000/12*ASSUMPTIONS!$B$92,0),0),0) -> 10833 | Q21: =IFERROR(IF(16>=1,ROUND(100000/12*ASSUMPTIONS!$B$92,0),0),0) -> 10833 | R21: =IFERROR(IF(17>=1,ROUND(100000/12*ASSUMPTIONS!$B$92,0),0),0) -> 10833 | S21: =IFERROR(IF(18>=1,ROUND(100000/12*ASSUMPTIONS!$B$92,0),0),0) -> 10833 | T21: =IFERROR(IF(19>=1,ROUND(100000/12*ASSUMPTIONS!$B$92,0),0),0) -> 10833 | U21: =IFERROR(IF(20>=1,ROUND(100000/12*ASSUMPTIONS!$B$92,0),0),0) -> 10833 | V21: =IFERROR(IF(21>=1,ROUND(100000/12*ASSUMPTIONS!$B$92,0),0),0) -> 10833 | W21: =IFERROR(IF(22>=1,ROUND(100000/12*ASSUMPTIONS!$B$92,0),0),0) -> 10833 | X21: =IFERROR(IF(23>=1,ROUND(100000/12*ASSUMPTIONS!$B$92,0),0),0) -> 10833 | Y21: =IFERROR(IF(24>=1,ROUND(100000/12*ASSUMPTIONS!$B$92,0),0),0) -> 10833 | Z21: =IFERROR(IF(25>=1,ROUND(100000/12*ASSUMPTIONS!$B$92,0),0),0) -> 10833 | AA21: =IFERROR(IF(26>=1,ROUND(100000/12*ASSUMPTIONS!$B$92,0),0),0) -> 10833 | AB21: =IFERROR(IF(27>=1,ROUND(100000/12*ASSUMPTIONS!$B$92,0),0),0) -> 10833 | AC21: =IFERROR(IF(28>=1,ROUND(100000/12*ASSUMPTIONS!$B$92,0),0),0) -> 10833 | AD21: =IFERROR(IF(29>=1,ROUND(100000/12*ASSUMPTIONS!$B$92,0),0),0) -> 10833 | AE21: =IFERROR(IF(30>=1,ROUND(100000/12*ASSUMPTIONS!$B$92,0),0),0) -> 10833 | AF21: =IFERROR(IF(31>=1,ROUND(100000/12*ASSUMPTIONS!$B$92,0),0),0) -> 10833 | AG21: =IFERROR(IF(32>=1,ROUND(100000/12*ASSUMPTIONS!$B$92,0),0),0) -> 10833 | AH21: =IFERROR(IF(33>=1,ROUND(100000/12*ASSUMPTIONS!$B$92,0),0),0) -> 10833 | AI21: =IFERROR(IF(34>=1,ROUND(100000/12*ASSUMPTIONS!$B$92,0),0),0) -> 10833 | AJ21: =IFERROR(IF(35>=1,ROUND(100000/12*ASSUMPTIONS!$B$92,0),0),0) -> 10833 | AK21: =IFERROR(IF(36>=1,ROUND(100000/12*ASSUMPTIONS!$B$92,0),0),0) -> 10833
A22: AE #1 | B22: =IFERROR(IF(1>=4,ROUND(85000/12*ASSUMPTIONS!$B$92,0),0),0) -> 0 | C22: =IFERROR(IF(2>=4,ROUND(85000/12*ASSUMPTIONS!$B$92,0),0),0) -> 0 | D22: =IFERROR(IF(3>=4,ROUND(85000/12*ASSUMPTIONS!$B$92,0),0),0) -> 0 | E22: =IFERROR(IF(4>=4,ROUND(85000/12*ASSUMPTIONS!$B$92,0),0),0) -> 9208 | F22: =IFERROR(IF(5>=4,ROUND(85000/12*ASSUMPTIONS!$B$92,0),0),0) -> 9208 | G22: =IFERROR(IF(6>=4,ROUND(85000/12*ASSUMPTIONS!$B$92,0),0),0) -> 9208 | H22: =IFERROR(IF(7>=4,ROUND(85000/12*ASSUMPTIONS!$B$92,0),0),0) -> 9208 | I22: =IFERROR(IF(8>=4,ROUND(85000/12*ASSUMPTIONS!$B$92,0),0),0) -> 9208 | J22: =IFERROR(IF(9>=4,ROUND(85000/12*ASSUMPTIONS!$B$92,0),0),0) -> 9208 | K22: =IFERROR(IF(10>=4,ROUND(85000/12*ASSUMPTIONS!$B$92,0),0),0) -> 9208 | L22: =IFERROR(IF(11>=4,ROUND(85000/12*ASSUMPTIONS!$B$92,0),0),0) -> 9208 | M22: =IFERROR(IF(12>=4,ROUND(85000/12*ASSUMPTIONS!$B$92,0),0),0) -> 9208 | N22: =IFERROR(IF(13>=4,ROUND(85000/12*ASSUMPTIONS!$B$92,0),0),0) -> 9208 | O22: =IFERROR(IF(14>=4,ROUND(85000/12*ASSUMPTIONS!$B$92,0),0),0) -> 9208 | P22: =IFERROR(IF(15>=4,ROUND(85000/12*ASSUMPTIONS!$B$92,0),0),0) -> 9208 | Q22: =IFERROR(IF(16>=4,ROUND(85000/12*ASSUMPTIONS!$B$92,0),0),0) -> 9208 | R22: =IFERROR(IF(17>=4,ROUND(85000/12*ASSUMPTIONS!$B$92,0),0),0) -> 9208 | S22: =IFERROR(IF(18>=4,ROUND(85000/12*ASSUMPTIONS!$B$92,0),0),0) -> 9208 | T22: =IFERROR(IF(19>=4,ROUND(85000/12*ASSUMPTIONS!$B$92,0),0),0) -> 9208 | U22: =IFERROR(IF(20>=4,ROUND(85000/12*ASSUMPTIONS!$B$92,0),0),0) -> 9208 | V22: =IFERROR(IF(21>=4,ROUND(85000/12*ASSUMPTIONS!$B$92,0),0),0) -> 9208 | W22: =IFERROR(IF(22>=4,ROUND(85000/12*ASSUMPTIONS!$B$92,0),0),0) -> 9208 | X22: =IFERROR(IF(23>=4,ROUND(85000/12*ASSUMPTIONS!$B$92,0),0),0) -> 9208 | Y22: =IFERROR(IF(24>=4,ROUND(85000/12*ASSUMPTIONS!$B$92,0),0),0) -> 9208 | Z22: =IFERROR(IF(25>=4,ROUND(85000/12*ASSUMPTIONS!$B$92,0),0),0) -> 9208 | AA22: =IFERROR(IF(26>=4,ROUND(85000/12*ASSUMPTIONS!$B$92,0),0),0) -> 9208 | AB22: =IFERROR(IF(27>=4,ROUND(85000/12*ASSUMPTIONS!$B$92,0),0),0) -> 9208 | AC22: =IFERROR(IF(28>=4,ROUND(85000/12*ASSUMPTIONS!$B$92,0),0),0) -> 9208 | AD22: =IFERROR(IF(29>=4,ROUND(85000/12*ASSUMPTIONS!$B$92,0),0),0) -> 9208 | AE22: =IFERROR(IF(30>=4,ROUND(85000/12*ASSUMPTIONS!$B$92,0),0),0) -> 9208 | AF22: =IFERROR(IF(31>=4,ROUND(85000/12*ASSUMPTIONS!$B$92,0),0),0) -> 9208 | AG22: =IFERROR(IF(32>=4,ROUND(85000/12*ASSUMPTIONS!$B$92,0),0),0) -> 9208 | AH22: =IFERROR(IF(33>=4,ROUND(85000/12*ASSUMPTIONS!$B$92,0),0),0) -> 9208 | AI22: =IFERROR(IF(34>=4,ROUND(85000/12*ASSUMPTIONS!$B$92,0),0),0) -> 9208 | AJ22: =IFERROR(IF(35>=4,ROUND(85000/12*ASSUMPTIONS!$B$92,0),0),0) -> 9208 | AK22: =IFERROR(IF(36>=4,ROUND(85000/12*ASSUMPTIONS!$B$92,0),0),0) -> 9208
A23: AE #2 | B23: =IFERROR(IF(1>=8,ROUND(85000/12*ASSUMPTIONS!$B$92,0),0),0) -> 0 | C23: =IFERROR(IF(2>=8,ROUND(85000/12*ASSUMPTIONS!$B$92,0),0),0) -> 0 | D23: =IFERROR(IF(3>=8,ROUND(85000/12*ASSUMPTIONS!$B$92,0),0),0) -> 0 | E23: =IFERROR(IF(4>=8,ROUND(85000/12*ASSUMPTIONS!$B$92,0),0),0) -> 0 | F23: =IFERROR(IF(5>=8,ROUND(85000/12*ASSUMPTIONS!$B$92,0),0),0) -> 0 | G23: =IFERROR(IF(6>=8,ROUND(85000/12*ASSUMPTIONS!$B$92,0),0),0) -> 0 | H23: =IFERROR(IF(7>=8,ROUND(85000/12*ASSUMPTIONS!$B$92,0),0),0) -> 0 | I23: =IFERROR(IF(8>=8,ROUND(85000/12*ASSUMPTIONS!$B$92,0),0),0) -> 9208 | J23: =IFERROR(IF(9>=8,ROUND(85000/12*ASSUMPTIONS!$B$92,0),0),0) -> 9208 | K23: =IFERROR(IF(10>=8,ROUND(85000/12*ASSUMPTIONS!$B$92,0),0),0) -> 9208 | L23: =IFERROR(IF(11>=8,ROUND(85000/12*ASSUMPTIONS!$B$92,0),0),0) -> 9208 | M23: =IFERROR(IF(12>=8,ROUND(85000/12*ASSUMPTIONS!$B$92,0),0),0) -> 9208 | N23: =IFERROR(IF(13>=8,ROUND(85000/12*ASSUMPTIONS!$B$92,0),0),0) -> 9208 | O23: =IFERROR(IF(14>=8,ROUND(85000/12*ASSUMPTIONS!$B$92,0),0),0) -> 9208 | P23: =IFERROR(IF(15>=8,ROUND(85000/12*ASSUMPTIONS!$B$92,0),0),0) -> 9208 | Q23: =IFERROR(IF(16>=8,ROUND(85000/12*ASSUMPTIONS!$B$92,0),0),0) -> 9208 | R23: =IFERROR(IF(17>=8,ROUND(85000/12*ASSUMPTIONS!$B$92,0),0),0) -> 9208 | S23: =IFERROR(IF(18>=8,ROUND(85000/12*ASSUMPTIONS!$B$92,0),0),0) -> 9208 | T23: =IFERROR(IF(19>=8,ROUND(85000/12*ASSUMPTIONS!$B$92,0),0),0) -> 9208 | U23: =IFERROR(IF(20>=8,ROUND(85000/12*ASSUMPTIONS!$B$92,0),0),0) -> 9208 | V23: =IFERROR(IF(21>=8,ROUND(85000/12*ASSUMPTIONS!$B$92,0),0),0) -> 9208 | W23: =IFERROR(IF(22>=8,ROUND(85000/12*ASSUMPTIONS!$B$92,0),0),0) -> 9208 | X23: =IFERROR(IF(23>=8,ROUND(85000/12*ASSUMPTIONS!$B$92,0),0),0) -> 9208 | Y23: =IFERROR(IF(24>=8,ROUND(85000/12*ASSUMPTIONS!$B$92,0),0),0) -> 9208 | Z23: =IFERROR(IF(25>=8,ROUND(85000/12*ASSUMPTIONS!$B$92,0),0),0) -> 9208 | AA23: =IFERROR(IF(26>=8,ROUND(85000/12*ASSUMPTIONS!$B$92,0),0),0) -> 9208 | AB23: =IFERROR(IF(27>=8,ROUND(85000/12*ASSUMPTIONS!$B$92,0),0),0) -> 9208 | AC23: =IFERROR(IF(28>=8,ROUND(85000/12*ASSUMPTIONS!$B$92,0),0),0) -> 9208 | AD23: =IFERROR(IF(29>=8,ROUND(85000/12*ASSUMPTIONS!$B$92,0),0),0) -> 9208 | AE23: =IFERROR(IF(30>=8,ROUND(85000/12*ASSUMPTIONS!$B$92,0),0),0) -> 9208 | AF23: =IFERROR(IF(31>=8,ROUND(85000/12*ASSUMPTIONS!$B$92,0),0),0) -> 9208 | AG23: =IFERROR(IF(32>=8,ROUND(85000/12*ASSUMPTIONS!$B$92,0),0),0) -> 9208 | AH23: =IFERROR(IF(33>=8,ROUND(85000/12*ASSUMPTIONS!$B$92,0),0),0) -> 9208 | AI23: =IFERROR(IF(34>=8,ROUND(85000/12*ASSUMPTIONS!$B$92,0),0),0) -> 9208 | AJ23: =IFERROR(IF(35>=8,ROUND(85000/12*ASSUMPTIONS!$B$92,0),0),0) -> 9208 | AK23: =IFERROR(IF(36>=8,ROUND(85000/12*ASSUMPTIONS!$B$92,0),0),0) -> 9208
A24: SDR | B24: =IFERROR(IF(1>=6,ROUND(55000/12*ASSUMPTIONS!$B$92,0),0),0) -> 0 | C24: =IFERROR(IF(2>=6,ROUND(55000/12*ASSUMPTIONS!$B$92,0),0),0) -> 0 | D24: =IFERROR(IF(3>=6,ROUND(55000/12*ASSUMPTIONS!$B$92,0),0),0) -> 0 | E24: =IFERROR(IF(4>=6,ROUND(55000/12*ASSUMPTIONS!$B$92,0),0),0) -> 0 | F24: =IFERROR(IF(5>=6,ROUND(55000/12*ASSUMPTIONS!$B$92,0),0),0) -> 0 | G24: =IFERROR(IF(6>=6,ROUND(55000/12*ASSUMPTIONS!$B$92,0),0),0) -> 5958 | H24: =IFERROR(IF(7>=6,ROUND(55000/12*ASSUMPTIONS!$B$92,0),0),0) -> 5958 | I24: =IFERROR(IF(8>=6,ROUND(55000/12*ASSUMPTIONS!$B$92,0),0),0) -> 5958 | J24: =IFERROR(IF(9>=6,ROUND(55000/12*ASSUMPTIONS!$B$92,0),0),0) -> 5958 | K24: =IFERROR(IF(10>=6,ROUND(55000/12*ASSUMPTIONS!$B$92,0),0),0) -> 5958 | L24: =IFERROR(IF(11>=6,ROUND(55000/12*ASSUMPTIONS!$B$92,0),0),0) -> 5958 | M24: =IFERROR(IF(12>=6,ROUND(55000/12*ASSUMPTIONS!$B$92,0),0),0) -> 5958 | N24: =IFERROR(IF(13>=6,ROUND(55000/12*ASSUMPTIONS!$B$92,0),0),0) -> 5958 | O24: =IFERROR(IF(14>=6,ROUND(55000/12*ASSUMPTIONS!$B$92,0),0),0) -> 5958 | P24: =IFERROR(IF(15>=6,ROUND(55000/12*ASSUMPTIONS!$B$92,0),0),0) -> 5958 | Q24: =IFERROR(IF(16>=6,ROUND(55000/12*ASSUMPTIONS!$B$92,0),0),0) -> 5958 | R24: =IFERROR(IF(17>=6,ROUND(55000/12*ASSUMPTIONS!$B$92,0),0),0) -> 5958 | S24: =IFERROR(IF(18>=6,ROUND(55000/12*ASSUMPTIONS!$B$92,0),0),0) -> 5958 | T24: =IFERROR(IF(19>=6,ROUND(55000/12*ASSUMPTIONS!$B$92,0),0),0) -> 5958 | U24: =IFERROR(IF(20>=6,ROUND(55000/12*ASSUMPTIONS!$B$92,0),0),0) -> 5958 | V24: =IFERROR(IF(21>=6,ROUND(55000/12*ASSUMPTIONS!$B$92,0),0),0) -> 5958 | W24: =IFERROR(IF(22>=6,ROUND(55000/12*ASSUMPTIONS!$B$92,0),0),0) -> 5958 | X24: =IFERROR(IF(23>=6,ROUND(55000/12*ASSUMPTIONS!$B$92,0),0),0) -> 5958 | Y24: =IFERROR(IF(24>=6,ROUND(55000/12*ASSUMPTIONS!$B$92,0),0),0) -> 5958 | Z24: =IFERROR(IF(25>=6,ROUND(55000/12*ASSUMPTIONS!$B$92,0),0),0) -> 5958 | AA24: =IFERROR(IF(26>=6,ROUND(55000/12*ASSUMPTIONS!$B$92,0),0),0) -> 5958 | AB24: =IFERROR(IF(27>=6,ROUND(55000/12*ASSUMPTIONS!$B$92,0),0),0) -> 5958 | AC24: =IFERROR(IF(28>=6,ROUND(55000/12*ASSUMPTIONS!$B$92,0),0),0) -> 5958 | AD24: =IFERROR(IF(29>=6,ROUND(55000/12*ASSUMPTIONS!$B$92,0),0),0) -> 5958 | AE24: =IFERROR(IF(30>=6,ROUND(55000/12*ASSUMPTIONS!$B$92,0),0),0) -> 5958 | AF24: =IFERROR(IF(31>=6,ROUND(55000/12*ASSUMPTIONS!$B$92,0),0),0) -> 5958 | AG24: =IFERROR(IF(32>=6,ROUND(55000/12*ASSUMPTIONS!$B$92,0),0),0) -> 5958 | AH24: =IFERROR(IF(33>=6,ROUND(55000/12*ASSUMPTIONS!$B$92,0),0),0) -> 5958 | AI24: =IFERROR(IF(34>=6,ROUND(55000/12*ASSUMPTIONS!$B$92,0),0),0) -> 5958 | AJ24: =IFERROR(IF(35>=6,ROUND(55000/12*ASSUMPTIONS!$B$92,0),0),0) -> 5958 | AK24: =IFERROR(IF(36>=6,ROUND(55000/12*ASSUMPTIONS!$B$92,0),0),0) -> 5958
A25: Total SALES ($) | B25: =SUM(B21:B24) -> 10833 | C25: =SUM(C21:C24) -> 10833 | D25: =SUM(D21:D24) -> 10833 | E25: =SUM(E21:E24) -> 20041 | F25: =SUM(F21:F24) -> 20041 | G25: =SUM(G21:G24) -> 25999 | H25: =SUM(H21:H24) -> 25999 | I25: =SUM(I21:I24) -> 35207 | ... AK25: =SUM(AK21:AK24) -> 35207
A26: MARKETING
A27: Marketing Lead | B27: =IFERROR(IF(1>=3,ROUND(95000/12*ASSUMPTIONS!$B$92,0),0),0) -> 0 | C27: =IFERROR(IF(2>=3,ROUND(95000/12*ASSUMPTIONS!$B$92,0),0),0) -> 0 | D27: =IFERROR(IF(3>=3,ROUND(95000/12*ASSUMPTIONS!$B$92,0),0),0) -> 10292 | E27: =IFERROR(IF(4>=3,ROUND(95000/12*ASSUMPTIONS!$B$92,0),0),0) -> 10292 | F27: =IFERROR(IF(5>=3,ROUND(95000/12*ASSUMPTIONS!$B$92,0),0),0) -> 10292 | G27: =IFERROR(IF(6>=3,ROUND(95000/12*ASSUMPTIONS!$B$92,0),0),0) -> 10292 | H27: =IFERROR(IF(7>=3,ROUND(95000/12*ASSUMPTIONS!$B$92,0),0),0) -> 10292 | I27: =IFERROR(IF(8>=3,ROUND(95000/12*ASSUMPTIONS!$B$92,0),0),0) -> 10292 | J27: =IFERROR(IF(9>=3,ROUND(95000/12*ASSUMPTIONS!$B$92,0),0),0) -> 10292 | K27: =IFERROR(IF(10>=3,ROUND(95000/12*ASSUMPTIONS!$B$92,0),0),0) -> 10292 | L27: =IFERROR(IF(11>=3,ROUND(95000/12*ASSUMPTIONS!$B$92,0),0),0) -> 10292 | M27: =IFERROR(IF(12>=3,ROUND(95000/12*ASSUMPTIONS!$B$92,0),0),0) -> 10292 | N27: =IFERROR(IF(13>=3,ROUND(95000/12*ASSUMPTIONS!$B$92,0),0),0) -> 10292 | O27: =IFERROR(IF(14>=3,ROUND(95000/12*ASSUMPTIONS!$B$92,0),0),0) -> 10292 | P27: =IFERROR(IF(15>=3,ROUND(95000/12*ASSUMPTIONS!$B$92,0),0),0) -> 10292 | Q27: =IFERROR(IF(16>=3,ROUND(95000/12*ASSUMPTIONS!$B$92,0),0),0) -> 10292 | R27: =IFERROR(IF(17>=3,ROUND(95000/12*ASSUMPTIONS!$B$92,0),0),0) -> 10292 | S27: =IFERROR(IF(18>=3,ROUND(95000/12*ASSUMPTIONS!$B$92,0),0),0) -> 10292 | T27: =IFERROR(IF(19>=3,ROUND(95000/12*ASSUMPTIONS!$B$92,0),0),0) -> 10292 | U27: =IFERROR(IF(20>=3,ROUND(95000/12*ASSUMPTIONS!$B$92,0),0),0) -> 10292 | V27: =IFERROR(IF(21>=3,ROUND(95000/12*ASSUMPTIONS!$B$92,0),0),0) -> 10292 | W27: =IFERROR(IF(22>=3,ROUND(95000/12*ASSUMPTIONS!$B$92,0),0),0) -> 10292 | X27: =IFERROR(IF(23>=3,ROUND(95000/12*ASSUMPTIONS!$B$92,0),0),0) -> 10292 | Y27: =IFERROR(IF(24>=3,ROUND(95000/12*ASSUMPTIONS!$B$92,0),0),0) -> 10292 | Z27: =IFERROR(IF(25>=3,ROUND(95000/12*ASSUMPTIONS!$B$92,0),0),0) -> 10292 | AA27: =IFERROR(IF(26>=3,ROUND(95000/12*ASSUMPTIONS!$B$92,0),0),0) -> 10292 | AB27: =IFERROR(IF(27>=3,ROUND(95000/12*ASSUMPTIONS!$B$92,0),0),0) -> 10292 | AC27: =IFERROR(IF(28>=3,ROUND(95000/12*ASSUMPTIONS!$B$92,0),0),0) -> 10292 | AD27: =IFERROR(IF(29>=3,ROUND(95000/12*ASSUMPTIONS!$B$92,0),0),0) -> 10292 | AE27: =IFERROR(IF(30>=3,ROUND(95000/12*ASSUMPTIONS!$B$92,0),0),0) -> 10292 | AF27: =IFERROR(IF(31>=3,ROUND(95000/12*ASSUMPTIONS!$B$92,0),0),0) -> 10292 | AG27: =IFERROR(IF(32>=3,ROUND(95000/12*ASSUMPTIONS!$B$92,0),0),0) -> 10292 | AH27: =IFERROR(IF(33>=3,ROUND(95000/12*ASSUMPTIONS!$B$92,0),0),0) -> 10292 | AI27: =IFERROR(IF(34>=3,ROUND(95000/12*ASSUMPTIONS!$B$92,0),0),0) -> 10292 | AJ27: =IFERROR(IF(35>=3,ROUND(95000/12*ASSUMPTIONS!$B$92,0),0),0) -> 10292 | AK27: =IFERROR(IF(36>=3,ROUND(95000/12*ASSUMPTIONS!$B$92,0),0),0) -> 10292
A28: Growth | B28: =IFERROR(IF(1>=6,ROUND(80000/12*ASSUMPTIONS!$B$92,0),0),0) -> 0 | C28: =IFERROR(IF(2>=6,ROUND(80000/12*ASSUMPTIONS!$B$92,0),0),0) -> 0 | D28: =IFERROR(IF(3>=6,ROUND(80000/12*ASSUMPTIONS!$B$92,0),0),0) -> 0 | E28: =IFERROR(IF(4>=6,ROUND(80000/12*ASSUMPTIONS!$B$92,0),0),0) -> 0 | F28: =IFERROR(IF(5>=6,ROUND(80000/12*ASSUMPTIONS!$B$92,0),0),0) -> 0 | G28: =IFERROR(IF(6>=6,ROUND(80000/12*ASSUMPTIONS!$B$92,0),0),0) -> 8667 | H28: =IFERROR(IF(7>=6,ROUND(80000/12*ASSUMPTIONS!$B$92,0),0),0) -> 8667 | I28: =IFERROR(IF(8>=6,ROUND(80000/12*ASSUMPTIONS!$B$92,0),0),0) -> 8667 | J28: =IFERROR(IF(9>=6,ROUND(80000/12*ASSUMPTIONS!$B$92,0),0),0) -> 8667 | K28: =IFERROR(IF(10>=6,ROUND(80000/12*ASSUMPTIONS!$B$92,0),0),0) -> 8667 | L28: =IFERROR(IF(11>=6,ROUND(80000/12*ASSUMPTIONS!$B$92,0),0),0) -> 8667 | M28: =IFERROR(IF(12>=6,ROUND(80000/12*ASSUMPTIONS!$B$92,0),0),0) -> 8667 | N28: =IFERROR(IF(13>=6,ROUND(80000/12*ASSUMPTIONS!$B$92,0),0),0) -> 8667 | O28: =IFERROR(IF(14>=6,ROUND(80000/12*ASSUMPTIONS!$B$92,0),0),0) -> 8667 | P28: =IFERROR(IF(15>=6,ROUND(80000/12*ASSUMPTIONS!$B$92,0),0),0) -> 8667 | Q28: =IFERROR(IF(16>=6,ROUND(80000/12*ASSUMPTIONS!$B$92,0),0),0) -> 8667 | R28: =IFERROR(IF(17>=6,ROUND(80000/12*ASSUMPTIONS!$B$92,0),0),0) -> 8667 | S28: =IFERROR(IF(18>=6,ROUND(80000/12*ASSUMPTIONS!$B$92,0),0),0) -> 8667 | T28: =IFERROR(IF(19>=6,ROUND(80000/12*ASSUMPTIONS!$B$92,0),0),0) -> 8667 | U28: =IFERROR(IF(20>=6,ROUND(80000/12*ASSUMPTIONS!$B$92,0),0),0) -> 8667 | V28: =IFERROR(IF(21>=6,ROUND(80000/12*ASSUMPTIONS!$B$92,0),0),0) -> 8667 | W28: =IFERROR(IF(22>=6,ROUND(80000/12*ASSUMPTIONS!$B$92,0),0),0) -> 8667 | X28: =IFERROR(IF(23>=6,ROUND(80000/12*ASSUMPTIONS!$B$92,0),0),0) -> 8667 | Y28: =IFERROR(IF(24>=6,ROUND(80000/12*ASSUMPTIONS!$B$92,0),0),0) -> 8667 | Z28: =IFERROR(IF(25>=6,ROUND(80000/12*ASSUMPTIONS!$B$92,0),0),0) -> 8667 | AA28: =IFERROR(IF(26>=6,ROUND(80000/12*ASSUMPTIONS!$B$92,0),0),0) -> 8667 | AB28: =IFERROR(IF(27>=6,ROUND(80000/12*ASSUMPTIONS!$B$92,0),0),0) -> 8667 | AC28: =IFERROR(IF(28>=6,ROUND(80000/12*ASSUMPTIONS!$B$92,0),0),0) -> 8667 | AD28: =IFERROR(IF(29>=6,ROUND(80000/12*ASSUMPTIONS!$B$92,0),0),0) -> 8667 | AE28: =IFERROR(IF(30>=6,ROUND(80000/12*ASSUMPTIONS!$B$92,0),0),0) -> 8667 | AF28: =IFERROR(IF(31>=6,ROUND(80000/12*ASSUMPTIONS!$B$92,0),0),0) -> 8667 | AG28: =IFERROR(IF(32>=6,ROUND(80000/12*ASSUMPTIONS!$B$92,0),0),0) -> 8667 | AH28: =IFERROR(IF(33>=6,ROUND(80000/12*ASSUMPTIONS!$B$92,0),0),0) -> 8667 | AI28: =IFERROR(IF(34>=6,ROUND(80000/12*ASSUMPTIONS!$B$92,0),0),0) -> 8667 | AJ28: =IFERROR(IF(35>=6,ROUND(80000/12*ASSUMPTIONS!$B$92,0),0),0) -> 8667 | AK28: =IFERROR(IF(36>=6,ROUND(80000/12*ASSUMPTIONS!$B$92,0),0),0) -> 8667
A29: Total MARKETING ($) | B29: =SUM(B27:B28) -> 0 | C29: =SUM(C27:C28) -> 0 | D29: =SUM(D27:D28) -> 10292 | E29: =SUM(E27:E28) -> 10292 | F29: =SUM(F27:F28) -> 10292 | G29: =SUM(G27:G28) -> 18959 | H29: =SUM(H27:H28) -> 18959 | I29: =SUM(I27:I28) -> 18959 | ... AK29: =SUM(AK27:AK28) -> 18959
A30: CUSTOMER SUCCESS
A31: CS Lead | B31: =IFERROR(IF(1>=4,ROUND(80000/12*ASSUMPTIONS!$B$92,0),0),0) -> 0 | C31: =IFERROR(IF(2>=4,ROUND(80000/12*ASSUMPTIONS!$B$92,0),0),0) -> 0 | D31: =IFERROR(IF(3>=4,ROUND(80000/12*ASSUMPTIONS!$B$92,0),0),0) -> 0 | E31: =IFERROR(IF(4>=4,ROUND(80000/12*ASSUMPTIONS!$B$92,0),0),0) -> 8667 | F31: =IFERROR(IF(5>=4,ROUND(80000/12*ASSUMPTIONS!$B$92,0),0),0) -> 8667 | G31: =IFERROR(IF(6>=4,ROUND(80000/12*ASSUMPTIONS!$B$92,0),0),0) -> 8667 | H31: =IFERROR(IF(7>=4,ROUND(80000/12*ASSUMPTIONS!$B$92,0),0),0) -> 8667 | I31: =IFERROR(IF(8>=4,ROUND(80000/12*ASSUMPTIONS!$B$92,0),0),0) -> 8667 | J31: =IFERROR(IF(9>=4,ROUND(80000/12*ASSUMPTIONS!$B$92,0),0),0) -> 8667 | K31: =IFERROR(IF(10>=4,ROUND(80000/12*ASSUMPTIONS!$B$92,0),0),0) -> 8667 | L31: =IFERROR(IF(11>=4,ROUND(80000/12*ASSUMPTIONS!$B$92,0),0),0) -> 8667 | M31: =IFERROR(IF(12>=4,ROUND(80000/12*ASSUMPTIONS!$B$92,0),0),0) -> 8667 | N31: =IFERROR(IF(13>=4,ROUND(80000/12*ASSUMPTIONS!$B$92,0),0),0) -> 8667 | O31: =IFERROR(IF(14>=4,ROUND(80000/12*ASSUMPTIONS!$B$92,0),0),0) -> 8667 | P31: =IFERROR(IF(15>=4,ROUND(80000/12*ASSUMPTIONS!$B$92,0),0),0) -> 8667 | Q31: =IFERROR(IF(16>=4,ROUND(80000/12*ASSUMPTIONS!$B$92,0),0),0) -> 8667 | R31: =IFERROR(IF(17>=4,ROUND(80000/12*ASSUMPTIONS!$B$92,0),0),0) -> 8667 | S31: =IFERROR(IF(18>=4,ROUND(80000/12*ASSUMPTIONS!$B$92,0),0),0) -> 8667 | T31: =IFERROR(IF(19>=4,ROUND(80000/12*ASSUMPTIONS!$B$92,0),0),0) -> 8667 | U31: =IFERROR(IF(20>=4,ROUND(80000/12*ASSUMPTIONS!$B$92,0),0),0) -> 8667 | V31: =IFERROR(IF(21>=4,ROUND(80000/12*ASSUMPTIONS!$B$92,0),0),0) -> 8667 | W31: =IFERROR(IF(22>=4,ROUND(80000/12*ASSUMPTIONS!$B$92,0),0),0) -> 8667 | X31: =IFERROR(IF(23>=4,ROUND(80000/12*ASSUMPTIONS!$B$92,0),0),0) -> 8667 | Y31: =IFERROR(IF(24>=4,ROUND(80000/12*ASSUMPTIONS!$B$92,0),0),0) -> 8667 | Z31: =IFERROR(IF(25>=4,ROUND(80000/12*ASSUMPTIONS!$B$92,0),0),0) -> 8667 | AA31: =IFERROR(IF(26>=4,ROUND(80000/12*ASSUMPTIONS!$B$92,0),0),0) -> 8667 | AB31: =IFERROR(IF(27>=4,ROUND(80000/12*ASSUMPTIONS!$B$92,0),0),0) -> 8667 | AC31: =IFERROR(IF(28>=4,ROUND(80000/12*ASSUMPTIONS!$B$92,0),0),0) -> 8667 | AD31: =IFERROR(IF(29>=4,ROUND(80000/12*ASSUMPTIONS!$B$92,0),0),0) -> 8667 | AE31: =IFERROR(IF(30>=4,ROUND(80000/12*ASSUMPTIONS!$B$92,0),0),0) -> 8667 | AF31: =IFERROR(IF(31>=4,ROUND(80000/12*ASSUMPTIONS!$B$92,0),0),0) -> 8667 | AG31: =IFERROR(IF(32>=4,ROUND(80000/12*ASSUMPTIONS!$B$92,0),0),0) -> 8667 | AH31: =IFERROR(IF(33>=4,ROUND(80000/12*ASSUMPTIONS!$B$92,0),0),0) -> 8667 | AI31: =IFERROR(IF(34>=4,ROUND(80000/12*ASSUMPTIONS!$B$92,0),0),0) -> 8667 | AJ31: =IFERROR(IF(35>=4,ROUND(80000/12*ASSUMPTIONS!$B$92,0),0),0) -> 8667 | AK31: =IFERROR(IF(36>=4,ROUND(80000/12*ASSUMPTIONS!$B$92,0),0),0) -> 8667
A32: CS #1 | B32: =IFERROR(IF(1>=8,ROUND(60000/12*ASSUMPTIONS!$B$92,0),0),0) -> 0 | C32: =IFERROR(IF(2>=8,ROUND(60000/12*ASSUMPTIONS!$B$92,0),0),0) -> 0 | D32: =IFERROR(IF(3>=8,ROUND(60000/12*ASSUMPTIONS!$B$92,0),0),0) -> 0 | E32: =IFERROR(IF(4>=8,ROUND(60000/12*ASSUMPTIONS!$B$92,0),0),0) -> 0 | F32: =IFERROR(IF(5>=8,ROUND(60000/12*ASSUMPTIONS!$B$92,0),0),0) -> 0 | G32: =IFERROR(IF(6>=8,ROUND(60000/12*ASSUMPTIONS!$B$92,0),0),0) -> 0 | H32: =IFERROR(IF(7>=8,ROUND(60000/12*ASSUMPTIONS!$B$92,0),0),0) -> 0 | I32: =IFERROR(IF(8>=8,ROUND(60000/12*ASSUMPTIONS!$B$92,0),0),0) -> 6500 | J32: =IFERROR(IF(9>=8,ROUND(60000/12*ASSUMPTIONS!$B$92,0),0),0) -> 6500 | K32: =IFERROR(IF(10>=8,ROUND(60000/12*ASSUMPTIONS!$B$92,0),0),0) -> 6500 | L32: =IFERROR(IF(11>=8,ROUND(60000/12*ASSUMPTIONS!$B$92,0),0),0) -> 6500 | M32: =IFERROR(IF(12>=8,ROUND(60000/12*ASSUMPTIONS!$B$92,0),0),0) -> 6500 | N32: =IFERROR(IF(13>=8,ROUND(60000/12*ASSUMPTIONS!$B$92,0),0),0) -> 6500 | O32: =IFERROR(IF(14>=8,ROUND(60000/12*ASSUMPTIONS!$B$92,0),0),0) -> 6500 | P32: =IFERROR(IF(15>=8,ROUND(60000/12*ASSUMPTIONS!$B$92,0),0),0) -> 6500 | Q32: =IFERROR(IF(16>=8,ROUND(60000/12*ASSUMPTIONS!$B$92,0),0),0) -> 6500 | R32: =IFERROR(IF(17>=8,ROUND(60000/12*ASSUMPTIONS!$B$92,0),0),0) -> 6500 | S32: =IFERROR(IF(18>=8,ROUND(60000/12*ASSUMPTIONS!$B$92,0),0),0) -> 6500 | T32: =IFERROR(IF(19>=8,ROUND(60000/12*ASSUMPTIONS!$B$92,0),0),0) -> 6500 | U32: =IFERROR(IF(20>=8,ROUND(60000/12*ASSUMPTIONS!$B$92,0),0),0) -> 6500 | V32: =IFERROR(IF(21>=8,ROUND(60000/12*ASSUMPTIONS!$B$92,0),0),0) -> 6500 | W32: =IFERROR(IF(22>=8,ROUND(60000/12*ASSUMPTIONS!$B$92,0),0),0) -> 6500 | X32: =IFERROR(IF(23>=8,ROUND(60000/12*ASSUMPTIONS!$B$92,0),0),0) -> 6500 | Y32: =IFERROR(IF(24>=8,ROUND(60000/12*ASSUMPTIONS!$B$92,0),0),0) -> 6500 | Z32: =IFERROR(IF(25>=8,ROUND(60000/12*ASSUMPTIONS!$B$92,0),0),0) -> 6500 | AA32: =IFERROR(IF(26>=8,ROUND(60000/12*ASSUMPTIONS!$B$92,0),0),0) -> 6500 | AB32: =IFERROR(IF(27>=8,ROUND(60000/12*ASSUMPTIONS!$B$92,0),0),0) -> 6500 | AC32: =IFERROR(IF(28>=8,ROUND(60000/12*ASSUMPTIONS!$B$92,0),0),0) -> 6500 | AD32: =IFERROR(IF(29>=8,ROUND(60000/12*ASSUMPTIONS!$B$92,0),0),0) -> 6500 | AE32: =IFERROR(IF(30>=8,ROUND(60000/12*ASSUMPTIONS!$B$92,0),0),0) -> 6500 | AF32: =IFERROR(IF(31>=8,ROUND(60000/12*ASSUMPTIONS!$B$92,0),0),0) -> 6500 | AG32: =IFERROR(IF(32>=8,ROUND(60000/12*ASSUMPTIONS!$B$92,0),0),0) -> 6500 | AH32: =IFERROR(IF(33>=8,ROUND(60000/12*ASSUMPTIONS!$B$92,0),0),0) -> 6500 | AI32: =IFERROR(IF(34>=8,ROUND(60000/12*ASSUMPTIONS!$B$92,0),0),0) -> 6500 | AJ32: =IFERROR(IF(35>=8,ROUND(60000/12*ASSUMPTIONS!$B$92,0),0),0) -> 6500 | AK32: =IFERROR(IF(36>=8,ROUND(60000/12*ASSUMPTIONS!$B$92,0),0),0) -> 6500
A33: Total CUSTOMER SUCCESS ($) | B33: =SUM(B31:B32) -> 0 | C33: =SUM(C31:C32) -> 0 | D33: =SUM(D31:D32) -> 0 | E33: =SUM(E31:E32) -> 8667 | F33: =SUM(F31:F32) -> 8667 | G33: =SUM(G31:G32) -> 8667 | H33: =SUM(H31:H32) -> 8667 | I33: =SUM(I31:I32) -> 15167 | ... AK33: =SUM(AK31:AK32) -> 15167
A34: G&A
A35: CEO | B35: =IFERROR(IF(1>=1,ROUND(120000/12*ASSUMPTIONS!$B$92,0),0),0) -> 13000 | C35: =IFERROR(IF(2>=1,ROUND(120000/12*ASSUMPTIONS!$B$92,0),0),0) -> 13000 | D35: =IFERROR(IF(3>=1,ROUND(120000/12*ASSUMPTIONS!$B$92,0),0),0) -> 13000 | E35: =IFERROR(IF(4>=1,ROUND(120000/12*ASSUMPTIONS!$B$92,0),0),0) -> 13000 | F35: =IFERROR(IF(5>=1,ROUND(120000/12*ASSUMPTIONS!$B$92,0),0),0) -> 13000 | G35: =IFERROR(IF(6>=1,ROUND(120000/12*ASSUMPTIONS!$B$92,0),0),0) -> 13000 | H35: =IFERROR(IF(7>=1,ROUND(120000/12*ASSUMPTIONS!$B$92,0),0),0) -> 13000 | I35: =IFERROR(IF(8>=1,ROUND(120000/12*ASSUMPTIONS!$B$92,0),0),0) -> 13000 | J35: =IFERROR(IF(9>=1,ROUND(120000/12*ASSUMPTIONS!$B$92,0),0),0) -> 13000 | K35: =IFERROR(IF(10>=1,ROUND(120000/12*ASSUMPTIONS!$B$92,0),0),0) -> 13000 | L35: =IFERROR(IF(11>=1,ROUND(120000/12*ASSUMPTIONS!$B$92,0),0),0) -> 13000 | M35: =IFERROR(IF(12>=1,ROUND(120000/12*ASSUMPTIONS!$B$92,0),0),0) -> 13000 | N35: =IFERROR(IF(13>=1,ROUND(120000/12*ASSUMPTIONS!$B$92,0),0),0) -> 13000 | O35: =IFERROR(IF(14>=1,ROUND(120000/12*ASSUMPTIONS!$B$92,0),0),0) -> 13000 | P35: =IFERROR(IF(15>=1,ROUND(120000/12*ASSUMPTIONS!$B$92,0),0),0) -> 13000 | Q35: =IFERROR(IF(16>=1,ROUND(120000/12*ASSUMPTIONS!$B$92,0),0),0) -> 13000 | R35: =IFERROR(IF(17>=1,ROUND(120000/12*ASSUMPTIONS!$B$92,0),0),0) -> 13000 | S35: =IFERROR(IF(18>=1,ROUND(120000/12*ASSUMPTIONS!$B$92,0),0),0) -> 13000 | T35: =IFERROR(IF(19>=1,ROUND(120000/12*ASSUMPTIONS!$B$92,0),0),0) -> 13000 | U35: =IFERROR(IF(20>=1,ROUND(120000/12*ASSUMPTIONS!$B$92,0),0),0) -> 13000 | V35: =IFERROR(IF(21>=1,ROUND(120000/12*ASSUMPTIONS!$B$92,0),0),0) -> 13000 | W35: =IFERROR(IF(22>=1,ROUND(120000/12*ASSUMPTIONS!$B$92,0),0),0) -> 13000 | X35: =IFERROR(IF(23>=1,ROUND(120000/12*ASSUMPTIONS!$B$92,0),0),0) -> 13000 | Y35: =IFERROR(IF(24>=1,ROUND(120000/12*ASSUMPTIONS!$B$92,0),0),0) -> 13000 | Z35: =IFERROR(IF(25>=1,ROUND(120000/12*ASSUMPTIONS!$B$92,0),0),0) -> 13000 | AA35: =IFERROR(IF(26>=1,ROUND(120000/12*ASSUMPTIONS!$B$92,0),0),0) -> 13000 | AB35: =IFERROR(IF(27>=1,ROUND(120000/12*ASSUMPTIONS!$B$92,0),0),0) -> 13000 | AC35: =IFERROR(IF(28>=1,ROUND(120000/12*ASSUMPTIONS!$B$92,0),0),0) -> 13000 | AD35: =IFERROR(IF(29>=1,ROUND(120000/12*ASSUMPTIONS!$B$92,0),0),0) -> 13000 | AE35: =IFERROR(IF(30>=1,ROUND(120000/12*ASSUMPTIONS!$B$92,0),0),0) -> 13000 | AF35: =IFERROR(IF(31>=1,ROUND(120000/12*ASSUMPTIONS!$B$92,0),0),0) -> 13000 | AG35: =IFERROR(IF(32>=1,ROUND(120000/12*ASSUMPTIONS!$B$92,0),0),0) -> 13000 | AH35: =IFERROR(IF(33>=1,ROUND(120000/12*ASSUMPTIONS!$B$92,0),0),0) -> 13000 | AI35: =IFERROR(IF(34>=1,ROUND(120000/12*ASSUMPTIONS!$B$92,0),0),0) -> 13000 | AJ35: =IFERROR(IF(35>=1,ROUND(120000/12*ASSUMPTIONS!$B$92,0),0),0) -> 13000 | AK35: =IFERROR(IF(36>=1,ROUND(120000/12*ASSUMPTIONS!$B$92,0),0),0) -> 13000
A36: Ops/Finance | B36: =IFERROR(IF(1>=6,ROUND(90000/12*ASSUMPTIONS!$B$92,0),0),0) -> 0 | C36: =IFERROR(IF(2>=6,ROUND(90000/12*ASSUMPTIONS!$B$92,0),0),0) -> 0 | D36: =IFERROR(IF(3>=6,ROUND(90000/12*ASSUMPTIONS!$B$92,0),0),0) -> 0 | E36: =IFERROR(IF(4>=6,ROUND(90000/12*ASSUMPTIONS!$B$92,0),0),0) -> 0 | F36: =IFERROR(IF(5>=6,ROUND(90000/12*ASSUMPTIONS!$B$92,0),0),0) -> 0 | G36: =IFERROR(IF(6>=6,ROUND(90000/12*ASSUMPTIONS!$B$92,0),0),0) -> 9750 | H36: =IFERROR(IF(7>=6,ROUND(90000/12*ASSUMPTIONS!$B$92,0),0),0) -> 9750 | I36: =IFERROR(IF(8>=6,ROUND(90000/12*ASSUMPTIONS!$B$92,0),0),0) -> 9750 | J36: =IFERROR(IF(9>=6,ROUND(90000/12*ASSUMPTIONS!$B$92,0),0),0) -> 9750 | K36: =IFERROR(IF(10>=6,ROUND(90000/12*ASSUMPTIONS!$B$92,0),0),0) -> 9750 | L36: =IFERROR(IF(11>=6,ROUND(90000/12*ASSUMPTIONS!$B$92,0),0),0) -> 9750 | M36: =IFERROR(IF(12>=6,ROUND(90000/12*ASSUMPTIONS!$B$92,0),0),0) -> 9750 | N36: =IFERROR(IF(13>=6,ROUND(90000/12*ASSUMPTIONS!$B$92,0),0),0) -> 9750 | O36: =IFERROR(IF(14>=6,ROUND(90000/12*ASSUMPTIONS!$B$92,0),0),0) -> 9750 | P36: =IFERROR(IF(15>=6,ROUND(90000/12*ASSUMPTIONS!$B$92,0),0),0) -> 9750 | Q36: =IFERROR(IF(16>=6,ROUND(90000/12*ASSUMPTIONS!$B$92,0),0),0) -> 9750 | R36: =IFERROR(IF(17>=6,ROUND(90000/12*ASSUMPTIONS!$B$92,0),0),0) -> 9750 | S36: =IFERROR(IF(18>=6,ROUND(90000/12*ASSUMPTIONS!$B$92,0),0),0) -> 9750 | T36: =IFERROR(IF(19>=6,ROUND(90000/12*ASSUMPTIONS!$B$92,0),0),0) -> 9750 | U36: =IFERROR(IF(20>=6,ROUND(90000/12*ASSUMPTIONS!$B$92,0),0),0) -> 9750 | V36: =IFERROR(IF(21>=6,ROUND(90000/12*ASSUMPTIONS!$B$92,0),0),0) -> 9750 | W36: =IFERROR(IF(22>=6,ROUND(90000/12*ASSUMPTIONS!$B$92,0),0),0) -> 9750 | X36: =IFERROR(IF(23>=6,ROUND(90000/12*ASSUMPTIONS!$B$92,0),0),0) -> 9750 | Y36: =IFERROR(IF(24>=6,ROUND(90000/12*ASSUMPTIONS!$B$92,0),0),0) -> 9750 | Z36: =IFERROR(IF(25>=6,ROUND(90000/12*ASSUMPTIONS!$B$92,0),0),0) -> 9750 | AA36: =IFERROR(IF(26>=6,ROUND(90000/12*ASSUMPTIONS!$B$92,0),0),0) -> 9750 | AB36: =IFERROR(IF(27>=6,ROUND(90000/12*ASSUMPTIONS!$B$92,0),0),0) -> 9750 | AC36: =IFERROR(IF(28>=6,ROUND(90000/12*ASSUMPTIONS!$B$92,0),0),0) -> 9750 | AD36: =IFERROR(IF(29>=6,ROUND(90000/12*ASSUMPTIONS!$B$92,0),0),0) -> 9750 | AE36: =IFERROR(IF(30>=6,ROUND(90000/12*ASSUMPTIONS!$B$92,0),0),0) -> 9750 | AF36: =IFERROR(IF(31>=6,ROUND(90000/12*ASSUMPTIONS!$B$92,0),0),0) -> 9750 | AG36: =IFERROR(IF(32>=6,ROUND(90000/12*ASSUMPTIONS!$B$92,0),0),0) -> 9750 | AH36: =IFERROR(IF(33>=6,ROUND(90000/12*ASSUMPTIONS!$B$92,0),0),0) -> 9750 | AI36: =IFERROR(IF(34>=6,ROUND(90000/12*ASSUMPTIONS!$B$92,0),0),0) -> 9750 | AJ36: =IFERROR(IF(35>=6,ROUND(90000/12*ASSUMPTIONS!$B$92,0),0),0) -> 9750 | AK36: =IFERROR(IF(36>=6,ROUND(90000/12*ASSUMPTIONS!$B$92,0),0),0) -> 9750
A37: Total G&A ($) | B37: =SUM(B35:B36) -> 13000 | C37: =SUM(C35:C36) -> 13000 | D37: =SUM(D35:D36) -> 13000 | E37: =SUM(E35:E36) -> 13000 | F37: =SUM(F35:F36) -> 13000 | G37: =SUM(G35:G36) -> 22750 | H37: =SUM(H35:H36) -> 22750 | I37: =SUM(I35:I36) -> 22750 | ... AK37: =SUM(AK35:AK36) -> 22750
A39: TOTAL HEADCOUNT COST ($) | B39: =B14+B19+B25+B29+B33+B37 -> 53083 | C39: =C14+C19+C25+C29+C33+C37 -> 53083 | D39: =D14+D19+D25+D29+D33+D37 -> 90458 | E39: =E14+E19+E25+E29+E33+E37 -> 118625 | F39: =F14+F19+F25+F29+F33+F37 -> 118625 | G39: =G14+G19+G25+G29+G33+G37 -> 167917 | H39: =H14+H19+H25+H29+H33+H37 -> 167917 | I39: =I14+I19+I25+I29+I33+I37 -> 183625 | ... AK39: =AK14+AK19+AK25+AK29+AK33+AK37 -> 209625

Sheet P&L
A1: PROFIT & LOSS STATEMENT
A2: Auto from REVENUE + HEADCOUNT. Green = cross-sheet.
B4: YEAR 1 | N4: YEAR 2 | Z4: YEAR 3
B5: Jan | C5: Feb | D5: Mar | E5: Apr | F5: May | G5: Jun | H5: Jul | I5: Aug | J5: Sep | K5: Oct | L5: Nov | M5: Dec | N5: Jan | O5: Feb | P5: Mar | Q5: Apr | R5: May | S5: Jun | T5: Jul | U5: Aug | V5: Sep | W5: Oct | X5: Nov | Y5: Dec | Z5: Jan | AA5: Feb | AB5: Mar | AC5: Apr | AD5: May | AE5: Jun | AF5: Jul | AG5: Aug | AH5: Sep | AI5: Oct | AJ5: Nov | AK5: Dec | AL5: Y1 Total | AM5: Y2 Total | AN5: Y3 Total
A6: REVENUE
A8: Marketplace Revenue ($) | B8: =IFERROR(REVENUE!B19,0) -> 5995 | C8: =IFERROR(REVENUE!C19,0) -> 7500 | D8: =IFERROR(REVENUE!D19,0) -> 9005 | E8: =IFERROR(REVENUE!E19,0) -> 10510 | F8: =IFERROR(REVENUE!F19,0) -> 12105 | G8: =IFERROR(REVENUE!G19,0) -> 13790 | H8: =IFERROR(REVENUE!H19,0) -> 15516 | I8: =IFERROR(REVENUE!I19,0) -> 17422 | ... AK8: =IFERROR(REVENUE!AK19,0) -> 169891
A9: SaaS Revenue ($) | B9: =IFERROR(REVENUE!B25,0) -> 2838 | C9: =IFERROR(REVENUE!C25,0) -> 3870 | D9: =IFERROR(REVENUE!D25,0) -> 5031 | E9: =IFERROR(REVENUE!E25,0) -> 6321 | F9: =IFERROR(REVENUE!F25,0) -> 7611 | G9: =IFERROR(REVENUE!G25,0) -> 9030 | H9: =IFERROR(REVENUE!H25,0) -> 10578 | I9: =IFERROR(REVENUE!I25,0) -> 12126 | ... AK9: =IFERROR(REVENUE!AK25,0) -> 147834
A10: TOTAL REVENUE ($) | B10: =B8+B9 -> 8833 | C10: =C8+C9 -> 11370 | D10: =D8+D9 -> 14036 | E10: =E8+E9 -> 16831 | F10: =F8+F9 -> 19716 | G10: =G8+G9 -> 22820 | H10: =H8+H9 -> 26094 | I10: =I8+I9 -> 29548 | ... AK10: =AK8+AK9 -> 317725
A12: COST OF GOODS SOLD
A13: COGS ($) | B13: =IFERROR((REVENUE!B9+REVENUE!B24)*(ASSUMPTIONS!$B$60+ASSUMPTIONS!$B$62)+B10*ASSUMPTIONS!$B$61,0) -> 745.825 | C13: =IFERROR((REVENUE!C9+REVENUE!C24)*(ASSUMPTIONS!$B$60+ASSUMPTIONS!$B$62)+C10*ASSUMPTIONS!$B$61,0) -> 963.25 | D13: =IFERROR((REVENUE!D9+REVENUE!D24)*(ASSUMPTIONS!$B$60+ASSUMPTIONS!$B$62)+D10*ASSUMPTIONS!$B$61,0) -> 1190.9 | E13: =IFERROR((REVENUE!E9+REVENUE!E24)*(ASSUMPTIONS!$B$60+ASSUMPTIONS!$B$62)+E10*ASSUMPTIONS!$B$61,0) -> 1428.775 | F13: =IFERROR((REVENUE!F9+REVENUE!F24)*(ASSUMPTIONS!$B$60+ASSUMPTIONS!$B$62)+F10*ASSUMPTIONS!$B$61,0) -> 1675.9 | G13: =IFERROR((REVENUE!G9+REVENUE!G24)*(ASSUMPTIONS!$B$60+ASSUMPTIONS!$B$62)+G10*ASSUMPTIONS!$B$61,0) -> 1942.5 | H13: =IFERROR((REVENUE!H9+REVENUE!H24)*(ASSUMPTIONS!$B$60+ASSUMPTIONS!$B$62)+H10*ASSUMPTIONS!$B$61,0) -> 2227.35 | I13: =IFERROR((REVENUE!I9+REVENUE!I24)*(ASSUMPTIONS!$B$60+ASSUMPTIONS!$B$62)+I10*ASSUMPTIONS!$B$61,0) -> 2530.7 | ... AK13: =IFERROR((REVENUE!AK9+REVENUE!AK24)*(ASSUMPTIONS!$B$60+ASSUMPTIONS!$B$62)+AK10*ASSUMPTIONS!$B$61,0) -> 28649.125
A14: GROSS PROFIT ($) | B14: =B10-B13 -> 8087.175 | C14: =C10-C13 -> 10406.75 | D14: =D10-D13 -> 12845.1 | E14: =E10-E13 -> 15402.225 | F14: =F10-F13 -> 18040.1 | G14: =G10-G13 -> 20877.5 | H14: =H10-H13 -> 23866.65 | I14: =I10-I13 -> 27017.3 | ... AK14: =AK10-AK13 -> 289075.88
A15: Gross Margin % | B15: =IFERROR(B14/B10,0) -> 0.91556379 | C15: =IFERROR(C14/C10,0) -> 0.91528144 | D15: =IFERROR(D14/D10,0) -> 0.91515389 | E15: =IFERROR(E14/E10,0) -> 0.91511051 | F15: =IFERROR(F14/F10,0) -> 0.91499797 | G15: =IFERROR(G14/G10,0) -> 0.9148773 | H15: =IFERROR(H14/H10,0) -> 0.9146413 | I15: =IFERROR(I14/I10,0) -> 0.91435292 | ... AK15: =IFERROR(AK14/AK10,0) -> 0.90983044
A17: OPERATING EXPENSES
A18: Headcount ($) | B18: =IFERROR(HEADCOUNT!B39,0) -> 53083 | C18: =IFERROR(HEADCOUNT!C39,0) -> 53083 | D18: =IFERROR(HEADCOUNT!D39,0) -> 90458 | E18: =IFERROR(HEADCOUNT!E39,0) -> 118625 | F18: =IFERROR(HEADCOUNT!F39,0) -> 118625 | G18: =IFERROR(HEADCOUNT!G39,0) -> 167917 | H18: =IFERROR(HEADCOUNT!H39,0) -> 167917 | I18: =IFERROR(HEADCOUNT!I39,0) -> 183625 | ... AK18: =IFERROR(HEADCOUNT!AK39,0) -> 209625
A19: ENGINEERING ($) | B19: =IFERROR(HEADCOUNT!B14,0) -> 29250 | C19: =IFERROR(HEADCOUNT!C14,0) -> 29250 | D19: =IFERROR(HEADCOUNT!D14,0) -> 42250 | E19: =IFERROR(HEADCOUNT!E14,0) -> 42250 | F19: =IFERROR(HEADCOUNT!F14,0) -> 42250 | G19: =IFERROR(HEADCOUNT!G14,0) -> 55250 | H19: =IFERROR(HEADCOUNT!H14,0) -> 55250 | I19: =IFERROR(HEADCOUNT!I14,0) -> 55250 | ... AK19: =IFERROR(HEADCOUNT!AK14,0) -> 81250
A20: PRODUCT ($) | B20: =IFERROR(HEADCOUNT!B19,0) -> 0 | C20: =IFERROR(HEADCOUNT!C19,0) -> 0 | D20: =IFERROR(HEADCOUNT!D19,0) -> 14083 | E20: =IFERROR(HEADCOUNT!E19,0) -> 24375 | F20: =IFERROR(HEADCOUNT!F19,0) -> 24375 | G20: =IFERROR(HEADCOUNT!G19,0) -> 36292 | H20: =IFERROR(HEADCOUNT!H19,0) -> 36292 | I20: =IFERROR(HEADCOUNT!I19,0) -> 36292 | ... AK20: =IFERROR(HEADCOUNT!AK19,0) -> 36292
A21: SALES ($) | B21: =IFERROR(HEADCOUNT!B25,0) -> 10833 | C21: =IFERROR(HEADCOUNT!C25,0) -> 10833 | D21: =IFERROR(HEADCOUNT!D25,0) -> 10833 | E21: =IFERROR(HEADCOUNT!E25,0) -> 20041 | F21: =IFERROR(HEADCOUNT!F25,0) -> 20041 | G21: =IFERROR(HEADCOUNT!G25,0) -> 25999 | H21: =IFERROR(HEADCOUNT!H25,0) -> 25999 | I21: =IFERROR(HEADCOUNT!I25,0) -> 35207 | ... AK21: =IFERROR(HEADCOUNT!AK25,0) -> 35207
A22: MARKETING ($) | B22: =IFERROR(HEADCOUNT!B29,0) -> 0 | C22: =IFERROR(HEADCOUNT!C29,0) -> 0 | D22: =IFERROR(HEADCOUNT!D29,0) -> 10292 | E22: =IFERROR(HEADCOUNT!E29,0) -> 10292 | F22: =IFERROR(HEADCOUNT!F29,0) -> 10292 | G22: =IFERROR(HEADCOUNT!G29,0) -> 18959 | H22: =IFERROR(HEADCOUNT!H29,0) -> 18959 | I22: =IFERROR(HEADCOUNT!I29,0) -> 18959 | ... AK22: =IFERROR(HEADCOUNT!AK29,0) -> 18959
A23: CUSTOMER SUCCESS ($) | B23: =IFERROR(HEADCOUNT!B33,0) -> 0 | C23: =IFERROR(HEADCOUNT!C33,0) -> 0 | D23: =IFERROR(HEADCOUNT!D33,0) -> 0 | E23: =IFERROR(HEADCOUNT!E33,0) -> 8667 | F23: =IFERROR(HEADCOUNT!F33,0) -> 8667 | G23: =IFERROR(HEADCOUNT!G33,0) -> 8667 | H23: =IFERROR(HEADCOUNT!H33,0) -> 8667 | I23: =IFERROR(HEADCOUNT!I33,0) -> 15167 | ... AK23: =IFERROR(HEADCOUNT!AK33,0) -> 15167
A24: G&A ($) | B24: =IFERROR(HEADCOUNT!B37,0) -> 13000 | C24: =IFERROR(HEADCOUNT!C37,0) -> 13000 | D24: =IFERROR(HEADCOUNT!D37,0) -> 13000 | E24: =IFERROR(HEADCOUNT!E37,0) -> 13000 | F24: =IFERROR(HEADCOUNT!F37,0) -> 13000 | G24: =IFERROR(HEADCOUNT!G37,0) -> 22750 | H24: =IFERROR(HEADCOUNT!H37,0) -> 22750 | I24: =IFERROR(HEADCOUNT!I37,0) -> 22750 | ... AK24: =IFERROR(HEADCOUNT!AK37,0) -> 22750
A25: Marketing ($) | B25: =IFERROR(ASSUMPTIONS!$B$95,0) -> 8000 | C25: =IFERROR(ROUND(B25*(1+ASSUMPTIONS!$B$96),0),0) -> 8480 | D25: =IFERROR(ROUND(C25*(1+ASSUMPTIONS!$B$96),0),0) -> 8989 | E25: =IFERROR(ROUND(D25*(1+ASSUMPTIONS!$B$96),0),0) -> 9528 | F25: =IFERROR(ROUND(E25*(1+ASSUMPTIONS!$B$96),0),0) -> 10100 | G25: =IFERROR(ROUND(F25*(1+ASSUMPTIONS!$B$96),0),0) -> 10706 | H25: =IFERROR(ROUND(G25*(1+ASSUMPTIONS!$B$96),0),0) -> 11348 | I25: =IFERROR(ROUND(H25*(1+ASSUMPTIONS!$B$96),0),0) -> 12029 | J25: =IFERROR(ROUND(I25*(1+ASSUMPTIONS!$B$96),0),0) -> 12751 | ... AK25: =IFERROR(ROUND(AJ25*(1+ASSUMPTIONS!$B$96),0),0) -> 61490
A26: Other OpEx ($) | B26: =IFERROR(ASSUMPTIONS!$B$97+ASSUMPTIONS!$B$98+ASSUMPTIONS!$B$99+ASSUMPTIONS!$B$100,0) -> 7500 | C26: =IFERROR(ASSUMPTIONS!$B$97+ASSUMPTIONS!$B$98+ASSUMPTIONS!$B$99+ASSUMPTIONS!$B$100,0) -> 7500 | D26: =IFERROR(ASSUMPTIONS!$B$97+ASSUMPTIONS!$B$98+ASSUMPTIONS!$B$99+ASSUMPTIONS!$B$100,0) -> 7500 | E26: =IFERROR(ASSUMPTIONS!$B$97+ASSUMPTIONS!$B$98+ASSUMPTIONS!$B$99+ASSUMPTIONS!$B$100,0) -> 7500 | F26: =IFERROR(ASSUMPTIONS!$B$97+ASSUMPTIONS!$B$98+ASSUMPTIONS!$B$99+ASSUMPTIONS!$B$100,0) -> 7500 | G26: =IFERROR(ASSUMPTIONS!$B$97+ASSUMPTIONS!$B$98+ASSUMPTIONS!$B$99+ASSUMPTIONS!$B$100,0) -> 7500 | H26: =IFERROR(ASSUMPTIONS!$B$97+ASSUMPTIONS!$B$98+ASSUMPTIONS!$B$99+ASSUMPTIONS!$B$100,0) -> 7500 | I26: =IFERROR(ASSUMPTIONS!$B$97+ASSUMPTIONS!$B$98+ASSUMPTIONS!$B$99+ASSUMPTIONS!$B$100,0) -> 7500 | ... AK26: =IFERROR(ASSUMPTIONS!$B$97+ASSUMPTIONS!$B$98+ASSUMPTIONS!$B$99+ASSUMPTIONS!$B$100,0) -> 7500
A27: TOTAL OPEX ($) | B27: =B18+B25+B26 -> 68583 | C27: =C18+C25+C26 -> 69063 | D27: =D18+D25+D26 -> 106947 | E27: =E18+E25+E26 -> 135653 | F27: =F18+F25+F26 -> 136225 | G27: =G18+G25+G26 -> 186123 | H27: =H18+H25+H26 -> 186765 | I27: =I18+I25+I26 -> 203154 | ... AK27: =AK18+AK25+AK26 -> 278615
A29: EBITDA ($) | B29: =B14-B27 -> -60495.825 | C29: =C14-C27 -> -58656.25 | D29: =D14-D27 -> -94101.9 | E29: =E14-E27 -> -120250.77 | F29: =F14-F27 -> -118184.9 | G29: =G14-G27 -> -165245.5 | H29: =H14-H27 -> -162898.35 | I29: =I14-I27 -> -176136.7 | ... AK29: =AK14-AK27 -> 10460.875
A30: EBITDA Margin % | B30: =IFERROR(B29/B10,0) -> -6.8488424 | C30: =IFERROR(C29/C10,0) -> -5.158861 | D30: =IFERROR(D29/D10,0) -> -6.7043246 | E30: =IFERROR(E29/E10,0) -> -7.1446007 | F30: =IFERROR(F29/F10,0) -> -5.994365 | G30: =IFERROR(G29/G10,0) -> -7.2412577 | H30: =IFERROR(H29/H10,0) -> -6.2427512 | I30: =IFERROR(I29/I10,0) -> -5.9610363 | ... AK30: =IFERROR(AK29/AK10,0) -> 0.032924306

Sheet CASH FLOW
A1: CASH FLOW STATEMENT
A2: Monthly. Auto-calculated.
B4: YEAR 1 | N4: YEAR 2 | Z4: YEAR 3
B5: Jan | C5: Feb | D5: Mar | E5: Apr | F5: May | G5: Jun | H5: Jul | I5: Aug | J5: Sep | K5: Oct | L5: Nov | M5: Dec | N5: Jan | O5: Feb | P5: Mar | Q5: Apr | R5: May | S5: Jun | T5: Jul | U5: Aug | V5: Sep | W5: Oct | X5: Nov | Y5: Dec | Z5: Jan | AA5: Feb | AB5: Mar | AC5: Apr | AD5: May | AE5: Jun | AF5: Jul | AG5: Aug | AH5: Sep | AI5: Oct | AJ5: Nov | AK5: Dec | AL5: Y1 Total | AM5: Y2 Total | AN5: Y3 Total
A6: OPENING CASH
A7: Opening Cash ($) | B7: =ASSUMPTIONS!$B$103 -> 500000 | C7: =IFERROR(B17,0) -> 439504.17 | D7: =IFERROR(C17,0) -> 380847.92 | E7: =IFERROR(D17,0) -> 286746.03 | F7: =IFERROR(E17,0) -> 166495.25 | G7: =IFERROR(F17,0) -> 48310.35 | H7: =IFERROR(G17,0) -> 4883064.8 | I7: =IFERROR(H17,0) -> 4720166.5 | J7: =IFERROR(I17,0) -> 4544029.8 | ... AK7: =IFERROR(AJ17,0) -> 1025717.9
A9: OPERATIONS
A10: EBITDA | B10: =IFERROR('P&L'!B29,0) -> -60495.825 | C10: =IFERROR('P&L'!C29,0) -> -58656.25 | D10: =IFERROR('P&L'!D29,0) -> -94101.9 | E10: =IFERROR('P&L'!E29,0) -> -120250.77 | F10: =IFERROR('P&L'!F29,0) -> -118184.9 | G10: =IFERROR('P&L'!G29,0) -> -165245.5 | H10: =IFERROR('P&L'!H29,0) -> -162898.35 | I10: =IFERROR('P&L'!I29,0) -> -176136.7 | ... AK10: =IFERROR('P&L'!AK29,0) -> 10460.875
A11: CASH FROM OPS ($) | B11: =B10 -> -60495.825 | C11: =C10 -> -58656.25 | D11: =D10 -> -94101.9 | E11: =E10 -> -120250.77 | F11: =F10 -> -118184.9 | G11: =G10 -> -165245.5 | H11: =H10 -> -162898.35 | I11: =I10 -> -176136.7 | ... AK11: =AK10 -> 10460.875
A13: FINANCING
A14: Series A Raise ($) | B14: =IF(1=ASSUMPTIONS!$B$105,ASSUMPTIONS!$B$104,0) -> 0 | C14: =IF(2=ASSUMPTIONS!$B$105,ASSUMPTIONS!$B$104,0) -> 0 | D14: =IF(3=ASSUMPTIONS!$B$105,ASSUMPTIONS!$B$104,0) -> 0 | E14: =IF(4=ASSUMPTIONS!$B$105,ASSUMPTIONS!$B$104,0) -> 0 | F14: =IF(5=ASSUMPTIONS!$B$105,ASSUMPTIONS!$B$104,0) -> 0 | G14: =IF(6=ASSUMPTIONS!$B$105,ASSUMPTIONS!$B$104,0) -> 5000000 | H14: =IF(7=ASSUMPTIONS!$B$105,ASSUMPTIONS!$B$104,0) -> 0 | I14: =IF(8=ASSUMPTIONS!$B$105,ASSUMPTIONS!$B$104,0) -> 0 | J14: =IF(9=ASSUMPTIONS!$B$105,ASSUMPTIONS!$B$104,0) -> 0 | K14: =IF(10=ASSUMPTIONS!$B$105,ASSUMPTIONS!$B$104,0) -> 0 | L14: =IF(11=ASSUMPTIONS!$B$105,ASSUMPTIONS!$B$104,0) -> 0 | M14: =IF(12=ASSUMPTIONS!$B$105,ASSUMPTIONS!$B$104,0) -> 0 | N14: =IF(13=ASSUMPTIONS!$B$105,ASSUMPTIONS!$B$104,0) -> 0 | O14: =IF(14=ASSUMPTIONS!$B$105,ASSUMPTIONS!$B$104,0) -> 0 | P14: =IF(15=ASSUMPTIONS!$B$105,ASSUMPTIONS!$B$104,0) -> 0 | Q14: =IF(16=ASSUMPTIONS!$B$105,ASSUMPTIONS!$B$104,0) -> 0 | R14: =IF(17=ASSUMPTIONS!$B$105,ASSUMPTIONS!$B$104,0) -> 0 | S14: =IF(18=ASSUMPTIONS!$B$105,ASSUMPTIONS!$B$104,0) -> 0 | T14: =IF(19=ASSUMPTIONS!$B$105,ASSUMPTIONS!$B$104,0) -> 0 | U14: =IF(20=ASSUMPTIONS!$B$105,ASSUMPTIONS!$B$104,0) -> 0 | V14: =IF(21=ASSUMPTIONS!$B$105,ASSUMPTIONS!$B$104,0) -> 0 | W14: =IF(22=ASSUMPTIONS!$B$105,ASSUMPTIONS!$B$104,0) -> 0 | X14: =IF(23=ASSUMPTIONS!$B$105,ASSUMPTIONS!$B$104,0) -> 0 | Y14: =IF(24=ASSUMPTIONS!$B$105,ASSUMPTIONS!$B$104,0) -> 0 | Z14: =IF(25=ASSUMPTIONS!$B$105,ASSUMPTIONS!$B$104,0) -> 0 | AA14: =IF(26=ASSUMPTIONS!$B$105,ASSUMPTIONS!$B$104,0) -> 0 | AB14: =IF(27=ASSUMPTIONS!$B$105,ASSUMPTIONS!$B$104,0) -> 0 | AC14: =IF(28=ASSUMPTIONS!$B$105,ASSUMPTIONS!$B$104,0) -> 0 | AD14: =IF(29=ASSUMPTIONS!$B$105,ASSUMPTIONS!$B$104,0) -> 0 | AE14: =IF(30=ASSUMPTIONS!$B$105,ASSUMPTIONS!$B$104,0) -> 0 | AF14: =IF(31=ASSUMPTIONS!$B$105,ASSUMPTIONS!$B$104,0) -> 0 | AG14: =IF(32=ASSUMPTIONS!$B$105,ASSUMPTIONS!$B$104,0) -> 0 | AH14: =IF(33=ASSUMPTIONS!$B$105,ASSUMPTIONS!$B$104,0) -> 0 | AI14: =IF(34=ASSUMPTIONS!$B$105,ASSUMPTIONS!$B$104,0) -> 0 | AJ14: =IF(35=ASSUMPTIONS!$B$105,ASSUMPTIONS!$B$104,0) -> 0 | AK14: =IF(36=ASSUMPTIONS!$B$105,ASSUMPTIONS!$B$104,0) -> 0
A16: NET CASH ($) | B16: =B11+B14 -> -60495.825 | C16: =C11+C14 -> -58656.25 | D16: =D11+D14 -> -94101.9 | E16: =E11+E14 -> -120250.77 | F16: =F11+F14 -> -118184.9 | G16: =G11+G14 -> 4834754.5 | H16: =H11+H14 -> -162898.35 | I16: =I11+I14 -> -176136.7 | ... AK16: =AK11+AK14 -> 10460.875
A17: CLOSING CASH ($) | B17: =B7+B16 -> 439504.17 | C17: =C7+C16 -> 380847.92 | D17: =D7+D16 -> 286746.03 | E17: =E7+E16 -> 166495.25 | F17: =F7+F16 -> 48310.35 | G17: =G7+G16 -> 4883064.8 | H17: =H7+H16 -> 4720166.5 | I17: =I7+I16 -> 4544029.8 | ... AK17: =AK7+AK16 -> 1036178.8
A19: Burn ($) | B19: =B11 -> -60495.825 | C19: =C11 -> -58656.25 | D19: =D11 -> -94101.9 | E19: =E11 -> -120250.77 | F19: =F11 -> -118184.9 | G19: =G11 -> -165245.5 | H19: =H11 -> -162898.35 | I19: =I11 -> -176136.7 | ... AK19: =AK11 -> 10460.875
A20: Runway (months) | B20: =IFERROR(IF(B19<0,B17/ABS(B19),"∞"),0) -> 7.2650332 | C20: =IFERROR(IF(C19<0,C17/ABS(C19),"∞"),0) -> 6.4928788 | D20: =IFERROR(IF(D19<0,D17/ABS(D19),"∞"),0) -> 3.0471863 | E20: =IFERROR(IF(E19<0,E17/ABS(E19),"∞"),0) -> 1.384567 | F20: =IFERROR(IF(F19<0,F17/ABS(F19),"∞"),0) -> 0.40876923 | G20: =IFERROR(IF(G19<0,G17/ABS(G19),"∞"),0) -> 29.550365 | H20: =IFERROR(IF(H19<0,H17/ABS(H19),"∞"),0) -> 28.976147 | I20: =IFERROR(IF(I19<0,I17/ABS(I19),"∞"),0) -> 25.798313 | ... AK20: =IFERROR(IF(AK19<0,AK17/ABS(AK19),"∞"),0) -> ∞

Sheet BALANCE SHEET
A1: BALANCE SHEET
A2: Auto from P&L and Cash Flow. Balance check must = 0.
B4: YEAR 1 | N4: YEAR 2 | Z4: YEAR 3
B5: Jan | C5: Feb | D5: Mar | E5: Apr | F5: May | G5: Jun | H5: Jul | I5: Aug | J5: Sep | K5: Oct | L5: Nov | M5: Dec | N5: Jan | O5: Feb | P5: Mar | Q5: Apr | R5: May | S5: Jun | T5: Jul | U5: Aug | V5: Sep | W5: Oct | X5: Nov | Y5: Dec | Z5: Jan | AA5: Feb | AB5: Mar | AC5: Apr | AD5: May | AE5: Jun | AF5: Jul | AG5: Aug | AH5: Sep | AI5: Oct | AJ5: Nov | AK5: Dec | AL5: Y1 Total | AM5: Y2 Total | AN5: Y3 Total
A6: ASSETS
A7: Cash ($) | B7: =IFERROR('CASH FLOW'!B17,0) -> 439504.17 | C7: =IFERROR('CASH FLOW'!C17,0) -> 380847.92 | D7: =IFERROR('CASH FLOW'!D17,0) -> 286746.03 | E7: =IFERROR('CASH FLOW'!E17,0) -> 166495.25 | F7: =IFERROR('CASH FLOW'!F17,0) -> 48310.35 | G7: =IFERROR('CASH FLOW'!G17,0) -> 4883064.8 | H7: =IFERROR('CASH FLOW'!H17,0) -> 4720166.5 | I7: =IFERROR('CASH FLOW'!I17,0) -> 4544029.8 | ... AK7: =IFERROR('CASH FLOW'!AK17,0) -> 1036178.8
A8: TOTAL ASSETS ($) | B8: =B7 -> 439504.17 | C8: =C7 -> 380847.92 | D8: =D7 -> 286746.03 | E8: =E7 -> 166495.25 | F8: =F7 -> 48310.35 | G8: =G7 -> 4883064.8 | H8: =H7 -> 4720166.5 | I8: =I7 -> 4544029.8 | ... AK8: =AK7 -> 1036178.8
A10: LIABILITIES
A11: Accounts Payable ($) | B11: =0 -> 0 | C11: =0 -> 0 | D11: =0 -> 0 | E11: =0 -> 0 | F11: =0 -> 0 | G11: =0 -> 0 | H11: =0 -> 0 | I11: =0 -> 0 | ... AK11: =0 -> 0
A12: TOTAL LIABILITIES ($) | B12: =B11 -> 0 | C12: =C11 -> 0 | D12: =D11 -> 0 | E12: =E11 -> 0 | F12: =F11 -> 0 | G12: =G11 -> 0 | H12: =H11 -> 0 | I12: =I11 -> 0 | ... AK12: =AK11 -> 0
A14: EQUITY
A15: Share Capital ($) | B15: =ASSUMPTIONS!$B$103+B14 -> 500000 | C15: =B15+C14 -> 500000 | D15: =C15+D14 -> 500000 | E15: =D15+E14 -> 500000 | F15: =E15+F14 -> 500000 | G15: =F15+G14 -> 500000 | H15: =G15+H14 -> 500000 | I15: =H15+I14 -> 500000 | J15: =I15+J14 -> 500000 | ... AK15: =AJ15+AK14 -> 500000
A16: Retained Earnings ($) | B16: ='P&L'!B29 -> -60495.825 | C16: =B16+'P&L'!C29 -> -119152.07 | D16: =C16+'P&L'!D29 -> -213253.98 | E16: =D16+'P&L'!E29 -> -333504.75 | F16: =E16+'P&L'!F29 -> -451689.65 | G16: =F16+'P&L'!G29 -> -616935.15 | H16: =G16+'P&L'!H29 -> -779833.5 | I16: =H16+'P&L'!I29 -> -955970.2 | J16: =I16+'P&L'!J29 -> -1142478.7 | ... AK16: =AJ16+'P&L'!AK29 -> -4463821.2
A17: TOTAL EQUITY ($) | B17: =B15+B16 -> 439504.17 | C17: =C15+C16 -> 380847.92 | D17: =D15+D16 -> 286746.03 | E17: =E15+E16 -> 166495.25 | F17: =F15+F16 -> 48310.35 | G17: =G15+G16 -> -116935.15 | H17: =H15+H16 -> -279833.5 | I17: =I15+I16 -> -455970.2 | ... AK17: =AK15+AK16 -> -3963821.2
A18: TOTAL L + E ($) | B18: =B12+B17 -> 439504.17 | C18: =C12+C17 -> 380847.92 | D18: =D12+D17 -> 286746.03 | E18: =E12+E17 -> 166495.25 | F18: =F12+F17 -> 48310.35 | G18: =G12+G17 -> -116935.15 | H18: =H12+H17 -> -279833.5 | I18: =I12+I17 -> -455970.2 | ... AK18: =AK12+AK17 -> -3963821.2
A19: BALANCE CHECK (must = 0) | B19: =ROUND(B8-B18,0) -> 0 | C19: =ROUND(C8-C18,0) -> 0 | D19: =ROUND(D8-D18,0) -> 0 | E19: =ROUND(E8-E18,0) -> 0 | F19: =ROUND(F8-F18,0) -> 0 | G19: =ROUND(G8-G18,0) -> 5000000 | H19: =ROUND(H8-H18,0) -> 5000000 | I19: =ROUND(I8-I18,0) -> 5000000 | ... AK19: =ROUND(AK8-AK18,0) -> 5000000

Sheet UNIT ECONOMICS
A1: UNIT ECONOMICS
A2: CAC, LTV, LTV:CAC, payback period.
B4: YEAR 1 | N4: YEAR 2 | Z4: YEAR 3
B5: Jan | C5: Feb | D5: Mar | E5: Apr | F5: May | G5: Jun | H5: Jul | I5: Aug | J5: Sep | K5: Oct | L5: Nov | M5: Dec | N5: Jan | O5: Feb | P5: Mar | Q5: Apr | R5: May | S5: Jun | T5: Jul | U5: Aug | V5: Sep | W5: Oct | X5: Nov | Y5: Dec | Z5: Jan | AA5: Feb | AB5: Mar | AC5: Apr | AD5: May | AE5: Jun | AF5: Jul | AG5: Aug | AH5: Sep | AI5: Oct | AJ5: Nov | AK5: Dec | AL5: Y1 Total | AM5: Y2 Total | AN5: Y3 Total
A6: UNIT ECONOMICS — SAAS SEGMENT
A8: Blended CAC ($) | B8: =IFERROR(ASSUMPTIONS!$B$55,0) -> 120 | C8: =IFERROR(ASSUMPTIONS!$B$55,0) -> 120 | D8: =IFERROR(ASSUMPTIONS!$B$55,0) -> 120 | E8: =IFERROR(ASSUMPTIONS!$B$55,0) -> 120 | F8: =IFERROR(ASSUMPTIONS!$B$55,0) -> 120 | G8: =IFERROR(ASSUMPTIONS!$B$55,0) -> 120 | H8: =IFERROR(ASSUMPTIONS!$B$55,0) -> 120 | I8: =IFERROR(ASSUMPTIONS!$B$55,0) -> 120 | ... AK8: =IFERROR(ASSUMPTIONS!$B$55,0) -> 120
A9: SaaS LTV ($) | B9: =IFERROR(ASSUMPTIONS!$B$52*ASSUMPTIONS!$B$56/ASSUMPTIONS!$B$51,0) -> 2948.5714 | C9: =IFERROR(ASSUMPTIONS!$B$52*ASSUMPTIONS!$B$56/ASSUMPTIONS!$B$51,0) -> 2948.5714 | D9: =IFERROR(ASSUMPTIONS!$B$52*ASSUMPTIONS!$B$56/ASSUMPTIONS!$B$51,0) -> 2948.5714 | E9: =IFERROR(ASSUMPTIONS!$B$52*ASSUMPTIONS!$B$56/ASSUMPTIONS!$B$51,0) -> 2948.5714 | F9: =IFERROR(ASSUMPTIONS!$B$52*ASSUMPTIONS!$B$56/ASSUMPTIONS!$B$51,0) -> 2948.5714 | G9: =IFERROR(ASSUMPTIONS!$B$52*ASSUMPTIONS!$B$56/ASSUMPTIONS!$B$51,0) -> 2948.5714 | H9: =IFERROR(ASSUMPTIONS!$B$52*ASSUMPTIONS!$B$56/ASSUMPTIONS!$B$51,0) -> 2948.5714 | I9: =IFERROR(ASSUMPTIONS!$B$52*ASSUMPTIONS!$B$56/ASSUMPTIONS!$B$51,0) -> 2948.5714 | ... AK9: =IFERROR(ASSUMPTIONS!$B$52*ASSUMPTIONS!$B$56/ASSUMPTIONS!$B$51,0) -> 2948.5714
A10: LTV:CAC Ratio | B10: =IFERROR(B9/B8,0) -> 24.571429 | C10: =IFERROR(C9/C8,0) -> 24.571429 | D10: =IFERROR(D9/D8,0) -> 24.571429 | E10: =IFERROR(E9/E8,0) -> 24.571429 | F10: =IFERROR(F9/F8,0) -> 24.571429 | G10: =IFERROR(G9/G8,0) -> 24.571429 | H10: =IFERROR(H9/H8,0) -> 24.571429 | I10: =IFERROR(I9/I8,0) -> 24.571429 | ... AK10: =IFERROR(AK9/AK8,0) -> 24.571429
A11: Payback Period (months) | B11: =IFERROR(B8/(ASSUMPTIONS!$B$52*ASSUMPTIONS!$B$56),0) -> 1.1627907 | C11: =IFERROR(C8/(ASSUMPTIONS!$B$52*ASSUMPTIONS!$B$56),0) -> 1.1627907 | D11: =IFERROR(D8/(ASSUMPTIONS!$B$52*ASSUMPTIONS!$B$56),0) -> 1.1627907 | E11: =IFERROR(E8/(ASSUMPTIONS!$B$52*ASSUMPTIONS!$B$56),0) -> 1.1627907 | F11: =IFERROR(F8/(ASSUMPTIONS!$B$52*ASSUMPTIONS!$B$56),0) -> 1.1627907 | G11: =IFERROR(G8/(ASSUMPTIONS!$B$52*ASSUMPTIONS!$B$56),0) -> 1.1627907 | H11: =IFERROR(H8/(ASSUMPTIONS!$B$52*ASSUMPTIONS!$B$56),0) -> 1.1627907 | I11: =IFERROR(I8/(ASSUMPTIONS!$B$52*ASSUMPTIONS!$B$56),0) -> 1.1627907 | ... AK11: =IFERROR(AK8/(ASSUMPTIONS!$B$52*ASSUMPTIONS!$B$56),0) -> 1.1627907

Sheet KPI DASHBOARD
B1: KPI Dashboard — Series A Model
B2: Year-end metrics | Auto-populated
C4: Year 1 | D4: Year 2 | E4: Year 3
A6: REVENUE & GROWTH
B7: Total Revenue ($) | C7: =SUM(REVENUE!B28:M28) -> 305457 | D7: =SUM(REVENUE!N28:Y28) -> 997446 | E7: =SUM(REVENUE!Z28:AK28) -> 2585867
B8: Marketplace Revenue ($) | C8: =SUM(REVENUE!B19:M19) -> 182391 | D8: =SUM(REVENUE!N19:Y19) -> 555105 | E8: =SUM(REVENUE!Z19:AK19) -> 1394165
B9: SaaS Revenue ($) | C9: =SUM(REVENUE!B25:M25) -> 123066 | D9: =SUM(REVENUE!N25:Y25) -> 442341 | E9: =SUM(REVENUE!Z25:AK25) -> 1191702
B10: Active Buyers (year-end) | C10: =REVENUE!M9 -> 248 | D10: =REVENUE!Y9 -> 702 | E10: =REVENUE!AK9 -> 1812
B11: Active SaaS Subs (year-end) | C11: =REVENUE!M24 -> 148 | D11: =REVENUE!Y24 -> 439 | E11: =REVENUE!AK24 -> 1146
A13: MARGINS & PROFITABILITY
B14: Gross Margin % | C14: =IFERROR(SUM('P&L'!B14:M14)/SUM('P&L'!B10:M10),0) -> 0.91429424 | D14: =IFERROR(SUM('P&L'!N14:Y14)/SUM('P&L'!N10:Y10),0) -> 0.91206326 | E14: =IFERROR(SUM('P&L'!Z14:AK14)/SUM('P&L'!Z10:AK10),0) -> 0.91032111
B15: EBITDA ($) | C15: =SUM('P&L'!B29:M29) -> -1698516.4 | D15: =SUM('P&L'!N29:Y29) -> -1967333.1 | E15: =SUM('P&L'!Z29:AK29) -> -797971.68
A17: CASH & RUNWAY
B18: Closing Cash ($) | C18: ='CASH FLOW'!M17 -> 3801483.6 | D18: ='CASH FLOW'!Y17 -> 1834150.4 | E18: ='CASH FLOW'!AK17 -> 1036178.8
B19: Runway (months) | C19: ='CASH FLOW'!M20 -> 19.885154 | D19: ='CASH FLOW'!Y20 -> 13.743515 | E19: ='CASH FLOW'!AK20 -> ∞

Sheet SENSITIVITY
A1: SENSITIVITY ANALYSIS
A2: Shows Year 1 EBITDA impact under different churn and ARPU scenarios.
A4: Year 1 EBITDA at Different Churn Rates
A5: Monthly Churn Rate | B5: 0.02 | C5: 0.03 | D5: 0.04 | E5: 0.05 | F5: 0.06 | G5: 0.08
A6: Y1 EBITDA ($) — manual entry
A8: Instructions:
A9: 1. Change churn rate in ASSUMPTIONS → note Y1 EBITDA from KPI Dashboard
A10: 2. Enter the value in the corresponding column above
A11: 3. Repeat for each scenario to build the sensitivity table
